Workbook

Sheet Ppto 24-25 2Oct
C2: 2023/2024 | P2: 2024/2025
C3: Sep | D3: Oct | E3: Nov | F3: Dic | G3: Ene | H3: Feb | I3: Mar | J3: Abr | K3: May | L3: Jun | M3: Jul | N3: Ago | O3: Totales | P3: Sep | Q3: Oct | R3: Nov | S3: Dic | T3: Ene | U3: Feb | V3: Mar | W3: Abr | X3: May | Y3: Jun | Z3: Jul | AA3: Ago | AB3: Totales
B4: Vacuno
B5: Cobros | C5: 556.3 | D5: 33077.51 | E5: 51305.32 | F5: 0 | G5: 37253.67 | H5: 0 | I5: 0 | J5: 24907.2 | K5: 32803.2 | L5: 19326.06 | M5: 2174.17 | N5: 17183.67 | O5: 218587.1 | P5: 20013.44 | Q5: 9188.82 | R5: 12093 | S5: 14132.5 | T5: 13450 | U5: 8561.19 | V5: 13856.19 | W5: 8349 | X5: 22011 | Y5: 29601 | Z5: 15180 | AA5: 14049 | AB5: 180485.14
B6: Pagos | C6: 0 | D6: 0 | E6: 2310.58 | F6: 836.06 | G6: 4329.7136 | H6: 16.5 | I6: 383.08 | J6: 2104.36 | K6: 637.4 | L6: 632.11 | M6: 3107.17 | N6: 791.98 | O6: 15148.954 | P6: 705.64 | Q6: 2948.81 | R6: -1142.77 | S6: 700 | T6: 5568.9036 | U6: 600 | V6: 1300 | W6: 1574.56 | X6: 725 | Y6: 600 | Z6: 2961.41 | AA6: 600 | AB6: 17141.554
B8: Caja Operaciones (mes) | C8: 556.3 | D8: 33077.51 | E8: 48994.74 | F8: -836.06 | G8: 32923.956 | H8: -16.5 | I8: -383.08 | J8: 22802.84 | K8: 32165.8 | L8: 18693.95 | M8: -933 | N8: 16391.69 | P8: 19307.8 | Q8: 6240.01 | R8: 13235.77 | S8: 13432.5 | T8: 7881.0964 | U8: 7961.19 | V8: 12556.19 | W8: 6774.44 | X8: 21286 | Y8: 29001 | Z8: 12218.59 | AA8: 13449
B9: Caja Operaciones (acum.) | C9: 556.3 | D9: 33633.81 | E9: 82628.55 | F9: 81792.49 | G9: 114716.45 | H9: 114699.95 | I9: 114316.87 | J9: 137119.71 | K9: 169285.51 | L9: 187979.46 | M9: 187046.46 | N9: 203438.15 | O9: 203438.15 | P9: 19307.8 | Q9: 25547.81 | R9: 38783.58 | S9: 52216.08 | T9: 60097.176 | U9: 68058.366 | V9: 80614.556 | W9: 87388.996 | X9: 108675 | Y9: 137676 | Z9: 149894.59 | AA9: 163343.59 | AB9: 163343.59
B10: Porcino
B11: Cobros | C11: 4256.95 | D11: 280.97 | E11: 7918.95 | F11: 5851.53 | G11: 6817.68 | H11: 1725.36 | I11: 2334.57 | J11: 34055.67 | K11: 47976.1 | L11: 21953.81 | M11: 11.84 | N11: 7039.33 | O11: 140222.76 | P11: 1689.99 | Q11: 7042.67 | R11: 0 | S11: 0 | T11: 33800 | U11: 4032 | V11: 0 | W11: 0 | X11: 0 | Y11: 30000 | Z11: 60480 | AA11: 0 | AB11: 137044.66
B12: Pagos | C12: 0 | D12: 2580.26 | E12: 4060.27 | F12: 5231.09 | G12: 6014.37 | H12: 3635.26 | I12: 1494.8879 | J12: 6161.82 | K12: 6469.54 | L12: 6495.07 | M12: 5823.66 | N12: 2236.42 | O12: 50202.648 | P12: 1967.14 | Q12: 10 | R12: 186.08 | S12: 1251.77 | T12: 1416.14 | U12: 749.76 | V12: 260 | W12: 260 | X12: 260 | Y12: 260 | Z12: 260 | AA12: 260 | AB12: 7140.89
B14: Caja Operaciones (mes) | C14: 4256.95 | D14: -2299.29 | E14: 3858.68 | F14: 620.44 | G14: 803.31 | H14: -1909.9 | I14: 839.6821 | J14: 27893.85 | K14: 41506.56 | L14: 15458.74 | M14: -5811.82 | N14: 4802.91 | P14: -277.15 | Q14: 7032.67 | R14: -186.08 | S14: -1251.77 | T14: 32383.86 | U14: 3282.24 | V14: -260 | W14: -260 | X14: -260 | Y14: 29740 | Z14: 60220 | AA14: -260
B15: Caja Operaciones (acum.) | C15: 4256.95 | D15: 1957.66 | E15: 5816.34 | F15: 6436.78 | G15: 7240.09 | H15: 5330.19 | I15: 6169.8721 | J15: 34063.722 | K15: 75570.282 | L15: 91029.022 | M15: 85217.202 | N15: 90020.112 | O15: 90020.112 | P15: -277.15 | Q15: 6755.52 | R15: 6569.44 | S15: 5317.67 | T15: 37701.53 | U15: 40983.77 | V15: 40723.77 | W15: 40463.77 | X15: 40203.77 | Y15: 69943.77 | Z15: 130163.77 | AA15: 129903.77 | AB15: 129903.77
B16: Ovino
B17: Cobros | C17: 0 | D17: 0 | E17: 11902 | F17: 0 | G17: 2858.9 | H17: 0 | I17: 0 | J17: 0 | K17: 0 | L17: 0 | M17: 0 | N17: 0 | O17: 14760.9 | P17: 0 | Q17: 0 | R17: 0 | S17: 0 | T17: 0 | U17: 0 | V17: 0 | W17: 0 | X17: 0 | Y17: 0 | Z17: 0 | AA17: 0 | AB17: 0
B18: Pagos | C18: 0 | D18: 0 | E18: 363.84 | F18: 50.2 | G18: 0 | H18: 0 | I18: 0 | J18: 0 | K18: 16.5 | L18: 0 | M18: 0 | N18: 0 | O18: 430.54 | P18: 0 | Q18: 0 | R18: 0 | S18: 0 | T18: 0 | U18: 0 | V18: 0 | W18: 0 | X18: 0 | Y18: 0 | Z18: 0 | AA18: 0 | AB18: 0
B20: Caja Operaciones (mes) | C20: 0 | D20: 0 | E20: 11538.16 | F20: -50.2 | G20: 2858.9 | H20: 0 | I20: 0 | J20: 0 | K20: -16.5 | L20: 0 | M20: 0 | N20: 0 | P20: 0 | Q20: 0 | R20: 0 | S20: 0 | T20: 0 | U20: 0 | V20: 0 | W20: 0 | X20: 0 | Y20: 0 | Z20: 0 | AA20: 0
B21: Caja Operaciones (acum.) | C21: 0 | D21: 0 | E21: 11538.16 | F21: 11487.96 | G21: 14346.86 | H21: 14346.86 | I21: 14346.86 | J21: 14346.86 | K21: 14330.36 | L21: 14330.36 | M21: 14330.36 | N21: 14330.36 | O21: 14330.36 | P21: 0 | Q21: 0 | R21: 0 | S21: 0 | T21: 0 | U21: 0 | V21: 0 | W21: 0 | X21: 0 | Y21: 0 | Z21: 0 | AA21: 0 | AB21: 0
B22: Gastos generales
B23: Act. Ganadera | C23: -5295.41 | D23: -12564.86 | E23: -10574.68 | F23: -48375.95 | G23: -31144.988 | H23: -7833.02 | I23: -9072.2 | J23: -9847.07 | K23: -13520.65 | L23: -16253.92 | M23: -25828.97 | N23: -91147.8 | O23: -281459.52 | P23: -6553.13 | Q23: -56284.99 | R23: -26352.11 | S23: -13966.47 | T23: -7422.86 | U23: -4859.62 | V23: -12986.37 | W23: -9095.36 | X23: -13334.45 | Y23: -12310.01 | Z23: -6970.36 | AA23: -6597.86 | AB23: -176733.59
B25: Caja Operaciones (mes) | C25: -5295.41 | D25: -12564.86 | E25: -10574.68 | F25: -48375.95 | G25: -31144.988 | H25: -7833.02 | I25: -9072.2 | J25: -9847.07 | K25: -13520.65 | L25: -16253.92 | M25: -25828.97 | N25: -91147.8 | P25: -6553.13 | Q25: -56284.99 | R25: -26352.11 | S25: -13966.47 | T25: -7422.86 | U25: -4859.62 | V25: -12986.37 | W25: -9095.36 | X25: -13334.45 | Y25: -12310.01 | Z25: -6970.36 | AA25: -6597.86
B26: Caja Inversiones (acum.) | C26: -5295.41 | D26: -17860.27 | E26: -28434.95 | F26: -76810.9 | G26: -107955.89 | H26: -115788.91 | I26: -124861.11 | J26: -134708.18 | K26: -148228.83 | L26: -164482.75 | M26: -190311.72 | N26: -281459.52 | O26: -281459.52 | P26: -6553.13 | Q26: -62838.12 | R26: -89190.23 | S26: -103156.7 | T26: -110579.56 | U26: -115439.18 | V26: -128425.55 | W26: -137520.91 | X26: -150855.36 | Y26: -163165.37 | Z26: -170135.73 | AA26: -176733.59 | AB26: -176733.59
B27: Inversiones
B28: Act. Ganadera | C28: 0 | D28: 0 | E28: 0 | F28: 0 | G28: -544.5 | H28: -10393.93 | I28: 0 | J28: -1739.155 | K28: -4112.9 | L28: 0 | M28: 0 | N28: 0 | O28: -16790.485 | P28: 0 | Q28: 0 | R28: 0 | S28: 0 | T28: 0 | U28: 0 | V28: 0 | W28: 0 | X28: 0 | Y28: 0 | Z28: 0 | AA28: 0 | AB28: 0
B30: Caja Inversiones (mes) | C30: 0 | D30: 0 | E30: 0 | F30: 0 | G30: -544.5 | H30: -10393.93 | I30: 0 | J30: -1739.155 | K30: -4112.9 | L30: 0 | M30: 0 | N30: 0 | P30: 0 | Q30: 0 | R30: 0 | S30: 0 | T30: 0 | U30: 0 | V30: 0 | W30: 0 | X30: 0 | Y30: 0 | Z30: 0 | AA30: 0
B31: Caja Inversiones (acum.) | C31: 0 | D31: 0 | E31: 0 | F31: 0 | G31: -544.5 | H31: -10938.43 | I31: -10938.43 | J31: -12677.585 | K31: -16790.485 | L31: -16790.485 | M31: -16790.485 | N31: -16790.485 | O31: -16790.485 | P31: 0 | Q31: 0 | R31: 0 | S31: 0 | T31: 0 | U31: 0 | V31: 0 | W31: 0 | X31: 0 | Y31: 0 | Z31: 0 | AA31: 0 | AB31: 0
B32: Financiación | C32: 743.05 | D32: 9000 | E32: 0 | F32: 0 | G32: 0 | H32: 0 | I32: 0 | J32: 0 | K32: 0 | L32: 0 | M32: 0 | N32: 0 | O32: 9743.05 | P32: 0 | Q32: 30000 | R32: 0 | S32: 0 | T32: -30000 | U32: 0 | V32: 0 | W32: 0 | X32: 0 | Y32: 0 | Z32: 0 | AA32: 0 | AB32: 0
B34: Caja Financiación (mes) | C34: 743.05 | D34: 9000 | E34: 0 | F34: 0 | G34: 0 | H34: 0 | I34: 0 | J34: 0 | K34: 0 | L34: 0 | M34: 0 | N34: 0 | P34: 0 | Q34: 30000 | R34: 0 | S34: 0 | T34: -30000 | U34: 0 | V34: 0 | W34: 0 | X34: 0 | Y34: 0 | Z34: 0 | AA34: 0
B35: Caja Financiación (acum.) | C35: 743.05 | D35: 9743.05 | E35: 9743.05 | F35: 9743.05 | G35: 9743.05 | H35: 9743.05 | I35: 9743.05 | J35: 9743.05 | K35: 9743.05 | L35: 9743.05 | M35: 9743.05 | N35: 9743.05 | O35: 9743.05 | P35: 0 | Q35: 30000 | R35: 30000 | S35: 30000 | T35: 0 | U35: 0 | V35: 0 | W35: 0 | X35: 0 | Y35: 0 | Z35: 0 | AA35: 0 | AB35: 0
B37: Caja opex, capex y serv. deuda | C37: 260.89 | D37: 27213.36 | E37: 53816.9 | F37: -48641.77 | G37: 4896.6782 | H37: -20153.35 | I37: -8615.5979 | J37: 39110.465 | K37: 56022.31 | L37: 17898.77 | M37: -32573.79 | N37: -69953.2 | O37: 19281.665 | P37: 12477.52 | Q37: -13012.31 | R37: -13302.42 | S37: -1785.74 | T37: 2842.0964 | U37: 6383.81 | V37: -690.18 | W37: -2580.92 | X37: 7691.55 | Y37: 46430.99 | Z37: 65468.23 | AA37: 6591.14 | AB37: 116513.77
B38: Check | O38: 0 | AB38: 0
B39: Total circulante
B41: Caja consolidada (mes) | C41: 260.89 | D41: 27213.36 | E41: 53816.9 | F41: -48641.77 | G41: 4896.6782 | H41: -20153.35 | I41: -8615.5979 | J41: 39110.465 | K41: 56022.31 | L41: 17898.77 | M41: -32573.79 | N41: -69953.2 | P41: 12477.52 | Q41: -13012.31 | R41: -13302.42 | S41: -1785.74 | T41: 2842.0964 | U41: 6383.81 | V41: -690.18 | W41: -2580.92 | X41: 7691.55 | Y41: 46430.99 | Z41: 65468.23 | AA41: 6591.14
B42: Caja consolidada (acumulada) | C42: 260.89 | D42: 27474.25 | E42: 81291.15 | F42: 32649.38 | G42: 37546.058 | H42: 17392.708 | I42: 8777.1103 | J42: 47887.575 | K42: 103909.89 | L42: 121808.66 | M42: 89234.865 | N42: 19281.665 | P42: 12477.52 | Q42: -534.79 | R42: -13837.21 | S42: -15622.95 | T42: -12780.854 | U42: -6397.0436 | V42: -7087.2236 | W42: -9668.1436 | X42: -1976.5936 | Y42: 44454.396 | Z42: 109922.63 | AA42: 116513.77
B44: Saldo Inicial | C44: 1178.6 | D44: 1439.49 | E44: 28652.85 | F44: 82469.75 | G44: 33827.98 | H44: 38724.658 | I44: 18571.308 | J44: 9955.7103 | K44: 49066.175 | L44: 105088.49 | M44: 122987.26 | N44: 90413.465 | P44: 20460.265 | Q44: 32937.785 | R44: 19925.475 | S44: 6623.0553 | T44: 4837.3153 | U44: 7679.4117 | V44: 14063.222 | W44: 13373.042 | X44: 10792.122 | Y44: 18483.672 | Z44: 64914.662 | AA44: 130382.89
B45: Caja consolidada | C45: 260.89 | D45: 27213.36 | E45: 53816.9 | F45: -48641.77 | G45: 4896.6782 | H45: -20153.35 | I45: -8615.5979 | J45: 39110.465 | K45: 56022.31 | L45: 17898.77 | M45: -32573.79 | N45: -69953.2 | P45: 12477.52 | Q45: -13012.31 | R45: -13302.42 | S45: -1785.74 | T45: 2842.0964 | U45: 6383.81 | V45: -690.18 | W45: -2580.92 | X45: 7691.55 | Y45: 46430.99 | Z45: 65468.23 | AA45: 6591.14
B46: Saldo final | C46: 1439.49 | D46: 28652.85 | E46: 82469.75 | F46: 33827.98 | G46: 38724.658 | H46: 18571.308 | I46: 9955.7103 | J46: 49066.175 | K46: 105088.49 | L46: 122987.26 | M46: 90413.465 | N46: 20460.265 | P46: 32937.785 | Q46: 19925.475 | R46: 6623.0553 | S46: 4837.3153 | T46: 7679.4117 | U46: 14063.222 | V46: 13373.042 | W46: 10792.122 | X46: 18483.672 | Y46: 64914.662 | Z46: 130382.89 | AA46: 136974.03
B47: Saldos bancarios
B48: Saldo Caixa EUR | C48: 1449.16 | D48: 29148.21 | E48: 82883.58 | F48: 34241.81 | G48: 36138.49 | H48: 16786.84 | I48: 8792.55 | J48: 47903.01 | K48: 74324.32 | L48: 90946.35 | M48: 56483.26 | N48: 18021.45 | P48: 921 | Q48: 0 | R48: 0 | S48: 0 | T48: 0 | U48: 0 | V48: 0 | W48: 0 | X48: 0 | Y48: 0 | Z48: 0 | AA48: 0
B49: Saldo Caja Rural | C49: -9.67 | D49: -27.86 | E49: 53.67 | F49: 53.67 | G49: 53.67 | H49: 51.97 | I49: 105.67 | J49: 105.67 | K49: 28726.67 | L49: 30003.41 | M49: 31892.71 | N49: 401.32 | P49: 29979.29 | Q49: 0 | R49: 0 | S49: 0 | T49: 0 | U49: 0 | V49: 0 | W49: 0 | X49: 0 | Y49: 0 | Z49: 0 | AA49: 0
B50: Saldo Caja | C50: 0 | D50: -467.5 | E50: -467.5 | F50: -467.5 | G50: 2532.5 | H50: 1732.5 | I50: 1057.5 | J50: 1057.5 | K50: 2037.5 | L50: 2037.5 | M50: 2037.5 | N50: 2037.5 | P50: 2037.5 | Q50: 0 | R50: 0 | S50: 0 | T50: 0 | U50: 0 | V50: 0 | W50: 0 | X50: 0 | Y50: 0 | Z50: 0 | AA50: 0
B51: Check | C51: 1439.49 | D51: 28652.85 | E51: 82469.75 | F51: 33827.98 | G51: 38724.66 | H51: 18571.31 | I51: 9955.72 | J51: 49066.18 | K51: 105088.49 | L51: 122987.26 | M51: 90413.47 | N51: 20460.27 | P51: 32937.79 | Q51: 0 | R51: 0 | S51: 0 | T51: 0 | U51: 0 | V51: 0 | W51: 0 | X51: 0 | Y51: 0 | Z51: 0 | AA51: 0
B52: Diferencia | C52: 0 | D52: 0 | E52: 0 | F52: 0 | G52: -0.0018 | H52: -0.0018 | I52: -0.0097 | J52: -0.0047 | K52: -0.0047 | L52: -0.0047 | M52: -0.0047 | N52: -0.0047 | P52: -0.0047

Sheet Animales
K3: Avance
C4: Presupuesto | E4: Avance | F4: 46112 | J4: Presupuesto | K4: 46112
C5: Animales | D5: % | E5: Animales | F5: % | J5: Animales | K5: Animales
B6: Madres fértiles | C6: 158 | D6: 1 | E6: 191 | F6: 1 | I6: Madres | J6: 30 | K6: 29
B7: Partos | C7: 147 | D7: =+C7/C6 -> 0.93037975 | E7: 138 | F7: =+E7/$E$6 -> 0.72251309 | I7: lechones/madre | J7: 6 | K7: =5.517 -> 5.517
B8: Terneros de 200kg | C8: =+C7-5 -> 142 | D8: =+C8/$C$6 -> 0.89873418 | E8: 138 | F8: =+E8/$E$6 -> 0.72251309 | I8: Partos | J8: =+J6*J7*2 -> 360 | K8: =+K6*K7*2 -> 319.986
B9: A venta | C9: 142 | D9: =+C9/$C$6 -> 0.89873418 | E9: 71 | F9: =+E9/$E$6 -> 0.37172775 | I9: Muertes | J9: 60 | K9: 0
B10: A cebo intermedio/remate | C10: 0 | D10: =+C10/$C$6 -> 0 | E10: 6 | F10: =+E10/$E$6 -> 0.031413613 | I10: lechones a término | J10: =+J8-J9 -> 300 | K10: =+K8-K9 -> 319.986
B11: A recría | C11: 0 | D11: =+C11/$C$6 -> 0 | E11: 49 | F11: =+E11/$E$6 -> 0.2565445 | I11: lechones | J11: 300 | K11: 320
B12: Total | C12: =SUM(C9:C11) -> 142 | D12: =+C12/$C$6 -> 0.89873418 | E12: =SUM(E9:E11) -> 126 | F12: =+E12/$E$6 -> 0.65968586 | I12: Marranos y primales | J12: 111 | K12: =128+95 -> 223 | L12: Baja de 32 marranos escapados
I13: Montanera | J13: =SUM(J14:J15) -> 287 | K13: =SUM(K14:K15) -> 277
B14: Ventas 200kg | C14: 85 | E14: 71 | I14: Propia | J14: 87 | K14: =86-4+6-5 -> 83
B15: Ventas remate | C15: =2+31 -> 33 | E15: 9 | I15: Terceros | J15: 200 | K15: =200-6 -> 194
B16: Total general | C16: =SUM(C14:C15) -> 118 | E16: =SUM(E14:E15) -> 80 | I16: Total | J16: =+J11+J12+J13 -> 698 | K16: =+K11+K12+K13 -> 820
I17: Maquila propía | K17: =43 -> 43
I18: Maquila terceros | K18: 3

Sheet Consolidado
C1: 2023/2024 | P1: 2024/2025 | AC1: 2025/2026 | AS1: 2026/2027
C2: Sep | D2: Oct | E2: Nov | F2: Dic | G2: Ene | H2: Feb | I2: Mar | J2: Abr | K2: May | L2: Jun | M2: Jul | N2: Ago | O2: Totales | P2: Sep | Q2: Oct | R2: Nov | S2: Dic | T2: Ene | U2: Feb | V2: Mar | W2: Abr | X2: May | Y2: Jun | Z2: Jul | AA2: Ago | AB2: Totales | AC2: Sep | AD2: Oct | AE2: Nov | AF2: Dic | AG2: Ene | AH2: Feb | AI2: Mar | AJ2: Abr | AK2: May | AL2: Jun | AM2: Jul | AN2: Ago | AO2: Totales | AS2: Sep | AT2: Oct | AU2: Nov | AV2: Dic | AW2: Ene | AX2: Feb | AY2: Mar | AZ2: Abr | BA2: May | BB2: Jun | BC2: Jul | BD2: Ago | BE2: Totales
B3: Vacuno
B4: Cobros | C4: ='Ing y gtos'!AE16 -> 556.3 | D4: ='Ing y gtos'!AF16 -> 33077.51 | E4: ='Ing y gtos'!AG16 -> 51305.32 | F4: ='Ing y gtos'!AH16 -> 0 | G4: ='Ing y gtos'!AI16 -> 37253.67 | H4: ='Ing y gtos'!AJ16 -> 0 | I4: ='Ing y gtos'!AK16 -> 0 | J4: ='Ing y gtos'!AL16 -> 24907.2 | ... N4: ='Ing y gtos'!AP16 -> 17183.67 | O4: =SUM(C4:N4) -> 218587.1 | P4: ='Ing y gtos'!AU16 -> 20013.44 | Q4: ='Ing y gtos'!AV16 -> 26949.06 | R4: ='Ing y gtos'!AW16 -> 315 | S4: ='Ing y gtos'!AX16 -> 12466.31 | T4: ='Ing y gtos'!AY16 -> 7989.53 | U4: ='Ing y gtos'!AZ16 -> 0 | V4: ='Ing y gtos'!BA16 -> 10410.67 | W4: ='Ing y gtos'!BB16 -> 11634.21 | ... AA4: ='Ing y gtos'!BF16 -> 24335.96 | AB4: =SUM(P4:AA4) -> 120683.72 | AC4: ='Ing y gtos'!BJ16 -> 8092.83 | AD4: ='Ing y gtos'!BK16 -> 29566.61 | AE4: ='Ing y gtos'!BL16 -> 35506.83 | AF4: ='Ing y gtos'!BM16 -> 5514.23 | AG4: ='Ing y gtos'!BN16 -> 8798.9 | AH4: ='Ing y gtos'!BO16 -> 0 | AI4: ='Ing y gtos'!BP16 -> 7620.43 | AJ4: ='Ing y gtos'!BQ16 -> 276.39 | ... AN4: ='Ing y gtos'!BU16 -> 28490.25 | AO4: =SUM(AC4:AN4) -> 176294.96 | AS4: ='Ing y gtos'!BY16 -> 5927.5 | AT4: ='Ing y gtos'!BZ16 -> 36282.5 | AU4: ='Ing y gtos'!CA16 -> 21097 | AV4: ='Ing y gtos'!CB16 -> 31411.5 | AW4: ='Ing y gtos'!CC16 -> 1185.5 | AX4: ='Ing y gtos'!CD16 -> 5927.5 | AY4: ='Ing y gtos'!CE16 -> 4742 | AZ4: ='Ing y gtos'!CF16 -> 2371 | ... BD4: ='Ing y gtos'!CJ16 -> 35517.58 | BE4: =SUM(AS4:BD4) -> 207530.68
B5: Pagos | C5: ='Ing y gtos'!AE33 -> 0 | D5: ='Ing y gtos'!AF33 -> 0 | E5: ='Ing y gtos'!AG33 -> 2310.58 | F5: ='Ing y gtos'!AH33 -> 836.06 | G5: ='Ing y gtos'!AI33 -> 5019.7136 | H5: ='Ing y gtos'!AJ33 -> 16.5 | I5: ='Ing y gtos'!AK33 -> 350 | J5: ='Ing y gtos'!AL33 -> 2104.36 | ... N5: ='Ing y gtos'!AP33 -> 791.98 | O5: =SUM(C5:N5) -> 15767.024 | P5: ='Ing y gtos'!AU33 -> 705.64 | Q5: ='Ing y gtos'!AV33 -> 2112.36 | R5: ='Ing y gtos'!AW33 -> -2118.78 | S5: ='Ing y gtos'!AX33 -> 1585.65 | T5: ='Ing y gtos'!AY33 -> 2063.23 | U5: ='Ing y gtos'!AZ33 -> -2875.88 | V5: ='Ing y gtos'!BA33 -> 1496.17 | W5: ='Ing y gtos'!BB33 -> 10323 | ... AA5: ='Ing y gtos'!BF33 -> 2493.1 | AB5: =SUM(P5:AA5) -> 10893.02 | AC5: ='Ing y gtos'!BJ33 -> 8.93 | AD5: ='Ing y gtos'!BK33 -> 4924.88 | AE5: ='Ing y gtos'!BL33 -> 1939.36 | AF5: ='Ing y gtos'!BM33 -> 1243.61 | AG5: ='Ing y gtos'!BN33 -> 1931.2 | AH5: ='Ing y gtos'!BO33 -> -1902.68 | AI5: ='Ing y gtos'!BP33 -> 1921.29 | AJ5: ='Ing y gtos'!BQ33 -> 1054.16 | ... AN5: ='Ing y gtos'!BU33 -> 1960 | AO5: =SUM(AC5:AN5) -> 21220.57 | AS5: ='Ing y gtos'!BY33 -> 600 | AT5: ='Ing y gtos'!BZ33 -> 2961.41 | AU5: ='Ing y gtos'!CA33 -> 600 | AV5: ='Ing y gtos'!CB33 -> 900 | AW5: ='Ing y gtos'!CC33 -> 4137.59 | AX5: ='Ing y gtos'!CD33 -> 600 | AY5: ='Ing y gtos'!CE33 -> 1300 | AZ5: ='Ing y gtos'!CF33 -> 1874.56 | ... BD5: ='Ing y gtos'!CJ33 -> 1760 | BE5: =SUM(AS5:BD5) -> 19094.97
B7: Caja Operaciones (mes) | C7: =C4-C5 -> 556.3 | D7: =D4-D5 -> 33077.51 | E7: =E4-E5 -> 48994.74 | F7: =F4-F5 -> -836.06 | G7: =G4-G5 -> 32233.956 | H7: =H4-H5 -> -16.5 | I7: =I4-I5 -> -350 | J7: =J4-J5 -> 22802.84 | ... N7: =N4-N5 -> 16391.69 | P7: =P4-P5 -> 19307.8 | Q7: =Q4-Q5 -> 24836.7 | R7: =R4-R5 -> 2433.78 | S7: =S4-S5 -> 10880.66 | T7: =T4-T5 -> 5926.3 | U7: =U4-U5 -> 2875.88 | V7: =V4-V5 -> 8914.5 | W7: =W4-W5 -> 1311.21 | ... AA7: =AA4-AA5 -> 21842.86 | AC7: =AC4-AC5 -> 8083.9 | AD7: =AD4-AD5 -> 24641.73 | AE7: =AE4-AE5 -> 33567.47 | AF7: =AF4-AF5 -> 4270.62 | AG7: =AG4-AG5 -> 6867.7 | AH7: =AH4-AH5 -> 1902.68 | AI7: =AI4-AI5 -> 5699.14 | AJ7: =AJ4-AJ5 -> -777.77 | ... AN7: =AN4-AN5 -> 26530.25 | AS7: =AS4-AS5 -> 5327.5 | AT7: =AT4-AT5 -> 33321.09 | AU7: =AU4-AU5 -> 20497 | AV7: =AV4-AV5 -> 30511.5 | AW7: =AW4-AW5 -> -2952.09 | AX7: =AX4-AX5 -> 5327.5 | AY7: =AY4-AY5 -> 3442 | AZ7: =AZ4-AZ5 -> 496.44 | ... BD7: =BD4-BD5 -> 33757.58
B8: Caja Operaciones (acum.) | C8: =C7 -> 556.3 | D8: =D7+C8 -> 33633.81 | E8: =E7+D8 -> 82628.55 | F8: =F7+E8 -> 81792.49 | G8: =G7+F8 -> 114026.45 | H8: =H7+G8 -> 114009.95 | I8: =I7+H8 -> 113659.95 | J8: =J7+I8 -> 136462.79 | K8: =K7+J8 -> 168628.59 | ... N8: =N7+M8 -> 202820.08 | O8: =O4-O5 -> 202820.08 | P8: =P7 -> 19307.8 | Q8: =Q7+P8 -> 44144.5 | R8: =R7+Q8 -> 46578.28 | S8: =S7+R8 -> 57458.94 | T8: =T7+S8 -> 63385.24 | U8: =U7+T8 -> 66261.12 | V8: =V7+U8 -> 75175.62 | W8: =W7+V8 -> 76486.83 | X8: =X7+W8 -> 85276.43 | ... AA8: =AA7+Z8 -> 109790.7 | AB8: =AB4-AB5 -> 109790.7 | AC8: =AC7 -> 8083.9 | AD8: =AD7+AC8 -> 32725.63 | AE8: =AE7+AD8 -> 66293.1 | AF8: =AF7+AE8 -> 70563.72 | AG8: =AG7+AF8 -> 77431.42 | AH8: =AH7+AG8 -> 79334.1 | AI8: =AI7+AH8 -> 85033.24 | AJ8: =AJ7+AI8 -> 84255.47 | AK8: =AK7+AJ8 -> 87308.63 | ... AN8: =AN7+AM8 -> 155074.39 | AO8: =AO4-AO5 -> 155074.39 | AS8: =AS7 -> 5327.5 | AT8: =AT7+AS8 -> 38648.59 | AU8: =AU7+AT8 -> 59145.59 | AV8: =AV7+AU8 -> 89657.09 | AW8: =AW7+AV8 -> 86705 | AX8: =AX7+AW8 -> 92032.5 | AY8: =AY7+AX8 -> 95474.5 | AZ8: =AZ7+AY8 -> 95970.94 | BA8: =BA7+AZ8 -> 114338.94 | ... BD8: =BD7+BC8 -> 188435.71 | BE8: =BE4-BE5 -> 188435.71
B9: Porcino
B10: Cobros | C10: ='Ing y gtos'!AE42 -> 4256.95 | D10: ='Ing y gtos'!AF42 -> 280.97 | E10: ='Ing y gtos'!AG42 -> 7918.95 | F10: ='Ing y gtos'!AH42 -> 5851.53 | G10: ='Ing y gtos'!AI42 -> 6817.68 | H10: ='Ing y gtos'!AJ42 -> 1725.36 | I10: ='Ing y gtos'!AK42 -> 2334.57 | J10: ='Ing y gtos'!AL42 -> 34055.67 | ... N10: ='Ing y gtos'!AP42 -> 7039.33 | O10: =SUM(C10:N10) -> 140332.76 | P10: ='Ing y gtos'!AU42 -> 1689.99 | Q10: ='Ing y gtos'!AV42 -> 5922.68 | R10: ='Ing y gtos'!AW42 -> 1825.73 | S10: ='Ing y gtos'!AX42 -> 3923.39 | T10: ='Ing y gtos'!AY42 -> 3567.39 | U10: ='Ing y gtos'!AZ42 -> 20249.95 | V10: ='Ing y gtos'!BA42 -> 18215.37 | W10: ='Ing y gtos'!BB42 -> 53326 | ... AA10: ='Ing y gtos'!BF42 -> 8485.09 | AB10: =SUM(P10:AA10) -> 144911.39 | AC10: ='Ing y gtos'!BJ42 -> 3918.04 | AD10: ='Ing y gtos'!BK42 -> 6447.53 | AE10: ='Ing y gtos'!BL42 -> 4972.37 | AF10: ='Ing y gtos'!BM42 -> 5951.74 | AG10: ='Ing y gtos'!BN42 -> 3440.39 | AH10: ='Ing y gtos'!BO42 -> 31356.42 | AI10: ='Ing y gtos'!BP42 -> 4000.67 | AJ10: ='Ing y gtos'!BQ42 -> 58156.46 | ... AN10: ='Ing y gtos'!BU42 -> 6321.49 | AO10: =SUM(AC10:AN10) -> 142778.8 | AS10: ='Ing y gtos'!BY42 -> 0 | AT10: ='Ing y gtos'!BZ42 -> 0 | AU10: ='Ing y gtos'!CA42 -> 0 | AV10: ='Ing y gtos'!CB42 -> 0 | AW10: ='Ing y gtos'!CC42 -> 0 | AX10: ='Ing y gtos'!CD42 -> 31824 | AY10: ='Ing y gtos'!CE42 -> 63648 | AZ10: ='Ing y gtos'!CF42 -> 31824 | ... BD10: ='Ing y gtos'!CJ42 -> 0 | BE10: =SUM(AS10:BD10) -> 143296
B11: Pagos | C11: ='Ing y gtos'!AE54 -> 0 | D11: ='Ing y gtos'!AF54 -> 2580.26 | E11: ='Ing y gtos'!AG54 -> 4060.27 | F11: ='Ing y gtos'!AH54 -> 5231.09 | G11: ='Ing y gtos'!AI54 -> 6014.37 | H11: ='Ing y gtos'!AJ54 -> 3635.26 | I11: ='Ing y gtos'!AK54 -> 1494.8879 | J11: ='Ing y gtos'!AL54 -> 6161.82 | ... N11: ='Ing y gtos'!AP54 -> 2308.35 | O11: =SUM(C11:N11) -> 50274.578 | P11: ='Ing y gtos'!AU54 -> 1967.14 | Q11: ='Ing y gtos'!AV54 -> 48.39 | R11: ='Ing y gtos'!AW54 -> 4608.29 | S11: ='Ing y gtos'!AX54 -> 3678.43 | T11: ='Ing y gtos'!AY54 -> 4127.2 | U11: ='Ing y gtos'!AZ54 -> 1865.58 | V11: ='Ing y gtos'!BA54 -> 1951.96 | W11: ='Ing y gtos'!BB54 -> 7250.01 | ... AA11: ='Ing y gtos'!BF54 -> 4600.94 | AB11: =SUM(P11:AA11) -> 47961.9 | AC11: ='Ing y gtos'!BJ54 -> 362.52 | AD11: ='Ing y gtos'!BK54 -> 8388.63 | AE11: ='Ing y gtos'!BL54 -> 10129.1 | AF11: ='Ing y gtos'!BM54 -> 9859.88 | AG11: ='Ing y gtos'!BN54 -> 3139.49 | AH11: ='Ing y gtos'!BO54 -> 7828.47 | AI11: ='Ing y gtos'!BP54 -> 6049.99 | AJ11: ='Ing y gtos'!BQ54 -> 6219.26 | ... AN11: ='Ing y gtos'!BU54 -> 1700 | AO11: =SUM(AC11:AN11) -> 67635.44 | AS11: ='Ing y gtos'!BY54 -> 750 | AT11: ='Ing y gtos'!BZ54 -> 250 | AU11: ='Ing y gtos'!CA54 -> 1750 | AV11: ='Ing y gtos'!CB54 -> 750 | AW11: ='Ing y gtos'!CC54 -> 750 | AX11: ='Ing y gtos'!CD54 -> 250 | AY11: ='Ing y gtos'!CE54 -> 250 | AZ11: ='Ing y gtos'!CF54 -> 2250 | ... BD11: ='Ing y gtos'!CJ54 -> 250 | BE11: =SUM(AS11:BD11) -> 8000
B13: Caja Operaciones (mes) | C13: =C10-C11 -> 4256.95 | D13: =D10-D11 -> -2299.29 | E13: =E10-E11 -> 3858.68 | F13: =F10-F11 -> 620.44 | G13: =G10-G11 -> 803.31 | H13: =H10-H11 -> -1909.9 | I13: =I10-I11 -> 839.6821 | J13: =J10-J11 -> 27893.85 | ... N13: =N10-N11 -> 4730.98 | P13: =P10-P11 -> -277.15 | Q13: =Q10-Q11 -> 5874.29 | R13: =R10-R11 -> -2782.56 | S13: =S10-S11 -> 244.96 | T13: =T10-T11 -> -559.81 | U13: =U10-U11 -> 18384.37 | V13: =V10-V11 -> 16263.41 | W13: =W10-W11 -> 46075.99 | ... AA13: =AA10-AA11 -> 3884.15 | AC13: =AC10-AC11 -> 3555.52 | AD13: =AD10-AD11 -> -1941.1 | AE13: =AE10-AE11 -> -5156.73 | AF13: =AF10-AF11 -> -3908.14 | AG13: =AG10-AG11 -> 300.9 | AH13: =AH10-AH11 -> 23527.95 | AI13: =AI10-AI11 -> -2049.32 | AJ13: =AJ10-AJ11 -> 51937.2 | ... AN13: =AN10-AN11 -> 4621.49 | AS13: =AS10-AS11 -> -750 | AT13: =AT10-AT11 -> -250 | AU13: =AU10-AU11 -> -1750 | AV13: =AV10-AV11 -> -750 | AW13: =AW10-AW11 -> -750 | AX13: =AX10-AX11 -> 31574 | AY13: =AY10-AY11 -> 63398 | AZ13: =AZ10-AZ11 -> 29574 | ... BD13: =BD10-BD11 -> -250
B14: Caja Operaciones (acum.) | C14: =C13 -> 4256.95 | D14: =D13+C14 -> 1957.66 | E14: =E13+D14 -> 5816.34 | F14: =F13+E14 -> 6436.78 | G14: =G13+F14 -> 7240.09 | H14: =H13+G14 -> 5330.19 | I14: =I13+H14 -> 6169.8721 | J14: =J13+I14 -> 34063.722 | K14: =K13+J14 -> 75680.282 | ... N14: =N13+M14 -> 90058.182 | O14: =O10-O11 -> 90058.182 | P14: =P13 -> -277.15 | Q14: =Q13+P14 -> 5597.14 | R14: =R13+Q14 -> 2814.58 | S14: =S13+R14 -> 3059.54 | T14: =T13+S14 -> 2499.73 | U14: =U13+T14 -> 20884.1 | V14: =V13+U14 -> 37147.51 | W14: =W13+V14 -> 83223.5 | X14: =X13+W14 -> 92182.93 | ... AA14: =AA13+Z14 -> 96949.49 | AB14: =AB10-AB11 -> 96949.49 | AC14: =AC13 -> 3555.52 | AD14: =AD13+AC14 -> 1614.42 | AE14: =AE13+AD14 -> -3542.31 | AF14: =AF13+AE14 -> -7450.45 | AG14: =AG13+AF14 -> -7149.55 | AH14: =AH13+AG14 -> 16378.4 | AI14: =AI13+AH14 -> 14329.08 | AJ14: =AJ13+AI14 -> 66266.28 | AK14: =AK13+AJ14 -> 64035.35 | ... AN14: =AN13+AM14 -> 75143.36 | AO14: =AO10-AO11 -> 75143.36 | AS14: =AS13 -> -750 | AT14: =AT13+AS14 -> -1000 | AU14: =AU13+AT14 -> -2750 | AV14: =AV13+AU14 -> -3500 | AW14: =AW13+AV14 -> -4250 | AX14: =AX13+AW14 -> 27324 | AY14: =AY13+AX14 -> 90722 | AZ14: =AZ13+AY14 -> 120296 | BA14: =BA13+AZ14 -> 128046 | ... BD14: =BD13+BC14 -> 135296 | BE14: =BE10-BE11 -> 135296
B15: Ovino
B16: Cobros | C16: ='Ing y gtos'!AE65 -> 0 | D16: ='Ing y gtos'!AF65 -> 0 | E16: ='Ing y gtos'!AG65 -> 11902 | F16: ='Ing y gtos'!AH65 -> 0 | G16: ='Ing y gtos'!AI65 -> 2858.9 | H16: ='Ing y gtos'!AJ65 -> 0 | I16: ='Ing y gtos'!AK65 -> 0 | J16: ='Ing y gtos'!AL65 -> 0 | ... N16: ='Ing y gtos'!AP65 -> 0 | O16: =SUM(C16:N16) -> 15735.9 | P16: ='Ing y gtos'!AU61 -> 0 | Q16: ='Ing y gtos'!AV61 -> 0 | R16: ='Ing y gtos'!AW61 -> 0 | S16: ='Ing y gtos'!AX61 -> 0 | T16: ='Ing y gtos'!AY61 -> 180 | U16: ='Ing y gtos'!AZ61 -> 0 | V16: ='Ing y gtos'!BA61 -> 0 | W16: ='Ing y gtos'!BB61 -> 1232 | ... AA16: ='Ing y gtos'!BF61 -> 0 | AB16: =SUM(P16:AA16) -> 1412 | AC16: ='Ing y gtos'!BJ61 -> 0 | AD16: ='Ing y gtos'!BK61 -> 0 | AE16: ='Ing y gtos'!BL61 -> 0 | AF16: ='Ing y gtos'!BM61 -> 365 | AG16: ='Ing y gtos'!BN61 -> 0 | AH16: ='Ing y gtos'!BO61 -> 400 | AI16: ='Ing y gtos'!BP61 -> 0 | AJ16: ='Ing y gtos'!BQ61 -> 1045 | ... AN16: ='Ing y gtos'!BU61 -> 0 | AO16: =SUM(AC16:AN16) -> 1810 | AS16: ='Ing y gtos'!BY61 -> 0 | AT16: ='Ing y gtos'!BZ61 -> 0 | AU16: ='Ing y gtos'!CA61 -> 0 | AV16: ='Ing y gtos'!CB61 -> 0 | AW16: ='Ing y gtos'!CC61 -> 0 | AX16: ='Ing y gtos'!CD61 -> 0 | AY16: ='Ing y gtos'!CE61 -> 0 | AZ16: ='Ing y gtos'!CF61 -> 0 | ... BD16: ='Ing y gtos'!CJ61 -> 0 | BE16: =SUM(AS16:BD16) -> 0
B17: Pagos | C17: ='Ing y gtos'!AE73 -> 0 | D17: ='Ing y gtos'!AF73 -> 0 | E17: ='Ing y gtos'!AG73 -> 363.84 | F17: ='Ing y gtos'!AH73 -> 50.2 | G17: ='Ing y gtos'!AI73 -> 0 | H17: ='Ing y gtos'!AJ73 -> 0 | I17: ='Ing y gtos'!AK73 -> 0 | J17: ='Ing y gtos'!AL73 -> 0 | ... N17: ='Ing y gtos'!AP73 -> 0 | O17: =SUM(C17:N17) -> 430.54 | P17: ='Ing y gtos'!AU73 -> 0 | Q17: ='Ing y gtos'!AV73 -> 0 | R17: ='Ing y gtos'!AW73 -> 0 | S17: ='Ing y gtos'!AX73 -> 0 | T17: ='Ing y gtos'!AY73 -> 57.2 | U17: ='Ing y gtos'!AZ73 -> 0 | V17: ='Ing y gtos'!BA73 -> 0 | W17: ='Ing y gtos'!BB73 -> 0 | ... AA17: ='Ing y gtos'!BF73 -> 94.6 | AB17: =SUM(P17:AA17) -> 271.8 | AC17: ='Ing y gtos'!BJ73 -> 0 | AD17: ='Ing y gtos'!BK73 -> 0 | AE17: ='Ing y gtos'!BL73 -> 0 | AF17: ='Ing y gtos'!BM73 -> 0 | AG17: ='Ing y gtos'!BN73 -> 0 | AH17: ='Ing y gtos'!BO73 -> 0 | AI17: ='Ing y gtos'!BP73 -> 0 | AJ17: ='Ing y gtos'!BQ73 -> 0 | ... AN17: ='Ing y gtos'!BU73 -> 0 | AO17: =SUM(AC17:AN17) -> 0 | AS17: ='Ing y gtos'!BY73 -> 0 | AT17: ='Ing y gtos'!BZ73 -> 0 | AU17: ='Ing y gtos'!CA73 -> 0 | AV17: ='Ing y gtos'!CB73 -> 0 | AW17: ='Ing y gtos'!CC73 -> 0 | AX17: ='Ing y gtos'!CD73 -> 0 | AY17: ='Ing y gtos'!CE73 -> 0 | AZ17: ='Ing y gtos'!CF73 -> 0 | ... BD17: ='Ing y gtos'!CJ73 -> 0 | BE17: =SUM(AS17:BD17) -> 0
B19: Caja Operaciones (mes) | C19: =C16-C17 -> 0 | D19: =D16-D17 -> 0 | E19: =E16-E17 -> 11538.16 | F19: =F16-F17 -> -50.2 | G19: =G16-G17 -> 2858.9 | H19: =H16-H17 -> 0 | I19: =I16-I17 -> 0 | J19: =J16-J17 -> 0 | ... N19: =N16-N17 -> 0 | P19: =P16-P17 -> 0 | Q19: =Q16-Q17 -> 0 | R19: =R16-R17 -> 0 | S19: =S16-S17 -> 0 | T19: =T16-T17 -> 122.8 | U19: =U16-U17 -> 0 | V19: =V16-V17 -> 0 | W19: =W16-W17 -> 1232 | ... AA19: =AA16-AA17 -> -94.6 | AC19: =AC16-AC17 -> 0 | AD19: =AD16-AD17 -> 0 | AE19: =AE16-AE17 -> 0 | AF19: =AF16-AF17 -> 365 | AG19: =AG16-AG17 -> 0 | AH19: =AH16-AH17 -> 400 | AI19: =AI16-AI17 -> 0 | AJ19: =AJ16-AJ17 -> 1045 | ... AN19: =AN16-AN17 -> 0 | AS19: =AS16-AS17 -> 0 | AT19: =AT16-AT17 -> 0 | AU19: =AU16-AU17 -> 0 | AV19: =AV16-AV17 -> 0 | AW19: =AW16-AW17 -> 0 | AX19: =AX16-AX17 -> 0 | AY19: =AY16-AY17 -> 0 | AZ19: =AZ16-AZ17 -> 0 | ... BD19: =BD16-BD17 -> 0
B20: Caja Operaciones (acum.) | C20: =C19 -> 0 | D20: =D19+C20 -> 0 | E20: =E19+D20 -> 11538.16 | F20: =F19+E20 -> 11487.96 | G20: =G19+F20 -> 14346.86 | H20: =H19+G20 -> 14346.86 | I20: =I19+H20 -> 14346.86 | J20: =J19+I20 -> 14346.86 | K20: =K19+J20 -> 14405.36 | ... N20: =N19+M20 -> 15305.36 | O20: =O16-O17 -> 15305.36 | P20: =P19 -> 0 | Q20: =Q19+P20 -> 0 | R20: =R19+Q20 -> 0 | S20: =S19+R20 -> 0 | T20: =T19+S20 -> 122.8 | U20: =U19+T20 -> 122.8 | V20: =V19+U20 -> 122.8 | W20: =W19+V20 -> 1354.8 | X20: =X19+W20 -> 1354.8 | ... AA20: =AA19+Z20 -> 1140.2 | AB20: =AB16-AB17 -> 1140.2 | AC20: =AC19 -> 0 | AD20: =AD19+AC20 -> 0 | AE20: =AE19+AD20 -> 0 | AF20: =AF19+AE20 -> 365 | AG20: =AG19+AF20 -> 365 | AH20: =AH19+AG20 -> 765 | AI20: =AI19+AH20 -> 765 | AJ20: =AJ19+AI20 -> 1810 | AK20: =AK19+AJ20 -> 1810 | ... AN20: =AN19+AM20 -> 1810 | AO20: =AO16-AO17 -> 1810 | AS20: =AS19 -> 0 | AT20: =AT19+AS20 -> 0 | AU20: =AU19+AT20 -> 0 | AV20: =AV19+AU20 -> 0 | AW20: =AW19+AV20 -> 0 | AX20: =AX19+AW20 -> 0 | AY20: =AY19+AX20 -> 0 | AZ20: =AZ19+AY20 -> 0 | BA20: =BA19+AZ20 -> 0 | ... BD20: =BD19+BC20 -> 0 | BE20: =BE16-BE17 -> 0
B21: Gastos generales
B22: Act. Ganadera | C22: =-'Ing y gtos'!AE121 -> -9552.36 | D22: =-'Ing y gtos'!AF121 -> -12097.36 | E22: =-'Ing y gtos'!AG121 -> -10574.68 | F22: =-'Ing y gtos'!AH121 -> -48375.95 | G22: =-'Ing y gtos'!AI121 -> -30644.988 | H22: =-'Ing y gtos'!AJ121 -> -7833.02 | I22: =-'Ing y gtos'!AK121 -> -9105.27 | J22: =-'Ing y gtos'!AL121 -> -10847.08 | ... N22: =-'Ing y gtos'!AP121 -> -91075.87 | O22: =SUM(C22:N22) -> -287843.97 | P22: =-'Ing y gtos'!AU121 -> -6343.13 | Q22: =-'Ing y gtos'!AV121 -> -23399.14 | R22: =-'Ing y gtos'!AW121 -> -41914.55 | S22: =-'Ing y gtos'!AX121 -> -25865.78 | T22: =-'Ing y gtos'!AY121 -> -27367.23 | U22: =-'Ing y gtos'!AZ121 -> -18293.24 | V22: =-'Ing y gtos'!BA121 -> -16871.13 | W22: =-'Ing y gtos'!BB121 -> -31497.31 | ... AA22: =-'Ing y gtos'!BF121 -> -15563.83 | AB22: =SUM(P22:AA22) -> -242893.59 | AC22: =-'Ing y gtos'!BJ121 -> -48879.29 | AD22: =-'Ing y gtos'!BK121 -> -29541.51 | AE22: =-'Ing y gtos'!BL121 -> -31309.26 | AF22: =-'Ing y gtos'!BM121 -> -26855.13 | AG22: =-'Ing y gtos'!BN121 -> -19974.99 | AH22: =-'Ing y gtos'!BO121 -> -15936.72 | AI22: =-'Ing y gtos'!BP121 -> -26195.73 | AJ22: =-'Ing y gtos'!BQ121 -> -8667.63 | ... AN22: =-'Ing y gtos'!BU121 -> -11996.58 | AO22: =SUM(AC22:AN22) -> -291033.99 | AS22: =-'Ing y gtos'!BY121 -> -48628.77 | AT22: =-'Ing y gtos'!BZ121 -> -22319.89 | AU22: =-'Ing y gtos'!CA121 -> -23747.79 | AV22: =-'Ing y gtos'!CB121 -> -33267.47 | AW22: =-'Ing y gtos'!CC121 -> -13804.79 | AX22: =-'Ing y gtos'!CD121 -> -12246.45 | AY22: =-'Ing y gtos'!CE121 -> -13303.84 | AZ22: =-'Ing y gtos'!CF121 -> -13711.51 | ... BD22: =-'Ing y gtos'!CJ121 -> -18763.07 | BE22: =SUM(AS22:BD22) -> -265853.09
B24: Caja Operaciones (mes) | C24: =C22 -> -9552.36 | D24: =D22 -> -12097.36 | E24: =E22 -> -10574.68 | F24: =F22 -> -48375.95 | G24: =G22 -> -30644.988 | H24: =H22 -> -7833.02 | I24: =I22 -> -9105.27 | J24: =J22 -> -10847.08 | ... N24: =N22 -> -91075.87 | P24: =P22 -> -6343.13 | Q24: =Q22 -> -23399.14 | R24: =R22 -> -41914.55 | S24: =S22 -> -25865.78 | T24: =T22 -> -27367.23 | U24: =U22 -> -18293.24 | V24: =V22 -> -16871.13 | W24: =W22 -> -31497.31 | ... AA24: =AA22 -> -15563.83 | AC24: =AC22 -> -48879.29 | AD24: =AD22 -> -29541.51 | AE24: =AE22 -> -31309.26 | AF24: =AF22 -> -26855.13 | AG24: =AG22 -> -19974.99 | AH24: =AH22 -> -15936.72 | AI24: =AI22 -> -26195.73 | AJ24: =AJ22 -> -8667.63 | ... AN24: =AN22 -> -11996.58 | AS24: =AS22 -> -48628.77 | AT24: =AT22 -> -22319.89 | AU24: =AU22 -> -23747.79 | AV24: =AV22 -> -33267.47 | AW24: =AW22 -> -13804.79 | AX24: =AX22 -> -12246.45 | AY24: =AY22 -> -13303.84 | AZ24: =AZ22 -> -13711.51 | ... BD24: =BD22 -> -18763.07
B25: Caja Inversiones (acum.) | C25: =C24 -> -9552.36 | D25: =D24+C25 -> -21649.72 | E25: =E24+D25 -> -32224.4 | F25: =F24+E25 -> -80600.35 | G25: =G24+F25 -> -111245.34 | H25: =H24+G25 -> -119078.36 | I25: =I24+H25 -> -128183.63 | J25: =J24+I25 -> -139030.71 | K25: =K24+J25 -> -153621.36 | ... N25: =N24+M25 -> -287843.97 | O25: =SUM(O22:O23) -> -287843.97 | P25: =P24 -> -6343.13 | Q25: =Q24+P25 -> -29742.27 | R25: =R24+Q25 -> -71656.82 | S25: =S24+R25 -> -97522.6 | T25: =T24+S25 -> -124889.83 | U25: =U24+T25 -> -143183.07 | V25: =V24+U25 -> -160054.2 | W25: =W24+V25 -> -191551.51 | X25: =X24+W25 -> -204786.95 | ... AA25: =AA24+Z25 -> -242893.59 | AB25: =SUM(AB22:AB23) -> -242893.59 | AC25: =AC24 -> -48879.29 | AD25: =AD24+AC25 -> -78420.8 | AE25: =AE24+AD25 -> -109730.06 | AF25: =AF24+AE25 -> -136585.19 | AG25: =AG24+AF25 -> -156560.18 | AH25: =AH24+AG25 -> -172496.9 | AI25: =AI24+AH25 -> -198692.63 | AJ25: =AJ24+AI25 -> -207360.26 | AK25: =AK24+AJ25 -> -237734.78 | ... AN25: =AN24+AM25 -> -291033.99 | AO25: =SUM(AO22:AO23) -> -291033.99 | AS25: =AS24 -> -48628.77 | AT25: =AT24+AS25 -> -70948.66 | AU25: =AU24+AT25 -> -94696.45 | AV25: =AV24+AU25 -> -127963.92 | AW25: =AW24+AV25 -> -141768.71 | AX25: =AX24+AW25 -> -154015.16 | AY25: =AY24+AX25 -> -167319 | AZ25: =AZ24+AY25 -> -181030.51 | BA25: =BA24+AZ25 -> -208100.84 | ... BD25: =BD24+BC25 -> -265853.09 | BE25: =SUM(BE22:BE23) -> -265853.09
B26: Inversiones
B27: Act. Ganadera | C27: =-SUM('Ing y gtos'!AE131:AE136) -> 0 | D27: =-SUM('Ing y gtos'!AF131:AF136) -> 0 | E27: =-SUM('Ing y gtos'!AG131:AG136) -> 0 | F27: =-SUM('Ing y gtos'!AH131:AH136) -> 0 | G27: =-SUM('Ing y gtos'!AI131:AI136) -> -544.5 | H27: =-SUM('Ing y gtos'!AJ131:AJ136) -> -10393.93 | I27: =-SUM('Ing y gtos'!AK131:AK136) -> 0 | J27: =-SUM('Ing y gtos'!AL131:AL136) -> -1739.155 | ... N27: =-SUM('Ing y gtos'!AP131:AP136) -> 0 | O27: =SUM(C27:N27) -> -16790.485 | P27: =-SUM('Ing y gtos'!AU131:AU136) -> 0 | Q27: =-SUM('Ing y gtos'!AV131:AV136) -> 0 | R27: =-SUM('Ing y gtos'!AW131:AW136) -> 2750 | S27: =-SUM('Ing y gtos'!AX131:AX136) -> 0 | T27: =-SUM('Ing y gtos'!AY131:AY136) -> 375.5 | U27: =-SUM('Ing y gtos'!AZ131:AZ136) -> 1620 | V27: =-SUM('Ing y gtos'!BA131:BA136) -> 0 | W27: =-SUM('Ing y gtos'!BB131:BB136) -> 0 | ... AA27: =-SUM('Ing y gtos'!BF131:BF136) -> 0 | AB27: =SUM(P27:AA27) -> 3677.02 | AC27: =-SUM('Ing y gtos'!BJ131:BJ136) -> 0 | AD27: =-SUM('Ing y gtos'!BK131:BK136) -> 2475 | AE27: =-SUM('Ing y gtos'!BL131:BL136) -> 0 | AF27: =-SUM('Ing y gtos'!BM131:BM136) -> 0 | AG27: =-SUM('Ing y gtos'!BN131:BN136) -> 0 | AH27: =-SUM('Ing y gtos'!BO131:BO136) -> 0 | AI27: =-SUM('Ing y gtos'!BP131:BP136) -> 0 | AJ27: =-SUM('Ing y gtos'!BQ131:BQ136) -> 0 | ... AN27: =-SUM('Ing y gtos'!BU131:BU136) -> 0 | AO27: =SUM(AC27:AN27) -> 2475 | AS27: =-SUM('Ing y gtos'!BY131:BY136) -> 0 | AT27: =-SUM('Ing y gtos'!BZ131:BZ136) -> 0 | AU27: =-SUM('Ing y gtos'!CA131:CA136) -> 0 | AV27: =-SUM('Ing y gtos'!CB131:CB136) -> 0 | AW27: =-SUM('Ing y gtos'!CC131:CC136) -> 0 | AX27: =-SUM('Ing y gtos'!CD131:CD136) -> 0 | AY27: =-SUM('Ing y gtos'!CE131:CE136) -> 0 | AZ27: =-SUM('Ing y gtos'!CF131:CF136) -> 0 | ... BD27: =-SUM('Ing y gtos'!CJ131:CJ136) -> 0 | BE27: =SUM(AS27:BD27) -> 0
B29: Caja Inversiones (mes) | C29: =C27 -> 0 | D29: =D27 -> 0 | E29: =E27 -> 0 | F29: =F27 -> 0 | G29: =G27 -> -544.5 | H29: =H27 -> -10393.93 | I29: =I27 -> 0 | J29: =J27 -> -1739.155 | ... N29: =N27 -> 0 | P29: =P27 -> 0 | Q29: =Q27 -> 0 | R29: =R27 -> 2750 | S29: =S27 -> 0 | T29: =T27 -> 375.5 | U29: =U27 -> 1620 | V29: =V27 -> 0 | W29: =W27 -> 0 | ... AA29: =AA27 -> 0 | AC29: =AC27 -> 0 | AD29: =AD27 -> 2475 | AE29: =AE27 -> 0 | AF29: =AF27 -> 0 | AG29: =AG27 -> 0 | AH29: =AH27 -> 0 | AI29: =AI27 -> 0 | AJ29: =AJ27 -> 0 | ... AN29: =AN27 -> 0 | AS29: =AS27 -> 0 | AT29: =AT27 -> 0 | AU29: =AU27 -> 0 | AV29: =AV27 -> 0 | AW29: =AW27 -> 0 | AX29: =AX27 -> 0 | AY29: =AY27 -> 0 | AZ29: =AZ27 -> 0 | ... BD29: =BD27 -> 0
B30: Caja Inversiones (acum.) | C30: =C29 -> 0 | D30: =D29+C30 -> 0 | E30: =E29+D30 -> 0 | F30: =F29+E30 -> 0 | G30: =G29+F30 -> -544.5 | H30: =H29+G30 -> -10938.43 | I30: =I29+H30 -> -10938.43 | J30: =J29+I30 -> -12677.585 | K30: =K29+J30 -> -16790.485 | ... N30: =N29+M30 -> -16790.485 | O30: =SUM(O27:O28) -> -16790.485 | P30: =N27 -> 0 | Q30: =Q29+P30 -> 0 | R30: =R29+Q30 -> 2750 | S30: =S29+R30 -> 2750 | T30: =T29+S30 -> 3125.5 | U30: =U29+T30 -> 4745.5 | V30: =V29+U30 -> 4745.5 | W30: =W29+V30 -> 4745.5 | X30: =X29+W30 -> 1077.02 | ... AA30: =AA29+Z30 -> 3677.02 | AB30: =SUM(AB27:AB28) -> 3677.02 | AC30: =AA27 -> 0 | AD30: =AD29+AC30 -> 2475 | AE30: =AE29+AD30 -> 2475 | AF30: =AF29+AE30 -> 2475 | AG30: =AG29+AF30 -> 2475 | AH30: =AH29+AG30 -> 2475 | AI30: =AI29+AH30 -> 2475 | AJ30: =AJ29+AI30 -> 2475 | AK30: =AK29+AJ30 -> 2475 | ... AN30: =AN29+AM30 -> 2475 | AO30: =SUM(AO27:AO28) -> 2475 | AS30: =AQ27 -> 0 | AT30: =AT29+AS30 -> 0 | AU30: =AU29+AT30 -> 0 | AV30: =AV29+AU30 -> 0 | AW30: =AW29+AV30 -> 0 | AX30: =AX29+AW30 -> 0 | AY30: =AY29+AX30 -> 0 | AZ30: =AZ29+AY30 -> 0 | BA30: =BA29+AZ30 -> 0 | ... BD30: =BD29+BC30 -> 0 | BE30: =SUM(BE27:BE28) -> 0
B31: Financiación | C31: ='Ing y gtos'!AE147+'Ing y gtos'!AE150+'Ing y gtos'!AE153 -> 5000 | D31: ='Ing y gtos'!AF147+'Ing y gtos'!AF150+'Ing y gtos'!AF153 -> 9000 | E31: ='Ing y gtos'!AG147+'Ing y gtos'!AG150+'Ing y gtos'!AG153 -> 0 | F31: ='Ing y gtos'!AH147+'Ing y gtos'!AH150+'Ing y gtos'!AH153 -> 0 | G31: ='Ing y gtos'!AI147+'Ing y gtos'!AI150+'Ing y gtos'!AI153 -> 0 | H31: ='Ing y gtos'!AJ147+'Ing y gtos'!AJ150+'Ing y gtos'!AJ153 -> 0 | I31: ='Ing y gtos'!AK147+'Ing y gtos'!AK150+'Ing y gtos'!AK153 -> 0 | J31: ='Ing y gtos'!AL147+'Ing y gtos'!AL150+'Ing y gtos'!AL153 -> 0 | ... N31: ='Ing y gtos'!AP147+'Ing y gtos'!AP150+'Ing y gtos'!AP153 -> 0 | O31: =SUM(C31:N31) -> 14000 | P31: ='Ing y gtos'!AU147+'Ing y gtos'!AU150+'Ing y gtos'!AU153 -> 0 | Q31: ='Ing y gtos'!AV147+'Ing y gtos'!AV150+'Ing y gtos'!AV153 -> 0 | R31: ='Ing y gtos'!AW147+'Ing y gtos'!AW150+'Ing y gtos'!AW153 -> 10000 | S31: ='Ing y gtos'!AX147+'Ing y gtos'!AX150+'Ing y gtos'!AX153 -> 21000 | T31: ='Ing y gtos'!AY147+'Ing y gtos'!AY150+'Ing y gtos'!AY153 -> 15000 | U31: ='Ing y gtos'!AZ147+'Ing y gtos'!AZ150+'Ing y gtos'!AZ153 -> 13500 | V31: ='Ing y gtos'!BA147+'Ing y gtos'!BA150+'Ing y gtos'!BA153 -> 0 | W31: ='Ing y gtos'!BB147+'Ing y gtos'!BB150+'Ing y gtos'!BB153 -> -10000 | X31: ='Ing y gtos'!BC147+'Ing y gtos'!BC150+'Ing y gtos'!BC153 -> -15000 | Y31: ='Ing y gtos'!BD141+'Ing y gtos'!BD147+'Ing y gtos'!BD150+'Ing y gtos'!BD153 -> 915 | Z31: ='Ing y gtos'!BE141+'Ing y gtos'!BE147+'Ing y gtos'!BE150+'Ing y gtos'!BE153 -> 0 | AA31: ='Ing y gtos'!BF141+'Ing y gtos'!BF147+'Ing y gtos'!BF150+'Ing y gtos'!BF153 -> 12000 | AB31: =SUM(P31:AA31) -> 47415 | AC31: ='Ing y gtos'!BJ141+'Ing y gtos'!BJ147+'Ing y gtos'!BJ150+'Ing y gtos'!BJ153 -> 5350 | AD31: ='Ing y gtos'!BK141+'Ing y gtos'!BK147+'Ing y gtos'!BK150+'Ing y gtos'!BK153 -> 33000 | AE31: ='Ing y gtos'!BL141+'Ing y gtos'!BL147+'Ing y gtos'!BL150+'Ing y gtos'!BL153 -> 250 | AF31: ='Ing y gtos'!BM141+'Ing y gtos'!BM147+'Ing y gtos'!BM150+'Ing y gtos'!BM153 -> 595 | AG31: ='Ing y gtos'!BN141+'Ing y gtos'!BN147+'Ing y gtos'!BN150+'Ing y gtos'!BN153 -> 12000 | AH31: ='Ing y gtos'!BO141+'Ing y gtos'!BO147+'Ing y gtos'!BO150+'Ing y gtos'!BO153 -> 5000 | AI31: ='Ing y gtos'!BP141+'Ing y gtos'!BP147+'Ing y gtos'!BP150+'Ing y gtos'!BP153 -> 12150 | AJ31: ='Ing y gtos'!BQ141+'Ing y gtos'!BQ147+'Ing y gtos'!BQ150+'Ing y gtos'!BQ153 -> -21405 | ... AN31: ='Ing y gtos'!BU141+'Ing y gtos'!BU147+'Ing y gtos'!BU150+'Ing y gtos'!BU153 -> 0 | AO31: =SUM(AC31:AN31) -> 49085 | AS31: ='Ing y gtos'!BY147+'Ing y gtos'!BY150+'Ing y gtos'!BY153 -> 20000 | AT31: ='Ing y gtos'!BZ147+'Ing y gtos'!BZ150+'Ing y gtos'!BZ153 -> 0 | AU31: ='Ing y gtos'!CA147+'Ing y gtos'!CA150+'Ing y gtos'!CA153 -> 0 | AV31: ='Ing y gtos'!CB147+'Ing y gtos'!CB150+'Ing y gtos'!CB153 -> 0 | AW31: ='Ing y gtos'!CC147+'Ing y gtos'!CC150+'Ing y gtos'!CC153 -> 25000 | AX31: ='Ing y gtos'!CD147+'Ing y gtos'!CD150+'Ing y gtos'!CD153 -> 0 | AY31: ='Ing y gtos'!CE147+'Ing y gtos'!CE150+'Ing y gtos'!CE153 -> -25000 | AZ31: ='Ing y gtos'!CF147+'Ing y gtos'!CF150+'Ing y gtos'!CF153 -> 0 | ... BD31: ='Ing y gtos'!CJ147+'Ing y gtos'!CJ150+'Ing y gtos'!CJ153 -> 0 | BE31: =SUM(AS31:BD31) -> -57000
B33: Caja Financiación (mes) | C33: =C31 -> 5000 | D33: =D31 -> 9000 | E33: =E31 -> 0 | F33: =F31 -> 0 | G33: =G31 -> 0 | H33: =H31 -> 0 | I33: =I31 -> 0 | J33: =J31 -> 0 | ... N33: =N31 -> 0 | P33: =P31 -> 0 | Q33: =Q31 -> 0 | R33: =R31 -> 10000 | S33: =S31 -> 21000 | T33: =T31 -> 15000 | U33: =U31 -> 13500 | V33: =V31 -> 0 | W33: =W31 -> -10000 | ... AA33: =AA31 -> 12000 | AC33: =AC31 -> 5350 | AD33: =AD31 -> 33000 | AE33: =AE31 -> 250 | AF33: =AF31 -> 595 | AG33: =AG31 -> 12000 | AH33: =AH31 -> 5000 | AI33: =AI31 -> 12150 | AJ33: =AJ31 -> -21405 | ... AN33: =AN31 -> 0 | AS33: =AS31 -> 20000 | AT33: =AT31 -> 0 | AU33: =AU31 -> 0 | AV33: =AV31 -> 0 | AW33: =AW31 -> 25000 | AX33: =AX31 -> 0 | AY33: =AY31 -> -25000 | AZ33: =AZ31 -> 0 | ... BD33: =BD31 -> 0
B34: Caja Financiación (acum.) | C34: =C33 -> 5000 | D34: =D33+C34 -> 14000 | E34: =E33+D34 -> 14000 | F34: =F33+E34 -> 14000 | G34: =G33+F34 -> 14000 | H34: =H33+G34 -> 14000 | I34: =I33+H34 -> 14000 | J34: =J33+I34 -> 14000 | K34: =K33+J34 -> 14000 | ... N34: =N33+M34 -> 14000 | O34: =SUM(O31:O32) -> 14000 | P34: =P33 -> 0 | Q34: =Q33+P34 -> 0 | R34: =R33+Q34 -> 10000 | S34: =S33+R34 -> 31000 | T34: =T33+S34 -> 46000 | U34: =U33+T34 -> 59500 | V34: =V33+U34 -> 59500 | W34: =W33+V34 -> 49500 | X34: =X33+W34 -> 34500 | ... AA34: =AA33+Z34 -> 47415 | AB34: =SUM(AB31:AB32) -> 47415 | AC34: =AC33 -> 5350 | AD34: =AD33+AC34 -> 38350 | AE34: =AE33+AD34 -> 38600 | AF34: =AF33+AE34 -> 39195 | AG34: =AG33+AF34 -> 51195 | AH34: =AH33+AG34 -> 56195 | AI34: =AI33+AH34 -> 68345 | AJ34: =AJ33+AI34 -> 46940 | AK34: =AK33+AJ34 -> 48940 | ... AN34: =AN33+AM34 -> 49085 | AO34: =SUM(AO31:AO32) -> 49085 | AS34: =AS33 -> 20000 | AT34: =AT33+AS34 -> 20000 | AU34: =AU33+AT34 -> 20000 | AV34: =AV33+AU34 -> 20000 | AW34: =AW33+AV34 -> 45000 | AX34: =AX33+AW34 -> 45000 | AY34: =AY33+AX34 -> 20000 | AZ34: =AZ33+AY34 -> 20000 | BA34: =BA33+AZ34 -> -2000 | ... BD34: =BD33+BC34 -> -57000 | BE34: =SUM(BE31:BE32) -> -57000
B36: Caja opex, capex y serv. deuda | C36: =C7+C13+C19+C24+C29+C33 -> 260.89 | D36: =D7+D13+D19+D24+D29+D33 -> 27680.86 | E36: =E7+E13+E19+E24+E29+E33 -> 53816.9 | F36: =F7+F13+F19+F24+F29+F33 -> -48641.77 | G36: =G7+G13+G19+G24+G29+G33 -> 4706.6782 | H36: =H7+H13+H19+H24+H29+H33 -> -20153.35 | I36: =I7+I13+I19+I24+I29+I33 -> -8615.5879 | J36: =J7+J13+J19+J24+J29+J33 -> 38110.455 | ... N36: =N7+N13+N19+N24+N29+N33 -> -69953.2 | O36: =SUM(O8,O14,O20,O25,O30,O34) -> 17549.165 | P36: =P7+P13+P19+P24+P29+P33 -> 12687.52 | Q36: =Q7+Q13+Q19+Q24+Q29+Q33 -> 7311.85 | R36: =R7+R13+R19+R24+R29+R33 -> -29513.33 | S36: =S7+S13+S19+S24+S29+S33 -> 6259.84 | T36: =T7+T13+T19+T24+T29+T33 -> -6502.44 | U36: =U7+U13+U19+U24+U29+U33 -> 18087.01 | V36: =V7+V13+V19+V24+V29+V33 -> 8306.78 | W36: =W7+W13+W19+W24+W29+W33 -> 7121.89 | ... AA36: =AA7+AA13+AA19+AA24+AA29+AA33 -> 22068.58 | AB36: =SUM(AB8,AB14,AB20,AB25,AB30,AB34) -> 16078.82 | AC36: =AC7+AC13+AC19+AC24+AC29+AC33 -> -31889.87 | AD36: =AD7+AD13+AD19+AD24+AD29+AD33 -> 28634.12 | AE36: =AE7+AE13+AE19+AE24+AE29+AE33 -> -2648.52 | AF36: =AF7+AF13+AF19+AF24+AF29+AF33 -> -25532.65 | AG36: =AG7+AG13+AG19+AG24+AG29+AG33 -> -806.39 | AH36: =AH7+AH13+AH19+AH24+AH29+AH33 -> 14893.91 | AI36: =AI7+AI13+AI19+AI24+AI29+AI33 -> -10395.91 | AJ36: =AJ7+AJ13+AJ19+AJ24+AJ29+AJ33 -> 22131.8 | ... AN36: =AN7+AN13+AN19+AN24+AN29+AN33 -> 19155.16 | AO36: =SUM(AO8,AO14,AO20,AO25,AO30,AO34) -> -7446.24 | AS36: =AS7+AS13+AS19+AS24+AS29+AS33 -> -24051.27 | AT36: =AT7+AT13+AT19+AT24+AT29+AT33 -> 10751.2 | AU36: =AU7+AU13+AU19+AU24+AU29+AU33 -> -5000.79 | AV36: =AV7+AV13+AV19+AV24+AV29+AV33 -> -3505.97 | AW36: =AW7+AW13+AW19+AW24+AW29+AW33 -> 7493.12 | AX36: =AX7+AX13+AX19+AX24+AX29+AX33 -> 24655.05 | AY36: =AY7+AY13+AY19+AY24+AY29+AY33 -> 28536.16 | AZ36: =AZ7+AZ13+AZ19+AZ24+AZ29+AZ33 -> 16358.93 | ... BD36: =BD7+BD13+BD19+BD24+BD29+BD33 -> 14744.51 | BE36: =SUM(BE8,BE14,BE20,BE25,BE30,BE34) -> 878.62
B37: Check | O37: =SUM(C36:N36)-O36 -> 0 | AB37: =SUM(P36:AA36)-AB36 -> 1.6370905e-11 | AO37: =SUM(AC36:AN36)-AO36 -> 4.3655746e-11 | BE37: =SUM(AS36:BD36)-BE36 -> 4.3655746e-11
B38: Total circulante
B40: Caja consolidada (mes) | C40: =C7+C13+C19+C24+C29+C33 -> 260.89 | D40: =D7+D13+D19+D24+D29+D33 -> 27680.86 | E40: =E7+E13+E19+E24+E29+E33 -> 53816.9 | F40: =F7+F13+F19+F24+F29+F33 -> -48641.77 | G40: =G7+G13+G19+G24+G29+G33 -> 4706.6782 | H40: =H7+H13+H19+H24+H29+H33 -> -20153.35 | I40: =I7+I13+I19+I24+I29+I33 -> -8615.5879 | J40: =J7+J13+J19+J24+J29+J33 -> 38110.455 | ... N40: =N7+N13+N19+N24+N29+N33 -> -69953.2 | P40: =P7+P13+P19+P24+P29+P33 -> 12687.52 | Q40: =Q7+Q13+Q19+Q24+Q29+Q33 -> 7311.85 | R40: =R7+R13+R19+R24+R29+R33 -> -29513.33 | S40: =S7+S13+S19+S24+S29+S33 -> 6259.84 | T40: =T7+T13+T19+T24+T29+T33 -> -6502.44 | U40: =U7+U13+U19+U24+U29+U33 -> 18087.01 | V40: =V7+V13+V19+V24+V29+V33 -> 8306.78 | W40: =W7+W13+W19+W24+W29+W33 -> 7121.89 | ... AA40: =AA7+AA13+AA19+AA24+AA29+AA33 -> 22068.58 | AC40: =AC7+AC13+AC19+AC24+AC29+AC33 -> -31889.87 | AD40: =AD7+AD13+AD19+AD24+AD29+AD33 -> 28634.12 | AE40: =AE7+AE13+AE19+AE24+AE29+AE33 -> -2648.52 | AF40: =AF7+AF13+AF19+AF24+AF29+AF33 -> -25532.65 | AG40: =AG7+AG13+AG19+AG24+AG29+AG33 -> -806.39 | AH40: =AH7+AH13+AH19+AH24+AH29+AH33 -> 14893.91 | AI40: =AI7+AI13+AI19+AI24+AI29+AI33 -> -10395.91 | AJ40: =AJ7+AJ13+AJ19+AJ24+AJ29+AJ33 -> 22131.8 | ... AN40: =AN7+AN13+AN19+AN24+AN29+AN33 -> 19155.16 | AS40: =AS7+AS13+AS19+AS24+AS29+AS33 -> -24051.27 | AT40: =AT7+AT13+AT19+AT24+AT29+AT33 -> 10751.2 | AU40: =AU7+AU13+AU19+AU24+AU29+AU33 -> -5000.79 | AV40: =AV7+AV13+AV19+AV24+AV29+AV33 -> -3505.97 | AW40: =AW7+AW13+AW19+AW24+AW29+AW33 -> 7493.12 | AX40: =AX7+AX13+AX19+AX24+AX29+AX33 -> 24655.05 | AY40: =AY7+AY13+AY19+AY24+AY29+AY33 -> 28536.16 | AZ40: =AZ7+AZ13+AZ19+AZ24+AZ29+AZ33 -> 16358.93 | ... BD40: =BD7+BD13+BD19+BD24+BD29+BD33 -> 14744.51
B41: Caja consolidada (acumulada) | C41: =C40 -> 260.89 | D41: =D40+C41 -> 27941.75 | E41: =E40+D41 -> 81758.65 | F41: =F40+E41 -> 33116.88 | G41: =G40+F41 -> 37823.558 | H41: =H40+G41 -> 17670.208 | I41: =I40+H41 -> 9054.6203 | J41: =J40+I41 -> 47165.075 | K41: =K40+J41 -> 102302.39 | ... N41: =N40+M41 -> 17549.165 | P41: =P40 -> 12687.52 | Q41: =Q40+P41 -> 19999.37 | R41: =R40+Q41 -> -9513.96 | S41: =S40+R41 -> -3254.12 | T41: =T40+S41 -> -9756.56 | U41: =U40+T41 -> 8330.45 | V41: =V40+U41 -> 16637.23 | W41: =W40+V41 -> 23759.12 | X41: =X40+W41 -> 9604.23 | ... AA41: =AA40+Z41 -> 16078.82 | AC41: =AC40 -> -31889.87 | AD41: =AD40+AC41 -> -3255.75 | AE41: =AE40+AD41 -> -5904.27 | AF41: =AF40+AE41 -> -31436.92 | AG41: =AG40+AF41 -> -32243.31 | AH41: =AH40+AG41 -> -17349.4 | AI41: =AI40+AH41 -> -27745.31 | AJ41: =AJ40+AI41 -> -5613.51 | AK41: =AK40+AJ41 -> -33165.8 | ... AN41: =AN40+AM41 -> -7446.24 | AS41: =AS40 -> -24051.27 | AT41: =AT40+AS41 -> -13300.07 | AU41: =AU40+AT41 -> -18300.86 | AV41: =AV40+AU41 -> -21806.83 | AW41: =AW40+AV41 -> -14313.71 | AX41: =AX40+AW41 -> 10341.34 | AY41: =AY40+AX41 -> 38877.5 | AZ41: =AZ40+AY41 -> 55236.43 | BA41: =BA40+AZ41 -> 32284.1 | ... BD41: =BD40+BC41 -> 878.62
B43: Saldo Inicial | C43: ='Ing y gtos'!$AA$157 -> 1178.6 | D43: =C45 -> 1439.49 | E43: =D45 -> 29120.35 | F43: =E45 -> 82937.25 | G43: =F45 -> 34295.48 | H43: =G45 -> 39002.158 | I43: =H45 -> 18848.808 | J43: =I45 -> 10233.22 | K43: =J45 -> 48343.675 | ... N43: =M45 -> 88680.965 | P43: =N45 -> 18727.765 | Q43: =P45 -> 31415.285 | R43: =Q45 -> 38727.135 | S43: =R45 -> 9213.8053 | T43: =S45 -> 15473.645 | U43: =T45 -> 8971.2053 | V43: =U45 -> 27058.215 | W43: =V45 -> 35364.995 | X43: =W45 -> 42486.885 | ... AA43: =Z45 -> 12738.005 | AC43: =AA45 -> 34806.585 | AD43: =AC45 -> 2916.7153 | AE43: =AD45 -> 31550.835 | AF43: =AE45 -> 28902.315 | AG43: =AF45 -> 3369.6653 | AH43: =AG45 -> 2563.2753 | AI43: =AH45 -> 17457.185 | AJ43: =AI45 -> 7061.2753 | AK43: =AJ45 -> 29193.075 | ... AN43: =AM45 -> 8205.1853 | AS43: =AN45 -> 27360.345 | AT43: =AS45 -> 3309.0753 | AU43: =AT45 -> 14060.275 | AV43: =AU45 -> 9059.4853 | AW43: =AV45 -> 5553.5153 | AX43: =AW45 -> 13046.635 | AY43: =AX45 -> 37701.685 | AZ43: =AY45 -> 66237.845 | BA43: =AZ45 -> 82596.775 | ... BD43: =BC45 -> 13494.455
B44: Caja consolidada | C44: =C40 -> 260.89 | D44: =D40 -> 27680.86 | E44: =E40 -> 53816.9 | F44: =F40 -> -48641.77 | G44: =G40 -> 4706.6782 | H44: =H40 -> -20153.35 | I44: =I40 -> -8615.5879 | J44: =J40 -> 38110.455 | ... N44: =N40 -> -69953.2 | P44: =P40 -> 12687.52 | Q44: =Q40 -> 7311.85 | R44: =R40 -> -29513.33 | S44: =S40 -> 6259.84 | T44: =T40 -> -6502.44 | U44: =U40 -> 18087.01 | V44: =V40 -> 8306.78 | W44: =W40 -> 7121.89 | ... AA44: =AA40 -> 22068.58 | AC44: =AC40 -> -31889.87 | AD44: =AD40 -> 28634.12 | AE44: =AE40 -> -2648.52 | AF44: =AF40 -> -25532.65 | AG44: =AG40 -> -806.39 | AH44: =AH40 -> 14893.91 | AI44: =AI40 -> -10395.91 | AJ44: =AJ40 -> 22131.8 | ... AN44: =AN40 -> 19155.16 | AS44: =AS40 -> -24051.27 | AT44: =AT40 -> 10751.2 | AU44: =AU40 -> -5000.79 | AV44: =AV40 -> -3505.97 | AW44: =AW40 -> 7493.12 | AX44: =AX40 -> 24655.05 | AY44: =AY40 -> 28536.16 | AZ44: =AZ40 -> 16358.93 | ... BD44: =BD40 -> 14744.51
B45: Saldo final | C45: =SUM(C43:C44) -> 1439.49 | D45: =SUM(D43:D44) -> 29120.35 | E45: =SUM(E43:E44) -> 82937.25 | F45: =SUM(F43:F44) -> 34295.48 | G45: =SUM(G43:G44) -> 39002.158 | H45: =SUM(H43:H44) -> 18848.808 | I45: =SUM(I43:I44) -> 10233.22 | J45: =SUM(J43:J44) -> 48343.675 | ... N45: =SUM(N43:N44) -> 18727.765 | P45: =SUM(P43:P44) -> 31415.285 | Q45: =SUM(Q43:Q44) -> 38727.135 | R45: =SUM(R43:R44) -> 9213.8053 | S45: =SUM(S43:S44) -> 15473.645 | T45: =SUM(T43:T44) -> 8971.2053 | U45: =SUM(U43:U44) -> 27058.215 | V45: =SUM(V43:V44) -> 35364.995 | W45: =SUM(W43:W44) -> 42486.885 | ... AA45: =SUM(AA43:AA44) -> 34806.585 | AC45: =SUM(AC43:AC44) -> 2916.7153 | AD45: =SUM(AD43:AD44) -> 31550.835 | AE45: =SUM(AE43:AE44) -> 28902.315 | AF45: =SUM(AF43:AF44) -> 3369.6653 | AG45: =SUM(AG43:AG44) -> 2563.2753 | AH45: =SUM(AH43:AH44) -> 17457.185 | AI45: =SUM(AI43:AI44) -> 7061.2753 | AJ45: =SUM(AJ43:AJ44) -> 29193.075 | ... AN45: =SUM(AN43:AN44) -> 27360.345 | AS45: =SUM(AS43:AS44) -> 3309.0753 | AT45: =SUM(AT43:AT44) -> 14060.275 | AU45: =SUM(AU43:AU44) -> 9059.4853 | AV45: =SUM(AV43:AV44) -> 5553.5153 | AW45: =SUM(AW43:AW44) -> 13046.635 | AX45: =SUM(AX43:AX44) -> 37701.685 | AY45: =SUM(AY43:AY44) -> 66237.845 | AZ45: =SUM(AZ43:AZ44) -> 82596.775 | ... BD45: =SUM(BD43:BD44) -> 28238.965
B46: Saldos bancarios
B47: Saldo Caixa EUR | C47: ='Ing y gtos'!AE159 -> 1449.16 | D47: ='Ing y gtos'!AF159 -> 29148.21 | E47: ='Ing y gtos'!AG159 -> 82883.58 | F47: ='Ing y gtos'!AH159 -> 34241.81 | G47: ='Ing y gtos'!AI159 -> 36138.49 | H47: ='Ing y gtos'!AJ159 -> 16786.84 | I47: ='Ing y gtos'!AK159 -> 8792.55 | J47: ='Ing y gtos'!AL159 -> 47903.01 | ... N47: ='Ing y gtos'!AP159 -> 18021.45 | P47: ='Ing y gtos'!AU158 -> 921 | Q47: ='Ing y gtos'!AV158 -> 14978.31 | R47: ='Ing y gtos'!AW158 -> 957.31 | S47: ='Ing y gtos'!AX158 -> 2913.34 | T47: ='Ing y gtos'!AY158 -> 199.29 | U47: ='Ing y gtos'!AZ158 -> 79.29 | V47: ='Ing y gtos'!BA158 -> 39.29 | W47: ='Ing y gtos'!BB158 -> 1347.93 | ... AA47: ='Ing y gtos'!BF158 -> 166.96 | AC47: ='Ing y gtos'!BJ158 -> 126.96 | AD47: ='Ing y gtos'!BK158 -> 18595.53 | AE47: ='Ing y gtos'!BL158 -> 17889.95 | AF47: ='Ing y gtos'!BM158 -> 215.55 | AG47: ='Ing y gtos'!BN158 -> 205.55 | AH47: ='Ing y gtos'!BO158 -> 205.55 | AI47: ='Ing y gtos'!BP158 -> 40.56 | AJ47: ='Ing y gtos'!BQ158 -> 40.56 | ... AN47: ='Ing y gtos'!BU158 -> 0 | AS47: ='Ing y gtos'!BW158 -> 0 | AT47: ='Ing y gtos'!#REF! -> #REF! | AU47: ='Ing y gtos'!BX158 -> 0 | AV47: ='Ing y gtos'!BY158 -> 0 | AW47: ='Ing y gtos'!BZ158 -> 0 | AX47: ='Ing y gtos'!CA158 -> 0 | AY47: ='Ing y gtos'!CB158 -> 0 | AZ47: ='Ing y gtos'!CC158 -> 0 | BA47: ='Ing y gtos'!CD158 -> 0 | BB47: ='Ing y gtos'!CE158 -> 0 | ... BD47: ='Ing y gtos'!CG158 -> 0
B48: Saldo Caja Rural | C48: ='Ing y gtos'!AE158 -> -9.67 | D48: ='Ing y gtos'!AF158 -> -27.86 | E48: ='Ing y gtos'!AG158 -> 53.67 | F48: ='Ing y gtos'!AH158 -> 53.67 | G48: ='Ing y gtos'!AI158 -> 53.67 | H48: ='Ing y gtos'!AJ158 -> 51.97 | I48: ='Ing y gtos'!AK158 -> 105.67 | J48: ='Ing y gtos'!AL158 -> 105.67 | ... N48: ='Ing y gtos'!AP158 -> 401.32 | P48: ='Ing y gtos'!AU159 -> 29979.29 | Q48: ='Ing y gtos'!AV159 -> 23100.83 | R48: ='Ing y gtos'!AW159 -> 8218.5 | S48: ='Ing y gtos'!AX159 -> 12522.31 | T48: ='Ing y gtos'!AY159 -> 6795.92 | U48: ='Ing y gtos'!AZ159 -> 23832.93 | V48: ='Ing y gtos'!BA159 -> 32169.71 | W48: ='Ing y gtos'!BB159 -> 37982.96 | ... AA48: ='Ing y gtos'!BF159 -> 34559.63 | AC48: ='Ing y gtos'!BJ159 -> 2789.76 | AD48: ='Ing y gtos'!BK159 -> 12955.31 | AE48: ='Ing y gtos'!BL159 -> 11012.37 | AF48: ='Ing y gtos'!BM159 -> 3154.12 | AG48: ='Ing y gtos'!BN159 -> 2357.73 | AH48: ='Ing y gtos'!BO159 -> 16681.64 | AI48: ='Ing y gtos'!BP159 -> 7020.72 | AJ48: ='Ing y gtos'!BQ159 -> 29152.51 | ... AN48: ='Ing y gtos'!BU159 -> 0 | AS48: ='Ing y gtos'!BW159 -> 0 | AT48: ='Ing y gtos'!#REF! -> #REF! | AU48: ='Ing y gtos'!BX159 -> 0 | AV48: ='Ing y gtos'!BY159 -> 0 | AW48: ='Ing y gtos'!BZ159 -> 0 | AX48: ='Ing y gtos'!CA159 -> 0 | AY48: ='Ing y gtos'!CB159 -> 0 | AZ48: ='Ing y gtos'!CC159 -> 0 | BA48: ='Ing y gtos'!CD159 -> 0 | BB48: ='Ing y gtos'!CE159 -> 0 | ... BD48: ='Ing y gtos'!CG159 -> 0
B49: Saldo Caja | C49: ='Ing y gtos'!AE160 -> 0 | D49: ='Ing y gtos'!AF160 -> 0 | E49: ='Ing y gtos'!AG160 -> 0 | F49: ='Ing y gtos'!AH160 -> 0 | G49: ='Ing y gtos'!AI160 -> 2810 | H49: ='Ing y gtos'!AJ160 -> 2010 | I49: ='Ing y gtos'!AK160 -> 1335 | J49: ='Ing y gtos'!AL160 -> 335 | ... N49: ='Ing y gtos'!AP160 -> 305 | P49: ='Ing y gtos'!AU160 -> 515 | Q49: ='Ing y gtos'!AV160 -> 648 | R49: ='Ing y gtos'!AW160 -> 38 | S49: ='Ing y gtos'!AX160 -> 38 | T49: ='Ing y gtos'!AY160 -> 1976 | U49: ='Ing y gtos'!AZ160 -> 3146 | V49: ='Ing y gtos'!BA160 -> 3156 | W49: ='Ing y gtos'!BB160 -> 3156 | ... AA49: ='Ing y gtos'!BF160 -> 80 | AC49: ='Ing y gtos'!BJ160 -> 0 | AD49: ='Ing y gtos'!BK160 -> 0 | AE49: ='Ing y gtos'!BL160 -> 0 | AF49: ='Ing y gtos'!BM160 -> 0 | AG49: ='Ing y gtos'!BN160 -> 0 | AH49: ='Ing y gtos'!BO160 -> 570 | AI49: ='Ing y gtos'!BP160 -> 0 | AJ49: ='Ing y gtos'!BQ160 -> 0 | ... AN49: ='Ing y gtos'!BU160 -> 0 | AS49: ='Ing y gtos'!BW160 -> 0 | AT49: ='Ing y gtos'!#REF! -> #REF! | AU49: ='Ing y gtos'!BX160 -> 0 | AV49: ='Ing y gtos'!BY160 -> 0 | AW49: ='Ing y gtos'!BZ160 -> 0 | AX49: ='Ing y gtos'!CA160 -> 0 | AY49: ='Ing y gtos'!CB160 -> 0 | AZ49: ='Ing y gtos'!CC160 -> 0 | BA49: ='Ing y gtos'!CD160 -> 0 | BB49: ='Ing y gtos'!CE160 -> 0 | ... BD49: ='Ing y gtos'!CG160 -> 0
B50: Check | C50: =SUM(C47:C49) -> 1439.49 | D50: =SUM(D47:D49) -> 29120.35 | E50: =SUM(E47:E49) -> 82937.25 | F50: =SUM(F47:F49) -> 34295.48 | G50: =SUM(G47:G49) -> 39002.16 | H50: =SUM(H47:H49) -> 18848.81 | I50: =SUM(I47:I49) -> 10233.22 | J50: =SUM(J47:J49) -> 48343.68 | ... N50: =SUM(N47:N49) -> 18727.77 | P50: =SUM(P47:P49) -> 31415.29 | Q50: =SUM(Q47:Q49) -> 38727.14 | R50: =SUM(R47:R49) -> 9213.81 | S50: =SUM(S47:S49) -> 15473.65 | T50: =SUM(T47:T49) -> 8971.21 | U50: =SUM(U47:U49) -> 27058.22 | V50: =SUM(V47:V49) -> 35365 | W50: =SUM(W47:W49) -> 42486.89 | ... AA50: =SUM(AA47:AA49) -> 34806.59 | AC50: =SUM(AC47:AC49) -> 2916.72 | AD50: =SUM(AD47:AD49) -> 31550.84 | AE50: =SUM(AE47:AE49) -> 28902.32 | AF50: =SUM(AF47:AF49) -> 3369.67 | AG50: =SUM(AG47:AG49) -> 2563.28 | AH50: =SUM(AH47:AH49) -> 17457.19 | AI50: =SUM(AI47:AI49) -> 7061.28 | AJ50: =SUM(AJ47:AJ49) -> 29193.07 | ... AN50: =SUM(AN47:AN49) -> 0 | AS50: =SUM(AS47:AS49) -> 0 | AT50: =SUM(AT47:AT49) -> #REF! | AU50: =SUM(AU47:AU49) -> 0 | AV50: =SUM(AV47:AV49) -> 0 | AW50: =SUM(AW47:AW49) -> 0 | AX50: =SUM(AX47:AX49) -> 0 | AY50: =SUM(AY47:AY49) -> 0 | AZ50: =SUM(AZ47:AZ49) -> 0 | ... BD50: =SUM(BD47:BD49) -> 0
B51: Diferencia | C51: =C45-C50 -> 0 | D51: =D45-D50 -> 0 | E51: =E45-E50 -> 0 | F51: =F45-F50 -> 0 | G51: =G45-G50 -> -0.0018 | H51: =H45-H50 -> -0.0018 | I51: =I45-I50 -> 0.00030000001 | J51: =J45-J50 -> -0.0047 | ... N51: =N45-N50 -> -0.0047 | P51: =P45-P50 -> -0.0047 | Q51: =Q45-Q50 -> -0.0047 | R51: =R45-R50 -> -0.0047 | S51: =S45-S50 -> -0.0047 | T51: =T45-T50 -> -0.0047 | U51: =U45-U50 -> -0.0047 | V51: =V45-V50 -> -0.0047 | W51: =W45-W50 -> -0.0047 | ... AA51: =AA45-AA50 -> -0.0047 | AC51: =AC45-AC50 -> -0.0047 | AD51: =AD45-AD50 -> -0.0047 | AE51: =AE45-AE50 -> -0.0047 | AF51: =AF45-AF50 -> -0.0047 | AG51: =AG45-AG50 -> -0.0047 | AH51: =AH45-AH50 -> -0.0047 | AI51: =AI45-AI50 -> -0.0047 | AJ51: =AJ45-AJ50 -> 0.0053 | AS51: =AS45-AS50 -> 3309.0753 | AT51: =AT45-AT50 -> #REF! | AU51: =AU45-AU50 -> 9059.4853 | AV51: =AV45-AV50 -> 5553.5153

Sheet Comparativa cuadros
N1: 23-24 | O1: 24-25 | P1: 26-26
B2: PRESUPUESTO 25-26 | N2: Totales | O2: TOTALES
A3: Ventas vacuno | B3: 46162 | M3: Ventas vacuno
A4: Venta de terneros/as | B4: 113346.91 | D4: ='Ing y gtos'!BV4 -> 113346.91 | E4: =D4-B4 -> 0 | F4: aumento de 2 terneros de venta intermedio y 1 mas de remate. | M4: Venta de terneros/as | N4: 167719.55 | O4: 73996.36 | P4: ='Ing y gtos'!BV4 -> 113346.91 | Q4: ¿Por qué disminuye del 23-24 al 24-25? 1º no hemos vendido tantos terneros y 2º el primero año vendidmos mas terneros engorde.
A5: Venta de carne | B5: 18260.02 | D5: ='Ing y gtos'!BV5 -> 18260.02 | E5: =D5-B5 -> 0 | F5: Facturas emitidas | M5: Venta de carne | N5: 13344.7 | O5: 8865.17 | P5: ='Ing y gtos'!BV5 -> 18260.02
A6: Total Ventas vacuno | B6: 131606.93 | D6: ='Ing y gtos'!BV6 -> 131606.93 | E6: =D6-B6 -> 0 | F6: AUMENTA COBROS | M6: Total Ventas vacuno | N6: 181064.25 | O6: 82861.53 | P6: ='Ing y gtos'!BV6 -> 131606.93
A7: Check | B7: 0 | D7: ='Ing y gtos'!BV7 -> 0 | M7: Check | N7: 0 | O7: 0 | P7: ='Ing y gtos'!BV7 -> 0
A9: Subvención PAC ganaderos extensivos de vacuno de carne | B9: 11610.39 | D9: ='Ing y gtos'!BV9 -> 11610.39 | E9: =D9-B9 -> 0 | M9: Subvención PAC ganaderos extensivos de vacuno de carne | N9: 12767.42 | O9: 11139.77 | P9: ='Ing y gtos'!BV9 -> 11610.39
A10: Subvención PAC ganado ecológico | B10: 0 | D10: ='Ing y gtos'!BV10 -> 0 | E10: =D10-B10 -> 0 | M10: Subvención PAC ganado ecológico | N10: 0 | O10: 0 | P10: ='Ing y gtos'!BV10 -> 0
A11: Subvención PAC ayuda basica a la renta y pago redistributivo | B11: 18438.27 | D11: ='Ing y gtos'!BV11 -> 18438.27 | E11: =D11-B11 -> 0 | M11: Subvención PAC ayuda basica a la renta y pago redistributivo | N11: 8056.6 | O11: 18834.78 | P11: ='Ing y gtos'!BV11 -> 18438.27
A12: Subvención PAC pastoreo extensivo | B12: 7590.12 | D12: ='Ing y gtos'!BV12 -> 7590.12 | E12: =D12-B12 -> 0 | M12: Subvención PAC pastoreo extensivo | N12: 10973.02 | O12: 7847.64 | P12: ='Ing y gtos'!BV12 -> 7590.12
A13: Subvención medicamentos vacas | B13: 0 | D13: ='Ing y gtos'!BV13 -> 0 | E13: =D13-B13 -> 0 | M13: Subvención medicamentos vacas | N13: 0 | O13: 0 | P13: ='Ing y gtos'!BV13 -> 0
A14: Subvención agroseguro vacas | B14: 1711.8 | D14: ='Ing y gtos'!BV14 -> 1711.8 | E14: =D14-B14 -> 0 | M14: Subvención agroseguro vacas | N14: 5725.81 | O14: 0 | P14: ='Ing y gtos'!BV14 -> 1711.8
A15: Subvenciones extraordinarias | B15: 5337.45 | D15: ='Ing y gtos'!BV15 -> 5337.45 | E15: =D15-B15 -> 0 | M15: Total cobros vacuno | N15: 218587.1 | O15: 120683.72 | P15: ='Ing y gtos'!BV16 -> 176294.96
A16: Total cobros vacuno | B16: 176294.96 | D16: ='Ing y gtos'!BV16 -> 176294.96 | E16: =D16-B16 -> 0 | F16: AUMENTA COBROS | M16: Check | N16: 0 | O16: 0 | P16: ='Ing y gtos'!BV17 -> 0
A17: Check | B17: 0 | D17: ='Ing y gtos'!BV17 -> 0 | M17: Gastos vacuno
A18: Gastos vacuno | M18: Compra terneros | N18: 0 | O18: 0 | P18: ='Ing y gtos'!BV19 -> 0
A19: Compra terneros | B19: 0 | D19: ='Ing y gtos'!BV19 -> 0 | E19: =D19-B19 -> 0 | M19: Medicamentos, veterinario y saneamientos | N19: 8991.32 | O19: 10113.08 | P19: ='Ing y gtos'!BV20 -> 10361.79
A20: Medicamentos, veterinario y saneamientos | B20: 7845.52 | D20: ='Ing y gtos'!BV20 -> 10361.79 | E20: =D20-B20 -> 2516.27 | F20: Disminuye prevision gastos mayo | M20: Programa de gestión | N20: 921.0036 | O20: 1650.81 | P20: ='Ing y gtos'!BV21 -> 1046.89
A21: Programa de gestión | B21: 1046.89 | D21: ='Ing y gtos'!BV21 -> 1046.89 | E21: =D21-B21 -> 0 | M21: Registro Angus | N21: 0 | O21: 0 | P21: ='Ing y gtos'!BV22 -> 350
A22: Registro Angus | B22: 350 | D22: ='Ing y gtos'!BV22 -> 350 | E22: =D22-B22 -> 0 | M22: Animales muertos | N22: 0 | O22: 883.96 | P22: ='Ing y gtos'!BV23 -> 1257.5
A23: Animales muertos | B23: 1257.5 | D23: ='Ing y gtos'!BV23 -> 1257.5 | E23: =D23-B23 -> 0 | M23: Cert. Ecológico - Agrocolor | N23: 1486.49 | O23: 1160.75 | P23: ='Ing y gtos'!BV24 -> 2560.58
A24: Cert. Ecológico - Agrocolor | B24: 2560.58 | D24: ='Ing y gtos'!BV24 -> 2560.58 | E24: =D24-B24 -> 0 | M24: Seguro Vacas | N24: 2557.09 | O24: -3912.61 | P24: ='Ing y gtos'!BV25 -> 3949.81
A25: Seguro Vacas | B25: 3949.81 | D25: ='Ing y gtos'!BV25 -> 3949.81 | E25: =D25-B25 -> 0 | M25: Matadero (Para venta de carne) | N25: 0 | O25: 0 | P25: ='Ing y gtos'!BV26 -> 0
A26: Matadero (Para venta de carne) | B26: 0 | D26: ='Ing y gtos'!BV26 -> 0 | E26: =D26-B26 -> 0 | M26: Portes (Para venta de carne) | N26: 0 | O26: 160.19 | P26: ='Ing y gtos'!BV27 -> 0
A27: Portes (Para venta de carne) | B27: 0 | D27: ='Ing y gtos'!BV27 -> 0 | E27: =D27-B27 -> 0 | M27: Envasado y refrigeración | N27: 0 | O27: 0 | P27: ='Ing y gtos'!BV28 -> 0
A28: Envasado y refrigeración | B28: 0 | D28: ='Ing y gtos'!BV28 -> 0 | E28: =D28-B28 -> 0 | M28: Asaja | N28: 0 | O28: 0 | P28: ='Ing y gtos'!BV29 -> 200
A29: Asaja | B29: 200 | D29: ='Ing y gtos'!BV29 -> 200 | E29: =D29-B29 -> 0 | M29: Servicio precios lonja | N29: 350 | O29: 360 | P29: ='Ing y gtos'!BV30 -> 360
A30: Servicio precios lonja | B30: 360 | D30: ='Ing y gtos'!BV30 -> 360 | E30: =D30-B30 -> 0 | M30: Portes | N30: 411.4 | O30: 1323.84 | P30: ='Ing y gtos'!BV31 -> 1134
A31: Portes | B31: 1134 | D31: ='Ing y gtos'!BV31 -> 1134 | E31: =D31-B31 -> 0 | M31: Comisiones corredor | N31: 1049.72 | O31: 0 | P31: ='Ing y gtos'!BV32 -> 0
A32: Comisiones corredor | B32: 0 | D32: ='Ing y gtos'!BV32 -> 0 | E32: =D32-B32 -> 0 | M32: Total pagos vacuno | N32: 15767.024 | O32: 11740.02 | P32: ='Ing y gtos'!BV33 -> 21220.57
A33: Total pagos vacuno | B33: 18704.3 | D33: ='Ing y gtos'!BV33 -> 21220.57 | E33: =D33-B33 -> 2516.27 | F33: DIMINUYE EL GASTO | M33: Check | N33: 0 | O33: 0 | P33: ='Ing y gtos'!BV34 -> 0
A34: Check | B34: 0 | D34: ='Ing y gtos'!BV34 -> 0
M35: Saldo vacuno (mes) | N35: 202820.08 | O35: 108943.7 | P35: ='Ing y gtos'!BV36 -> 155074.39
A36: Saldo vacuno (mes) | B36: 157590.66 | D36: ='Ing y gtos'!BV36 -> 155074.39 | M36: Check | N36: 0 | O36: 0 | P36: ='Ing y gtos'!BV37 -> 0
A37: Check | B37: 0 | D37: ='Ing y gtos'!BV37 -> 0 | M37: Ventas porcino
A38: Ventas porcino | M38: Montanera propios y de terceros | N38: 89804.28 | O38: 99425.12 | P38: ='Ing y gtos'!BV39 -> 70566.15
A39: Montanera propios y de terceros | B39: 70566.15 | D39: ='Ing y gtos'!BV39 -> 70566.15 | E39: =D39-B39 -> 0 | M39: Ventas de carne | N39: 50418.48 | O39: 38788.54 | P39: ='Ing y gtos'!BV40 -> 50674.6
A40: Ventas de carne | B40: 38303.56 | D40: ='Ing y gtos'!BV40 -> 50674.6 | E40: =D40-B40 -> 12371.04 | F40: Aumenta fras emitidas de gapestore | M40: Venta chacinas y paletas | N40: 110 | O40: 6697.73 | P40: ='Ing y gtos'!BV41 -> 21538.05
A41: Venta chacinas y paletas | B41: 23421.27 | D41: ='Ing y gtos'!BV41 -> 21538.05 | E41: =D41-B41 -> -1883.22 | F41: Diferencia IVA de tickets emitidos | M41: Total cobros porcino | N41: 140332.76 | O41: 144911.39 | P41: ='Ing y gtos'!BV42 -> 142778.8
A42: Total cobros porcino | B42: 132290.98 | D42: ='Ing y gtos'!BV42 -> 142778.8 | E42: =D42-B42 -> 10487.82 | F42: AUMENTAN COBROS | M42: Check | N42: 0 | O42: 0 | P42: ='Ing y gtos'!BV43 -> 0
A43: Check | B43: 0 | D43: ='Ing y gtos'!BV43 -> 0 | M43: Gastos porcino
A44: Gastos porcino | M44: Compra de animales | N44: 0 | O44: 0 | P44: ='Ing y gtos'!BV45 -> 0
A45: Compra de animales | B45: 0 | D45: ='Ing y gtos'!BV45 -> 0 | E45: =D45-B45 -> 0 | M45: Comisiones corredor | N45: 0 | O45: 0 | P45: ='Ing y gtos'!BV46 -> 0
A46: Comisiones corredor | B46: 0 | D46: ='Ing y gtos'!BV46 -> 0 | E46: =D46-B46 -> 0 | M46: Medicamentos y Vet. | N46: 3066.86 | O46: 1386.14 | P46: ='Ing y gtos'!BV47 -> 2084.03
A47: Medicamentos y Vet. | B47: 1900.77 | D47: ='Ing y gtos'!BV47 -> 2084.03 | E47: =D47-B47 -> 183.26 | F47: ajustamos gasto en medicinas/vet. | M47: Compra de carne | N47: 38275.67 | O47: 31048.55 | P47: ='Ing y gtos'!BV48 -> 43164.64
A48: Compra de carne | B48: 38841.63 | D48: ='Ing y gtos'!BV48 -> 43164.64 | E48: =D48-B48 -> 4323.01 | F48: Incluimos facturas de carne | M48: Matadero (Para venta de carne) | N48: 829.4 | O48: 73.57 | P48: ='Ing y gtos'!BV49 -> 0
A49: Matadero (Para venta de carne) | B49: 0 | D49: ='Ing y gtos'!BV49 -> 0 | E49: =D49-B49 -> 0 | M49: Envasado y almacenamiento | N49: 782.75 | O49: 6128.57 | P49: ='Ing y gtos'!BV50 -> 11875.64
A50: Envasado y almacenamiento | B50: 9921.47 | D50: ='Ing y gtos'!BV50 -> 11875.64 | E50: =D50-B50 -> 1954.17 | F50: Incluimos fras no previstas los romeros de jagugo. | M50: Certificación Bellota | N50: 2168.32 | O50: 2798.95 | P50: ='Ing y gtos'!BV51 -> 3818.11
A51: Certificación Bellota | B51: 3818.11 | D51: ='Ing y gtos'!BV51 -> 3818.11 | E51: =D51-B51 -> 0 | M51: Portes | N51: 3473.0379 | O51: 4549.12 | P51: ='Ing y gtos'!BV52 -> 6693.02
A52: Portes | B52: 6288.35 | D52: ='Ing y gtos'!BV52 -> 6693.02 | E52: =D52-B52 -> 404.67 | F52: Inluimos facturas (tradipack y Narval) | M52: Saneamientos | N52: 0 | O52: 0 | P52: ='Ing y gtos'!BV53 -> 0
A53: Saneamientos | B53: 0 | D53: ='Ing y gtos'!BV53 -> 0 | E53: =D53-B53 -> 0 | M53: Total pagos porcino | N53: 48596.038 | O53: 45984.9 | P53: ='Ing y gtos'!BV54 -> 67635.44
A54: Total pagos porcino | B54: 60770.33 | D54: ='Ing y gtos'!BV54 -> 67635.44 | E54: =D54-B54 -> 6865.11 | F54: AUMENTAN GASTOS | M54: Check | N54: -1678.54 | O54: 0 | P54: ='Ing y gtos'!BV55 -> 0
A55: Check | B55: 0 | D55: ='Ing y gtos'!BV55 -> 0
M56: Saldo porcino (mes) | N56: 91736.722 | O56: 98926.49 | P56: ='Ing y gtos'!BV57 -> 75143.36
A57: Saldo porcino (mes) | B57: 71520.65 | D57: ='Ing y gtos'!BV57 -> 75143.36 | E57: =D57-B57 -> 3622.71 | F57: DISMINUYE SALDO PORCINO | M57: Check | N57: 1678.54 | O57: 0 | P57: ='Ing y gtos'!BV58 -> 0
A58: Check | B58: 0 | D58: ='Ing y gtos'!BV58 -> 0 | M58: Ventas ovino
A59: Ventas ovino | M59: Corderos/ovejas/carneros | N59: 15735.9 | O59: 1412 | P59: ='Ing y gtos'!BV60 -> 1810
A60: Corderos/ovejas/carneros | B60: 1810 | D60: ='Ing y gtos'!BV60 -> 1810 | E60: =D60-B60 -> 0 | F60: Venta ovejas | M60: Total Ventas ovino | N60: 15735.9 | O60: 1412 | P60: ='Ing y gtos'!BV61 -> 1810
A61: Total Ventas ovino | B61: 1810 | D61: ='Ing y gtos'!BV61 -> 1810 | E61: =D61-B61 -> 0 | M61: Check | P61: ='Ing y gtos'!BV62 -> 0
A62: Check | M62: Subvención ovejas | N62: 0 | O62: 0 | P62: ='Ing y gtos'!BV63 -> 0
A63: Subvención ovejas | B63: 0 | D63: ='Ing y gtos'!BV63 -> 0 | E63: =D63-B63 -> 0
M64: Total cobros ovino | N64: 15735.9 | O64: 1412 | P64: ='Ing y gtos'!BV65 -> 1810
A65: Total cobros ovino | B65: 1810 | D65: ='Ing y gtos'!BV65 -> 1810 | E65: =D65-B65 -> 0 | F65: AUMENTA COBROS | N65: 0 | P65: ='Ing y gtos'!BV66 -> 0
B66: 0 | D66: ='Ing y gtos'!BV66 -> 0 | M66: Gastos Ovino
A67: Gastos Ovino | M67: Medicamentos y Vet. | N67: 66.7 | O67: 151.8 | P67: ='Ing y gtos'!BV68 -> 0
A68: Medicamentos y Vet. | B68: 0 | D68: ='Ing y gtos'!BV68 -> 0 | E68: =D68-B68 -> 0 | M68: Crotales | N68: 0 | O68: 0 | P68: ='Ing y gtos'!BV69 -> 0
A69: Crotales | B69: 0 | D69: ='Ing y gtos'!BV69 -> 0 | E69: =D69-B69 -> 0 | M69: Programa de gestión | N69: 0 | O69: 0 | P69: ='Ing y gtos'!BV70 -> 0
A70: Programa de gestión | B70: 0 | D70: ='Ing y gtos'!BV70 -> 0 | E70: =D70-B70 -> 0 | M70: Saneamientos | N70: 0 | O70: 0 | P70: ='Ing y gtos'!BV71 -> 0
A71: Saneamientos | B71: 0 | D71: ='Ing y gtos'!BV71 -> 0 | E71: =D71-B71 -> 0 | M71: Comision corredor | N71: 363.84 | O71: 0 | P71: ='Ing y gtos'!BV72 -> 0
A72: Comision corredor | B72: 0 | D72: ='Ing y gtos'!BV72 -> 0 | E72: =D72-B72 -> 0 | M72: Total pagos Ovino | N72: 430.54 | O72: 151.8 | P72: ='Ing y gtos'!BV73 -> 0
A73: Total pagos Ovino | B73: 0 | D73: ='Ing y gtos'!BV73 -> 0 | E73: =D73-B73 -> 0 | M73: Check | N73: 0 | P73: ='Ing y gtos'!BV74 -> 0
A74: Check | B74: 0 | D74: ='Ing y gtos'!BV74 -> 0 | M74: Saldo ovino (mes) | N74: 15305.36 | O74: 1260.2 | P74: ='Ing y gtos'!BV75 -> 1810
A75: Saldo ovino (mes) | B75: 1810 | D75: ='Ing y gtos'!BV75 -> 1810 | E75: =D75-B75 -> 0 | F75: AUMENTA SALDO OVEJAS | M75: Check | N75: 0 | P75: ='Ing y gtos'!BV76 -> 0
A76: Check | B76: 0 | D76: ='Ing y gtos'!BV76 -> 0 | M76: Gastos generales
A77: Gastos generales | M77: Alimento cereal | N77: 39951.35 | O77: 18529.03 | P77: ='Ing y gtos'!BV78 -> 19748.02
A78: Alimento cereal | B78: 19748.02 | D78: ='Ing y gtos'!BV78 -> 19748.02 | E78: =D78-B78 -> 0 | F78: Aumento prevision compra de cereal en junio. | M78: Alimento DDG/leguminosa | N78: 0 | O78: 0 | P78: ='Ing y gtos'!BV79 -> 19387.9
A79: Alimento DDG/leguminosa | B79: 19387.9 | D79: ='Ing y gtos'!BV79 -> 19387.9 | E79: =D79-B79 -> 0 | M79: Alimento Forraje/fibra | N79: 26820.74 | O79: 4290.5 | P79: ='Ing y gtos'!BV80 -> 2796.48
A80: Alimento Forraje/fibra | B80: 2796.48 | D80: ='Ing y gtos'!BV80 -> 2796.48 | E80: =D80-B80 -> 0 | M80: Alimento pienso lechones | N80: 0 | O80: 0 | P80: ='Ing y gtos'!BV81 -> 1847.26
A81: Alimento pienso lechones | B81: 1847.26 | D81: ='Ing y gtos'!BV81 -> 1847.26 | E81: =D81-B81 -> 0 | F81: eliminamos prevision de compra. | M81: Alimento pienso marranos | N81: 0 | O81: 13327.91 | P81: ='Ing y gtos'!BV82 -> 10972.34
A82: Alimento pienso marranos | B82: 10972.34 | D82: ='Ing y gtos'!BV82 -> 10972.34 | E82: =D82-B82 -> 0 | F82: reducimos preveision de agosto. | M82: Alimento pienso montanera | N82: 25321.4 | O82: 33226.15 | P82: ='Ing y gtos'!BV83 -> 36786.37
A83: Alimento pienso montanera | B83: 36786.37 | D83: ='Ing y gtos'!BV83 -> 36786.37 | E83: =D83-B83 -> 0 | M83: Alimento pienso terneros lactantes | N83: 21429.48 | O83: 968 | P83: ='Ing y gtos'!BV84 -> 0
A84: Alimento pienso terneros lactantes | B84: 0 | D84: ='Ing y gtos'!BV84 -> 0 | E84: =D84-B84 -> 0 | M84: Alimento pienso cebo | N84: 25119.5 | O84: 28626.02 | P84: ='Ing y gtos'!BV85 -> 54497.55
A85: Alimento pienso cebo | B85: 54497.55 | D85: ='Ing y gtos'!BV85 -> 54497.55 | E85: =D85-B85 -> 0 | F85: Compra en mayo no prevista. | M85: Alimento taco Madres | N85: 0 | O85: 6776.15 | P85: ='Ing y gtos'!BV86 -> 15511.24
A86: Alimento taco Madres | B86: 15511.24 | D86: ='Ing y gtos'!BV86 -> 15511.24 | E86: =D86-B86 -> 0 | N86: 0 | O86: 0 | P86: ='Ing y gtos'!BV87 -> 0
B87: 0 | D87: ='Ing y gtos'!BV87 -> 0 | E87: =D87-B87 -> 0 | M87: Siembra y cosechado | N87: 36213.34 | O87: 41502.41 | P87: ='Ing y gtos'!BV88 -> 24610.09
A88: Siembra y cosechado | B88: 24610.09 | D88: ='Ing y gtos'!BV88 -> 24610.09 | E88: =D88-B88 -> 0 | M88: Seguro RC | N88: 0 | O88: 0 | P88: ='Ing y gtos'!BV89 -> 1157.18
A89: Seguro RC | B89: 1157.18 | D89: ='Ing y gtos'!BV89 -> 1157.18 | E89: =D89-B89 -> 0 | M89: Seguro vehículos y maquinaria | N89: 201.74 | O89: 672.85 | P89: ='Ing y gtos'!BV90 -> 890.2
A90: Seguro vehículos y maquinaria | B90: 532.39 | D90: ='Ing y gtos'!BV90 -> 890.2 | E90: =D90-B90 -> 357.81 | M90: Seguro Convenio | N90: 0 | O90: 292.31 | P90: ='Ing y gtos'!BV91 -> 477.34
A91: Seguro Convenio | B91: 409.37 | D91: ='Ing y gtos'!BV91 -> 477.34 | E91: =D91-B91 -> 67.97 | M91: IVA | N91: 11842.18 | O91: -6012.9 | P91: ='Ing y gtos'!BV92 -> -11638.33
A92: IVA | B92: -10122.74 | D92: ='Ing y gtos'!BV92 -> -11638.33 | E92: =D92-B92 -> -1515.59 | F92: Ajustamos previsin de IVA. Estaba duplicado. | M92: IRPF | N92: 897.31 | O92: 837.6 | P92: ='Ing y gtos'!BV93 -> 1523.77
A93: IRPF | B93: 1523.77 | D93: ='Ing y gtos'!BV93 -> 1523.77 | E93: =D93-B93 -> 0 | F93: Aumento del IRPF del 1º trim. | M93: IS | N93: 0 | O93: 6901.23 | P93: ='Ing y gtos'!BV94 -> 6236.59
A94: IS | B94: 7158.19 | D94: ='Ing y gtos'!BV94 -> 6236.59 | E94: =D94-B94 -> -921.6 | F94: Pago a cuenta no previsto. | M94: Otras tasas e impuestos (IBI, RM, IVTM, …) | N94: 44.18 | O94: 0 | P94: ='Ing y gtos'!BV95 -> 5995.59
A95: Otras tasas e impuestos (IBI, RM, IVTM, …) | B95: 0 | D95: ='Ing y gtos'!BV95 -> 5995.59 | E95: =D95-B95 -> 5995.59 | M95: Mantenimiento finca y maquinaria | N95: 13536.028 | O95: 11586.25 | P95: ='Ing y gtos'!BV96 -> 13517.46
A96: Mantenimiento finca y maquinaria | B96: 12156.2 | D96: ='Ing y gtos'!BV96 -> 13517.46 | E96: =D96-B96 -> 1361.26 | M96: Gasoil B maquinaria | N96: 6805.98 | O96: 8557.04 | P96: ='Ing y gtos'!BV97 -> 8105
A97: Gasoil B maquinaria | B97: 8431 | D97: ='Ing y gtos'!BV97 -> 8105 | E97: =D97-B97 -> -326 | M97: Gasoil A o gasolina y butano | N97: 3490.75 | O97: 5340.39 | P97: ='Ing y gtos'!BV98 -> 4965.36
A98: Gasoil A o gasolina y butano | B98: 5333.42 | D98: ='Ing y gtos'!BV98 -> 4965.36 | E98: =D98-B98 -> -368.06 | F98: Aumento previsión fras gasolina. | M98: Alquiler Fincas | N98: 5415 | O98: 700 | P98: ='Ing y gtos'!BV99 -> 4450
A99: Alquiler Fincas | B99: 4450 | D99: ='Ing y gtos'!BV99 -> 4450 | E99: =D99-B99 -> 0 | M99: Gastos o ingresos auxiliares | N99: 1445 | O99: 1350 | P99: ='Ing y gtos'!BV100 -> -2017.59
A100: Gastos o ingresos auxiliares | B100: -2017.59 | D100: ='Ing y gtos'!BV100 -> -2017.59 | E100: =D100-B100 -> 0 | F100: Eliminamos ingreso coto de caza. | M100: Nomina Jhonathan Borrero Ruiz | N100: 3777.32 | O100: 4753.76 | P100: ='Ing y gtos'!BV101 -> 10367.72
A101: Nomina Jhonathan Borrero Ruiz | B101: 10387.72 | D101: ='Ing y gtos'!BV101 -> 10367.72 | E101: =D101-B101 -> -20 | F101: Eliminamos nomina mes de abril. | M101: Nomina Mariano López Valero | N101: 12174.34 | O101: 14941.52 | P101: ='Ing y gtos'!BV102 -> 18001.58
...

Sheet Ing y gtos
C1: 30 | D1: 31 | E1: 30 | F1: 31 | G1: 31 | H1: 28 | I1: 31 | J1: 30 | K1: 31 | L1: 30 | M1: 31 | N1: 31 | P1: 30 | Q1: 31 | R1: 30 | S1: 31 | T1: 31 | U1: 28 | V1: 31 | W1: 30 | X1: 31 | Y1: 30 | Z1: 31 | AA1: 31 | AE1: 30 | AF1: 31 | AG1: 30 | AH1: 31 | AI1: 31 | AJ1: 28 | AK1: 31 | AL1: 30 | AM1: 31 | AN1: 30 | AO1: 31 | AP1: 31
C2: 44469 | D2: =+C2+D1 -> 44500 | E2: =+D2+E1 -> 44530 | F2: =+E2+F1 -> 44561 | G2: =+F2+G1 -> 44592 | H2: =+G2+H1 -> 44620 | I2: =+H2+I1 -> 44651 | J2: =+I2+J1 -> 44681 | K2: =+J2+K1 -> 44712 | ... N2: =+M2+N1 -> 44804 | O2: Totales | P2: =N2+P1 -> 44834 | Q2: =+P2+Q1 -> 44865 | R2: =+Q2+R1 -> 44895 | S2: =+R2+S1 -> 44926 | T2: =+S2+T1 -> 44957 | U2: =+T2+U1 -> 44985 | V2: =+U2+V1 -> 45016 | W2: =+V2+W1 -> 45046 | X2: =+W2+X1 -> 45077 | ... AA2: =+Z2+AA1 -> 45169 | AB2: Totales | AE2: 45199 | AF2: 45230 | AG2: 45260 | AH2: 45291 | AI2: 45322 | AJ2: 45350 | AK2: 45382 | AL2: 45412 | AM2: 45443 | AN2: 45473 | AO2: 45504 | AP2: 45535 | AQ2: Totales | AU2: 45565 | AV2: 45596 | AW2: 45626 | AX2: 45657 | AY2: 45688 | AZ2: 45716 | BA2: 45747 | BB2: 45777 | BC2: 45808 | BD2: 45838 | BE2: 45869 | BF2: 45900 | BG2: TOTALES | BJ2: 45930 | BK2: 45961 | BL2: 45991 | BM2: 46022 | BN2: 46053 | BO2: 46081 | BP2: 46112 | BQ2: 46142 | BR2: 46173 | BS2: 46203 | BT2: 46234 | BU2: 46265 | BY2: 46295 | BZ2: 46326 | CA2: 46356 | CB2: 46387 | CC2: 46053 | CD2: 46446 | CE2: 46477 | CF2: 46507 | CG2: 46538 | CH2: 46568 | CI2: 46599 | CJ2: 46630 | CN2: 46660 | CO2: 46691 | CP2: 46721 | CQ2: 46752 | CR2: 46783 | CS2: 46811 | CT2: 46843 | CU2: 46873 | CV2: 46904 | CW2: 46934 | CX2: 46965 | CY2: 46996 | DB2: Incidencia | DC2: Eliminado
B3: Ventas vacuno
B4: Venta de terneros/as | O4: =SUM(C4:N4) -> 0 | AB4: =SUM(P4:AA4) -> 0 | AF4: 33077.51 | AG4: 50600 | AI4: =28971.32+3000+(5112.56) -> 37083.88 | AL4: =17578.74 -> 17578.74 | AM4: 980 | AN4: =17671.47 -> 17671.47 | AO4: 0 | AP4: =10727.95 -> 10727.95 | AQ4: =SUM(AE4:AP4) -> 167719.55 | AU4: =19401.76 -> 19401.76 | AV4: =SUM('Alimento y ventas'!P305:P309) -> 0 | AW4: =SUM('Alimento y ventas'!Q305:Q309) -> 0 | AX4: =SUM('Alimento y ventas'!R305:R309)*0+3000 -> 3000 | AY4: =SUM('Alimento y ventas'!S305:S309)*0+444.77+7493.05 -> 7937.82 | AZ4: =SUM('Alimento y ventas'!T305:T309)*0 -> 0 | BA4: =SUM('Alimento y ventas'!U305:U309)*0+9666.11 -> 9666.11 | BB4: =SUM('Alimento y ventas'!V305:V309)*0+9762.07 -> 9762.07 | BC4: =SUM('Alimento y ventas'!W305:W309)*0 -> 0 | BD4: =SUM('Alimento y ventas'!X305:X309) -> 0 | BE4: =SUM('Alimento y ventas'!Y305:Y309) -> 0 | BF4: =SUM('Alimento y ventas'!Z305:Z309)*0+24228.6 -> 24228.6 | BG4: =SUM(AU4:BF4) -> 73996.36 | BJ4: =SUM('Alimento y ventas'!AA305:AA309) -> 0 | BK4: =SUM('Alimento y ventas'!AB305:AB309)*0+10566.74 -> 10566.74 | BL4: =SUM('Alimento y ventas'!AC305:AC309)*0+31111.52 -> 31111.52 | BM4: =SUM('Alimento y ventas'!AD305:AD309)*0 -> 0 | BN4: =SUM('Alimento y ventas'!AE305:AE309)+8798.9 -> 8798.9 | BO4: =SUM('Alimento y ventas'!AF305:AF309)*0 -> 0 | BP4: =SUM('Alimento y ventas'!AG305:AG309)*0 -> 0 | BQ4: =SUM('Alimento y ventas'!AH305:AH309) -> 0 | BR4: =SUM('Alimento y ventas'!AI305:AI309) -> 0 | BS4: =SUM('Alimento y ventas'!AJ305:AJ309) -> 14226 | BT4: =SUM('Alimento y ventas'!AK305:AK309) -> 20153.5 | BU4: =SUM('Alimento y ventas'!AL305:AL309) -> 28490.25 | BV4: =SUM(BJ4:BU4) -> 113346.91 | BY4: =SUM('Alimento y ventas'!AM305:AM309) -> 5927.5 | BZ4: =SUM('Alimento y ventas'!AN305:AN309) -> 17782.5 | CA4: =SUM('Alimento y ventas'!AO305:AO309) -> 16597 | CB4: =SUM('Alimento y ventas'!AP305:AP309) -> 15411.5 | CC4: =SUM('Alimento y ventas'!AQ305:AQ309) -> 1185.5 | CD4: =SUM('Alimento y ventas'!AR305:AR309) -> 5927.5 | CE4: =SUM('Alimento y ventas'!AS305:AS309) -> 4742 | CF4: =SUM('Alimento y ventas'!AT305:AT309) -> 2371 | ... CJ4: =SUM('Alimento y ventas'!AX305:AX309) -> 35517.58 | CK4: =SUM(BY4:CJ4) -> 168530.68 | CN4: =SUM('Alimento y ventas'!AY305:AY309) -> 29722.333 | CO4: =SUM('Alimento y ventas'!AZ305:AZ309) -> 35582.25 | CP4: =SUM('Alimento y ventas'!BA305:BA309) -> 30280.68 | CQ4: =SUM('Alimento y ventas'!BB305:BB309) -> 7570.17 | CR4: =SUM('Alimento y ventas'!BC305:BC309) -> 5046.78 | CS4: =SUM('Alimento y ventas'!BD305:BD309) -> 7353.3239 | CT4: =SUM('Alimento y ventas'!BE305:BE309) -> 5563.2 | CU4: =SUM('Alimento y ventas'!BF305:BF309) -> 2952.6 | ... CY4: =SUM('Alimento y ventas'!BJ305:BJ309) -> 39724.44 | CZ4: =SUM(CN4:CY4) -> 238188.74
B5: Venta de carne | O5: =SUM(C5:N5) -> 0 | AB5: =SUM(P5:AA5) -> 0 | AE5: 556.3 | AG5: =705.32 -> 705.32 | AI5: =169.79 -> 169.79 | AL5: =438.02+32.34+189.42+961.62+378.41+5328.65 -> 7328.46 | AM5: =199.71+168.63+109.89+369.6+168.58+2100.87+84.92 -> 3202.2 | AN5: =199.65+178.2 -> 377.85 | AO5: =58+72.1+144.77 -> 274.87 | AP5: =400.71+92.2+83.2+66.4+87.4 -> 729.91 | AQ5: =SUM(AE5:AP5) -> 13344.7 | AU5: =52 -> 52 | AV5: =395.48+315+204.6+1961.67 -> 2876.75 | AW5: 315 | AX5: =1860.9+114.32+187.11 -> 2162.33 | AY5: =51.71 -> 51.71 | BA5: =355.95+139.13+113.08+136.4 -> 744.56 | BB5: =366.63+102.27+94.6 -> 563.5 | BC5: =1045.59+171.6+242.66 -> 1459.85 | BD5: =247.43+102.52 -> 349.95 | BE5: =89.76+92.4 -> 182.16 | BF5: =107.36 -> 107.36 | BG5: =SUM(AU5:BF5) -> 8865.17 | BJ5: =1500*5*0+6795.66+1297.17 -> 8092.83 | BK5: =175.56+139.92+215.82 -> 531.3 | BL5: =93.39 -> 93.39 | BM5: =194.7+68.75+101.2 -> 364.65 | BP5: =2282.98 -> 2282.98 | BQ5: =276.39 -> 276.39 | BR5: =3147.68+75.9 -> 3223.58 | BS5: =280.5+744.55+463.79+188.19+442.86+150.68+187.11+233.84+55.84+314.58+1045.59+171.6+242.66-1297.17+170.28 -> 3394.9 | BV5: =SUM(BJ5:BU5) -> 18260.02 | CK5: =SUM(BY5:CJ5) -> 0 | CZ5: =SUM(CN5:CY5) -> 0
B6: Total Ventas vacuno | C6: =SUM(C4:C4) -> 0 | D6: =SUM(D4:D4) -> 0 | E6: =SUM(E4:E4) -> 0 | F6: =SUM(F4:F4) -> 0 | G6: =SUM(G4:G4) -> 0 | H6: =SUM(H4:H4) -> 0 | I6: =SUM(I4:I4) -> 0 | J6: =SUM(J4:J4) -> 0 | ... AB6: =SUM(AB4:AB4) -> 0 | AE6: =SUM(AE4:AE5) -> 556.3 | AF6: =SUM(AF4:AF5) -> 33077.51 | AG6: =SUM(AG4:AG5) -> 51305.32 | AH6: =SUM(AH4:AH5) -> 0 | AI6: =SUM(AI4:AI5) -> 37253.67 | AJ6: =SUM(AJ4:AJ5) -> 0 | AK6: =SUM(AK4:AK5) -> 0 | AL6: =SUM(AL4:AL5) -> 24907.2 | ... AQ6: =SUM(AQ4:AQ5) -> 181064.25 | AU6: =SUM(AU4:AU5) -> 19453.76 | AV6: =SUM(AV4:AV5) -> 2876.75 | AW6: =SUM(AW4:AW5) -> 315 | AX6: =SUM(AX4:AX5) -> 5162.33 | AY6: =SUM(AY4:AY5) -> 7989.53 | AZ6: =SUM(AZ4:AZ5) -> 0 | BA6: =SUM(BA4:BA5) -> 10410.67 | BB6: =SUM(BB4:BB5) -> 10325.57 | ... BG6: =SUM(BG4:BG5) -> 82861.53 | BJ6: =SUM(BJ4:BJ5) -> 8092.83 | BK6: =SUM(BK4:BK5) -> 11098.04 | BL6: =SUM(BL4:BL5) -> 31204.91 | BM6: =SUM(BM4:BM5) -> 364.65 | BN6: =SUM(BN4:BN5) -> 8798.9 | BO6: =SUM(BO4:BO5) -> 0 | BP6: =SUM(BP4:BP5) -> 2282.98 | BQ6: =SUM(BQ4:BQ5) -> 276.39 | ... BV6: =SUM(BV4:BV5) -> 131606.93 | BY6: =SUM(BY4:BY4) -> 5927.5 | BZ6: =SUM(BZ4:BZ4) -> 17782.5 | CA6: =SUM(CA4:CA4) -> 16597 | CB6: =SUM(CB4:CB4) -> 15411.5 | CC6: =SUM(CC4:CC4) -> 1185.5 | CD6: =SUM(CD4:CD4) -> 5927.5 | CE6: =SUM(CE4:CE4) -> 4742 | CF6: =SUM(CF4:CF4) -> 2371 | ... CK6: =SUM(CK4:CK4) -> 168530.68 | CN6: =SUM(CN4:CN4) -> 29722.333 | CO6: =SUM(CO4:CO4) -> 35582.25 | CP6: =SUM(CP4:CP4) -> 30280.68 | CQ6: =SUM(CQ4:CQ4) -> 7570.17 | CR6: =SUM(CR4:CR4) -> 5046.78 | CS6: =SUM(CS4:CS4) -> 7353.3239 | CT6: =SUM(CT4:CT4) -> 5563.2 | CU6: =SUM(CU4:CU4) -> 2952.6 | ... CZ6: =SUM(CZ4:CZ4) -> 238188.74
B7: Check | O7: =O6-SUM(C6:N6) -> 0 | AB7: =AB6-SUM(P6:AA6) -> 0 | AQ7: =AQ6-SUM(AE6:AP6) -> 0 | BG7: =BG6-SUM(AU6:BF6) -> 0 | BV7: =BV6-SUM(BJ6:BU6) -> 0 | CK7: =CK6-SUM(BY6:CJ6) -> 0 | CZ7: =CZ6-SUM(CN6:CY6) -> 0
B9: Subvención PAC ganaderos extensivos de vacuno de carne | O9: =SUM(C9:N9) -> 0 | AB9: =SUM(P9:AA9) -> 0 | AM9: 11490.68 | AN9: 1276.74 | AQ9: =SUM(AE9:AP9) -> 12767.42 | AV9: 8664.27 | AX9: 2475.5 | BG9: =SUM(AU9:BF9) -> 11139.77 | BK9: =9030.3 -> 9030.3 | BM9: 2580.09 | BV9: =SUM(BJ9:BU9) -> 11610.39 | BZ9: 9000 | CB9: 2000 | CK9: =SUM(BY9:CJ9) -> 11000 | CO9: 9000 | CQ9: 2000 | CZ9: =SUM(CN9:CY9) -> 11000
B10: Subvención PAC ganado ecológico | O10: =SUM(C10:N10) -> 0 | AB10: =SUM(P10:AA10) -> 0 | AP10: =10321.7*0 -> 0 | AQ10: =SUM(AE10:AP10) -> 0 | BE10: =10321.7*0 -> 0 | BG10: =SUM(AU10:BF10) -> 0 | BT10: =10321.7*0 -> 0 | BV10: =SUM(BJ10:BU10) -> 0 | CI10: =10321.7*0 -> 0 | CK10: =SUM(BY10:CJ10) -> 0 | CX10: =10321.7*0 -> 0 | CZ10: =SUM(CN10:CY10) -> 0
B11: Subvención PAC ayuda basica a la renta y pago redistributivo | O11: =SUM(C11:N11) -> 0 | AB11: =SUM(P11:AA11) -> 0 | AM11: =4562.34+2688.59 -> 7250.93 | AO11: =805.67 -> 805.67 | AP11: 5725.81 | AQ11: =SUM(AE11:AP11) -> 13782.41 | AU11: 559.68 | AV11: 9635.8 | AX11: 2753.08 | BB11: =327.16+981.48 -> 1308.64 | BD11: =1484.87+1509.13+1583.58 -> 4577.58 | BG11: =SUM(AU11:BF11) -> 18834.78 | BK11: =445.15+8993.12 -> 9438.27 | BM11: 2569.49 | BT11: 6430.51 | BV11: =SUM(BJ11:BU11) -> 18438.27 | BZ11: 9500 | CB11: 9000 | CK11: =SUM(BY11:CJ11) -> 18500 | CO11: 9500 | CQ11: 9000 | CZ11: =SUM(CN11:CY11) -> 18500
B12: Subvención PAC pastoreo extensivo | O12: =SUM(C12:N12) -> 0 | AB12: =SUM(P12:AA12) -> 0 | AM12: 9879.39 | AO12: =1093.63 -> 1093.63 | AQ12: =SUM(AE12:AP12) -> 10973.02 | AV12: 5772.24 | AX12: 2075.4 | BG12: =SUM(AU12:BF12) -> 7847.64 | BL12: 2590.12 | BT12: 5000 | BV12: =SUM(BJ12:BU12) -> 7590.12 | CA12: 2500 | CB12: 5000 | CK12: =SUM(BY12:CJ12) -> 7500 | CP12: 2500 | CQ12: 5000 | CZ12: =SUM(CN12:CY12) -> 7500
B13: Subvención medicamentos vacas | O13: =SUM(C13:N13) -> 0 | AB13: =SUM(P13:AA13) -> 0 | AQ13: =SUM(AE13:AP13) -> 0 | BG13: =SUM(AU13:BF13) -> 0 | BV13: =SUM(BJ13:BU13) -> 0 | CK13: =SUM(BY13:CJ13) -> 0 | CZ13: =SUM(CN13:CY13) -> 0
B14: Subvención agroseguro vacas | O14: =SUM(C14:N14) -> 0 | AB14: =SUM(P14:AA14) -> 0 | AP14: 0 | AQ14: =SUM(AE14:AP14) -> 0 | BG14: =SUM(AU14:BF14) -> 0 | BL14: 1711.8 | BV14: =SUM(BJ14:BU14) -> 1711.8 | CA14: 2000 | CK14: =SUM(BY14:CJ14) -> 2000 | CP14: 2000 | CZ14: =SUM(CN14:CY14) -> 2000
B15: Subvenciones extraordinarias | BP15: 5337.45 | BV15: =SUM(BJ15:BU15) -> 5337.45
B16: Total cobros vacuno | C16: =SUM(C9:C14)+C6 -> 0 | D16: =SUM(D9:D14)+D6 -> 0 | E16: =SUM(E9:E14)+E6 -> 0 | F16: =SUM(F9:F14)+F6 -> 0 | G16: =SUM(G11:G14)+G6 -> 0 | H16: =SUM(H9:H14)+H6 -> 0 | I16: =SUM(I9:I14)+I6 -> 0 | J16: =SUM(J9:J14)+J6 -> 0 | K16: =SUM(K9:K14)+K6 -> 0 | L16: =SUM(L9:L14)+L6 -> 0 | M16: =SUM(M9:M14)+M6 -> 0 | N16: =SUM(N9:N14)+N6 -> 0 | O16: =SUM(O9:O14)+O6 -> 0 | ... AB16: =SUM(AB9:AB14)+AB6 -> 0 | AE16: =SUM(AE9:AE14)+AE6 -> 556.3 | AF16: =SUM(AF9:AF14)+AF6 -> 33077.51 | AG16: =SUM(AG9:AG14)+AG6 -> 51305.32 | AH16: =SUM(AH9:AH14)+AH6 -> 0 | AI16: =SUM(AI9:AI14)+AI6 -> 37253.67 | AJ16: =SUM(AJ9:AJ14)+AJ6 -> 0 | AK16: =SUM(AK9:AK14)+AK6 -> 0 | AL16: =SUM(AL9:AL14)+AL6 -> 24907.2 | ... AQ16: =SUM(AQ9:AQ14)+AQ6 -> 218587.1 | AU16: =SUM(AU9:AU14)+AU6 -> 20013.44 | AV16: =SUM(AV9:AV14)+AV6 -> 26949.06 | AW16: =SUM(AW9:AW14)+AW6 -> 315 | AX16: =SUM(AX9:AX14)+AX6 -> 12466.31 | AY16: =SUM(AY9:AY14)+AY6 -> 7989.53 | AZ16: =SUM(AZ9:AZ14)+AZ6 -> 0 | BA16: =SUM(BA9:BA14)+BA6 -> 10410.67 | BB16: =SUM(BB9:BB14)+BB6 -> 11634.21 | ... BG16: =SUM(BG9:BG14)+BG6 -> 120683.72 | BJ16: =SUM(BJ9:BJ15)+BJ6 -> 8092.83 | BK16: =SUM(BK9:BK15)+BK6 -> 29566.61 | BL16: =SUM(BL9:BL15)+BL6 -> 35506.83 | BM16: =SUM(BM9:BM15)+BM6 -> 5514.23 | BN16: =SUM(BN9:BN15)+BN6 -> 8798.9 | BO16: =SUM(BO9:BO15)+BO6 -> 0 | BP16: =SUM(BP9:BP15)+BP6 -> 7620.43 | BQ16: =SUM(BQ9:BQ15)+BQ6 -> 276.39 | ... BV16: =SUM(BV9:BV15)+BV6 -> 176294.96 | BY16: =SUM(BY9:BY14)+BY6 -> 5927.5 | BZ16: =SUM(BZ9:BZ14)+BZ6 -> 36282.5 | CA16: =SUM(CA9:CA14)+CA6 -> 21097 | CB16: =SUM(CB9:CB14)+CB6 -> 31411.5 | CC16: =SUM(CC9:CC14)+CC6 -> 1185.5 | CD16: =SUM(CD9:CD14)+CD6 -> 5927.5 | CE16: =SUM(CE9:CE14)+CE6 -> 4742 | CF16: =SUM(CF9:CF14)+CF6 -> 2371 | ... CK16: =SUM(CK9:CK14)+CK6 -> 207530.68 | CN16: =SUM(CN9:CN14)+CN6 -> 29722.333 | CO16: =SUM(CO9:CO14)+CO6 -> 54082.25 | CP16: =SUM(CP9:CP14)+CP6 -> 34780.68 | CQ16: =SUM(CQ9:CQ14)+CQ6 -> 23570.17 | CR16: =SUM(CR9:CR14)+CR6 -> 5046.78 | CS16: =SUM(CS9:CS14)+CS6 -> 7353.3239 | CT16: =SUM(CT9:CT14)+CT6 -> 5563.2 | CU16: =SUM(CU9:CU14)+CU6 -> 2952.6 | ... CZ16: =SUM(CZ9:CZ14)+CZ6 -> 277188.74
B17: Check | O17: =O16-SUM(C16:N16) -> 0 | AB17: =AB16-SUM(P16:AA16) -> 0 | AQ17: =AQ16-SUM(AE16:AP16) -> 0 | BG17: =BG16-SUM(AU16:BF16) -> 0 | BV17: =BV16-SUM(BJ16:BU16) -> 0 | CK17: =CK16-SUM(BY16:CJ16) -> 0 | CZ17: =CZ16-SUM(CN16:CY16) -> 0
B18: Gastos vacuno
B19: Compra terneros | O19: =SUM(C19:N19) -> 0 | AB19: =SUM(P19:AA19) -> 0 | AQ19: =SUM(AE19:AP19) -> 0 | BG19: =SUM(AU19:BF19) -> 0 | BV19: =SUM(BJ19:BU19) -> 0 | CK19: =SUM(BY19:CJ19) -> 0 | CZ19: =SUM(CN19:CY19) -> 0
B20: Medicamentos, veterinario y saneamientos | O20: =SUM(C20:N20) -> 0 | AB20: =SUM(P20:AA20) -> 0 | AG20: =20.37+32.39+108.93+2148.89 -> 2310.58 | AH20: =126.5+292.6+0.7+371.8+0.7+43.76 -> 836.06 | AI20: =1490.3+72.2 -> 1562.5 | AJ20: =16.5 -> 16.5 | AL20: =590+165+163.32+60.5+101.48+49.5 -> 1129.8 | AM20: =282.72+186*1.1+154.01 -> 641.33 | AN20: =152.86+413.17+27.23 -> 593.26 | AO20: =181.5+165.54+(134.2+134.2)+898.3 -> 1513.74 | AP20: =272+100.79+14.76 -> 387.55 | AQ20: =SUM(AE20:AP20) -> 8991.32 | AU20: =388+7.82+90.26+137.78+21.78+60 -> 705.64 | AV20: =587.4+1275.54+5.01 -> 1867.95 | AW20: =5.6+101.6+184.84+17.67 -> 309.71 | AX20: =280.24+848.47+59.4+22+162.8+64.68+101.6+46.46 -> 1585.65 | AY20: =68.2+32.87 -> 101.07 | BA20: 175.23 | BB20: =206*0+744.52+134.2+98.53+66+147.13+46.46 -> 1236.84 | BC20: =296*0+91.78+156.2+81.08+24.71+101.6+3.74 -> 459.11 | BD20: =217.33+149.05+94.6+457.47 -> 918.45 | BE20: =293.3+225.72+89.18+2.53+9.08+194.48+10.1+181.5 -> 1005.89 | BF20: =1366.95+170.49+138.6+71.5+217.29+183.21+124.18+119.94+30.01 -> 2422.17 | BG20: =SUM(AU20:BF20) -> 10787.71 | BJ20: 8.93 | BK20: =791.78+75.63+10.1+18.22 -> 895.73 | BL20: =281.65+1550.38+50.58+56.75 -> 1939.36 | BM20: =539.66 -> 539.66 | BN20: =920.08 -> 920.08 | BP20: =564.5+215.52+33+121 -> 934.02 | BQ20: =358.05+82.5+118.55+11.06 -> 570.16 | BR20: =187+50.58+178+181.5+280.34-707 -> 170.42 | BS20: =2546.12+416.86+51.63+48.2+9.81+105.61+5.2 -> 3183.43 | BT20: =6000/10 -> 600 | BU20: =6000/10 -> 600 | BV20: =SUM(BJ20:BU20) -> 10361.79 | BY20: =6000/10 -> 600 | BZ20: =6000/10 -> 600 | CA20: =6000/10 -> 600 | CB20: =6000/10 -> 600 | CC20: =6000/10 -> 600 | CD20: =6000/10 -> 600 | CE20: =6000/10 -> 600 | CF20: =6000/10 -> 600 | ... CJ20: =6000/10 -> 600 | CK20: =SUM(BY20:CJ20) -> 7200 | CN20: =6000/10 -> 600 | CO20: =6000/10 -> 600 | CP20: =6000/10 -> 600 | CQ20: =6000/10 -> 600 | CR20: =6000/10 -> 600 | CS20: =6000/10 -> 600 | CT20: =6000/10 -> 600 | CU20: =6000/10 -> 600 | ... CY20: =6000/10 -> 600 | CZ20: =SUM(CN20:CY20) -> 7200
B21: Programa de gestión | O21: =SUM(C21:N21) -> 0 | AB21: =SUM(P21:AA21) -> 0 | AI21: =761.16*1.21 -> 921.0036 | AQ21: =SUM(AE21:AP21) -> 921.0036 | AY21: =976.18 -> 976.18 | BG21: =SUM(AU21:BF21) -> 976.18 | BM21: 1046.89 | BV21: =SUM(BJ21:BU21) -> 1046.89 | CC21: 976.18 | CK21: =SUM(BY21:CJ21) -> 976.18 | CR21: 976.18 | CZ21: =SUM(CN21:CY21) -> 976.18
B22: Registro Angus | O22: =SUM(C22:N22) -> 0 | AB22: =SUM(P22:AA22) -> 0 | AQ22: =SUM(AE22:AP22) -> 0 | BG22: =SUM(AU22:BF22) -> 0 | BT22: 350 | BV22: =SUM(BJ22:BU22) -> 350 | CE22: 350 | CK22: =SUM(BY22:CJ22) -> 350 | CT22: 350 | CZ22: =SUM(CN22:CY22) -> 350
B23: Animales muertos | O23: =SUM(C23:N23) -> 0 | AB23: =SUM(P23:AA23) -> 0 | AQ23: =SUM(AE23:AP23) -> 0 | AY23: =146.08+152.86 -> 298.94 | AZ23: =160.56+139.3 -> 299.86 | BC23: =56.45+157.78 -> 214.23 | BF23: 70.93 | BG23: =SUM(AU23:BF23) -> 883.96 | BM23: 149.16 | BO23: =243.1 -> 243.1 | BP23: =144.23+175.34+45.67 -> 365.24 | BT23: 300 | BU23: 200 | BV23: =SUM(BJ23:BU23) -> 1257.5 | CB23: 300 | CF23: 300 | CI23: 200 | CK23: =SUM(BY23:CJ23) -> 800 | CQ23: 300 | CU23: 300 | CX23: 200 | CZ23: =SUM(CN23:CY23) -> 800
B24: Cert. Ecológico - Agrocolor | O24: =SUM(C24:N24) -> 0 | AB24: =SUM(P24:AA24) -> 0 | AI24: 1486.49 | AQ24: =SUM(AE24:AP24) -> 1486.49 | BA24: 1160.75 | BG24: =SUM(AU24:BF24) -> 1160.75 | BK24: 1400.58 | BU24: 1160 | BV24: =SUM(BJ24:BU24) -> 2560.58 | CJ24: 1160 | CK24: =SUM(BY24:CJ24) -> 1160 | CY24: 1160 | CZ24: =SUM(CN24:CY24) -> 1160
B25: Seguro Vacas | O25: =SUM(C25:N25) -> 0 | AB25: =SUM(P25:AA25) -> 0 | AL25: 974.56 | AM25: -3.93 | AO25: =2266.39-672.96 -> 1593.43 | AP25: -6.97 | AQ25: =SUM(AE25:AP25) -> 2557.09 | AV25: =2012.18-1767.77 -> 244.41 | AW25: =-1121.6-1306.89 -> -2428.49 | AY25: =-1325.83+2012.87 -> 687.04 | AZ25: =-1452.1-315.87-1452.1-315.67 -> -3535.74 | BB25: 8609.32 | BC25: =-8609.32+1082.91-476.68 -> -8003.09 | BD25: =-1578.37 -> -1578.37 | BE25: =2628.57-536.26 -> 2092.31 | BG25: =SUM(AU25:BF25) -> -3912.61 | BK25: =2628.57 -> 2628.57 | BM25: -492.1 | BN25: =-1618.25+2629.37 -> 1011.12 | BO25: -2145.78 | BP25: =-387.97 -> -387.97 | BS25: 974.56 | BT25: =2361.41 -> 2361.41 | BV25: =SUM(BJ25:BU25) -> 3949.81 | BZ25: =2361.41 -> 2361.41 | CC25: =2361.41 -> 2361.41 | CF25: 974.56 | CI25: =2361.41 -> 2361.41 | CK25: =SUM(BY25:CJ25) -> 8058.79 | CO25: =2361.41 -> 2361.41 | CR25: =2361.41 -> 2361.41 | CU25: 974.56 | CX25: =2361.41 -> 2361.41 | CZ25: =SUM(CN25:CY25) -> 8058.79
B26: Matadero (Para venta de carne) | O26: =SUM(C26:N26) -> 0 | AB26: =SUM(P26:AA26) -> 0 | AQ26: =SUM(AE26:AP26) -> 0 | BG26: =SUM(AU26:BF26) -> 0 | BV26: =SUM(BJ26:BU26) -> 0 | CK26: =SUM(BY26:CJ26) -> 0 | CZ26: =SUM(CN26:CY26) -> 0
B27: Portes (Para venta de carne) | O27: =SUM(C27:N27) -> 0 | AB27: =SUM(P27:AA27) -> 0 | AQ27: =SUM(AE27:AP27) -> 0 | BA27: 160.19 | BG27: =SUM(AU27:BF27) -> 160.19 | BV27: =SUM(BJ27:BU27) -> 0 | CK27: =SUM(BY27:CJ27) -> 0 | CZ27: =SUM(CN27:CY27) -> 0
B28: Envasado y refrigeración | O28: =SUM(C28:N28) -> 0 | AB28: =SUM(P28:AA28) -> 0 | AQ28: =SUM(AE28:AP28) -> 0 | BG28: =SUM(AU28:BF28) -> 0 | BV28: =SUM(BJ28:BU28) -> 0 | CK28: =SUM(BY28:CJ28) -> 0 | CZ28: =SUM(CN28:CY28) -> 0
B29: Asaja | O29: =SUM(C29:N29) -> 0 | AB29: =SUM(P29:AA29) -> 0 | AQ29: =SUM(AE29:AP29) -> 0 | BG29: =SUM(AU29:BF29) -> 0 | BT29: 200 | BV29: =SUM(BJ29:BU29) -> 200 | CC29: 200 | CK29: =SUM(BY29:CJ29) -> 200 | CR29: 200 | CZ29: =SUM(CN29:CY29) -> 200
B30: Servicio precios lonja | O30: =SUM(C30:N30) -> 0 | AB30: =SUM(P30:AA30) -> 0 | AK30: 350 | AQ30: =SUM(AE30:AP30) -> 350 | AZ30: 360 | BG30: =SUM(AU30:BF30) -> 360 | BP30: 360 | BV30: =SUM(BJ30:BU30) -> 360 | CE30: 350 | CK30: =SUM(BY30:CJ30) -> 350 | CT30: 350 | CZ30: =SUM(CN30:CY30) -> 350
B31: Portes | O31: =SUM(C31:N31) -> 0 | AB31: =SUM(P31:AA31) -> 0 | AP31: 411.4 | AQ31: =SUM(AE31:AP31) -> 411.4 | BB31: =53.34+423.5 -> 476.84 | BG31: =SUM(AU31:BF31) -> 476.84 | BP31: 650 | BQ31: 484 | BV31: =SUM(BJ31:BU31) -> 1134 | CK31: =SUM(BY31:CJ31) -> 0 | CZ31: =SUM(CN31:CY31) -> 0
B32: Comisiones corredor | O32: =SUM(C32:N32) -> 0 | AB32: =SUM(P32:AA32) -> 0 | AI32: =359.72+690 -> 1049.72 | AQ32: =SUM(AE32:AP32) -> 1049.72 | BG32: =SUM(AU32:BF32) -> 0 | BV32: =SUM(BJ32:BU32) -> 0 | CK32: =SUM(BY32:CJ32) -> 0 | CZ32: =SUM(CN32:CY32) -> 0
B33: Total pagos vacuno | C33: =SUM(C19:C32) -> 0 | D33: =SUM(D19:D32) -> 0 | E33: =SUM(E19:E32) -> 0 | F33: =SUM(F19:F32) -> 0 | G33: =SUM(G19:G32) -> 0 | H33: =SUM(H19:H32) -> 0 | I33: =SUM(I19:I32) -> 0 | J33: =SUM(J19:J32) -> 0 | ... AB33: =SUM(AB19:AB32) -> 0 | AE33: =SUM(AE19:AE32) -> 0 | AF33: =SUM(AF19:AF32) -> 0 | AG33: =SUM(AG19:AG32) -> 2310.58 | AH33: =SUM(AH19:AH32) -> 836.06 | AI33: =SUM(AI19:AI32) -> 5019.7136 | AJ33: =SUM(AJ19:AJ32) -> 16.5 | AK33: =SUM(AK19:AK32) -> 350 | AL33: =SUM(AL19:AL32) -> 2104.36 | ... AQ33: =SUM(AQ19:AQ32) -> 15767.024 | AU33: =SUM(AU19:AU32) -> 705.64 | AV33: =SUM(AV19:AV32) -> 2112.36 | AW33: =SUM(AW19:AW32) -> -2118.78 | AX33: =SUM(AX19:AX32) -> 1585.65 | AY33: =SUM(AY19:AY32) -> 2063.23 | AZ33: =SUM(AZ19:AZ32) -> -2875.88 | BA33: =SUM(BA19:BA32) -> 1496.17 | BB33: =SUM(BB19:BB32) -> 10323 | ... BG33: =SUM(BG19:BG32) -> 10893.02 | BJ33: =SUM(BJ19:BJ32) -> 8.93 | BK33: =SUM(BK19:BK32) -> 4924.88 | BL33: =SUM(BL19:BL32) -> 1939.36 | BM33: =SUM(BM19:BM32) -> 1243.61 | BN33: =SUM(BN19:BN32) -> 1931.2 | BO33: =SUM(BO19:BO32) -> -1902.68 | BP33: =SUM(BP19:BP32) -> 1921.29 | BQ33: =SUM(BQ19:BQ32) -> 1054.16 | ... BV33: =SUM(BV19:BV32) -> 21220.57 | BY33: =SUM(BY19:BY32) -> 600 | BZ33: =SUM(BZ19:BZ32) -> 2961.41 | CA33: =SUM(CA19:CA32) -> 600 | CB33: =SUM(CB19:CB32) -> 900 | CC33: =SUM(CC19:CC32) -> 4137.59 | CD33: =SUM(CD19:CD32) -> 600 | CE33: =SUM(CE19:CE32) -> 1300 | CF33: =SUM(CF19:CF32) -> 1874.56 | ... CK33: =SUM(CK19:CK32) -> 19094.97 | CN33: =SUM(CN19:CN32) -> 600 | CO33: =SUM(CO19:CO32) -> 2961.41 | CP33: =SUM(CP19:CP32) -> 600 | CQ33: =SUM(CQ19:CQ32) -> 900 | CR33: =SUM(CR19:CR32) -> 4137.59 | CS33: =SUM(CS19:CS32) -> 600 | CT33: =SUM(CT19:CT32) -> 1300 | CU33: =SUM(CU19:CU32) -> 1874.56 | ... CZ33: =SUM(CZ19:CZ32) -> 19094.97
B34: Check | O34: =SUM(C33:N33)-O33 -> 0 | AB34: =AB33-SUM(P33:AA33) -> 0 | AQ34: =AQ33-SUM(AE33:AP33) -> 0 | BG34: =BG33-SUM(AU33:BF33) -> 0 | BV34: =BV33-SUM(BJ33:BU33) -> 0 | CK34: =CK33-SUM(BY33:CJ33) -> 0 | CZ34: =CZ33-SUM(CN33:CY33) -> 0
B36: Saldo vacuno (mes) | C36: =C16-C33 -> 0 | D36: =D16-D33 -> 0 | E36: =E16-E33 -> 0 | F36: =F16-F33 -> 0 | G36: =G16-G33 -> 0 | H36: =H16-H33 -> 0 | I36: =I16-I33 -> 0 | J36: =J16-J33 -> 0 | ... AB36: =AB16-AB33 -> 0 | AE36: =AE16-AE33 -> 556.3 | AF36: =AF16-AF33 -> 33077.51 | AG36: =AG16-AG33 -> 48994.74 | AH36: =AH16-AH33 -> -836.06 | AI36: =AI16-AI33 -> 32233.956 | AJ36: =AJ16-AJ33 -> -16.5 | AK36: =AK16-AK33 -> -350 | AL36: =AL16-AL33 -> 22802.84 | ... AQ36: =AQ16-AQ33 -> 202820.08 | AU36: =AU16-AU33 -> 19307.8 | AV36: =AV16-AV33 -> 24836.7 | AW36: =AW16-AW33 -> 2433.78 | AX36: =AX16-AX33 -> 10880.66 | AY36: =AY16-AY33 -> 5926.3 | AZ36: =AZ16-AZ33 -> 2875.88 | BA36: =BA16-BA33 -> 8914.5 | BB36: =BB16-BB33 -> 1311.21 | ... BG36: =BG16-BG33 -> 109790.7 | BJ36: =BJ16-BJ33 -> 8083.9 | BK36: =BK16-BK33 -> 24641.73 | BL36: =BL16-BL33 -> 33567.47 | BM36: =BM16-BM33 -> 4270.62 | BN36: =BN16-BN33 -> 6867.7 | BO36: =BO16-BO33 -> 1902.68 | BP36: =BP16-BP33 -> 5699.14 | BQ36: =BQ16-BQ33 -> -777.77 | ... BV36: =BV16-BV33 -> 155074.39 | BY36: =BY16-BY33 -> 5327.5 | BZ36: =BZ16-BZ33 -> 33321.09 | CA36: =CA16-CA33 -> 20497 | CB36: =CB16-CB33 -> 30511.5 | CC36: =CC16-CC33 -> -2952.09 | CD36: =CD16-CD33 -> 5327.5 | CE36: =CE16-CE33 -> 3442 | CF36: =CF16-CF33 -> 496.44 | ... CK36: =CK16-CK33 -> 188435.71 | CN36: =CN16-CN33 -> 29122.333 | CO36: =CO16-CO33 -> 51120.84 | CP36: =CP16-CP33 -> 34180.68 | CQ36: =CQ16-CQ33 -> 22670.17 | CR36: =CR16-CR33 -> 909.19 | CS36: =CS16-CS33 -> 6753.3239 | CT36: =CT16-CT33 -> 4263.2 | CU36: =CU16-CU33 -> 1078.04 | ... CZ36: =CZ16-CZ33 -> 258093.77
B37: Check | O37: =O36-SUM(C36:N36) -> 0 | AB37: =AB36-SUM(P36:AA36) -> 0 | AQ37: =AQ36-SUM(AE36:AP36) -> 0 | BG37: =BG36-SUM(AU36:BF36) -> 0 | BV37: =BV36-SUM(BJ36:BU36) -> 0 | CK37: =CK36-SUM(BY36:CJ36) -> 0 | CZ37: =CZ36-SUM(CN36:CY36) -> 0
B38: Ventas porcino
B39: Montanera propios y de terceros | O39: =SUM(C39:N39) -> 0 | AB39: =SUM(P39:AA39) -> 0 | AL39: =11097.9+18432.79 -> 29530.69 | AM39: =22119.63+9843.78+9810.18 -> 41773.59 | AN39: =SUM('Alimento y ventas'!J304:J304)+18500 -> 18500 | AO39: =SUM('Alimento y ventas'!K304:K304) -> 0 | AP39: =SUM('Alimento y ventas'!L304:L304) -> 0 | AQ39: =SUM(AE39:AP39) -> 89804.28 | AU39: =SUM('Alimento y ventas'!M304:M304) -> 0 | AV39: =SUM('Alimento y ventas'!N304:N304) -> 0 | AW39: =SUM('Alimento y ventas'!O304:O304) -> 0 | AX39: =SUM('Alimento y ventas'!P304:P304) -> 0 | AY39: =SUM('Alimento y ventas'!Q304:Q304) -> 0 | AZ39: =SUM('Alimento y ventas'!T304:T304)*0+17320.32 -> 17320.32 | BA39: =SUM('Alimento y ventas'!U304:U304)*0+((13.9*50*40.55)/2)*1.1*0+14657.02 -> 14657.02 | BB39: =SUM('Alimento y ventas'!V304:V304)*0+17380.33+16491.59+16077.7 -> 49949.62 | BC39: =SUM('Alimento y ventas'!W304:W304)*0+((13.9*50*40.55)/2)*1.1*0+(87*4.66*39.35)*1.1*0+14715.83+1697.03 -> 16412.86 | BD39: =SUM('Alimento y ventas'!X304:X304)*0+541.45 -> 541.45 | BE39: =SUM('Alimento y ventas'!Y304:Y304)*0+543.85 -> 543.85 | BF39: =SUM('Alimento y ventas'!Z304:Z304) -> 0 | BG39: =SUM(AU39:BF39) -> 99425.12 | BJ39: =SUM('Alimento y ventas'!AA304:AA304) -> 0 | BK39: =SUM('Alimento y ventas'!AB304:AB304) -> 0 | BL39: =SUM('Alimento y ventas'!AC304:AC304) -> 0 | BM39: =SUM('Alimento y ventas'!AD304:AD304) -> 0 | BN39: =SUM('Alimento y ventas'!AE304:AE304) -> 0 | BO39: =SUM('Alimento y ventas'!AF304:AF304)*0+15035.34+840-48 -> 15827.34 | BP39: =SUM('Alimento y ventas'!AG304:AG304)/2*0+400 -> 400 | BQ39: =SUM('Alimento y ventas'!AH304:AH304)*0+15035.34+20132.13+6013.35+12813.98+344.01 -> 54338.81 | BR39: =SUM('Alimento y ventas'!AI304:AI304)*0+23768.62*0 -> 0 | BS39: =SUM('Alimento y ventas'!AJ304:AJ304)*0+12400*0 -> 0 | BT39: =SUM('Alimento y ventas'!AK304:AK304) -> 0 | BU39: =SUM('Alimento y ventas'!AL304:AL304) -> 0 | BV39: =SUM(BJ39:BU39) -> 70566.15 | BY39: =SUM('Alimento y ventas'!AM304:AM304) -> 0 | BZ39: =SUM('Alimento y ventas'!AN304:AN304) -> 0 | CA39: =SUM('Alimento y ventas'!AO304:AO304) -> 0 | CB39: =SUM('Alimento y ventas'!AP304:AP304) -> 0 | CC39: =SUM('Alimento y ventas'!AQ304:AQ304) -> 0 | CD39: =SUM('Alimento y ventas'!AR304:AR304) -> 31824 | CE39: =SUM('Alimento y ventas'!AS304:AS304) -> 63648 | CF39: =SUM('Alimento y ventas'!AT304:AT304) -> 31824 | ... CJ39: =SUM('Alimento y ventas'!AX304:AX304) -> 0 | CK39: =SUM(BY39:CJ39) -> 143296 | CN39: =SUM('Alimento y ventas'!AY304:AY304) -> 0 | CO39: =SUM('Alimento y ventas'!AZ304:AZ304) -> 0 | CP39: =SUM('Alimento y ventas'!BA304:BA304) -> 0 | CQ39: =SUM('Alimento y ventas'!BB304:BB304) -> 0 | CR39: =SUM('Alimento y ventas'!BC304:BC304) -> 0 | CS39: =SUM('Alimento y ventas'!BD304:BD304) -> 44640 | CT39: =SUM('Alimento y ventas'!BE304:BE304) -> 89280 | CU39: =SUM('Alimento y ventas'!BF304:BF304) -> 44640 | ... CY39: =SUM('Alimento y ventas'!BJ304:BJ304) -> 0 | CZ39: =SUM(CN39:CY39) -> 178560
B40: Ventas de carne | O40: =SUM(C40:N40) -> 0 | AB40: =SUM(P40:AA40) -> 0 | AE40: =1471.3+422.1+2363.55 -> 4256.95 | AF40: =280.97 -> 280.97 | AG40: =385.6+194.92+3614.33+291.87+405.44+3026.79 -> 7918.95 | AH40: =3683.86+588.23+163.17+600+569.16+114.72+132.39 -> 5851.53 | AI40: =5511+474.08+504.59+62+33.08+28.88+204.05 -> 6817.68 | AJ40: =1725.36 -> 1725.36 | AK40: =190.33+2144.24 -> 2334.57 | AL40: =3553.99+970.99 -> 4524.98 | AM40: =3538.39+2491.42+172.7 -> 6202.51 | AN40: =2805.95+176.55+341.58+30.82+26.75+37.91+34.25 -> 3453.81 | AO40: =11.84 -> 11.84 | AP40: =6962.31+77.02 -> 7039.33 | AQ40: =SUM(AE40:AP40) -> 50418.48 | AU40: 1689.99 | AV40: =4087.71+1754.56 -> 5842.27 | AW40: =363.03+264.86 -> 627.89 | AX40: =2217.47+519.42 -> 2736.89 | AY40: =3129.68 -> 3129.68 | AZ40: =2532.77 -> 2532.77 | BA40: =2677.63+202.38+370.13 -> 3250.14 | BB40: =1532.22 -> 1532.22 | BC40: =3341.7 -> 3341.7 | BD40: =1912.4 -> 1912.4 | BE40: =1444.85+2663.93 -> 4108.78 | BF40: =8083.81 -> 8083.81 | BG40: =SUM(AU40:BF40) -> 38788.54 | BJ40: =3179.61 -> 3179.61 | BK40: =6320.08 -> 6320.08 | BL40: =2131.46+657.22 -> 2788.68 | BM40: =5550.46 -> 5550.46 | BN40: 0 | BO40: =1612.44+5050.16+1071.21+347.37+218.9 -> 8300.08 | BP40: =3241.29 -> 3241.29 | BQ40: =2841.52 -> 2841.52 | BR40: =1845.35 -> 1845.35 | BS40: =4137.18-96.89+3799.58+196.2 -> 8036.07 | BT40: 3349.97 | BU40: 5221.49 | BV40: =SUM(BJ40:BU40) -> 50674.6 | CK40: =SUM(BY40:CJ40) -> 0 | CL40: =338*250 -> 84500 | CZ40: =SUM(CN40:CY40) -> 0
B41: Venta chacinas y paletas | O41: =SUM(C41:N41) -> 0 | AB41: =SUM(P41:AA41) -> 0 | AM41: 110 | AQ41: =SUM(AE41:AP41) -> 110 | AV41: =11.1+36.31+33 -> 80.41 | AW41: =720+235.84+84+88+70 -> 1197.84 | AX41: =89.2+114.4+227.04+111.76+184.4+459.7 -> 1186.5 | AY41: =124.96+139.15+95.6+78 -> 437.71 | AZ41: =178.62+106.92+111.32 -> 396.86 | BA41: =298.21+10 -> 308.21 | BB41: =132.11+150.81+233.97+137.61+168.96+218.4+136.89+144.77+285.44+235.2 -> 1844.16 | BC41: =225+205.65+29 -> 459.65 | BE41: =131.89+126.61+126.61 -> 385.11 | BF41: =142.89+127.82+130.57 -> 401.28 | BG41: =SUM(AU41:BF41) -> 6697.73 | BJ41: =129.25+108.9+500.28 -> 738.43 | BK41: 127.45 | BL41: =586.52+76.8+100.32+97.85+120.45+105.6+133.65+243.54+227.92+107.36+120.01+127.05+136.62 -> 2183.69 | BM41: =303.6+97.68 -> 401.28 | BN41: =241.12+140.25+296.5+150.7+141.5+337.04+254.54+110+121.6+156.7+156.2+152.46+135.88+141.24+154.66+750 -> 3440.39 | BO41: =106+2006.4+135.41+1996.37+165+140.69+116.8+136.95+141.46+111.32+287+479.6+556+850 -> 7229 | BP41: =113.08+123.54+122.76 -> 359.38 | BQ41: =150+380+134.68+157.23+154.22 -> 976.13 | BR41: =285.26+344.83+171.91+324.84 -> 1126.84 | BS41: =111.76+98.4+983.75+131.45+3015.32-1585.22 -> 2755.46 | BT41: 1100 | BU41: 1100 | BV41: =SUM(BJ41:BU41) -> 21538.05 | CK41: =SUM(BY41:CJ41) -> 0 | CZ41: =SUM(CN41:CY41) -> 0
B42: Total cobros porcino | C42: =SUM(C39:C41) -> 0 | D42: =SUM(D39:D41) -> 0 | E42: =SUM(E39:E41) -> 0 | F42: =SUM(F39:F41) -> 0 | G42: =SUM(G39:G41) -> 0 | H42: =SUM(H39:H41) -> 0 | I42: =SUM(I39:I41) -> 0 | J42: =SUM(J39:J41) -> 0 | ... AB42: =SUM(AB39:AB41) -> 0 | AE42: =SUM(AE39:AE41) -> 4256.95 | AF42: =SUM(AF39:AF41) -> 280.97 | AG42: =SUM(AG39:AG41) -> 7918.95 | AH42: =SUM(AH39:AH41) -> 5851.53 | AI42: =SUM(AI39:AI41) -> 6817.68 | AJ42: =SUM(AJ39:AJ41) -> 1725.36 | AK42: =SUM(AK39:AK41) -> 2334.57 | AL42: =SUM(AL39:AL41) -> 34055.67 | ... AQ42: =SUM(AQ39:AQ41) -> 140332.76 | AU42: =SUM(AU39:AU41) -> 1689.99 | AV42: =SUM(AV39:AV41) -> 5922.68 | AW42: =SUM(AW39:AW41) -> 1825.73 | AX42: =SUM(AX39:AX41) -> 3923.39 | AY42: =SUM(AY39:AY41) -> 3567.39 | AZ42: =SUM(AZ39:AZ41) -> 20249.95 | BA42: =SUM(BA39:BA41) -> 18215.37 | BB42: =SUM(BB39:BB41) -> 53326 | ... BG42: =SUM(BG39:BG41) -> 144911.39 | BJ42: =SUM(BJ39:BJ41) -> 3918.04 | BK42: =SUM(BK39:BK41) -> 6447.53 | BL42: =SUM(BL39:BL41) -> 4972.37 | BM42: =SUM(BM39:BM41) -> 5951.74 | BN42: =SUM(BN39:BN41) -> 3440.39 | BO42: =SUM(BO39:BO41) -> 31356.42 | BP42: =SUM(BP39:BP41) -> 4000.67 | BQ42: =SUM(BQ39:BQ41) -> 58156.46 | ... BV42: =SUM(BV39:BV41) -> 142778.8 | BY42: =SUM(BY39:BY41) -> 0 | BZ42: =SUM(BZ39:BZ41) -> 0 | CA42: =SUM(CA39:CA41) -> 0 | CB42: =SUM(CB39:CB41) -> 0 | CC42: =SUM(CC39:CC41) -> 0 | CD42: =SUM(CD39:CD41) -> 31824 | CE42: =SUM(CE39:CE41) -> 63648 | CF42: =SUM(CF39:CF41) -> 31824 | ... CK42: =SUM(CK39:CK41) -> 143296 | CN42: =SUM(CN39:CN41) -> 0 | CO42: =SUM(CO39:CO41) -> 0 | CP42: =SUM(CP39:CP41) -> 0 | CQ42: =SUM(CQ39:CQ41) -> 0 | CR42: =SUM(CR39:CR41) -> 0 | CS42: =SUM(CS39:CS41) -> 44640 | CT42: =SUM(CT39:CT41) -> 89280 | CU42: =SUM(CU39:CU41) -> 44640 | ... CZ42: =SUM(CZ39:CZ41) -> 178560
B43: Check | O43: =O42-SUM(C42:N42) -> 0 | AB43: =AB42-SUM(P42:AA42) -> 0 | AQ43: =AQ42-SUM(AE42:AP42) -> 0 | BG43: =BG42-SUM(AU42:BF42) -> 0 | BV43: =BV42-SUM(BJ42:BU42) -> 0 | CK43: =CK42-SUM(BY42:CJ42) -> 0 | CZ43: =CZ42-SUM(CN42:CY42) -> 0
B44: Gastos porcino
B45: Compra de animales | O45: =SUM(C45:N45) -> 0 | AB45: =SUM(P45:AA45) -> 0 | AQ45: =SUM(AE45:AP45) -> 0 | BD45: =180+900 -> 1080 | BG45: =SUM(AU45:BF45) -> 1080 | BV45: =SUM(BJ45:BU45) -> 0 | CK45: =SUM(BY45:CJ45) -> 0 | CZ45: =SUM(CN45:CY45) -> 0 | DC45: 345.66
B46: Comisiones corredor | O46: =SUM(C46:N46) -> 0 | AB46: =SUM(P46:AA46) -> 0 | AQ46: =SUM(AE46:AP46) -> 0 | BG46: =SUM(AU46:BF46) -> 0 | BV46: =SUM(BJ46:BU46) -> 0 | CK46: =SUM(BY46:CJ46) -> 0 | CZ46: =SUM(CN46:CY46) -> 0
B47: Medicamentos y Vet. | O47: =SUM(C47:N47) -> 0 | AB47: =SUM(P47:AA47) -> 0 | AG47: =256.3 -> 256.3 | AH47: =88.7 -> 88.7 | AI47: =83.2+30.07+67.7+94.84+249.08+320.77 -> 845.66 | AJ47: =181.53 -> 181.53 | AK47: =110+886.8+94.84+33 -> 1124.64 | AL47: =280 -> 280 | AM47: =70*1.1 -> 77 | AO47: =141.1 -> 141.1 | AP47: 71.93 | AQ47: =SUM(AE47:AP47) -> 3066.86 | AU47: =154.5+133 -> 287.5 | AX47: =49.5+49.5+137.5 -> 236.5 | AY47: =53.3+29.04 -> 82.34 | AZ47: =225.53 -> 225.53 | BB47: =81*0 -> 0 | BC47: =77+90.2+142.32 -> 309.52 | BD47: =90.75+50 -> 140.75 | BF47: =154 -> 154 | BG47: =SUM(AU47:BF47) -> 1436.14 | BJ47: =212.5*0 -> 0 | BL47: =132+77+71.5+152.76+240.33+101.13 -> 774.72 | BM47: =137.5+200.62 -> 338.12 | BO47: 81.43 | BP47: =16.5 -> 16.5 | BR47: =71.5+66+183.26 -> 320.76 | BS47: =152.5 -> 152.5 | BT47: 200 | BU47: 200 | BV47: =SUM(BJ47:BU47) -> 2084.03 | BY47: 250 | BZ47: 250 | CA47: 250 | CB47: 250 | CC47: 250 | CD47: 250 | CE47: 250 | CF47: 250 | CG47: 250 | CH47: 250 | CI47: 250 | CJ47: 250 | CK47: =SUM(BY47:CJ47) -> 3000 | CN47: 250 | CO47: 250 | CP47: 250 | CQ47: 250 | CR47: 250 | CS47: 250 | CT47: 250 | CU47: 250 | CV47: 250 | CW47: 250 | CX47: 250 | CY47: 250 | CZ47: =SUM(CN47:CY47) -> 3000
B48: Compra de carne | O48: =SUM(C48:N48) -> 0 | AB48: =SUM(P48:AA48) -> 0 | AF48: =2442.5 -> 2442.5 | AG48: =3296.58 -> 3296.58 | AH48: =4125.2 -> 4125.2 | AI48: =1508.97+1228.16 -> 2737.13 | AJ48: 2925.45 | AL48: =2108.95+528+2850.34 -> 5487.29 | AM48: =3176.25+2362.94+325.96 -> 5865.15 | AN48: =1734.19+4360.55 -> 6094.74 | AO48: =171.29+163.74+1335.53+3631.07 -> 5301.63 | AP48: =1613.73+64.81 -> 1678.54 | AQ48: =SUM(AE48:AO48) -> 38275.67 | AU48: =317.39 -> 317.39 | AW48: =1796.93+2435.72 -> 4232.65 | AX48: =158.17+2749.76 -> 2907.93 | AY48: =247.5+201.96+2247.66+132.5 -> 2829.62 | AZ48: =1276.95 -> 1276.95 | BA48: =99.33+1459.37 -> 1558.7 | BB48: =308.56+291.49+1403.22+178.22+1475.18+85.78 -> 3742.45 | BC48: =313.56+346.52+2324.39+2324.39+1116.81 -> 6425.67 | BD48: =-2324.39+179.71+317.99+6406.57 -> 4579.88 | BF48: =197.62+1682.27+1297.42 -> 3177.31 | BG48: =SUM(AU48:BF48) -> 31048.55 | BK48: =1068.65+744.95+3347.29+557.25+1932.92 -> 7651.06 | BL48: =786.67+5107.61-21.53+316.56+1282.22+1282.22+316.56 -> 9070.31 | BM48: =-1282.22-295.03-21.53+1638.08+167.16+323.96 -> 530.42 | BO48: =3927.39+739.3+338.69+2722.38 -> 7727.76 | BP48: =3109.41+363.95+1679.72+141.16 -> 5294.24 | BQ48: =3408.8+148.97+140.7+2083.27 -> 5781.74 | BS48: =2786.1+781.11+94.38+3447.52 -> 7109.11 | BV48: =SUM(BJ48:BT48) -> 43164.64 | CK48: =SUM(BY48:CI48) -> 0 | CZ48: =SUM(CN48:CX48) -> 0
B49: Matadero (Para venta de carne) | O49: =SUM(C49:N49) -> 0 | AB49: =SUM(P49:AA49) -> 0 | AG49: =(82)*3.25*1.1 -> 293.15 | AH49: =150*3.25*1.1 -> 536.25 | AQ49: =SUM(AE49:AP49) -> 829.4 | AV49: 73.57 | BG49: =SUM(AU49:BF49) -> 73.57 | BV49: =SUM(BJ49:BU49) -> 0 | CK49: =SUM(BY49:CJ49) -> 0 | CZ49: =SUM(CN49:CY49) -> 0
B50: Envasado y almacenamiento | O50: =SUM(C50:N50) -> 0 | AB50: =SUM(P50:AA50) -> 0 | AF50: =137.76 -> 137.76 | AG50: 133.66 | AH50: =127.06+120.69 -> 247.75 | AI50: =34.26+96.8 -> 131.06 | AJ50: 31.29 | AL50: =25.93 -> 25.93 | AM50: =21.21 -> 21.21 | AN50: =15.56+17.06 -> 32.62 | AO50: 11.64 | AP50: 9.83 | AQ50: =SUM(AE50:AP50) -> 782.75 | AU50: 7.45 | AW50: =7.45+4.84 -> 12.29 | AX50: =9.68+2.61 -> 12.29 | AY50: =-2.23+7.45 -> 5.22 | BA50: 7.45 | BB50: =6.26+1105.78+89.22 -> 1201.26 | BC50: =1547.04+2596+5.07+5.07 -> 4153.18 | BD50: =5.07 -> 5.07 | BF50: =228.92+139.9+5.07+345.4+5.07 -> 724.36 | BG50: =SUM(AU50:BF50) -> 6128.57 | BK50: =5.07+5.07 -> 10.14 | BL50: =279.65+4.42 -> 284.07 | BM50: =3.76+4178.02+200.97 -> 4382.75 | BN50: =213.1+1261+982.28 -> 2456.38 | BP50: =3.76+3.76+3.76 -> 11.28 | BR50: =2759.9+16.95+1643.18 -> 4420.03 | BS50: =296+14.99 -> 310.99 | BV50: =SUM(BJ50:BU50) -> 11875.64 | CK50: =SUM(BY50:CJ50) -> 0 | CZ50: =SUM(CN50:CY50) -> 0
B51: Certificación Bellota | O51: =SUM(C51:N51) -> 0 | AB51: =SUM(P51:AA51) -> 0 | AH51: =130*1.21 -> 157.3 | AI51: =1829.52 -> 1829.52 | AP51: 181.5 | AQ51: =SUM(AE51:AP51) -> 2168.32 | AU51: =181.5+290.4 -> 471.9 | AX51: =181.5 -> 181.5 | BA51: =22 -> 22 | BB51: =1796.85+145.2 -> 1942.05 | BF51: 181.5 | BG51: =SUM(AU51:BF51) -> 2798.95 | BM51: =1346.13+771.98 -> 2118.11 | BT51: 200 | BU51: 1500 | BV51: =SUM(BJ51:BU51) -> 3818.11 | BY51: 500 | CA51: 1500 | CB51: 500 | CC51: 500 | CF51: 2000 | CK51: =SUM(BY51:CJ51) -> 5000 | CN51: 500 | CP51: 1500 | CQ51: 500 | CR51: 500 | CU51: 2000 | CZ51: =SUM(CN51:CY51) -> 5000
B52: Portes | O52: =SUM(C52:N52) -> 0 | AB52: =SUM(P52:AA52) -> 0 | AG52: =54.04+26.54 -> 80.58 | AH52: 75.89 | AI52: =471 -> 471 | AJ52: =369.44+127.55 -> 496.99 | AK52: =305.99*1.21 -> 370.2479 | AL52: =368.6 -> 368.6 | AM52: =367.89+138.29 -> 506.18 | AN52: =367.71 -> 367.71 | AO52: 369.29 | AP52: 366.55 | AQ52: =SUM(AE52:AP52) -> 3473.0379 | AU52: =518.38+364.52 -> 882.9 | AV52: =-25.18 -> -25.18 | AW52: 363.35 | AX52: =364.22-24.01 -> 340.21 | AY52: =363.02+847 -> 1210.02 | AZ52: 363.1 | BA52: 363.81 | BB52: 364.25 | BC52: 366.41 | BD52: 438.87 | BE52: 364.61 | BF52: 363.77 | BG52: =SUM(AU52:BF52) -> 5396.12 | BJ52: 362.52 | BK52: =363.12+364.31 -> 727.43 | BM52: =364.42+968+296.99+496.98+364.09 -> 2490.48 | BN52: =363.71+319.4 -> 683.11 | BO52: 19.28 | BP52: =363.87+364.1 -> 727.97 | BQ52: =159.22+278.3 -> 437.52 | BR52: =363.3+99.03 -> 462.33 | BS52: 377.71 | BT52: 404.67 | BV52: =SUM(BJ52:BU52) -> 6693.02 | CK52: =SUM(BY52:CJ52) -> 0 | CZ52: =SUM(CN52:CY52) -> 0
B53: Saneamientos | O53: =SUM(C53:N53) -> 0 | AB53: =SUM(P53:AA53) -> 0 | AQ53: =SUM(AE53:AP53) -> 0 | BG53: =SUM(AU53:BF53) -> 0 | BV53: =SUM(BJ53:BU53) -> 0 | CK53: =SUM(BY53:CJ53) -> 0 | CZ53: =SUM(CN53:CY53) -> 0
B54: Total pagos porcino | C54: =SUM(C45:C53) -> 0 | D54: =SUM(D45:D53) -> 0 | E54: =SUM(E45:E53) -> 0 | F54: =SUM(F45:F53) -> 0 | G54: =SUM(G45:G53) -> 0 | H54: =SUM(H45:H53) -> 0 | I54: =SUM(I45:I53) -> 0 | J54: =SUM(J45:J53) -> 0 | ... AB54: =SUM(AB45:AB53) -> 0 | AE54: =SUM(AE45:AE53) -> 0 | AF54: =SUM(AF45:AF53) -> 2580.26 | AG54: =SUM(AG45:AG53) -> 4060.27 | AH54: =SUM(AH45:AH53) -> 5231.09 | AI54: =SUM(AI45:AI53) -> 6014.37 | AJ54: =SUM(AJ45:AJ53) -> 3635.26 | AK54: =SUM(AK45:AK53) -> 1494.8879 | AL54: =SUM(AL45:AL53) -> 6161.82 | ... AQ54: =SUM(AQ45:AQ53) -> 48596.038 | AU54: =SUM(AU45:AU53) -> 1967.14 | AV54: =SUM(AV45:AV53) -> 48.39 | AW54: =SUM(AW45:AW53) -> 4608.29 | AX54: =SUM(AX45:AX53) -> 3678.43 | AY54: =SUM(AY45:AY53) -> 4127.2 | AZ54: =SUM(AZ45:AZ53) -> 1865.58 | BA54: =SUM(BA45:BA53) -> 1951.96 | BB54: =SUM(BB45:BB53) -> 7250.01 | ... BG54: =SUM(BG45:BG53) -> 47961.9 | BJ54: =SUM(BJ45:BJ53) -> 362.52 | BK54: =SUM(BK45:BK53) -> 8388.63 | BL54: =SUM(BL45:BL53) -> 10129.1 | BM54: =SUM(BM45:BM53) -> 9859.88 | BN54: =SUM(BN45:BN53) -> 3139.49 | BO54: =SUM(BO45:BO53) -> 7828.47 | BP54: =SUM(BP45:BP53) -> 6049.99 | BQ54: =SUM(BQ45:BQ53) -> 6219.26 | ... BV54: =SUM(BV45:BV53) -> 67635.44 | BY54: =SUM(BY45:BY53) -> 750 | BZ54: =SUM(BZ45:BZ53) -> 250 | CA54: =SUM(CA45:CA53) -> 1750 | CB54: =SUM(CB45:CB53) -> 750 | CC54: =SUM(CC45:CC53) -> 750 | CD54: =SUM(CD45:CD53) -> 250 | CE54: =SUM(CE45:CE53) -> 250 | CF54: =SUM(CF45:CF53) -> 2250 | ... CK54: =SUM(CK45:CK53) -> 8000 | CN54: =SUM(CN45:CN53) -> 750 | CO54: =SUM(CO45:CO53) -> 250 | CP54: =SUM(CP45:CP53) -> 1750 | CQ54: =SUM(CQ45:CQ53) -> 750 | CR54: =SUM(CR45:CR53) -> 750 | CS54: =SUM(CS45:CS53) -> 250 | CT54: =SUM(CT45:CT53) -> 250 | CU54: =SUM(CU45:CU53) -> 2250 | ... CZ54: =SUM(CZ45:CZ53) -> 8000
B55: Check | O55: =O54-SUM(C54:N54) -> 0 | AB55: =AB54-SUM(P54:AA54) -> 0 | AQ55: =AQ54-SUM(AE54:AP54) -> -1678.54 | BG55: =BG54-SUM(AU54:BF54) -> 0 | BV55: =BV54-SUM(BJ54:BU54) -> 0 | CK55: =CK54-SUM(BY54:CJ54) -> 0 | CZ55: =CZ54-SUM(CN54:CY54) -> 0
B57: Saldo porcino (mes) | C57: =C42-C54 -> 0 | D57: =D42-D54 -> 0 | E57: =E42-E54 -> 0 | F57: =F42-F54 -> 0 | G57: =G42-G54 -> 0 | H57: =H42-H54 -> 0 | I57: =I42-I54 -> 0 | J57: =J42-J54 -> 0 | ... AB57: =AB42-AB54 -> 0 | AE57: =AE42-AE54 -> 4256.95 | AF57: =AF42-AF54 -> -2299.29 | AG57: =AG42-AG54 -> 3858.68 | AH57: =AH42-AH54 -> 620.44 | AI57: =AI42-AI54 -> 803.31 | AJ57: =AJ42-AJ54 -> -1909.9 | AK57: =AK42-AK54 -> 839.6821 | AL57: =AL42-AL54 -> 27893.85 | ... AQ57: =AQ42-AQ54 -> 91736.722 | AU57: =AU42-AU54 -> -277.15 | AV57: =AV42-AV54 -> 5874.29 | AW57: =AW42-AW54 -> -2782.56 | AX57: =AX42-AX54 -> 244.96 | AY57: =AY42-AY54 -> -559.81 | AZ57: =AZ42-AZ54 -> 18384.37 | BA57: =BA42-BA54 -> 16263.41 | BB57: =BB42-BB54 -> 46075.99 | ... BG57: =BG42-BG54 -> 96949.49 | BJ57: =BJ42-BJ54 -> 3555.52 | BK57: =BK42-BK54 -> -1941.1 | BL57: =BL42-BL54 -> -5156.73 | BM57: =BM42-BM54 -> -3908.14 | BN57: =BN42-BN54 -> 300.9 | BO57: =BO42-BO54 -> 23527.95 | BP57: =BP42-BP54 -> -2049.32 | BQ57: =BQ42-BQ54 -> 51937.2 | ... BV57: =BV42-BV54 -> 75143.36 | BY57: =BY42-BY54 -> -750 | BZ57: =BZ42-BZ54 -> -250 | CA57: =CA42-CA54 -> -1750 | CB57: =CB42-CB54 -> -750 | CC57: =CC42-CC54 -> -750 | CD57: =CD42-CD54 -> 31574 | CE57: =CE42-CE54 -> 63398 | CF57: =CF42-CF54 -> 29574 | ... CK57: =CK42-CK54 -> 135296 | CN57: =CN42-CN54 -> -750 | CO57: =CO42-CO54 -> -250 | CP57: =CP42-CP54 -> -1750 | CQ57: =CQ42-CQ54 -> -750 | CR57: =CR42-CR54 -> -750 | CS57: =CS42-CS54 -> 44390 | CT57: =CT42-CT54 -> 89030 | CU57: =CU42-CU54 -> 42390 | ... CZ57: =CZ42-CZ54 -> 170560
B58: Check | O58: =O57-SUM(C57:N57) -> 0 | AB58: =AB57-SUM(P57:AA57) -> 0 | AQ58: =AQ57-SUM(AE57:AP57) -> 1678.54 | BG58: =BG57-SUM(AU57:BF57) -> 0 | BV58: =BV57-SUM(BJ57:BU57) -> 0 | CK58: =CK57-SUM(BY57:CJ57) -> 0 | CZ58: =CZ57-SUM(CN57:CY57) -> 0
B59: Ventas ovino
B60: Corderos/ovejas/carneros | AB60: =SUM(P60:AA60) -> 0 | AG60: =352+(120*75+30*35)*1.1+450*1.1 -> 11902 | AI60: =2858.9 -> 2858.9 | AM60: 75 | AN60: 900 | AQ60: =SUM(AE60:AP60) -> 15735.9 | AY60: 180 | BB60: 1232 | BG60: =SUM(AU60:BF60) -> 1412 | BM60: 365 | BO60: 400 | BQ60: 1045 | BV60: =SUM(BJ60:BU60) -> 1810 | CK60: =SUM(BY60:CJ60) -> 0 | CZ60: =SUM(CN60:CY60) -> 0 | DC60: =-2858.9 -> -2858.9
B61: Total Ventas ovino | P61: =SUM(P60:P60) -> 0 | Q61: =SUM(Q60:Q60) -> 0 | R61: =SUM(R60:R60) -> 0 | S61: =SUM(S60:S60) -> 0 | T61: =SUM(T60:T60) -> 0 | U61: =SUM(U60:U60) -> 0 | V61: =SUM(V60:V60) -> 0 | W61: =SUM(W60:W60) -> 0 | ... AA61: =SUM(AA60:AA60) -> 0 | AB61: =AB60 -> 0 | AE61: =SUM(AE60:AE60) -> 0 | AF61: =SUM(AF60:AF60) -> 0 | AG61: =SUM(AG60:AG60) -> 11902 | AH61: =SUM(AH60:AH60) -> 0 | AI61: =SUM(AI60:AI60) -> 2858.9 | AJ61: =SUM(AJ60:AJ60) -> 0 | AK61: =SUM(AK60:AK60) -> 0 | AL61: =SUM(AL60:AL60) -> 0 | ... AP61: =SUM(AP60:AP60) -> 0 | AQ61: =AQ60 -> 15735.9 | AU61: =SUM(AU60:AU60) -> 0 | AV61: =SUM(AV60:AV60) -> 0 | AW61: =SUM(AW60:AW60) -> 0 | AX61: =SUM(AX60:AX60) -> 0 | AY61: =SUM(AY60:AY60) -> 180 | AZ61: =SUM(AZ60:AZ60) -> 0 | BA61: =SUM(BA60:BA60) -> 0 | BB61: =SUM(BB60:BB60) -> 1232 | ... BF61: =SUM(BF60:BF60) -> 0 | BG61: =BG60 -> 1412 | BJ61: =SUM(BJ60:BJ60) -> 0 | BK61: =SUM(BK60:BK60) -> 0 | BL61: =SUM(BL60:BL60) -> 0 | BM61: =SUM(BM60:BM60) -> 365 | BN61: =SUM(BN60:BN60) -> 0 | BO61: =SUM(BO60:BO60) -> 400 | BP61: =SUM(BP60:BP60) -> 0 | BQ61: =SUM(BQ60:BQ60) -> 1045 | ... BU61: =SUM(BU60:BU60) -> 0 | BV61: =BV60 -> 1810 | BY61: =SUM(BY60:BY60) -> 0 | BZ61: =SUM(BZ60:BZ60) -> 0 | CA61: =SUM(CA60:CA60) -> 0 | CB61: =SUM(CB60:CB60) -> 0 | CC61: =SUM(CC60:CC60) -> 0 | CD61: =SUM(CD60:CD60) -> 0 | CE61: =SUM(CE60:CE60) -> 0 | CF61: =SUM(CF60:CF60) -> 0 | ... CJ61: =SUM(CJ60:CJ60) -> 0 | CK61: =CK60 -> 0 | CN61: =SUM(CN60:CN60) -> 0 | CO61: =SUM(CO60:CO60) -> 0 | CP61: =SUM(CP60:CP60) -> 0 | CQ61: =SUM(CQ60:CQ60) -> 0 | CR61: =SUM(CR60:CR60) -> 0 | CS61: =SUM(CS60:CS60) -> 0 | CT61: =SUM(CT60:CT60) -> 0 | CU61: =SUM(CU60:CU60) -> 0 | ... CY61: =SUM(CY60:CY60) -> 0 | CZ61: =CZ60 -> 0
B62: Check
B63: Subvención ovejas | AB63: =SUM(P63:AA63) -> 0 | AQ63: =SUM(AE63:AP63) -> 0 | BG63: =SUM(AU63:BF63) -> 0 | BV63: =SUM(BJ63:BU63) -> 0 | CK63: =SUM(BY63:CJ63) -> 0 | CZ63: =SUM(CN63:CY63) -> 0
B65: Total cobros ovino | P65: =P63+P61 -> 0 | Q65: =Q63+Q61 -> 0 | R65: =R63+R61 -> 0 | S65: =S63+S61 -> 0 | T65: =T63+T61 -> 0 | U65: =U63+U61 -> 0 | V65: =V63+V61 -> 0 | W65: =W63+W61 -> 0 | ... AA65: =AA63+AA61 -> 0 | AB65: =AB61+AB63 -> 0 | AE65: =AE63+AE61 -> 0 | AF65: =AF63+AF61 -> 0 | AG65: =AG63+AG61 -> 11902 | AH65: =AH63+AH61 -> 0 | AI65: =AI63+AI61 -> 2858.9 | AJ65: =AJ63+AJ61 -> 0 | AK65: =AK63+AK61 -> 0 | AL65: =AL63+AL61 -> 0 | ... AP65: =AP63+AP61 -> 0 | AQ65: =AQ61+AQ63 -> 15735.9 | AU65: =AU63+AU61 -> 0 | AV65: =AV63+AV61 -> 0 | AW65: =AW63+AW61 -> 0 | AX65: =AX63+AX61 -> 0 | AY65: =AY63+AY61 -> 180 | AZ65: =AZ63+AZ61 -> 0 | BA65: =BA63+BA61 -> 0 | BB65: =BB63+BB61 -> 1232 | ... BF65: =BF63+BF61 -> 0 | BG65: =BG61+BG63 -> 1412 | BJ65: =BJ63+BJ61 -> 0 | BK65: =BK63+BK61 -> 0 | BL65: =BL63+BL61 -> 0 | BM65: =BM63+BM61 -> 365 | BN65: =BN63+BN61 -> 0 | BO65: =BO63+BO61 -> 400 | BP65: =BP63+BP61 -> 0 | BQ65: =BQ63+BQ61 -> 1045 | ... BU65: =BU63+BU61 -> 0 | BV65: =BV61+BV63 -> 1810 | BY65: =BY63+BY61 -> 0 | BZ65: =BZ63+BZ61 -> 0 | CA65: =CA63+CA61 -> 0 | CB65: =CB63+CB61 -> 0 | CC65: =CC63+CC61 -> 0 | CD65: =CD63+CD61 -> 0 | CE65: =CE63+CE61 -> 0 | CF65: =CF63+CF61 -> 0 | ... CJ65: =CJ63+CJ61 -> 0 | CK65: =CK61+CK63 -> 0 | CN65: =CN63+CN61 -> 0 | CO65: =CO63+CO61 -> 0 | CP65: =CP63+CP61 -> 0 | CQ65: =CQ63+CQ61 -> 0 | CR65: =CR63+CR61 -> 0 | CS65: =CS63+CS61 -> 0 | CT65: =CT63+CT61 -> 0 | CU65: =CU63+CU61 -> 0 | ... CY65: =CY63+CY61 -> 0 | CZ65: =CZ61+CZ63 -> 0
AQ66: =AQ65-SUM(AE65:AP65) -> 0
B67: Gastos Ovino
B68: Medicamentos y Vet. | AB68: =SUM(P68:AA68) -> 0 | AH68: =49.5+0.7 -> 50.2 | AM68: =15*1.1 -> 16.5 | AQ68: =SUM(AE68:AP68) -> 66.7 | AY68: 57.2 | BF68: =72.6+22 -> 94.6 | BG68: =SUM(AU68:BF68) -> 151.8 | BV68: =SUM(BJ68:BU68) -> 0 | CK68: =SUM(BY68:CJ68) -> 0 | CZ68: =SUM(CN68:CY68) -> 0
B69: Crotales | AB69: =SUM(P69:AA69) -> 0 | AQ69: =SUM(AE69:AP69) -> 0 | BG69: =SUM(AU69:BF69) -> 0 | BV69: =SUM(BJ69:BU69) -> 0 | CK69: =SUM(BY69:CJ69) -> 0 | CZ69: =SUM(CN69:CY69) -> 0
B70: Programa de gestión | AB70: =SUM(P70:AA70) -> 0 | AQ70: =SUM(AE70:AP70) -> 0 | BG70: =SUM(AU70:BF70) -> 0 | BV70: =SUM(BJ70:BU70) -> 0 | CK70: =SUM(BY70:CJ70) -> 0 | CZ70: =SUM(CN70:CY70) -> 0
B71: Saneamientos | AB71: =SUM(P71:AA71) -> 0 | AQ71: =SUM(AE71:AP71) -> 0 | BG71: =SUM(AU71:BF71) -> 0 | BV71: =SUM(BJ71:BU71) -> 0 | CK71: =SUM(BY71:CJ71) -> 0 | CZ71: =SUM(CN71:CY71) -> 0
B72: Comision corredor | AG72: 363.84 | AQ72: =SUM(AE72:AP72) -> 363.84 | BD72: 120 | BG72: =SUM(AU72:BF72) -> 120 | BV72: =SUM(BJ72:BU72) -> 0 | CK72: =SUM(BY72:CJ72) -> 0 | CZ72: =SUM(CN72:CY72) -> 0
B73: Total pagos Ovino | P73: =SUM(P68:P71) -> 0 | Q73: =SUM(Q68:Q71) -> 0 | R73: =SUM(R68:R71) -> 0 | S73: =SUM(S68:S71) -> 0 | T73: =SUM(T68:T71) -> 0 | U73: =SUM(U68:U71) -> 0 | V73: =SUM(V68:V71) -> 0 | W73: =SUM(W68:W71) -> 0 | ... AB73: =SUM(AB68:AB71) -> 0 | AE73: =SUM(AE68:AE71) -> 0 | AF73: =SUM(AF68:AF71) -> 0 | AG73: =SUM(AG68:AG72) -> 363.84 | AH73: =SUM(AH68:AH72) -> 50.2 | AI73: =SUM(AI68:AI72) -> 0 | AJ73: =SUM(AJ68:AJ72) -> 0 | AK73: =SUM(AK68:AK72) -> 0 | AL73: =SUM(AL68:AL72) -> 0 | AM73: =SUM(AM68:AM72) -> 16.5 | AN73: =SUM(AN68:AN72) -> 0 | ... AQ73: =SUM(AQ68:AQ72) -> 430.54 | AU73: =SUM(AU68:AU71) -> 0 | AV73: =SUM(AV68:AV71) -> 0 | AW73: =SUM(AW68:AW71) -> 0 | AX73: =SUM(AX68:AX71) -> 0 | AY73: =SUM(AY68:AY71) -> 57.2 | AZ73: =SUM(AZ68:AZ71) -> 0 | BA73: =SUM(BA68:BA71) -> 0 | BB73: =SUM(BB68:BB71) -> 0 | BC73: =SUM(BC68:BC71) -> 0 | BD73: =SUM(BD68:BD72) -> 120 | BE73: =SUM(BE68:BE72) -> 0 | BF73: =SUM(BF68:BF72) -> 94.6 | BG73: =SUM(BG68:BG72) -> 271.8 | BJ73: =SUM(BJ68:BJ72) -> 0 | BK73: =SUM(BK68:BK72) -> 0 | BL73: =SUM(BL68:BL72) -> 0 | BM73: =SUM(BM68:BM72) -> 0 | BN73: =SUM(BN68:BN72) -> 0 | BO73: =SUM(BO68:BO72) -> 0 | BP73: =SUM(BP68:BP72) -> 0 | BQ73: =SUM(BQ68:BQ72) -> 0 | ... BV73: =SUM(BV68:BV72) -> 0 | BY73: =SUM(BY68:BY72) -> 0 | BZ73: =SUM(BZ68:BZ72) -> 0 | CA73: =SUM(CA68:CA72) -> 0 | CB73: =SUM(CB68:CB72) -> 0 | CC73: =SUM(CC68:CC72) -> 0 | CD73: =SUM(CD68:CD72) -> 0 | CE73: =SUM(CE68:CE72) -> 0 | CF73: =SUM(CF68:CF72) -> 0 | ... CK73: =SUM(CK68:CK72) -> 0 | CN73: =SUM(CN68:CN72) -> 0 | CO73: =SUM(CO68:CO72) -> 0 | CP73: =SUM(CP68:CP72) -> 0 | CQ73: =SUM(CQ68:CQ72) -> 0 | CR73: =SUM(CR68:CR72) -> 0 | CS73: =SUM(CS68:CS72) -> 0 | CT73: =SUM(CT68:CT72) -> 0 | CU73: =SUM(CU68:CU72) -> 0 | ... CZ73: =SUM(CZ68:CZ72) -> 0
B74: Check | AQ74: =AQ73-SUM(AE73:AP73) -> 0
B75: Saldo ovino (mes) | P75: =P65-P73 -> 0 | Q75: =Q65-Q73 -> 0 | R75: =R65-R73 -> 0 | S75: =S65-S73 -> 0 | T75: =T65-T73 -> 0 | U75: =U65-U73 -> 0 | V75: =V65-V73 -> 0 | W75: =W65-W73 -> 0 | ... AB75: =AB65-AB73 -> 0 | AE75: =AE65-AE73 -> 0 | AF75: =AF65-AF73 -> 0 | AG75: =AG65-AG73 -> 11538.16 | AH75: =AH65-AH73 -> -50.2 | AI75: =AI65-AI73 -> 2858.9 | AJ75: =AJ65-AJ73 -> 0 | AK75: =AK65-AK73 -> 0 | AL75: =AL65-AL73 -> 0 | ... AQ75: =AQ65-AQ73 -> 15305.36 | AU75: =AU65-AU73 -> 0 | AV75: =AV65-AV73 -> 0 | AW75: =AW65-AW73 -> 0 | AX75: =AX65-AX73 -> 0 | AY75: =AY65-AY73 -> 122.8 | AZ75: =AZ65-AZ73 -> 0 | BA75: =BA65-BA73 -> 0 | BB75: =BB65-BB73 -> 1232 | ... BG75: =BG65-BG73 -> 1140.2 | BJ75: =BJ65-BJ73 -> 0 | BK75: =BK65-BK73 -> 0 | BL75: =BL65-BL73 -> 0 | BM75: =BM65-BM73 -> 365 | BN75: =BN65-BN73 -> 0 | BO75: =BO65-BO73 -> 400 | BP75: =BP65-BP73 -> 0 | BQ75: =BQ65-BQ73 -> 1045 | ... BV75: =BV65-BV73 -> 1810 | BY75: =BY65-BY73 -> 0 | BZ75: =BZ65-BZ73 -> 0 | CA75: =CA65-CA73 -> 0 | CB75: =CB65-CB73 -> 0 | CC75: =CC65-CC73 -> 0 | CD75: =CD65-CD73 -> 0 | CE75: =CE65-CE73 -> 0 | CF75: =CF65-CF73 -> 0 | ... CK75: =CK65-CK73 -> 0 | CN75: =CN65-CN73 -> 0 | CO75: =CO65-CO73 -> 0 | CP75: =CP65-CP73 -> 0 | CQ75: =CQ65-CQ73 -> 0 | CR75: =CR65-CR73 -> 0 | CS75: =CS65-CS73 -> 0 | CT75: =CT65-CT73 -> 0 | CU75: =CU65-CU73 -> 0 | ... CZ75: =CZ65-CZ73 -> 0
B76: Check | AQ76: =AQ75-SUM(AE75:AP75) -> 0
B77: Gastos generales
B78: Alimento cereal | O78: =SUM(C78:N78) -> 0 | AB78: =SUM(P78:AA78) -> 0 | AH78: 6185.7 | AO78: =5842.92 -> 5842.92 | AP78: =6355.44+6379.12+6164.32+9023.85 -> 27922.73 | AQ78: =SUM(AE78:AP78) -> 39951.35 | AU78: ='Alimento y ventas'!O216 -> 0 | AV78: ='Alimento y ventas'!P216*0+5834.73 -> 5834.73 | AW78: ='Alimento y ventas'!Q216 -> 0 | AX78: ='Alimento y ventas'!R216 -> 0 | AY78: ='Alimento y ventas'!S216*0 -> 0 | AZ78: ='Alimento y ventas'!T216*0+6676.86 -> 6676.86 | BA78: ='Alimento y ventas'!U216 -> 0 | BB78: ='Alimento y ventas'!V216 -> 0 | BC78: ='Alimento y ventas'!W216 -> 0 | BD78: ='Alimento y ventas'!X216*0 -> 0 | BE78: ='Alimento y ventas'!Y216 -> 0 | BF78: ='Alimento y ventas'!Z216+6017.44 -> 6017.44 | BG78: =SUM(AU78:BF78) -> 18529.03 | BJ78: ='Alimento y ventas'!AA216*0 -> 0 | BK78: ='Alimento y ventas'!AB216*0+5413.82 -> 5413.82 | BL78: ='Alimento y ventas'!AC216+9.64*225*1.04-3.64*225*1.04 -> 1404 | BM78: ='Alimento y ventas'!AD216 -> 0 | BN78: ='Alimento y ventas'!AE216*0 -> 0 | BO78: ='Alimento y ventas'!AF216*0 -> 0 | BP78: ='Alimento y ventas'!AG216*0 -> 0 | BQ78: ='Alimento y ventas'!AH216*0 -> 0 | BR78: ='Alimento y ventas'!AI216+6872.2 -> 6872.2 | BS78: ='Alimento y ventas'!AJ216 -> 6058 | BT78: ='Alimento y ventas'!AK216 -> 0 | BU78: ='Alimento y ventas'!AL216 -> 0 | BV78: =SUM(BJ78:BU78) -> 19748.02 | BY78: ='Alimento y ventas'!AM216 -> 6058 | BZ78: ='Alimento y ventas'!AN216 -> 0 | CA78: ='Alimento y ventas'!AO216 -> 0 | CB78: ='Alimento y ventas'!AP216 -> 0 | CC78: ='Alimento y ventas'!AQ216 -> 0 | CD78: ='Alimento y ventas'!AR216 -> 0 | CE78: ='Alimento y ventas'!AS216 -> 6058 | CF78: ='Alimento y ventas'!AT216 -> 0 | ... CJ78: ='Alimento y ventas'!AX216 -> 0 | CK78: =SUM(BY78:CJ78) -> 24232 | CN78: ='Alimento y ventas'!AY216 -> 5668 | CO78: ='Alimento y ventas'!AZ216 -> 0 | CP78: ='Alimento y ventas'!BA216 -> 0 | CQ78: ='Alimento y ventas'!BB216 -> 0 | CR78: ='Alimento y ventas'!BC216 -> 0 | CS78: ='Alimento y ventas'!BD216 -> 5668 | CT78: ='Alimento y ventas'!BE216 -> 0 | CU78: ='Alimento y ventas'!BF216 -> 0 | ... CY78: ='Alimento y ventas'!BJ216 -> 0 | CZ78: =SUM(CN78:CY78) -> 22672 | DC78: =1677.06+528 -> 2205.06
B79: Alimento DDG/leguminosa | O79: =SUM(C79:N79) -> 0 | AB79: =SUM(P79:AA79) -> 0 | AQ79: =SUM(AE79:AP79) -> 0 | AU79: ='Alimento y ventas'!O223 -> 0 | AV79: ='Alimento y ventas'!O223 -> 0 | AW79: ='Alimento y ventas'!P223 -> 0 | AX79: ='Alimento y ventas'!Q223 -> 0 | AY79: ='Alimento y ventas'!R223 -> 0 | AZ79: ='Alimento y ventas'!S223 -> 0 | BA79: ='Alimento y ventas'!T223 -> 0 | BB79: ='Alimento y ventas'!U223 -> 0 | BC79: ='Alimento y ventas'!V223 -> 0 | ... BF79: ='Alimento y ventas'!Y223 -> 0 | BG79: =SUM(AU79:BF79) -> 0 | BJ79: ='Alimento y ventas'!AA223*0 -> 0 | BK79: ='Alimento y ventas'!AB223*0+7804.99 -> 7804.99 | BL79: ='Alimento y ventas'!AC223*0+6758.67-9.64*225*1.04 -> 4502.91 | BM79: ='Alimento y ventas'!AD223 -> 0 | BN79: ='Alimento y ventas'!AE223 -> 0 | BO79: ='Alimento y ventas'!AF223 -> 0 | BP79: ='Alimento y ventas'!AG223 -> 0 | BQ79: ='Alimento y ventas'!AH223*0 -> 0 | BR79: ='Alimento y ventas'!AI223 -> 0 | BS79: ='Alimento y ventas'!AJ223 -> 7080 | BT79: ='Alimento y ventas'!AK223 -> 0 | BU79: ='Alimento y ventas'!AL223 -> 0 | BV79: =SUM(BJ79:BU79) -> 19387.9 | BY79: ='Alimento y ventas'!AM223 -> 7080 | BZ79: ='Alimento y ventas'!AN223 -> 0 | CA79: ='Alimento y ventas'!AO223 -> 0 | CB79: ='Alimento y ventas'!AP223 -> 7080 | CC79: ='Alimento y ventas'!AQ223 -> 0 | CD79: ='Alimento y ventas'!AR223 -> 0 | CE79: ='Alimento y ventas'!AS223 -> 0 | CF79: ='Alimento y ventas'!AT223 -> 0 | ... CJ79: ='Alimento y ventas'!AX223 -> 0 | CK79: =SUM(BY79:CJ79) -> 28320 | CN79: ='Alimento y ventas'!AY223 -> 9048 | CO79: ='Alimento y ventas'!AZ223 -> 0 | CP79: ='Alimento y ventas'!BA223 -> 0 | CQ79: ='Alimento y ventas'!BB223 -> 0 | CR79: ='Alimento y ventas'!BC223 -> 0 | CS79: ='Alimento y ventas'!BD223 -> 0 | CT79: ='Alimento y ventas'!BE223 -> 9048 | CU79: ='Alimento y ventas'!BF223 -> 0 | ... CY79: ='Alimento y ventas'!BJ223 -> 4524 | CZ79: =SUM(CN79:CY79) -> 31668
B80: Alimento Forraje/fibra | O80: =SUM(C80:N80) -> 0 | AB80: =SUM(P80:AA80) -> 0 | AE80: =1350 -> 1350 | AF80: =1674.36+1848+1800 -> 5322.36 | AG80: =-1350 -> -1350 | AH80: =1422.85+508.2+508.2+1853.5+1623.6 -> 5916.35 | AI80: =1450.59+387.2 -> 1837.79 | AJ80: =600 -> 600 | AN80: =1155+2640+330+4836.49 -> 8961.49 | AP80: =11000/3*0+4182.75 -> 4182.75 | AQ80: =SUM(AE80:AP80) -> 26820.74 | AU80: 0 | AV80: 0 | AW80: ='Alimento y ventas'!Q230 -> 0 | AX80: ='Alimento y ventas'!R230 -> 0 | AY80: ='Alimento y ventas'!S230 -> 0 | AZ80: ='Alimento y ventas'!T230 -> 0 | BA80: ='Alimento y ventas'!U230 -> 0 | BB80: ='Alimento y ventas'!V230+1974.5 -> 1974.5 | BC80: ='Alimento y ventas'!W230*0 -> 0 | BD80: ='Alimento y ventas'!X230 -> 0 | BE80: ='Alimento y ventas'!Y230 -> 0 | BF80: ='Alimento y ventas'!Z243*0 -> 0 | BG80: =SUM(AU80:BF80) -> 1974.5 | BJ80: ='Alimento y ventas'!AA230 -> 0 | BK80: ='Alimento y ventas'!AB200 -> 0 | BL80: ='Alimento y ventas'!AC230 -> 0 | BM80: ='Alimento y ventas'!AD200*0+750.98 -> 750.98 | BN80: ='Alimento y ventas'!AE200 -> 0 | BO80: ='Alimento y ventas'!AF224 -> 0 | BP80: ='Alimento y ventas'!AG200 -> 0 | BQ80: ='Alimento y ventas'!AH200 -> 0 | BR80: ='Alimento y ventas'!AI200 -> 0 | BS80: ='Alimento y ventas'!AJ200+(270.9+90+615+1290)+(108+350+840+201.6)-1720 -> 2045.5 | BT80: ='Alimento y ventas'!AK200 -> 0 | BU80: ='Alimento y ventas'!AL200 -> 0 | BV80: =SUM(BJ80:BU80) -> 2796.48 | BY80: ='Alimento y ventas'!AM230 -> 0 | BZ80: ='Alimento y ventas'!AN200 -> 0 | CA80: ='Alimento y ventas'!AO200 -> 0 | CB80: ='Alimento y ventas'!AP200 -> 0 | CC80: ='Alimento y ventas'!AQ200 -> 0 | CD80: ='Alimento y ventas'!AR200 -> 0 | CE80: ='Alimento y ventas'!AS200 -> 0 | CF80: ='Alimento y ventas'!AT200 -> 0 | CG80: ='Alimento y ventas'!AU200 -> 0 | ... CJ80: ='Alimento y ventas'!AX200 -> 0 | CK80: =SUM(BY80:CJ80) -> 0 | CN80: ='Alimento y ventas'!AY230 -> 0 | CO80: ='Alimento y ventas'!AZ230 -> 0 | CP80: ='Alimento y ventas'!BA230 -> 0 | CQ80: ='Alimento y ventas'!BB230 -> 0 | CR80: ='Alimento y ventas'!BC230 -> 0 | CS80: ='Alimento y ventas'!BD230 -> 0 | CT80: ='Alimento y ventas'!BE230 -> 0 | CU80: ='Alimento y ventas'!BF230 -> 0 | ... CY80: ='Alimento y ventas'!BJ230 -> 0 | CZ80: =SUM(CN80:CY80) -> 0
B81: Alimento pienso lechones | O81: =SUM(C81:N81) -> 0 | AB81: =SUM(P81:AA81) -> 0 | AQ81: =SUM(AE81:AP81) -> 0 | AU81: 0 | AV81: ='Alimento y ventas'!P244 -> 0 | AW81: ='Alimento y ventas'!Q244 -> 0 | AX81: ='Alimento y ventas'!R244 -> 0 | AY81: ='Alimento y ventas'!S244 -> 0 | AZ81: ='Alimento y ventas'!T244 -> 0 | BA81: ='Alimento y ventas'!U244 -> 0 | BB81: ='Alimento y ventas'!V244 -> 0 | BC81: ='Alimento y ventas'!W244 -> 0 | ... BE81: ='Alimento y ventas'!Y244 -> 0 | BF81: ='Alimento y ventas'!Z244*0 -> 0 | BG81: =SUM(AU81:BF81) -> 0 | BJ81: ='Alimento y ventas'!AA244*0+1847.26 -> 1847.26 | BK81: ='Alimento y ventas'!AB244 -> 0 | BL81: ='Alimento y ventas'!AC244 -> 0 | BM81: ='Alimento y ventas'!AD244 -> 0 | BN81: ='Alimento y ventas'!AE244 -> 0 | BO81: ='Alimento y ventas'!AF244 -> 0 | BP81: ='Alimento y ventas'!AG244*0 -> 0 | BQ81: ='Alimento y ventas'!AH244*0 -> 0 | BR81: ='Alimento y ventas'!AI244 -> 0 | BS81: ='Alimento y ventas'!AJ244 -> 0 | BT81: ='Alimento y ventas'!AK244 -> 0 | BU81: ='Alimento y ventas'!AL244 -> 0 | BV81: =SUM(BJ81:BU81) -> 1847.26 | BY81: ='Alimento y ventas'!AM244 -> 220.77 | BZ81: ='Alimento y ventas'!AN244 -> 0 | CA81: ='Alimento y ventas'!AO244 -> 0 | CB81: ='Alimento y ventas'!AP244 -> 0 | CC81: ='Alimento y ventas'!AQ244 -> 0 | CD81: ='Alimento y ventas'!AR244 -> 0 | CE81: ='Alimento y ventas'!AS244 -> 220.77 | CF81: ='Alimento y ventas'!AT244 -> 0 | ... CJ81: ='Alimento y ventas'!AX244 -> 0 | CK81: =SUM(BY81:CJ81) -> 441.54 | CN81: ='Alimento y ventas'!AY244 -> 216.6835 | CO81: ='Alimento y ventas'!AZ244 -> 0 | CP81: ='Alimento y ventas'!BA244 -> 0 | CQ81: ='Alimento y ventas'!BB244 -> 0 | CR81: ='Alimento y ventas'!BC244 -> 0 | CS81: ='Alimento y ventas'!BD244 -> 0 | CT81: ='Alimento y ventas'!BE244 -> 216.6835 | CU81: ='Alimento y ventas'!BF244 -> 0 | ... CY81: ='Alimento y ventas'!BJ244 -> 0 | CZ81: =SUM(CN81:CY81) -> 433.367
B82: Alimento pienso marranos | O82: =SUM(C82:N82) -> 0 | AB82: =SUM(P82:AA82) -> 0 | AQ82: =SUM(AE82:AP82) -> 0 | AU82: 0 | AV82: ='Alimento y ventas'!P251*0 -> 0 | AW82: ='Alimento y ventas'!Q251+2015.6 -> 2015.6 | AX82: ='Alimento y ventas'!R251 -> 0 | AY82: ='Alimento y ventas'!S251 -> 0 | AZ82: ='Alimento y ventas'!T251 -> 0 | BA82: ='Alimento y ventas'!U251 -> 0 | BB82: ='Alimento y ventas'!V251+5838.02 -> 5838.02 | BC82: ='Alimento y ventas'!W251*0+5474.29 -> 5474.29 | BD82: ='Alimento y ventas'!X251 -> 0 | BE82: ='Alimento y ventas'!Y251 -> 0 | BF82: ='Alimento y ventas'!Z251*0 -> 0 | BG82: =SUM(AU82:BF82) -> 13327.91 | BJ82: ='Alimento y ventas'!AA251*0+4239.06 -> 4239.06 | BK82: ='Alimento y ventas'!AB251 -> 0 | BL82: ='Alimento y ventas'!AC251 -> 0 | BM82: ='Alimento y ventas'!AD251*0 -> 0 | BN82: ='Alimento y ventas'!AE251 -> 0 | BO82: ='Alimento y ventas'!AF251*0 -> 0 | BP82: ='Alimento y ventas'!AG251*0 -> 0 | BQ82: ='Alimento y ventas'!AH251*0 -> 0 | BR82: ='Alimento y ventas'!AI251+5067.74 -> 5067.74 | BS82: ='Alimento y ventas'!AJ251 -> 0 | BT82: ='Alimento y ventas'!AK251 -> 0 | BU82: ='Alimento y ventas'!AL251 -> 1665.54 | BV82: =SUM(BJ82:BU82) -> 10972.34 | BY82: ='Alimento y ventas'!AM251 -> 4441.44 | BZ82: ='Alimento y ventas'!AN251 -> 0 | CA82: ='Alimento y ventas'!AO251 -> 0 | CB82: ='Alimento y ventas'!AP251 -> 4441.44 | CC82: ='Alimento y ventas'!AQ251 -> 0 | CD82: ='Alimento y ventas'!AR251 -> 0 | CE82: ='Alimento y ventas'!AS251 -> 0 | CF82: ='Alimento y ventas'!AT251 -> 4441.44 | ... CJ82: ='Alimento y ventas'!AX251 -> 0 | CK82: =SUM(BY82:CJ82) -> 17765.76 | CN82: ='Alimento y ventas'!AY251 -> 0 | CO82: ='Alimento y ventas'!AZ251 -> 0 | CP82: ='Alimento y ventas'!BA251 -> 4595.2 | CQ82: ='Alimento y ventas'!BB251 -> 0 | CR82: ='Alimento y ventas'!BC251 -> 0 | CS82: ='Alimento y ventas'!BD251 -> 4595.2 | CT82: ='Alimento y ventas'!BE251 -> 0 | CU82: ='Alimento y ventas'!BF251 -> 0 | ... CY82: ='Alimento y ventas'!BJ251 -> 0 | CZ82: =SUM(CN82:CY82) -> 13785.6
B83: Alimento pienso montanera | O83: =SUM(C83:N83) -> 0 | AB83: =SUM(P83:AA83) -> 0 | AO83: 5836.84 | AP83: =+(5027.48-185.49)+4100.82+10541.75 -> 19484.56 | AQ83: =SUM(AE83:AP83) -> 25321.4 | AU83: 0 | AV83: ='Alimento y ventas'!P258*0 -> 0 | AW83: ='Alimento y ventas'!Q258*0+9408.2 -> 9408.2 | AX83: ='Alimento y ventas'!R258*0 -> 0 | AY83: ='Alimento y ventas'!S258*0+8315.34+8385.51 -> 16700.85 | AZ83: ='Alimento y ventas'!T258*0+4157.8-725.11+4252.74-185.49 -> 7499.94 | BA83: ='Alimento y ventas'!U258 -> 0 | BB83: ='Alimento y ventas'!V258 -> 0 | BC83: ='Alimento y ventas'!W258-191.47-191.37 -> -382.84 | BD83: ='Alimento y ventas'!X258 -> 0 | BE83: ='Alimento y ventas'!Y258 -> 0 | BF83: ='Alimento y ventas'!Z258 -> 0 | BG83: =SUM(AU83:BF83) -> 33226.15 | BJ83: ='Alimento y ventas'!AA258 -> 0 | BK83: ='Alimento y ventas'!AB258*0+3609.43 -> 3609.43 | BL83: ='Alimento y ventas'!AC258*0+5925.92+3504.77+6025.56 -> 15456.25 | BM83: ='Alimento y ventas'!AD258*0+6045.57-219.22 -> 5826.35 | BN83: ='Alimento y ventas'!AE258*0 -> 0 | BO83: ='Alimento y ventas'!AF258*0+6051.58-269.81+6112.57 -> 11894.34 | BP83: ='Alimento y ventas'!AG258 -> 0 | BQ83: ='Alimento y ventas'!AH258 -> 0 | BR83: ='Alimento y ventas'!AI258 -> 0 | BS83: ='Alimento y ventas'!AJ258 -> 0 | BT83: ='Alimento y ventas'!AK258 -> 0 | BU83: ='Alimento y ventas'!AL258 -> 0 | BV83: =SUM(BJ83:BU83) -> 36786.37 | BY83: ='Alimento y ventas'!AM258 -> 0 | BZ83: ='Alimento y ventas'!AN258 -> 8154.72 | CA83: ='Alimento y ventas'!AO258 -> 8154.72 | CB83: ='Alimento y ventas'!AP258 -> 8154.72 | CC83: ='Alimento y ventas'!AQ258 -> 8154.72 | CD83: ='Alimento y ventas'!AR258 -> 5096.7 | CE83: ='Alimento y ventas'!AS258 -> 0 | CF83: ='Alimento y ventas'!AT258 -> 0 | ... CJ83: ='Alimento y ventas'!AX258 -> 0 | CK83: =SUM(BY83:CJ83) -> 37715.58 | CN83: ='Alimento y ventas'!AY258 -> 0 | CO83: ='Alimento y ventas'!AZ258 -> 8645.04 | CP83: ='Alimento y ventas'!BA258 -> 8645.04 | CQ83: ='Alimento y ventas'!BB258 -> 8645.04 | CR83: ='Alimento y ventas'!BC258 -> 8645.04 | CS83: ='Alimento y ventas'!BD258 -> 6123.57 | CT83: ='Alimento y ventas'!BE258 -> 0 | CU83: ='Alimento y ventas'!BF258 -> 0 | ... CY83: ='Alimento y ventas'!BJ258 -> 0 | CZ83: =SUM(CN83:CY83) -> 40703.73
B84: Alimento pienso terneros lactantes | O84: =SUM(C84:N84) -> 0 | AB84: =SUM(P84:AA84) -> 0 | AI84: =10234.68 -> 10234.68 | AP84: =11194.8 -> 11194.8 | AQ84: =SUM(AE84:AP84) -> 21429.48 | AU84: 0 | AV84: ='Alimento y ventas'!P265 -> 0 | AW84: ='Alimento y ventas'!Q265 -> 0 | AX84: ='Alimento y ventas'!R265*0 -> 0 | AY84: ='Alimento y ventas'!S265*0 -> 0 | AZ84: ='Alimento y ventas'!T265 -> 0 | BA84: ='Alimento y ventas'!U265 -> 0 | BB84: ='Alimento y ventas'!V265 -> 0 | BC84: ='Alimento y ventas'!W265*0 -> 0 | BD84: ='Alimento y ventas'!X265+968 -> 968 | BE84: ='Alimento y ventas'!Y265 -> 0 | BF84: ='Alimento y ventas'!Z265 -> 0 | BG84: =SUM(AU84:BF84) -> 968 | BJ84: ='Alimento y ventas'!AA265*0 -> 0 | BK84: ='Alimento y ventas'!AB265*0 -> 0 | BL84: ='Alimento y ventas'!AC265*0 -> 0 | BM84: ='Alimento y ventas'!AD265 -> 0 | BN84: ='Alimento y ventas'!AE265 -> 0 | BO84: ='Alimento y ventas'!AF265 -> 0 | BP84: ='Alimento y ventas'!AG265 -> 0 | BQ84: ='Alimento y ventas'!AH265 -> 0 | BR84: ='Alimento y ventas'!AI265 -> 0 | BS84: ='Alimento y ventas'!AJ265 -> 0 | BT84: ='Alimento y ventas'!AK265 -> 0 | BU84: ='Alimento y ventas'!AL265 -> 0 | BV84: =SUM(BJ84:BU84) -> 0 | BY84: ='Alimento y ventas'!AM265 -> 0 | BZ84: ='Alimento y ventas'!AN265 -> 237.5 | CA84: ='Alimento y ventas'!AO265 -> 0 | CB84: ='Alimento y ventas'!AP265 -> 0 | CC84: ='Alimento y ventas'!AQ265 -> 0 | CD84: ='Alimento y ventas'!AR265 -> 0 | CE84: ='Alimento y ventas'!AS265 -> 0 | CF84: ='Alimento y ventas'!AT265 -> 475 | ... CJ84: ='Alimento y ventas'!AX265 -> 0 | CK84: =SUM(BY84:CJ84) -> 1187.5 | CN84: ='Alimento y ventas'!AY265 -> 0 | CO84: ='Alimento y ventas'!AZ265 -> 0 | CP84: ='Alimento y ventas'!BA265 -> 0 | CQ84: ='Alimento y ventas'!BB265 -> 0 | CR84: ='Alimento y ventas'!BC265 -> 0 | CS84: ='Alimento y ventas'!BD265 -> 0 | CT84: ='Alimento y ventas'!BE265 -> 450 | CU84: ='Alimento y ventas'!BF265 -> 0 | ... CY84: ='Alimento y ventas'!BJ265 -> 0 | CZ84: =SUM(CN84:CY84) -> 765
B85: Alimento pienso cebo | O85: =SUM(C85:N85) -> 0 | AB85: =SUM(P85:AA85) -> 0 | AI85: =9671.83 -> 9671.83 | AP85: =5233.25+10214.42 -> 15447.67 | AQ85: =SUM(AE85:AP85) -> 25119.5 | AU85: 0 | AV85: ='Alimento y ventas'!P272*0+7255.25 -> 7255.25 | AW85: ='Alimento y ventas'!Q272 -> 0 | AX85: ='Alimento y ventas'!R272 -> 0 | AY85: ='Alimento y ventas'!S272*0 -> 0 | AZ85: ='Alimento y ventas'!T272 -> 0 | BA85: ='Alimento y ventas'!U272 -> 0 | BB85: ='Alimento y ventas'!V272+7282.08+6636.06 -> 13918.14 | BC85: ='Alimento y ventas'!W272*0 -> 0 | BD85: ='Alimento y ventas'!X272 -> 0 | BE85: ='Alimento y ventas'!Y272*0 -> 0 | BF85: ='Alimento y ventas'!Z272*0+7452.63 -> 7452.63 | BG85: =SUM(AU85:BF85) -> 28626.02 | BJ85: ='Alimento y ventas'!AA272*0+6873.19+6801.7 -> 13674.89 | BK85: ='Alimento y ventas'!AB272*0 -> 0 | BL85: ='Alimento y ventas'!AC272*0 -> 0 | BM85: ='Alimento y ventas'!AD272+6957.14 -> 6957.14 | BN85: ='Alimento y ventas'!AE272*0+7239.34 -> 7239.34 | BO85: ='Alimento y ventas'!AF272 -> 0 | BP85: ='Alimento y ventas'!AG272*0+7046.08 -> 7046.08 | BQ85: ='Alimento y ventas'!AH272 -> 0 | BR85: ='Alimento y ventas'!AI272*0+7280.02+12.64 -> 7292.66 | BS85: ='Alimento y ventas'!AJ272 -> 0 | BT85: ='Alimento y ventas'!AK272+7587.44 -> 12287.44 | BU85: ='Alimento y ventas'!AL272 -> 0 | BV85: =SUM(BJ85:BU85) -> 54497.55 | BY85: ='Alimento y ventas'!AM272 -> 6768 | BZ85: ='Alimento y ventas'!AN272 -> 6768 | CA85: ='Alimento y ventas'!AO272 -> 6768 | CB85: ='Alimento y ventas'!AP272 -> 6768 | CC85: ='Alimento y ventas'!AQ272 -> 0 | CD85: ='Alimento y ventas'!AR272 -> 0 | CE85: ='Alimento y ventas'!AS272 -> 0 | CF85: ='Alimento y ventas'!AT272 -> 0 | ... CJ85: ='Alimento y ventas'!AX272 -> 6768 | CK85: =SUM(BY85:CJ85) -> 40608 | CN85: ='Alimento y ventas'!AY272 -> 0 | CO85: ='Alimento y ventas'!AZ272 -> 6552 | CP85: ='Alimento y ventas'!BA272 -> 0 | CQ85: ='Alimento y ventas'!BB272 -> 0 | CR85: ='Alimento y ventas'!BC272 -> 0 | CS85: ='Alimento y ventas'!BD272 -> 0 | CT85: ='Alimento y ventas'!BE272 -> 0 | CU85: ='Alimento y ventas'!BF272 -> 0 | ... CY85: ='Alimento y ventas'!BJ272 -> 1820 | CZ85: =SUM(CN85:CY85) -> 14924
B86: Alimento taco Madres | O86: =SUM(C86:N86) -> 0 | AB86: =SUM(P86:AA86) -> 0 | AQ86: =SUM(AE86:AP86) -> 0 | AU86: 0 | AV86: 0 | AW86: ='Alimento y ventas'!Q279*0+6012.75 -> 6012.75 | AX86: ='Alimento y ventas'!R279 -> 0 | AY86: ='Alimento y ventas'!S279+763.4 -> 763.4 | AZ86: ='Alimento y ventas'!T279 -> 0 | BA86: ='Alimento y ventas'!U279 -> 0 | BB86: ='Alimento y ventas'!V279 -> 0 | BC86: ='Alimento y ventas'!W279 -> 0 | BD86: ='Alimento y ventas'!X279 -> 0 | BE86: ='Alimento y ventas'!Y279 -> 0 | BF86: ='Alimento y ventas'!Z279 -> 0 | BG86: =SUM(AU86:BF86) -> 6776.15 | BJ86: ='Alimento y ventas'!AA279 -> 0 | BK86: ='Alimento y ventas'!AB279*0 -> 0 | BL86: ='Alimento y ventas'!AC279*0+1889.9 -> 1889.9 | BM86: ='Alimento y ventas'!AD279*0+2440.48 -> 2440.48 | BN86: ='Alimento y ventas'!AE279*0+5712.94 -> 5712.94 | BO86: ='Alimento y ventas'!AF279 -> 0 | BP86: ='Alimento y ventas'!AG279+5467.92 -> 5467.92 | BQ86: ='Alimento y ventas'!AH279 -> 0 | BR86: ='Alimento y ventas'!AI279 -> 0 | BS86: ='Alimento y ventas'!AJ279 -> 0 | BT86: ='Alimento y ventas'!AK279 -> 0 | BU86: ='Alimento y ventas'!AL279 -> 0 | BV86: =SUM(BJ86:BU86) -> 15511.24 | CK86: =SUM(BY86:CJ86) -> 0 | CZ86: =SUM(CN86:CY86) -> 0
O87: =SUM(C87:N87) -> 0 | AQ87: =SUM(AE87:AP87) -> 0 | BG87: =SUM(AU87:BF87) -> 0 | BV87: =SUM(BJ87:BU87) -> 0 | CK87: =SUM(BY87:CJ87) -> 0 | CZ87: =SUM(CN87:CY87) -> 0
B88: Siembra y cosechado | O88: =SUM(C88:N88) -> 0 | AB88: =SUM(P88:AA88) -> 0 | AE88: ='Alimento y ventas'!C300*0 -> 0 | AF88: ='Alimento y ventas'!D300*0+108 -> 108 | AG88: ='Alimento y ventas'!E300*0+1870+508.2 -> 2378.2 | AH88: =25845.6 -> 25845.6 | AI88: =360.1 -> 360.1 | AJ88: ='Alimento y ventas'!H300 -> 0 | AK88: ='Alimento y ventas'!I300 -> 0 | AL88: ='Alimento y ventas'!J300 -> 0 | AM88: ='Alimento y ventas'!K300 -> 0 | AN88: ='Alimento y ventas'!L300 -> 0 | AO88: ='Alimento y ventas'!M300+2948.4 -> 2948.4 | AP88: ='Alimento y ventas'!N300+4573.04 -> 4573.04 | AQ88: =SUM(AE88:AP88) -> 36213.34 | AU88: ='Alimento y ventas'!O300 -> 0 | AV88: ='Alimento y ventas'!P300*0+2860 -> 2860 | AW88: ='Alimento y ventas'!Q300*0+16381.64+544.5 -> 16926.14 | AX88: ='Alimento y ventas'!R300*0+12439.68+544.5 -> 12984.18 | AY88: ='Alimento y ventas'!S300 -> 0 | AZ88: ='Alimento y ventas'!T300+111.32 -> 111.32 | BA88: ='Alimento y ventas'!U300 -> 0 | BB88: ='Alimento y ventas'!V300 -> 0 | BC88: ='Alimento y ventas'!W300 -> 0 | BD88: 8499.82 | BE88: ='Alimento y ventas'!Y300*0 -> 0 | BF88: ='Alimento y ventas'!Z300+120.95 -> 120.95 | BG88: =SUM(AU88:BF88) -> 41502.41 | BJ88: ='Alimento y ventas'!AA300*0+15340 -> 15340 | BK88: =('Alimento y ventas'!AB300) -> 0 | BL88: ='Alimento y ventas'!AC300+3.64*225*1.04 -> 851.76 | BM88: ='Alimento y ventas'!AD300*0+(5*9*45)*1.21 -> 2450.25 | BN88: ='Alimento y ventas'!AE300 -> 0 | BO88: ='Alimento y ventas'!AF300 -> 0 | BP88: ='Alimento y ventas'!AG300+3015.14+2952.94 -> 5968.08 | BQ88: ='Alimento y ventas'!AH300 -> 0 | BR88: ='Alimento y ventas'!AI300 -> 0 | BS88: ='Alimento y ventas'!AJ300 -> 0 | BT88: ='Alimento y ventas'!AK300 -> 0 | BU88: ='Alimento y ventas'!AL300 -> 0 | BV88: =SUM(BJ88:BU88) -> 24610.09 | BY88: ='Alimento y ventas'!AM300 -> 15500 | BZ88: ='Alimento y ventas'!AN300 -> 0 | CA88: ='Alimento y ventas'!AO300 -> 0 | CB88: ='Alimento y ventas'!AP300 -> 0 | CC88: ='Alimento y ventas'!AQ300 -> 0 | CD88: ='Alimento y ventas'!AR300 -> 0 | CE88: ='Alimento y ventas'!AS300 -> 0 | CF88: ='Alimento y ventas'!AT300 -> 0 | ... CJ88: ='Alimento y ventas'!AX300 -> 5500 | CK88: =SUM(BY88:CJ88) -> 26500 | CN88: ='Alimento y ventas'!AY300 -> 5500 | CO88: ='Alimento y ventas'!AZ300 -> 0 | CP88: ='Alimento y ventas'!BA300 -> 0 | CQ88: ='Alimento y ventas'!BB300 -> 0 | CR88: ='Alimento y ventas'!BC300 -> 0 | CS88: ='Alimento y ventas'!BD300 -> 0 | CT88: ='Alimento y ventas'!BE300 -> 0 | CU88: ='Alimento y ventas'!BF300 -> 0 | ... CY88: ='Alimento y ventas'!BJ300 -> 5500 | CZ88: =SUM(CN88:CY88) -> 16500
B89: Seguro RC | O89: =SUM(C89:N89) -> 0 | AB89: =SUM(P89:AA89) -> 0 | AQ89: =SUM(AE89:AP89) -> 0 | BG89: =SUM(AU89:BF89) -> 0 | BJ89: 517.92 | BM89: =665.87*0 -> 0 | BS89: 639.26 | BV89: =SUM(BJ89:BU89) -> 1157.18 | CG89: 639.26 | CK89: =SUM(BY89:CJ89) -> 639.26 | CV89: 639.26 | CZ89: =SUM(CN89:CY89) -> 639.26
B90: Seguro vehículos y maquinaria | O90: =SUM(C90:N90) -> 0 | AB90: =SUM(P90:AA90) -> 0 | AM90: 201.74 | AQ90: =SUM(AE90:AP90) -> 201.74 | AU90: 444.67 | BC90: 228.18 | BG90: =SUM(AU90:BF90) -> 672.85 | BM90: 333.19 | BN90: 49.8 | BO90: 49.8 | BP90: 49.8 | BQ90: 49.8 | BR90: =49.8+258.21 -> 308.01 | BS90: 49.8 | BV90: =SUM(BJ90:BU90) -> 890.2 | CK90: =SUM(BY90:CJ90) -> 0 | CZ90: =SUM(CN90:CY90) -> 0
B91: Seguro Convenio | O91: =SUM(C91:N91) -> 0 | AB91: =SUM(P91:AA91) -> 0 | AQ91: =SUM(AE91:AP91) -> 0 | AX91: 292.31 | BG91: =SUM(AU91:BF91) -> 292.31 | BM91: 68.12 | BN91: 69.37 | BO91: =67.97 -> 67.97 | BP91: 67.97 | BQ91: 67.97 | BR91: 67.97 | BS91: 67.97 | BT91: =54.68*0 -> 0 | BV91: =SUM(BJ91:BU91) -> 477.34 | CD91: 54.68 | CK91: =SUM(BY91:CJ91) -> 54.68 | CS91: 54.68 | CZ91: =SUM(CN91:CY91) -> 54.68
B92: IVA | O92: =SUM(C92:N92) -> 0 | AB92: =SUM(P92:AA92) -> 0 | AG92: 2341.56 | AH92: 3213.57 | AL92: 1291.59 | AM92: =4995.46 -> 4995.46 | AQ92: =SUM(AE92:AP92) -> 11842.18 | AZ92: =-1333.46 -> -1333.46 | BA92: 4014.25 | BB92: 419.06 | BC92: 128.72 | BE92: =-2511.12 -> -2511.12 | BF92: -6730.35 | BG92: =SUM(AU92:BF92) -> -6012.9 | BJ92: 4638.02 | BL92: =2343.02-2111.26-1117.61-1752.01 -> -2637.86 | BM92: =-2969.99 -> -2969.99 | BO92: =12.58-3049.36 -> -3036.78 | BP92: 1159.4 | BT92: =-580.3-4995.15-1475.15-224.93-1515.59 -> -8791.12 | BV92: =SUM(BJ92:BU92) -> -11638.33 | CK92: =SUM(BY92:CJ92) -> 0 | CZ92: =SUM(CN92:CY92) -> 0
B93: IRPF | O93: =SUM(C93:N93) -> 0 | AB93: =SUM(P93:AA93) -> 0 | AF93: =240.35 -> 240.35 | AI93: =212.99 -> 212.99 | AL93: 338.13 | AO93: =105.84 -> 105.84 | AQ93: =SUM(AE93:AP93) -> 897.31 | AV93: =397.07 -> 397.07 | BB93: 182.72 | BE93: =257.81 -> 257.81 | BG93: =SUM(AU93:BF93) -> 837.6 | BK93: 69.45 | BN93: =237.05 -> 237.05 | BQ93: 917.27 | BT93: =300 -> 300 | BV93: =SUM(BJ93:BU93) -> 1523.77 | BZ93: =300 -> 300 | CC93: =300 -> 300 | CF93: =300 -> 300 | CI93: =300 -> 300 | CK93: =SUM(BY93:CJ93) -> 1200 | CO93: =300 -> 300 | CR93: =300 -> 300 | CU93: =300 -> 300 | CX93: =300 -> 300 | CZ93: =SUM(CN93:CY93) -> 1200
B94: IS | O94: =SUM(C94:N94) -> 0 | AB94: =SUM(P94:AA94) -> 0 | AQ94: =SUM(AE94:AP94) -> 0 | BA94: =5848.5 -> 5848.5 | BB94: =5848.5*0.18 -> 1052.73 | BG94: =SUM(AU94:BF94) -> 6901.23 | BK94: =5848.5*0.18 -> 1052.73 | BM94: =5848.5*0.18 -> 1052.73 | BQ94: 1052.73 | BR94: 3078.4 | BV94: =SUM(BJ94:BU94) -> 6236.59 | CK94: =SUM(BY94:CJ94) -> 0 | CZ94: =SUM(CN94:CY94) -> 0
B95: Otras tasas e impuestos (IBI, RM, IVTM, …) | D95: =107.9+31.84 -> 139.74 | O95: =SUM(C95:N95) -> 139.74 | Y95: =51.84+105.9 -> 157.74 | AB95: =SUM(P95:AA95) -> 157.74 | AF95: 44.18 | AQ95: =SUM(AE95:AP95) -> 44.18 | BG95: =SUM(AU95:BF95) -> 0 | BS95: 5995.59 | BV95: =SUM(BJ95:BU95) -> 5995.59 | CK95: =SUM(BY95:CJ95) -> 0 | CZ95: =SUM(CN95:CY95) -> 0
B96: Mantenimiento finca y maquinaria | O96: =SUM(C96:N96) -> 0 | AB96: =SUM(P96:AA96) -> 0 | AE96: 35 | AF96: =48.4 -> 48.4 | AG96: =598.95+556.96 -> 1155.91 | AI96: =58.75+60.66+124.42*1.21+116.16+639+210+29.6+447.29+60+80+50+80 -> 1982.0082 | AK96: =(167.34+157.18+597.37)+(85.84+275.88-108.9+108.9) -> 1283.61 | AL96: =175.4+93.29+246.06+1077.93 -> 1592.68 | AM96: =591.41+535.3+1012.92 -> 2139.63 | AN96: =31.8+16.46+82.28+856.49+119.83+822.61+35+810+60 -> 2834.47 | AO96: =263.65+4.4+1833.27+363 -> 2464.32 | AQ96: =SUM(AE96:AP96) -> 13536.028 | AU96: =105.27+140 -> 245.27 | AV96: =87+1095.43+462.29+300 -> 1944.72 | AW96: =435.01+580+35.51-150+50 -> 950.52 | AX96: =35.51+1373.35 -> 1408.86 | AY96: =659.97+264+112.72+298.87+10 -> 1345.56 | AZ96: =44 -> 44 | BA96: 110.11 | BB96: =496.24+54.45+847+392.04+589.34 -> 2379.07 | BC96: =425.12+142.78+124.63+60.5+120 -> 873.03 | BD96: =2327.36-968+130+1091 -> 2580.36 | BE96: =79.9 -> 79.9 | BF96: =439.9+525.95+470+90 -> 1525.85 | BG96: =SUM(AU96:BF96) -> 13487.25 | BJ96: =249.54+740+120+980 -> 2089.54 | BK96: =340.16+382.48+465.85+3515.87+150.81+432.42 -> 5287.59 | BL96: =370.66+335+157.3 -> 862.96 | BM96: =873.55+638.2+32.73 -> 1544.48 | BN96: =76.5 -> 76.5 | BP96: =121 -> 121 | BQ96: 374.13 | BR96: =512.24+362.94+26.46+1078.11 -> 1979.75 | BS96: =228.97+52.54 -> 281.51 | BU96: 900 | BV96: =SUM(BJ96:BU96) -> 13517.46 | BY96: 800 | BZ96: 800 | CA96: 800 | CB96: 800 | CC96: 800 | CD96: 800 | CE96: 800 | CF96: 800 | CG96: 800 | CH96: 800 | CI96: 800 | CJ96: 800 | CK96: =SUM(BY96:CJ96) -> 9600 | CN96: 800 | CO96: 800 | CP96: 800 | CQ96: 800 | CR96: 800 | CS96: 800 | CT96: 800 | CU96: 800 | CV96: 800 | CW96: 800 | CX96: 800 | CY96: 800 | CZ96: =SUM(CN96:CY96) -> 9600
B97: Gasoil B maquinaria | O97: =SUM(C97:N97) -> 0 | AB97: =SUM(P97:AA97) -> 0 | AH97: 2108.48 | AI97: 1024 | AL97: 530.5 | AO97: =1015+2128 -> 3143 | AQ97: =SUM(AE97:AP97) -> 6805.98 | AU97: 1700 | AX97: 3458.54 | BD97: 1272 | BF97: 2126.5 | BG97: =SUM(AU97:BF97) -> 8557.04 | BL97: 1884 | BP97: 1047 | BS97: 3174 | BU97: 2000 | BV97: =SUM(BJ97:BU97) -> 8105 | BY97: 2000 | CA97: 2000 | CF97: 2000 | CH97: 1000 | CK97: =SUM(BY97:CJ97) -> 7000 | CN97: 2000 | CP97: 2000 | CU97: 2000 | CW97: 1000 | CZ97: =SUM(CN97:CY97) -> 7000
B98: Gasoil A o gasolina y butano | O98: =SUM(C98:N98) -> 0 | AB98: =SUM(P98:AA98) -> 0 | AE98: =99.99+20 -> 119.99 | AF98: =50+50+81.01+10+67.4 -> 258.41 | AG98: =79.91+76.46 -> 156.37 | AH98: =48.5 -> 48.5 | AI98: =193.48+20 -> 213.48 | AJ98: =48.5+18 -> 66.5 | AK98: 84.79 | AL98: =229.08+249.95+327.41+(50.01+40+17.85+50) -> 964.3 | AM98: =64.71+100.47 -> 165.18 | AN98: =94.58+136.35+50 -> 280.93 | AO98: =83.14 -> 83.14 | AP98: =86.01+177.36+(323.02+462.77) -> 1049.16 | AQ98: =SUM(AE98:AP98) -> 3490.75 | AU98: =96.49 -> 96.49 | AV98: =184.93+81.06+39+36+106.2+84.74+64 -> 595.93 | AW98: =85.13+2.79+134.73+70+(74+50) -> 416.65 | AX98: =207.43+89.81+72.5+53.57+86.47 -> 509.78 | AY98: =74.46+80.53+110.73 -> 265.72 | AZ98: =90.93+73 -> 163.93 | BA98: =91.21+96.94+95.72+95.06+(50+80.01+70) -> 578.94 | BB98: =81.42+84.41+(66.01+55)+(74+58+70) -> 488.84 | BC98: =118+79.95+55+56.1+92.01+90.01+(55+60)+(71+71.01)+48.87 -> 796.95 | BD98: =109.44+72.93+(70.01+60.01)+68.01 -> 380.4 | BE98: =75.69+(70+70)+(72.01+66.01) -> 353.71 | BF98: =226.04+(70+68.97)+88.2+51.55+(114.29+74) -> 693.05 | BG98: =SUM(AU98:BF98) -> 5340.39 | BJ98: =(50+20+70+66+70)+47.01+87.7 -> 410.71 | BK98: =(70+50)+90 -> 210 | BL98: =272.44+106.33+50+84.92+96.58+(76.01+65+66) -> 817.28 | BM98: =168.76+91.83+(65+60.01+50) -> 435.6 | BN98: =134+88.01+87+90.49+85.11+80.03+(50+50)+59.8 -> 724.44 | BO98: =(60+65.01)+64 -> 189.01 | BP98: =62.01+70.01+90.01+20+85.92+87.12 -> 415.07 | BQ98: =112.3+78+(81+80.01+80) -> 431.31 | BR98: =129.01+103.11+(80.01+50+50) -> 412.13 | BS98: 119.81 | BT98: 400 | BU98: 400 | BV98: =SUM(BJ98:BU98) -> 4965.36 | BY98: =96.49+39 -> 135.49 | BZ98: 300 | CA98: 300 | CB98: 300 | CC98: 300 | CD98: 300 | CE98: 300 | CF98: 300 | CG98: 300 | CH98: 300 | CI98: 300 | CJ98: 300 | CK98: =SUM(BY98:CJ98) -> 3435.49 | CN98: =96.49+39 -> 135.49 | CO98: 300 | CP98: 300 | CQ98: 300 | CR98: 300 | CS98: 300 | CT98: 300 | CU98: 300 | CV98: 300 | CW98: 300 | CX98: 300 | CY98: 300 | CZ98: =SUM(CN98:CY98) -> 3435.49
B99: Alquiler Fincas | O99: =SUM(C99:N99) -> 0 | AB99: =SUM(P99:AA99) -> 0 | AE99: =1870 -> 1870 | AG99: =225+450+270 -> 945 | AI99: =300+300 -> 600 | AP99: 2000 | AQ99: =SUM(AE99:AP99) -> 5415 | AU99: -350 | AV99: =15*30 -> 450 | AY99: 600 | BG99: =SUM(AU99:BF99) -> 700 | BJ99: 2000 | BK99: =15*30 -> 450 | BU99: 2000 | BV99: =SUM(BJ99:BU99) -> 4450 | BZ99: =15*30 -> 450 | CJ99: 2000 | CK99: =SUM(BY99:CJ99) -> 2450 | CO99: =15*30 -> 450 | CY99: 2000 | CZ99: =SUM(CN99:CY99) -> 2450 | DB99: =240*7 -> 1680
B100: Gastos o ingresos auxiliares | O100: =SUM(C100:N100) -> 0 | AB100: =SUM(P100:AA100) -> 0 | AI100: -2100 | AJ100: =800 -> 800 | AK100: 675 | AL100: 1000 | AM100: 950 | AO100: 120 | AQ100: =SUM(AE100:AP100) -> 1445 | AV100: -400 | AW100: 650 | AY100: =800+950-700 -> 1050 | AZ100: =-350-1050+950+500 -> 50 | BD100: -200 | BG100: =SUM(AU100:BF100) -> 1150 | BJ100: =-400-370 -> -770 | BL100: =-200+450 -> 250 | BM100: =850-2000 -> -1150 | BO100: =1500-1050-810-400+70+700+500+380 -> 890 | BP100: =-963.49 -> -963.49 | BQ100: 100 | BU100: =-2000+875.9+6*125 -> -374.1 | BV100: =SUM(BJ100:BU100) -> -2017.59 | BZ100: -400 | CB100: -800 | CC100: =(-2100-50*5)/2 -> -1175 | CD100: 600 | CI100: 600 | CJ100: -2000 | CK100: =SUM(BY100:CJ100) -> -3175 | CO100: -400 | CQ100: -800 | CR100: =-2100-50*5 -> -2350 | CS100: 600 | CX100: 600 | CY100: -2000 | CZ100: =SUM(CN100:CY100) -> -4350
B101: Nomina Jhonathan Borrero Ruiz | O101: =SUM(C101:N101) -> 0 | AA101: 1176.59 | AB101: =SUM(P101:AA101) -> 1176.59 | AE101: 1176.59 | AF101: 1176.59 | AG101: 1176.59 | AH101: 247.55 | AQ101: =SUM(AE101:AP101) -> 3777.32 | AV101: 1100.08 | AW101: 1165.68 | AX101: 1165 | AY101: 1165 | AZ101: 158 | BG101: =SUM(AU101:BF101) -> 4753.76 | BK101: =1200/30*26 -> 1040 | BL101: =800+1200-200 -> 1800 | BM101: =1367.72-200 -> 1167.72 | BN101: =1200-200 -> 1000 | BO101: =880-200 -> 680 | BP101: 0 | BQ101: 0 | BR101: 1080 | BS101: 1200 | BT101: 1200 | BU101: 1200 | BV101: =SUM(BJ101:BU101) -> 10367.72 | BY101: 1200 | BZ101: 1200 | CA101: 1200 | CB101: 1200 | CC101: 1200 | CD101: 1200 | CE101: 1200 | CF101: 1200 | CG101: 1200 | CH101: 1200 | CI101: 1200 | CJ101: 1200 | CK101: =SUM(BY101:CJ101) -> 14400 | CN101: 1200 | CO101: 1200 | CP101: 1200 | CQ101: 1200 | CR101: 1200 | CS101: 1200 | CT101: 1200 | CU101: 1200 | CV101: 1200 | CW101: 1200 | CX101: 1200 | CY101: 1200 | CZ101: =SUM(CN101:CY101) -> 14400
B102: Nomina Mariano López Valero | O102: =SUM(C102:N102) -> 0 | AA102: 1200 | AB102: =SUM(P102:AA102) -> 1200 | AE102: -1200 | AF102: 1200 | AG102: 1200 | AH102: 1200 | AI102: 1200 | AJ102: =1211.87-1200+1211.87 -> 1223.74 | AK102: 1211.87 | AL102: 1211.87 | AM102: 1211.87 | AN102: 1238.33 | AO102: 1238.33 | AP102: 1238.33 | AQ102: =SUM(AE102:AP102) -> 12174.34 | AU102: 1238.33 | AV102: 1238.33 | AW102: 1238.33 | AX102: 1238.33 | AY102: 1238.2 | AZ102: 1250 | BA102: 1250 | BB102: 1250 | BC102: 1250 | BD102: 1250 | BE102: 1250 | BF102: 1250 | BG102: =SUM(AU102:BF102) -> 14941.52 | BJ102: 1250 | BK102: 1250 | BL102: 1250 | BM102: =1457.55+2000 -> 3457.55 | BN102: =1250+223.5 -> 1473.5 | BO102: =1250+223.5 -> 1473.5 | BP102: =1250+223.5 -> 1473.5 | BQ102: =1250+121.95 -> 1371.95 | BR102: =1250+1.58 -> 1251.58 | BS102: 1250 | BT102: 1250 | BU102: 1250 | BV102: =SUM(BJ102:BU102) -> 18001.58 | BY102: 1250 | BZ102: 1250 | CA102: 1250 | CB102: 1250 | CC102: 1250 | CD102: 1250 | CE102: 1250 | CF102: 1250 | CG102: 1250 | CH102: 1250 | CI102: 1250 | CJ102: 1250 | CK102: =SUM(BY102:CJ102) -> 15000 | CN102: 1250 | CO102: 1250 | CP102: 1250 | CQ102: 1250 | CR102: 1250 | CS102: 1250 | CT102: 1250 | CU102: 1250 | CV102: 1250 | CW102: 1250 | CX102: 1250 | CY102: 1250 | CZ102: =SUM(CN102:CY102) -> 15000
B103: Nomina Jaime Martin | O103: =SUM(C103:N103) -> 0 | AA103: 1176.59 | AB103: =SUM(P103:AA103) -> 1176.59 | AE103: 1176.59 | AF103: 1176.59 | AG103: 1176.59 | AH103: 1176.59 | AI103: 1176.33 | AJ103: =1211.87-1176.33+1211.87 -> 1247.41 | AK103: 1211.87 | AL103: 1211.87 | AM103: 1211.87 | AN103: 1238.33 | AO103: 1238.33 | AP103: 1238.33 | AQ103: =SUM(AE103:AP103) -> 14480.7 | AU103: 1238.33 | AV103: 320.69 | AW103: 661.02 | AX103: 112 | AZ103: 791.67 | BA103: 1250 | BB103: 1250 | BC103: =1250+300 -> 1550 | BD103: 1250 | BE103: 1250 | BF103: 1250 | BG103: =SUM(AU103:BF103) -> 10923.71 | BJ103: 1250 | BK103: 1250 | BL103: 1250 | BM103: 1520.63 | BN103: =1250+255.64 -> 1505.64 | BO103: =1250+255.64 -> 1505.64 | BP103: =1250+255.25 -> 1505.25 | BQ103: =1250+107.45 -> 1357.45 | BR103: =1250+1.35 -> 1251.35 | BS103: 1250 | BT103: 1250 | BU103: 1250 | BV103: =SUM(BJ103:BU103) -> 16145.96 | BY103: 1250 | BZ103: 1250 | CA103: 1250 | CB103: 1250 | CC103: 1250 | CD103: 1250 | CE103: 1250 | CF103: 1250 | CG103: 1250 | CH103: 1250 | CI103: 1250 | CJ103: 1250 | CK103: =SUM(BY103:CJ103) -> 15000 | CN103: 1250 | CO103: 1250 | CP103: 1250 | CQ103: 1250 | CR103: 1250 | CS103: 1250 | CT103: 1250 | CU103: 1250 | CV103: 1250 | CW103: 1250 | CX103: 1250 | CY103: 1250 | CZ103: =SUM(CN103:CY103) -> 15000
B104: Nomina Juan Carlos Jimenez Martinez | O104: =SUM(C104:N104) -> 0 | AB104: =SUM(P104:AA104) -> 0 | AH104: 589.45 | AI104: 1043.61 | AJ104: =1051.72-1043.61+1055.75 -> 1063.86 | AK104: 1051.72 | AL104: 1051.72 | AM104: 1051.72 | AN104: 1051.72 | AO104: 1051.72 | AP104: 1051.72 | AQ104: =SUM(AE104:AP104) -> 9007.24 | AU104: 400 | AX104: 995.26 | AY104: 1100 | AZ104: 1100 | BA104: 1150.04 | BB104: 1150.05 | BC104: =1195.67+300 -> 1495.67 | BD104: 1195.67 | BE104: 1093.96 | BG104: =SUM(AU104:BF104) -> 9680.65 | BJ104: 750 | BK104: 97.5 | BP104: 1050 | BQ104: 1059 | BV104: =SUM(BJ104:BU104) -> 2956.5 | CK104: =SUM(BY104:CJ104) -> 0 | CZ104: =SUM(CN104:CY104) -> 0
...

Sheet Alimento y ventas
C3: 30 | D3: 31 | E3: 30 | F3: 31 | G3: 31 | H3: 28 | I3: 31 | J3: 30 | K3: 31 | L3: 30 | M3: 31 | N3: 31 | O3: 30 | P3: 31 | Q3: 30 | R3: 31 | S3: 31 | T3: 28 | U3: 31 | V3: 30 | W3: 31 | X3: 30 | Y3: 31 | Z3: 31 | AA3: 30 | AB3: 31 | AC3: 30 | AD3: 31 | AE3: 31 | AF3: 28 | AG3: 31 | AH3: 30 | AI3: 31 | AJ3: 30 | AK3: 31 | AL3: 31 | AM3: 30 | AN3: 31 | AO3: 30 | AP3: 31 | AQ3: 31 | AR3: 28 | AS3: 31 | AT3: 30 | AU3: 31 | AV3: 30 | AW3: 31 | AX3: 31 | AY3: 30 | AZ3: 31 | BA3: 30 | BB3: 31 | BC3: 31 | BD3: 28 | BE3: 31 | BF3: 30 | BG3: 31 | BH3: 30 | BI3: 31 | BJ3: 31
C4: Sep23/Ago24 | O4: Sep24/Ago25 | AA4: Sep25/Ago26 | AM4: Sep26/Ago27 | AY4: Sep27/Ago28
C5: Sep | D5: Oct | E5: Nov | F5: Dic | G5: Ene | H5: Feb | I5: Mar | J5: Abr | K5: May | L5: Jun | M5: Jul | N5: Ago | O5: Sep | P5: Oct | Q5: Nov | R5: Dic | S5: Ene | T5: Feb | U5: Mar | V5: Abr | W5: May | X5: Jun | Y5: Jul | Z5: Ago | AA5: Sep | AB5: Oct | AC5: Nov | AD5: Dic | AE5: Ene | AF5: Feb | AG5: Mar | AH5: Abr | AI5: May | AJ5: Jun | AK5: Jul | AL5: Ago | AM5: Sep | AN5: Oct | AO5: Nov | AP5: Dic | AQ5: Ene | AR5: Feb | AS5: Mar | AT5: Abr | AU5: May | AV5: Jun | AW5: Jul | AX5: Ago | AY5: Sep | AZ5: Oct | BA5: Nov | BB5: Dic | BC5: Ene | BD5: Feb | BE5: Mar | BF5: Abr | BG5: May | BH5: Jun | BI5: Jul | BJ5: Ago
B6: Reproductoras y verracos
B7: Stock Inicial | C7: =15+2 -> 17 | D7: =+C14 -> 17 | E7: =+D14 -> 17 | F7: =+E14 -> 17 | G7: =+F14 -> 27 | H7: =+G14 -> 27 | I7: =+H14 -> 27 | J7: =+I14 -> 39 | K7: =+J14 -> 39 | ... BJ7: =+BI14 -> 28
B8: Entradas | C8: =SUM(C9:C10) -> 0 | D8: =SUM(D9:D10) -> 0 | E8: =SUM(E9:E10) -> 0 | F8: =SUM(F9:F10) -> 10 | G8: =SUM(G9:G10) -> 0 | H8: =SUM(H9:H10) -> 0 | I8: =SUM(I9:I10) -> 12 | J8: =SUM(J9:J10) -> 0 | ... BJ8: =SUM(BJ9:BJ10) -> 0
B9: Reposición | S9: 6 | X9: 1
B10: Compras | F10: 10 | I10: 12 | O10: 5
B11: Salidas | C11: =SUM(C12:C13) -> 0 | D11: =SUM(D12:D13) -> 0 | E11: =SUM(E12:E13) -> 0 | F11: =SUM(F12:F13) -> 0 | G11: =SUM(G12:G13) -> 0 | H11: =SUM(H12:H13) -> 0 | I11: =SUM(I12:I13) -> 0 | J11: =SUM(J12:J13) -> 0 | ... BJ11: =SUM(BJ12:BJ13) -> 0
B12: Ventas/cebo | S12: =-10-1-1-1 -> -13 | T12: -2
B13: Mermas | C13: 0 | N13: -2 | V13: -1 | X13: -1 | AB13: -1 | AH13: -3
B14: Stock Final | C14: =SUM(C7,C8,C11) -> 17 | D14: =SUM(D7,D8,D11) -> 17 | E14: =SUM(E7,E8,E11) -> 17 | F14: =SUM(F7,F8,F11) -> 27 | G14: =SUM(G7,G8,G11) -> 27 | H14: =SUM(H7,H8,H11) -> 27 | I14: =SUM(I7,I8,I11) -> 39 | J14: =SUM(J7,J8,J11) -> 39 | ... BJ14: =SUM(BJ7,BJ8,BJ11) -> 28
B15: Alimento
B16: kg/dia/animal | C16: 1.5 | D16: 1.5 | E16: 1.5 | F16: 1.5 | G16: 1.5 | H16: 1.5 | I16: 1.5 | J16: 1.5 | K16: 1.5 | L16: 1.5 | M16: 1.5 | N16: 1.5 | O16: 1.5 | P16: 1.5 | Q16: 1.5 | R16: 1.5 | S16: 1.5 | T16: 1.5 | U16: 1.5 | V16: 1.5 | W16: 1.5 | X16: 1.5 | Y16: 1.5 | Z16: 1.5 | AA16: 1.5 | AB16: 1.5 | AC16: 1.5 | AD16: 1.5 | AE16: 1.5 | AF16: 1.5 | AG16: 1.5 | AH16: 1.5 | AI16: 1.5 | AJ16: 1.5 | AK16: 1.5 | AL16: 1.5 | AM16: 1.5 | AN16: 1.5 | AO16: 1.5 | AP16: 1.5 | AQ16: 1.5 | AR16: 1.5 | AS16: 1.5 | AT16: 1.5 | AU16: 1.5 | AV16: 1.5 | AW16: 1.5 | AX16: 1.5 | AY16: 1.5 | AZ16: 1.5 | BA16: 1.5 | BB16: 1.5 | BC16: 1.5 | BD16: 1.5 | BE16: 1.5 | BF16: 1.5 | BG16: 1.5 | BH16: 1.5 | BI16: 1.5 | BJ16: 1.5
B17: kg/mes | C17: =+C16*C14*C3 -> 765 | D17: =+D16*D14*D3 -> 790.5 | E17: =+E16*E14*E3 -> 765 | F17: =+F16*F14*F3 -> 1255.5 | G17: =+G16*G14*G3 -> 1255.5 | H17: =+H16*H14*H3 -> 1134 | I17: =+I16*I14*I3 -> 1813.5 | J17: =+J16*J14*J3 -> 1755 | ... BJ17: =+BJ16*BJ14*BJ3 -> 1302
B18: No fertiles | C18: =SUM(C19:C20) -> 2 | D18: =SUM(D19:D20) -> 2 | E18: =SUM(E19:E20) -> 2 | F18: =SUM(F19:F20) -> 4 | G18: =SUM(G19:G20) -> 4 | H18: =SUM(H19:H20) -> 4 | I18: =SUM(I19:I20) -> 4 | J18: =SUM(J19:J20) -> 2 | ... BJ18: =SUM(BJ19:BJ20) -> 2
B19: Jóvenes | C19: 0 | D19: =+C19 -> 0 | E19: =+D19 -> 0 | F19: =+E19 -> 0 | G19: =+F19 -> 0 | H19: =+G19 -> 0 | I19: =+H19 -> 0 | J19: =+I19 -> 0 | K19: =+J19 -> 0 | ... BJ19: =+BI19 -> 0
B20: Verracos | C20: 2 | D20: =C20 -> 2 | E20: =D20 -> 2 | F20: =E20+2 -> 4 | G20: =F20 -> 4 | H20: =G20 -> 4 | I20: =H20 -> 4 | J20: =I20-2 -> 2 | K20: =J20 -> 2 | L20: =K20 -> 2 | M20: =L20 -> 2 | N20: =M20 -> 2 | O20: =N20 -> 2 | P20: =O20 -> 2 | Q20: =P20 -> 2 | R20: =Q20 -> 2 | ... BJ20: =BI20 -> 2
B21: Madres fertiles | C21: =+C14-C18 -> 15 | D21: =+D14-D18 -> 15 | E21: =+E14-E18 -> 15 | F21: =+F14-F18 -> 23 | G21: =+G14-G18 -> 23 | H21: =+H14-H18 -> 23 | I21: =+I14-I18 -> 35 | J21: =+J14-J18 -> 37 | ... BJ21: =+BJ14-BJ18 -> 26
B23: Lechones
B24: Stock Inicial | C24: 0 | D24: =+C28 -> 0 | E24: =+D28 -> 0 | F24: =+E28 -> 0 | G24: =+F28 -> 0 | H24: =+G28 -> 48 | I24: =+H28 -> 48 | J24: =+I28 -> 48 | K24: =+J28 -> 32 | ... BJ24: =+BI28 -> -19
B25: Partos (entrada) | G25: 48 | J25: 32 | M25: 30 | S25: 6 | T25: =5*3+8*2 -> 31 | U25: =157+9 -> 166 | Z25: 126 | AA25: 29 | AG25: 122 | AH25: 13 | AI25: 15 | AL25: 80 | AM25: 80 | AR25: 80 | AS25: 80 | AX25: 80 | AY25: 80 | BD25: 80 | BE25: 80 | BJ25: 80
B26: A marrano (salida) | J26: =-G25 -> -48 | M26: =-J25 -> -32 | P26: =-M25 -> -30 | U26: -22 | W26: -90 | AB26: -123 | AC26: -32 | AI26: -135 | AJ26: -15 | AN26: -80 | AO26: -80 | AT26: -80 | AU26: -80 | AZ26: -80 | BA26: -80 | BF26: -80 | BG26: -80
B27: Mermas | S27: -1 | T27: =-11-2 -> -13 | U27: -66 | V27: -7 | W27: -4 | AG27: -19
B28: Stock Final | C28: =SUM(C24:C27) -> 0 | D28: =SUM(D24:D27) -> 0 | E28: =SUM(E24:E27) -> 0 | F28: =SUM(F24:F27) -> 0 | G28: =SUM(G24:G27) -> 48 | H28: =SUM(H24:H27) -> 48 | I28: =SUM(I24:I27) -> 48 | J28: =SUM(J24:J27) -> 32 | ... BJ28: =SUM(BJ24:BJ27) -> 61
B30: Marranos
B31: Stock inicial | C31: 87 | D31: =+C35 -> 87 | E31: =+D35 -> 87 | F31: =+E35 -> 87 | G31: =+F35 -> 0 | H31: =+G35 -> 0 | I31: =+H35 -> 0 | J31: =+I35 -> 0 | K31: =+J35 -> 48 | ... BJ31: =+BI35 -> 160
B32: Entrada (de lechones) | C32: =-C26 -> 0 | D32: =-D26 -> 0 | E32: =-E26 -> 0 | F32: =-F26 -> 0 | G32: =-G26 -> 0 | H32: =-H26 -> 0 | I32: =-I26 -> 0 | J32: =-J26 -> 48 | ... M32: =-M26 -> 32 | N32: =-N12 -> 0 | O32: =-O26 -> 0 | P32: =-P26 -> 30 | Q32: =-Q26 -> 0 | R32: =-R26 -> 0 | S32: =-S26 -> 0 | T32: =-T26 -> 0 | U32: =-U26 -> 22 | V32: =-V26 -> 0 | W32: =-W26 -> 90 | X32: 18 | Y32: =-Y26 -> 0 | Z32: =-Z26 -> 0 | AA32: =-AA26 -> 0 | AB32: =-AB26 -> 123 | AC32: =-AC26 -> 32 | AD32: =-AD26 -> 0 | AE32: =-AE26 -> 0 | AF32: =-AF26 -> 0 | ... BJ32: =-BJ26 -> 0
B33: Mermas | X33: -1 | Y33: -5 | Z33: -2 | AA33: -15 | AB33: -4 | AC33: -4 | AD33: -1 | AF33: -4 | AG33: -32
B34: A primal (salida) | F34: =-C31 -> -87 | M34: =-J32+33 -> -15 | S34: =-32-33 -> -65 | T34: -17 | U34: -13 | AB34: -107 | AH34: -110 | AO34: -150 | AT34: -160 | AZ34: -160 | BF34: -160
B35: Stock final | C35: =SUM(C31:C34) -> 87 | D35: =SUM(D31:D34) -> 87 | E35: =SUM(E31:E34) -> 87 | F35: =SUM(F31:F34) -> 0 | G35: =SUM(G31:G34) -> 0 | H35: =SUM(H31:H34) -> 0 | I35: =SUM(I31:I34) -> 0 | J35: =SUM(J31:J34) -> 48 | ... BJ35: =SUM(BJ31:BJ34) -> 160
B37: Primales
B38: Stock inicial | C38: 84 | D38: =+C42 -> 84 | E38: =+D42 -> 84 | F38: =+E42 -> 0 | G38: =+F42 -> 87 | H38: =+G42 -> 87 | I38: =+H42 -> 87 | J38: =+I42 -> 87 | K38: =+J42 -> 87 | ... BJ38: =+BI42 -> 320
B39: Entrada (de marranos) | C39: =-C34 -> 0 | D39: =-D34 -> 0 | E39: =-E34 -> 0 | F39: =-F34 -> 87 | G39: =-G34 -> 0 | H39: =-H34 -> 0 | I39: =-I34 -> 0 | J39: =-J34 -> 0 | ... BJ39: =-BJ34 -> 0
B40: Mermas | S40: =-2-3+4 -> -1 | W40: -1 | X40: -1 | AD40: -1
B41: A montanera (salida) | E41: -84 | Q41: =-F39-M39-Q39 -> -102 | AB41: -87 | AN41: -221 | AZ41: =-AT39-AO39 -> -310
B42: Stock final | C42: =SUM(C38:C41) -> 84 | D42: =SUM(D38:D41) -> 84 | E42: =SUM(E38:E41) -> 0 | F42: =SUM(F38:F41) -> 87 | G42: =SUM(G38:G41) -> 87 | H42: =SUM(H38:H41) -> 87 | I42: =SUM(I38:I41) -> 87 | J42: =SUM(J38:J41) -> 87 | ... BJ42: =SUM(BJ38:BJ41) -> 320
B44: Montanera
B45: Stock inicial | C45: 0 | D45: =+C49 -> 0 | E45: =+D49 -> 0 | F45: =+E49 -> 84 | G45: =+F49 -> 84 | H45: =+G49 -> 84 | I45: =+H49 -> 56 | J45: =+I49 -> 0 | K45: =+J49 -> 0 | ... BJ45: =+BI49 -> 0
B46: Entrada (de primales) | C46: =-C41 -> 0 | D46: =-D41 -> 0 | E46: =-E41 -> 84 | F46: =-F41 -> 0 | G46: =-G41 -> 0 | H46: =-H41 -> 0 | I46: =-I41 -> 0 | J46: =-J41 -> 0 | ... BJ46: =-BJ41 -> 0
B47: Mermas | S47: =-1-2 -> -3 | AF47: =-3 -> -3 | AG47: =6-1-46 -> -41
B48: Venta (salida) | H48: -28 | I48: -56 | S48: =-46-3 -> -49 | U48: =-11-38 -> -49 | V48: -1 | AF48: =-40-2 -> -42 | AG48: =-1 -> -1 | AS48: =-AN46 -> -221 | BE48: =-AZ46 -> -310
B49: Stock final | C49: =SUM(C45:C48) -> 0 | D49: =SUM(D45:D48) -> 0 | E49: =SUM(E45:E48) -> 84 | F49: =SUM(F45:F48) -> 84 | G49: =SUM(G45:G48) -> 84 | H49: =SUM(H45:H48) -> 56 | I49: =SUM(I45:I48) -> 0 | J49: =SUM(J45:J48) -> 0 | ... BJ49: =SUM(BJ45:BJ48) -> 0
B51: Montanera terceros
B52: Stock inicial | C52: 0 | D52: =+C56 -> 0 | E52: =+D56 -> 0 | F52: =+E56 -> 150 | G52: =+F56 -> 150 | H52: =+G56 -> 150 | I52: =+H56 -> 99 | J52: =+I56 -> 0 | K52: =+J56 -> 0 | ... BJ52: =+BI56 -> 0
B53: Entrada | E53: 150 | P53: 150 | AB53: 200 | AN53: 80
B54: Mermas | H54: -1 | Q54: -1 | AG54: -6
B55: Venta (salida) | H55: -50 | I55: -99 | T55: =-60-87 -> -147 | W55: -2 | AF55: -100 | AG55: -94 | AS55: -80
B56: Stock final | C56: =SUM(C52:C55) -> 0 | D56: =SUM(D52:D55) -> 0 | E56: =SUM(E52:E55) -> 150 | F56: =SUM(F52:F55) -> 150 | G56: =SUM(G52:G55) -> 150 | H56: =SUM(H52:H55) -> 99 | I56: =SUM(I52:I55) -> 0 | J56: =SUM(J52:J55) -> 0 | ... BJ56: =SUM(BJ52:BJ55) -> 0
B58: Madres y verracos cereal
B59: kg/dia/animal | C59: 1.5 | D59: 1.5 | E59: 1.5 | F59: 1.5 | G59: 1.5 | H59: 3 | I59: 3 | J59: 1.5 | K59: 1.5 | L59: 1.5 | M59: 3 | N59: 3 | O59: 1.5 | P59: 1.5 | Q59: 1.5 | R59: 1.5 | S59: 2 | T59: 2.6 | U59: 3 | V59: 1.8 | W59: 1.6 | X59: 1.6 | Y59: 2 | Z59: 2.6 | AA59: 2.67 | AB59: 2.67 | AC59: 1.69 | AD59: 0.95 | AE59: 2 | AF59: 2.6 | AG59: 2.67 | AH59: 2.67 | AI59: 1.6 | AJ59: 1.6 | AK59: 1.8 | AL59: 2.6 | AM59: 3 | AN59: 1.8 | AO59: 1.4 | AP59: 1.5 | AQ59: 2 | AR59: 2.6 | AS59: 2.67 | AT59: 1.8 | AU59: 1.6 | AV59: 1.6 | AW59: 1.8 | AX59: 2.6 | AY59: 2.67 | AZ59: 1.8 | BA59: 1.4 | BB59: 1.5 | BC59: 2 | BD59: 2.6 | BE59: 3 | BF59: 1.8 | BG59: 1.6 | BH59: 1.6 | BI59: 1.8 | BJ59: 2.6
B60: kg/mes | C60: =(C14)*C59*C3 -> 765 | D60: =(D14)*D59*D3 -> 790.5 | E60: =(E14)*E59*E3 -> 765 | F60: =(F14)*F59*F3 -> 1255.5 | G60: =(G14)*G59*G3 -> 1255.5 | H60: =(H14)*H59*H3 -> 2268 | I60: =(I14)*I59*I3 -> 3627 | J60: =(J14)*J59*J3 -> 1755 | ... BJ60: =(BJ14)*BJ59*BJ3 -> 2256.8
B61: Madres y verracos leguminosa
B62: kg/dia/animal | AA62: 0.43 | AB62: 0.43 | AC62: 0.43 | AD62: 0.43 | AE62: 0.43 | AF62: 0.43 | AG62: 0.43 | AH62: 0.43 | AI62: 0.43 | AJ62: 0.43 | AK62: 0.43 | AL62: 0.43 | AM62: 0.43 | AN62: 0.43 | AO62: 0.43 | AP62: 0.43 | AQ62: 0.43 | AR62: 0.43 | AS62: 0.43 | AT62: 0.43 | AU62: 0.43 | AV62: 0.43 | AW62: 0.43 | AX62: 0.43 | AY62: 0.43 | AZ62: 0.43 | BA62: 0.43 | BB62: 0.43 | BC62: 0.43 | BD62: 0.43 | BE62: 0.43 | BF62: 0.43 | BG62: 0.43 | BH62: 0.43 | BI62: 0.43 | BJ62: 0.43
B63: kg/mes
B64: Lechones
B65: kg/dia/animal | C65: 0.1 | D65: 0.2 | I65: 0.1 | J65: 0.2 | O65: 0.1 | P65: 0.2 | U65: 0.1 | V65: 0.2 | AA65: 0.1 | AB65: 0.3 | AH65: 0.08 | AI65: 0.12 | AM65: 0.08 | AN65: 0.12 | AS65: 0.08 | AT65: 0.12 | AY65: 0.08 | AZ65: 0.12 | BE65: 0.08 | BF65: 0.12
B66: kg/mes | C66: =(C28)*C65*C3 -> 0 | D66: =(D28)*D65*D3 -> 0 | E66: =(E28)*E65*E3 -> 0 | F66: =(F28)*F65*F3 -> 0 | G66: =(G28)*G65*G3 -> 0 | H66: =(H28)*H65*H3 -> 0 | I66: =(I28)*I65*I3 -> 148.8 | J66: =(J28)*J65*J3 -> 192 | ... BJ66: =(BJ28)*BJ65*BJ3 -> 0
B67: Marranos pienso
B68: kg/dia/animal | C68: 0 | D68: 0 | E68: 0 | F68: 0 | G68: 0.5 | H68: 0 | I68: 0 | J68: 0.8 | K68: 0.95 | L68: 0.95 | M68: 0.95 | N68: 0.95 | O68: 0.95 | P68: 0.95 | Q68: 0.95 | R68: 0.95 | S68: 0.95 | T68: 0.9 | U68: 0.7 | V68: 0.85 | W68: 0.95 | X68: 0.9 | Y68: 1.5 | Z68: 1.93 | AA68: 1 | AB68: 0.7 | AC68: 0.85 | AD68: 1.19 | AE68: 1.31 | AF68: 0.9 | AG68: 0.7 | AH68: 0.85 | AI68: 0.95 | AJ68: 0.89 | AK68: 1.07 | AL68: 1.93 | AM68: 1 | AN68: 0.7 | AO68: 0.85 | AP68: 0.91 | AQ68: 1.03 | AR68: 0.9 | AS68: 0.7 | AT68: 0.85 | AU68: 0.95 | AV68: 0.9 | AW68: 1.5 | AX68: 1.5 | AY68: 1 | AZ68: 0.7 | BA68: 0.85 | BB68: 0.91 | BC68: 1.03 | BD68: 0.9 | BE68: 0.7 | BF68: 0.85 | BG68: 0.95 | BH68: 0.9 | BI68: 1.5 | BJ68: 1.5
B69: kg/mes | C69: =C68*C35*C3 -> 0 | D69: =D68*D35*D3 -> 0 | E69: =E68*E35*E3 -> 0 | F69: =F68*F35*F3 -> 0 | G69: =G68*G35*G3 -> 0 | H69: =H68*H35*H3 -> 0 | I69: =I68*I35*I3 -> 0 | J69: =J68*J35*J3 -> 1152 | ... BJ69: =BJ68*BJ35*BJ3 -> 7440
B70: Primales cereal
B71: kg/dia/animal | C71: =2.04+0.64 -> 2.68 | D71: =2.04+0.64 -> 2.68 | E71: 1.2384292 | F71: 1.4090301 | G71: 1.0391961 | H71: 0.29227105 | I71: 0.16179291 | J71: 0.6607243 | K71: 0.94276094 | L71: 1.87 | M71: 1.87 | N71: 1.87 | O71: 1.87 | P71: 1.87 | Q71: 1.87 | R71: 1.87 | S71: 1.8 | T71: 1.87 | U71: 1.8 | V71: 1 | W71: 1.13 | X71: 1.02 | Y71: 1.78 | Z71: 2.49 | AA71: 1.6 | AB71: 0.6 | AC71: 0.6 | AD71: 0.6 | AE71: 0.6 | AF71: 0.9 | AG71: 0.9 | AH71: 0.9 | AI71: 1.25 | AJ71: 1.6 | AK71: 1 | AL71: 0.9 | AM71: 1.6 | AN71: 0.6 | AO71: 0.6 | AP71: 0.6 | AQ71: 0.6 | AR71: 0.9 | AS71: 0.9 | AT71: 0.9 | AU71: 1.25 | AV71: 1.6 | AW71: 1 | AX71: 0.9 | AY71: 1.6 | AZ71: 0.6 | BA71: 0.6 | BB71: 0.6 | BC71: 0.6 | BD71: 0.9 | BE71: 0.9 | BF71: 0.9 | BG71: 1.25 | BH71: 1.6 | BI71: 1 | BJ71: 0.9
B72: kg/mes | C72: =C71*C42*C3 -> 6753.6 | D72: =D71*D42*D3 -> 6978.72 | E72: =E71*E42*E3 -> 0 | F72: =F71*F42*F3 -> 3800.1542 | G72: =G71*G42*G3 -> 2802.7119 | H72: =H71*H42*H3 -> 711.97229 | I72: =I71*I42*I3 -> 436.35547 | J72: =J71*J42*J3 -> 1724.4904 | ... BJ72: =BJ71*BJ42*BJ3 -> 8928
B73: Primales leguminosa
B74: kg/dia/animal | AA74: 1.6 | AB74: 0.58 | AC74: 0.6 | AD74: 0.6 | AE74: 0.6 | AF74: 0.9 | AG74: 0.9 | AH74: 0.9 | AI74: 1.25 | AJ74: 1.6 | AK74: 1 | AL74: 0.9 | AM74: 1.6 | AN74: 0.58 | AO74: 0.6 | AP74: 0.6 | AQ74: 0.6 | AR74: 0.9 | AS74: 0.9 | AT74: 0.9 | AU74: 1.25 | AV74: 1.6 | AW74: 1 | AX74: 0.9 | AY74: 1.6 | AZ74: 0.58 | BA74: 0.6 | BB74: 0.6 | BC74: 0.6 | BD74: 0.9 | BE74: 0.9 | BF74: 0.9 | BG74: 1.25 | BH74: 1.6 | BI74: 1 | BJ74: 0.9
B75: kg/mes | C75: =C74*C42*C3 -> 0 | D75: =D74*D42*D3 -> 0 | E75: =E74*E42*E3 -> 0 | F75: =F74*F42*F3 -> 0 | G75: =G74*G42*G3 -> 0 | H75: =H74*H42*H3 -> 0 | I75: =I74*I42*I3 -> 0 | J75: =J74*J42*J3 -> 0 | ... BJ75: =BJ74*BJ42*BJ3 -> 8928
B76: Montanera pienso
B77: kg/dia/animal | E77: 2 | F77: 1.5 | G77: 0.6 | H77: 0.6 | P77: 1.6 | Q77: 1.25 | R77: 2.7 | S77: 3.95 | T77: 3.95 | U77: 3.95 | AB77: 1.79 | AC77: 2.82 | AD77: 1.28 | AE77: 1.5 | AF77: 5 | AN77: 1.8 | AO77: 2.8 | AP77: 1.3 | AQ77: 1.5 | AR77: 5 | AZ77: 1.8 | BA77: 2.8 | BB77: 1.3 | BC77: 1.5 | BD77: 5
B78: kg/mes | C78: =C77*(C56+C49)*C3 -> 0 | D78: =D77*(D56+D49)*D3 -> 0 | E78: =E77*(E56+E49)*E3 -> 14040 | F78: =F77*(F56+F49)*F3 -> 10881 | G78: =G77*(G56+G49)*G3 -> 4352.4 | H78: =H77*(H56+H49)*H3 -> 2604 | I78: =I77*(I56+I49)*I3 -> 0 | J78: =J77*(J56+J49)*J3 -> 0 | ... BJ78: =BJ77*(BJ56+BJ49)*BJ3 -> 0
B80: Totales alimento (kg/mes)
B81: Cereal | C81: =C72+C60 -> 7518.6 | D81: =D72+D60 -> 7769.22 | E81: =E72+E60 -> 765 | F81: =F72+F60 -> 5055.6542 | G81: =G72+G60 -> 4058.2119 | H81: =H72+H60 -> 2979.9723 | I81: =I72+I60 -> 4063.3555 | J81: =J72+J60 -> 3479.4904 | ... BJ81: =BJ72+BJ60 -> 11184.8
B82: Leguminosa | C82: =C63+C75 -> 0 | D82: =D63+D75 -> 0 | E82: =E63+E75 -> 0 | F82: =F63+F75 -> 0 | G82: =G63+G75 -> 0 | H82: =H63+H75 -> 0 | I82: =I63+I75 -> 0 | J82: =J63+J75 -> 0 | ... BJ82: =BJ63+BJ75 -> 8928
B83: Paja y otras fibras
B84: Heno
B85: Pienso lechones | C85: =C66 -> 0 | D85: =D66 -> 0 | E85: =E66 -> 0 | F85: =F66 -> 0 | G85: =G66 -> 0 | H85: =H66 -> 0 | I85: =I66 -> 148.8 | J85: =J66 -> 192 | ... BJ85: =BJ66 -> 0
B86: Pienso Marrano | C86: =C69 -> 0 | D86: =D69 -> 0 | E86: =E69 -> 0 | F86: =F69 -> 0 | G86: =G69 -> 0 | H86: =H69 -> 0 | I86: =I69 -> 0 | J86: =J69 -> 1152 | ... BJ86: =BJ69 -> 7440
B87: Pienso Montanera | C87: =C78 -> 0 | D87: =D78 -> 0 | E87: =E78 -> 14040 | F87: =F78 -> 10881 | G87: =G78 -> 4352.4 | H87: =H78 -> 2604 | I87: =I78 -> 0 | J87: =J78 -> 0 | ... BJ87: =BJ78 -> 0
B90: Vacas y toros
B91: Stock Inicial | C91: 172 | D91: =+C98 -> 172 | E91: =+D98 -> 172 | F91: =+E98 -> 171 | G91: =+F98 -> 177 | H91: =+G98 -> 177 | I91: =+H98 -> 177 | J91: =+I98 -> 177 | K91: =+J98 -> 174 | ... BJ91: =+BI98 -> 269
B92: Entradas | C92: =SUM(C93:C94) -> 0 | D92: =SUM(D93:D94) -> 0 | E92: =SUM(E93:E94) -> 0 | F92: =SUM(F93:F94) -> 6 | G92: =SUM(G93:G94) -> 0 | H92: =SUM(H93:H94) -> 0 | I92: =SUM(I93:I94) -> 0 | J92: =SUM(J93:J94) -> 0 | ... BJ92: =SUM(BJ93:BJ94) -> 0
B93: Reposición | N93: 4 | AI93: 9 | AJ93: 7 | AK93: =7+4 -> 11 | AL93: =7+7 -> 14 | AO93: =13+1+4 -> 18 | AP93: =2+1 -> 3 | AR93: 4 | AS93: 7 | AT93: 6 | AU93: 6 | AX93: 6 | AY93: 5 | AZ93: 15 | BA93: 3
B94: Compras | F94: 6
B95: Salidas | C95: =SUM(C96:C97) -> 0 | D95: =SUM(D96:D97) -> 0 | E95: =SUM(E96:E97) -> -1 | F95: =SUM(F96:F97) -> 0 | G95: =SUM(G96:G97) -> 0 | H95: =SUM(H96:H97) -> 0 | I95: =SUM(I96:I97) -> 0 | J95: =SUM(J96:J97) -> -3 | ... BJ95: =SUM(BJ96:BJ97) -> 0
B96: Ventas/cebo | E96: -1 | J96: =-2-1 -> -3 | Q96: =-1-1-1 -> -3 | R96: =-1-1 -> -2 | AB96: =-1 -> -1 | AD96: -3
B97: Mermas | C97: 0 | O97: -1 | P97: -1 | Q97: -1 | R97: -1 | S97: -1 | T97: -1 | V97: -2 | Y97: -1 | AE97: -2 | AG97: -1 | AH97: -1 | AI97: -1
B98: Stock Final | C98: =SUM(C91,C92,C95) -> 172 | D98: =SUM(D91,D92,D95) -> 172 | E98: =SUM(E91,E92,E95) -> 171 | F98: =SUM(F91,F92,F95) -> 177 | G98: =SUM(G91,G92,G95) -> 177 | H98: =SUM(H91,H92,H95) -> 177 | I98: =SUM(I91,I92,I95) -> 177 | J98: =SUM(J91,J92,J95) -> 174 | ... BJ98: =SUM(BJ91,BJ92,BJ95) -> 269
B99: Alimento
B100: kg/dia/animal | C100: 11 | D100: 13 | E100: 13 | F100: 13 | G100: 13 | H100: 10 | I100: 10 | J100: 10 | K100: 10 | L100: 10 | M100: 10 | N100: 10 | O100: 10 | P100: 9 | Q100: 9 | R100: 9 | S100: 9 | T100: 10 | U100: 10 | V100: 10 | W100: 10 | X100: 10 | Y100: 10 | Z100: 10 | AA100: 9 | AB100: 9 | AC100: 9 | AD100: 9 | AE100: 10 | AF100: 10 | AG100: 10 | AH100: 10 | AI100: 10 | AJ100: 10 | AK100: 10 | AL100: 10 | AM100: 9 | AN100: 9 | AO100: 9 | AP100: 9 | AQ100: 10 | AR100: 10 | AS100: 10 | AT100: 10 | AU100: 10 | AV100: 10 | AW100: 10 | AX100: 10 | AY100: 9 | AZ100: 9 | BA100: 9 | BB100: 9 | BC100: 10 | BD100: 10 | BE100: 10 | BF100: 10 | BG100: 10 | BH100: 10 | BI100: 10 | BJ100: 10
B101: kg/mes | C101: =+C100*C98*C3 -> 56760 | D101: =+D100*D98*D3 -> 69316 | E101: =+E100*E98*E3 -> 66690 | F101: =+F100*F98*F3 -> 71331 | G101: =+G100*G98*G3 -> 71331 | H101: =+H100*H98*H3 -> 49560 | I101: =+I100*I98*I3 -> 54870 | J101: =+J100*J98*J3 -> 52200 | ... BJ101: =+BJ100*BJ98*BJ3 -> 83390
B102: Fertilidad | C102: =C107/(C107+C106) -> 0.81021898 | D102: =D107/(D107+D106) -> 0.81021898 | E102: =E107/(E107+E106) -> 0.68518519 | F102: =F107/(F107+F106) -> 0.68518519 | G102: =G107/(G107+G106) -> 0.68518519 | H102: =H107/(H107+H106) -> 0.68518519 | I102: =I107/(I107+I106) -> 0.68518519 | J102: =J107/(J107+J106) -> 0.6686747 | ... BJ102: =BJ107/(BJ107+BJ106) -> 0.80916031
B103: No preñadas | C103: =SUM(C104:C106) -> 61 | D103: =SUM(D104:D106) -> 61 | E103: =SUM(E104:E106) -> 60 | F103: =SUM(F104:F106) -> 66 | G103: =SUM(G104:G106) -> 66 | H103: =SUM(H104:H106) -> 66 | I103: =SUM(I104:I106) -> 66 | J103: =SUM(J104:J106) -> 63 | ... BJ103: =SUM(BJ104:BJ106) -> 57
B104: Jóvenes | C104: 26 | D104: =26 -> 26 | E104: 0 | F104: 6 | G104: =+F104 -> 6 | H104: =+G104 -> 6 | I104: =+H104 -> 6 | J104: 0 | K104: =+J104 -> 0 | L104: =+K104 -> 0 | M104: =+L104 -> 0 | N104: 4 | O104: =+N104 -> 4 | P104: =+O104 -> 4 | Q104: =+P104 -> 4 | R104: =+Q104 -> 4 | S104: =+R104 -> 4 | T104: =+S104 -> 4 | U104: =+T104 -> 4 | V104: =+U104 -> 4 | W104: =+V104 -> 4 | X104: 0 | Y104: 0 | Z104: =+Y104 -> 0 | AA104: =+Z104 -> 0 | AB104: =AA104 -> 0 | AC104: =+AB104 -> 0 | AD104: =+AC104 -> 0 | AE104: =+AD104 -> 0 | AF104: =AE104 -> 0 | AG104: =AF104 -> 0 | AH104: =AG104 -> 0 | AI104: =AH104 -> 0 | AJ104: =+AI104 -> 0 | AK104: =+AJ104 -> 0 | AL104: =+AK104 -> 0 | AM104: =+AL104 -> 0 | AN104: =+AM104 -> 0 | AO104: =+AN104 -> 0 | AP104: =+AO104 -> 0 | AQ104: =+AP104 -> 0 | ... BJ104: =+BI104 -> 0
B105: Toros | C105: 9 | D105: =C105 -> 9 | E105: =D105 -> 9 | F105: =E105 -> 9 | G105: =F105 -> 9 | H105: =G105 -> 9 | I105: =H105 -> 9 | J105: =I105-1 -> 8 | K105: =J105 -> 8 | L105: =K105 -> 8 | M105: =L105 -> 8 | N105: 8 | O105: =N105 -> 8 | P105: =O105 -> 8 | Q105: 6 | R105: =Q105 -> 6 | S105: =R105 -> 6 | T105: =S105 -> 6 | U105: =T105 -> 6 | V105: =U105 -> 6 | W105: =V105 -> 6 | X105: 7 | Y105: 6 | Z105: =Y105 -> 6 | AA105: =Z105 -> 6 | AB105: =AA105-1 -> 5 | AC105: =AB105 -> 5 | AD105: =AC105 -> 5 | AE105: =AD105 -> 5 | AF105: =AE105 -> 5 | AG105: =AF105 -> 5 | AH105: =AG105 -> 5 | AI105: 6 | AJ105: 6 | AK105: =AJ105 -> 6 | AL105: =AK105 -> 6 | AM105: =AL105 -> 6 | AN105: =AM105 -> 6 | AO105: =AN105+1 -> 7 | AP105: =AO105 -> 7 | AQ105: =AP105 -> 7 | AR105: =AQ105 -> 7 | AS105: =AR105 -> 7 | AT105: =AS105 -> 7 | AU105: =AT105 -> 7 | AV105: =AU105 -> 7 | AW105: =AV105 -> 7 | ... BJ105: =BI105 -> 7
B106: Vacias | C106: 26 | D106: =+C106 -> 26 | E106: 51 | F106: =E106 -> 51 | G106: =F106 -> 51 | H106: =G106 -> 51 | I106: =H106 -> 51 | J106: 55 | K106: 27 | L106: 27 | M106: 27 | N106: =M106 -> 27 | O106: =(O98-O105-O104)*0.1 -> 16.5 | P106: =(P98-P105-P104)*0.1 -> 16.4 | Q106: =(Q98-Q105-Q104)*0.1 -> 16.2 | R106: =(R98-R105-R104)*0.1 -> 15.9 | S106: =(S98-S105-S104)*0.1 -> 15.8 | T106: =(T98-T105-T104)*0.1 -> 15.7 | U106: =(U98-U105-U104)*0.1 -> 15.7 | V106: =(V98-V105-V104)*0.1 -> 15.5 | ... X106: =(X98-X105-X104)*0.1 -> 15.8 | Y106: 50 | Z106: 50 | AA106: 50 | AB106: 50 | AC106: 50 | AD106: 50 | AE106: 50 | AF106: 50 | AG106: 50 | AH106: 50 | AI106: 50 | AJ106: 50 | AK106: 50 | AL106: 50 | AM106: 50 | AN106: 50 | AO106: 50 | AP106: 50 | AQ106: 50 | AR106: 50 | AS106: 50 | AT106: 50 | AU106: 50 | AV106: 50 | AW106: 50 | AX106: 50 | AY106: 50 | AZ106: 50 | BA106: 50 | BB106: 50 | BC106: 50 | BD106: 50 | BE106: 50 | BF106: 50 | BG106: 50 | BH106: 50 | BI106: 50 | BJ106: 50
B107: Preñadas | C107: =+C98-C103 -> 111 | D107: =+D98-D103 -> 111 | E107: =+E98-E103 -> 111 | F107: =+F98-F103 -> 111 | G107: =+G98-G103 -> 111 | H107: =+H98-H103 -> 111 | I107: =+I98-I103 -> 111 | J107: =+J98-J103 -> 111 | ... BJ107: =+BJ98-BJ103 -> 212
C110: Paridera | O110: Paridera | AA110: Paridera | AM110: Paridera | AY110: Paridera
B111: Checks | C111: =SUM(C112:N112) -> 0.97382809 | N111: =SUM(C114:N114)-C107+C113 -> 8 | O111: =SUM(O112:Z112) -> 0.85398881 | Z111: =SUM(O114:Z114)-O107 -> -11.5 | AA111: =SUM(AA112:AL112) -> 0.90571251 | AL111: =SUM(AA114:AL114)-AA107 -> 33 | AM111: =SUM(AM112:AX112) -> 0.90108943 | AX111: =SUM(AM114:AX114)-AM107 -> 55.85948 | AY111: =SUM(AY112:BJ112) -> 0.90108943 | BJ111: =SUM(AY114:BJ114)-AY107 -> 41.674904
B112: Terneros Lactantes | C112: =(C113+C114)/(SUM($C$114:$N$114)+$C$113) -> 0.16806723 | D112: =(D114)/(SUM($C$114:$N$114)+$C$113) -> 0.067226891 | E112: =(E114)/(SUM($C$114:$N$114)+$C$113) -> 0.075630252 | F112: =(F114)/(SUM($C$114:$N$114)+$C$113) -> 0.21008403 | G112: =(G114)/(SUM($C$114:$N$114)+$C$113) -> 0.058823529 | H112: =(H114)/(SUM($C$114:$N$114)+$C$113) -> 0.050420168 | I112: =(I114)/(SUM($C$114:$N$114)+$C$113) -> 0.14285714 | J112: =(J114)/(SUM($C$114:$N$114)+$C$113) -> 0.067226891 | K112: =(K114)/(SUM($C$114:$N$114)+$C$113) -> 0.033613445 | ... M112: =(M114)/(SUM($C$114:$N$114)+$C$113) -> 0.016806723 | N112: =N114/(M107+M106) -> 0.06626506 | O112: =O114/(N107+N106) -> 0.06626506 | P112: =P114/(O107+O106) -> 0.048484848 | Q112: =Q114/(P107+P106) -> 0.12804878 | R112: =R114/(Q107+Q106) -> 0.17901235 | S112: =S114/(R107+R106) -> 0.088050314 | T112: =T114/(S107+S106) -> 0.088607595 | U112: =U114/(T107+T106) -> 0.057324841 | ... AP112: =AP114/(AO107+AO106) -> 0.057971014 | AQ112: 0.12 | AR112: 0.14 | AS112: =AG112 -> 0.12418301 | AT112: =AH112 -> 0.14473684 | AU112: 0.12 | AV112: 0.03 | AW112: 0.02 | AX112: =AL112 -> 0.028409091 | AY112: =AM112 -> 0.021052632 | AZ112: =AN112 -> 0.010526316 | BA112: =AO112 -> 0.084210526 | BB112: =AP112 -> 0.057971014 | BC112: =AQ112 -> 0.12 | BD112: =AR112 -> 0.14 | BE112: =AS112 -> 0.12418301 | ... BJ112: =AX112 -> 0.028409091
B113: Stock Inicial | C113: 14 | D113: =+C117 -> 20 | E113: =+D117 -> 25 | F113: =+E117 -> 33 | G113: =+F117 -> 55 | H113: =+G117 -> 49 | I113: =+H117 -> 49 | J113: =+I117 -> 49 | K113: =+J117 -> 30 | ... BJ113: =+BI117 -> 68.461053
...

Sheet Hoja1
B2: VENTAS CERDO | D2: 31171.96
B3: Compras de carne | D3: 27871.24
B4: Transporte TOTAL | D4: 4548.35
B5: MARGEN | D5: =D2-D3-D4 -> -1247.63
F6: 12 VIAJES VACA | H6: 0.48
F7: 13 VIAJES CARNE CERDO | H7: 0.52
J8: 0.48
B9: VENTAS CERDO | D9: 31171.96 | J9: 0.52
B10: Compras de carne | D10: 27871.24
B11: Transporte 50% | D11: =4548.35*0.52 -> 2365.142
B12: MARGEN | D12: =D9-D10-D11 -> 935.578
H16: 0.48
H17: 0.52
H23: Saldo caixa 25/09/25 | I23: 7760.23
H24: IVA agosto | I24: =-'Ing y gtos'!BJ92 -> -4638.02
H25: Nominas | I25: =-1250*2 -> -2500
H26: Seg. Sociales | I26: =-759.42 -> -759.42
H27: Facturas carne | I27: =-(1068.65+744.95+3347.29+557.25+1932.92+786.67) -> -8437.73
H28: Facturas mantenimento | I28: =-(249.54+340.16+382.48+465.85+3515.87+150.81) -> -5104.71
H30: TOTAL | I30: =SUM(I23:I28) -> -13679.65

Sheet Calculos
A1: VACUNO | C1: 45199 | D1: 45230 | E1: 45260 | F1: 45291 | G1: 45322 | H1: 45350 | I1: 45382 | J1: 45412 | K1: 45443 | L1: 45473 | M1: 45504 | N1: 45535 | O1: 45565 | P1: 45596 | Q1: 45626 | R1: 45657 | S1: 45688 | T1: 45716 | U1: 45747 | V1: 45777 | W1: 45808 | X1: 45838 | Y1: 45869 | Z1: 45900 | AA1: 45930 | AB1: 45961
A2: Existencias, entradas y salidas | B2: Ei
A3: Animales cebo 80-150 Kg | B3: 74 | C3: =B3+B4 -> 74 | D3: =C3+C4 -> 74 | E3: =D3+D4 -> 74 | F3: =E3+E4 -> 74 | G3: =F3+F4 -> 74 | H3: =G3+G4 -> 1 | I3: =H3+H4 -> 1 | J3: =I3+I4 -> 1 | ... AB3: =AA3+AA4 -> 0
A4: Movimientos cebo 80-150 Kg | G4: =-46-3-9-15 -> -73 | J4: =-1 -> -1
A5: Animales cebo 150-230 Kg | B5: 73 | C5: =B5+B6 -> 73 | D5: =C5+C6 -> 73 | E5: =D5+D6 -> 12 | F5: =E5+E6 -> 12 | G5: =F5+F6 -> 12 | H5: =G5+G6 -> 0 | I5: =H5+H6 -> 0 | J5: =I5+I6 -> 0 | ... AB5: =AA5+AA6 -> 0
A6: Movimientos cebo 150-230 Kg | D6: =-61 -> -61 | G6: =-12 -> -12
A7: Animales cebo 231-400 Kg | B7: 53 | C7: =B7+B8 -> 53 | D7: =C7+C8 -> 53 | E7: =D7+D8 -> 53 | F7: =E7+E8 -> 0 | G7: =F7+F8 -> 0 | H7: =G7+G8 -> 0 | I7: =H7+H8 -> 0 | J7: =I7+I8 -> 0 | ... AB7: =AA7+AA8 -> 0
A8: Movimientos cebo 231-400 Kg | E8: =-17-36 -> -53
A9: Animales cebo >400 Kg | B9: 9 | C9: =B9+B10 -> 9 | D9: =C9+C10 -> 9 | E9: =D9+D10 -> 9 | F9: =E9+E10 -> 9 | G9: =F9+F10 -> 9 | H9: =G9+G10 -> 9 | I9: =H9+H10 -> 1 | J9: =I9+I10 -> 1 | ... AB9: =AA9+AA10 -> 1
A10: Movimientos cebo >400 Kg | H10: =-8 -> -8
A11: Madres repro, gestantes y toros | B11: 55 | C11: =B11+B12 -> 55 | D11: =C11+C12 -> 55 | E11: =D11+D12 -> 81 | F11: =E11+E12 -> 81 | G11: =F11+F12 -> 81 | H11: =G11+G12 -> 81 | I11: =H11+H12 -> 81 | J11: =I11+I12 -> 81 | ... AB11: =AA11+AA12 -> 81
A12: Movimientos repro, gest y toros | D12: =26 -> 26
A13: Madres con ternero lactando | B13: 104 | C13: =B13+B14 -> 104 | D13: =C13+C14 -> 104 | E13: =D13+D14 -> 104 | F13: =E13+E14 -> 104 | G13: =F13+F14 -> 104 | H13: =G13+G14 -> 104 | I13: =H13+H14 -> 104 | J13: =I13+I14 -> 104 | ... AB13: =AA13+AA14 -> 104
A14: Movimientos madres con ternero
A15: Lactantes bajo madre | B15: 1 | C15: =B15+B16 -> 21 | D15: =C15+C16 -> 30 | E15: =D15+D16 -> 39 | F15: =E15+E16 -> 62 | G15: =F15+F16 -> 53 | H15: =G15+G16 -> 53 | I15: =H15+H16 -> 48 | J15: =I15+I16 -> 53 | ... AB15: =AA15+AA16 -> 53
A16: Movimientos Lactantes | B16: =15+5 -> 20 | C16: =6+3 -> 9 | D16: =6+2+1 -> 9 | E16: =19+4 -> 23 | F16: =5-14 -> -9 | G16: =6-6 -> 0 | H16: =16-21 -> -5 | I16: =6-1 -> 5
A17: Ventas de terneros | D17: =7688.45*2.89+3703.23*2.12 -> 30070.468 | E17: =(17*800+36*900) -> 46000 | G17: =(25*200*3.04+25*10.64*3.04/2+33*198.06*2.24)*0.97+(3*159.67*3.04+9*165.44*2.24)*0.97 -> 33985.285 | H17: =8*605.53*0 -> 0 | J17: =(2063*4.14+2505*2.97) -> 15980.67 | L17: 16604.97 | M17: =450*27*0.55*5+(39*200)*3.05 -> 57202.5 | P17: =(46*200)*3.05 -> 28060 | Q17: =(16*200)*3.05 -> 9760 | U17: =(26*200)*3.05 -> 15860 | W17: =(40*200)*3.05 -> 24400 | Y17: =(50*200)*3.05 -> 30500 | AB17: =(59*200)*3.05 -> 35990
A19: Receta actual | B19: Cebada | C19: DDG | D19: Paja | E19: Mezcla | F19: Receta sep23 | H19: Siembra/pasto | I19: Siembra | J19: Pasto | L19: Pienso destt | M19: Pienso destt
A20: Consumos/costes unitarios | B20: Kg/dia | C20: Kg/dia | D20: Kg/dia | E20: Kg/dia | F20: €/dia/animal | H20: Kg/dia | I20: €/dia/animal | J20: €/dia/animal | L20: Kg/dia | M20: €/dia/animal
A21: Animales cebo 80-150 Kg | B21: 1.5 | C21: 1.2 | D21: 3 | E21: =D21+C21+B21 -> 5.7 | F21: =($B$21*$B$31+$C$21*$C$31+$D$21*$D$31) -> 1.2312
A22: Animales cebo 150-230 Kg | B22: 1.5 | C22: 1.2 | D22: 3 | E22: =D22+C22+B22 -> 5.7 | F22: =($B$22*$B$31+$C$22*$C$31+$D$22*$D$31) -> 1.2312
A23: Animales cebo 231-400 Kg | B23: 3 | C23: 1 | D23: 7 | E23: =D23+C23+B23 -> 11 | F23: =($B$23*$B$31+$C$23*$C$31+$D$23*$D$31) -> 1.966
A24: Animales cebo >400 Kg | B24: 8 | C24: 9 | D24: 0 | E24: =D24+C24+B24 -> 17 | F24: =($B$24*$B$31+$C$24*$C$31+$D$24*$D$31) -> 6.074
A25: Madres repro, gestantes y toros | B25: 2 | C25: 3 | D25: 6.55 | E25: =D25+C25+B25 -> 11.55 | F25: =($B$25*$B$31+$C$25*$C$31+$D$25*$D$31) -> 2.493 | H25: 10 | I25: =(H25*$H$31) -> 0.8 | J25: 0
A26: Madres con ternero lactando | B26: 2 | C26: 2.7 | D26: 6.92 | E26: =D26+C26+B26 -> 11.62 | F26: =($B$26*$B$31+$C$26*$C$31+$D$26*$D$31) -> 2.4022 | H26: 10 | I26: =(H26*$H$31) -> 0.8 | J26: 0
A27: Lactantes bajo madre | L27: 0.5 | M27: =L27*L31 -> 0.275
A29: Precios alimento
A30: Eur/Kg | B30: 0.26 | C30: 0.39 | D30: =0.059 -> 0.059 | E30: =D30+C30+B30 -> 0.709
A31: Eur/Kg con transporte | B31: =B30+0.02 -> 0.28 | C31: =C30+(900/25000) -> 0.426 | D31: =D30+0.041 -> 0.1 | E31: =D31+C31+B31 -> 0.806 | H31: 0.08 | L31: 0.55
A33: Consumo mensual Eur
A34: Animales cebo 80-150 Kg | C34: =C3*$F$21*30 -> 2733.264 | D34: =D3*$F$21*30 -> 2733.264 | E34: =E3*$F$21*30 -> 2733.264 | F34: =F3*$F$21*30 -> 2733.264 | G34: =G3*$F$21*30 -> 2733.264 | H34: =H3*$F$21*30 -> 36.936 | I34: =I3*$F$21*30 -> 36.936 | J34: =J3*$F$21*30 -> 36.936 | ... AB34: =AB3*$F$21*30 -> 0
A35: Animales cebo 150-230 Kg | C35: =C5*$F$22*30 -> 2696.328 | D35: =D5*$F$22*30 -> 2696.328 | E35: =E5*$F$22*30 -> 443.232 | F35: =F5*$F$22*30 -> 443.232 | G35: =G5*$F$22*30 -> 443.232 | H35: =H5*$F$22*30 -> 0 | I35: =I5*$F$22*30 -> 0 | J35: =J5*$F$22*30 -> 0 | ... AB35: =AB5*$F$22*30 -> 0
A36: Animales cebo 231-400 Kg | C36: =C7*$F$23*30 -> 3125.94 | D36: =D7*$F$23*30 -> 3125.94 | E36: =E7*$F$23*30 -> 3125.94 | F36: =F7*$F$23*30 -> 0 | G36: =G7*$F$23*30 -> 0 | H36: =H7*$F$23*30 -> 0 | I36: =I7*$F$23*30 -> 0 | J36: =J7*$F$23*30 -> 0 | ... AB36: =AB7*$F$23*30 -> 0
A37: Animales cebo >400 Kg | C37: =C9*$F$24*30 -> 1639.98 | D37: =D9*$F$24*30 -> 1639.98 | E37: =E9*$F$24*30 -> 1639.98 | F37: =F9*$F$24*30 -> 1639.98 | G37: =G9*$F$24*30 -> 1639.98 | H37: =H9*$F$24*30 -> 1639.98 | I37: =I9*$F$24*30 -> 182.22 | J37: =J9*$F$24*30 -> 182.22 | ... AB37: =AB9*$F$24*30 -> 182.22
A38: Madres repro y sementales | C38: =C11*$F$25*30 -> 4113.45 | D38: =D11*$F$25*30 -> 4113.45 | E38: =E11*$F$25*30 -> 6057.99 | F38: =F11*$F$25*30 -> 6057.99 | G38: =G11*$F$25*30 -> 6057.99 | H38: =H11*$F$25*30*0 -> 0 | I38: =I11*$F$25*30*0 -> 0 | J38: =J11*$F$25*30*0 -> 0 | K38: =K11*$F$25*30*0 -> 0 | L38: =L11*$F$25*30*0 -> 0 | M38: =M11*$I$25*30 -> 1944 | N38: =N11*$I$25*30 -> 1944 | O38: =O11*$I$25*30 -> 1944 | P38: =P11*$I$25*30 -> 1944 | Q38: =Q11*$I$25*30 -> 1944 | R38: =R11*$I$25*30 -> 1944 | S38: =S11*$I$25*30 -> 1944 | T38: =T11*$F$25*30*0 -> 0 | U38: =U11*$F$25*30*0 -> 0 | V38: =V11*$F$25*30*0 -> 0 | W38: =W11*$F$25*30*0 -> 0 | X38: =X11*$F$25*30*0 -> 0 | Y38: =Y11*$F$25*30*0 -> 0 | Z38: =Z11*$F$25*30*0 -> 0 | AA38: =AA11*$F$25*30*0 -> 0 | AB38: =AB11*$F$25*30*0 -> 0
A39: Madres gestantes | C39: =C13*$F$26*30 -> 7494.864 | D39: =D13*$F$26*30 -> 7494.864 | E39: =E13*$F$26*30 -> 7494.864 | F39: =F13*$F$26*30 -> 7494.864 | G39: =G13*$F$26*30 -> 7494.864 | H39: =H13*$F$26*30*0 -> 0 | I39: =I13*$F$26*30*0 -> 0 | J39: =J13*$F$26*30*0 -> 0 | K39: =K13*$F$26*30*0 -> 0 | L39: =L13*$F$26*30*0 -> 0 | M39: =M13*$I$26*30 -> 2496 | N39: =N13*$I$26*30 -> 2496 | O39: =O13*$I$26*30 -> 2496 | P39: =P13*$I$26*30 -> 2496 | Q39: =Q13*$I$26*30 -> 2496 | R39: =R13*$I$26*30 -> 2496 | S39: =S13*$I$26*30 -> 2496 | T39: =T13*$F$26*30*0 -> 0 | U39: =U13*$F$26*30*0 -> 0 | V39: =V13*$F$26*30*0 -> 0 | W39: =W13*$F$26*30*0 -> 0 | X39: =X13*$F$26*30*0 -> 0 | Y39: =Y13*$F$26*30*0 -> 0 | Z39: =Z13*$F$26*30*0 -> 0 | AA39: =AA13*$F$26*30*0 -> 0 | AB39: =AB13*$F$26*30*0 -> 0
A40: Lactantes | C40: =C15*$M$27*30*0 -> 0 | D40: =D15*$M$27*30 -> 247.5 | E40: =E15*$M$27*30 -> 321.75 | F40: =F15*$M$27*30 -> 511.5 | G40: =G15*$M$27*30 -> 437.25 | H40: =H15*$M$27*30 -> 437.25 | I40: =I15*$M$27*30 -> 396 | J40: =J15*$M$27*30 -> 437.25 | K40: =K15*$M$27*30 -> 437.25 | ... AB40: =AB15*$M$27*30 -> 437.25
C41: =SUM(C34:C39) -> 21803.826 | D41: =SUM(D34:D39) -> 21803.826 | E41: =SUM(E34:E39) -> 21495.27 | F41: =SUM(F34:F39) -> 18369.33 | G41: =SUM(G34:G39) -> 18369.33 | H41: =SUM(H34:H39) -> 1676.916 | I41: =SUM(I34:I39) -> 219.156 | J41: =SUM(J34:J39) -> 219.156 | ... AB41: =SUM(AB34:AB39) -> 182.22
A43: PORCINO | J43: parto y lactancia (camping ocupados)
A44: Existencias, entradas y salidas | B44: Ei
A45: Primales cebo campo II | B45: 0 | C45: =B45 -> 0 | D45: =C45 -> 0 | E45: =D45 -> 0 | F45: =E45 -> 0 | G45: =F45 -> 0 | H45: =G45 -> 0 | I45: =H45 -> 0 | J45: =I45 -> 0 | ... R45: =Q45 -> 0 | S45: =R45+60 -> 60 | T45: =S45+60 -> 120 | U45: =T45 -> 120 | V45: =U45 -> 120 | W45: =V45 -> 120 | X45: =W45 -> 120 | Y45: =X45+60 -> 180 | Z45: =Y45+60 -> 240 | AA45: =Z45-120 -> 120 | AB45: =AA45 -> 120
A46: Marranos cebo campo II | B46: 0 | C46: =B46 -> 0 | D46: =C46 -> 0 | E46: =D46 -> 0 | F46: =E46 -> 0 | G46: =F46 -> 0 | H46: =G46 -> 0 | I46: =H46 -> 0 | J46: =I46 -> 0 | ... M46: =L46 -> 0 | N46: =60 -> 60 | O46: =N46+60 -> 120 | P46: =O46 -> 120 | Q46: =P46 -> 120 | R46: =Q46 -> 120 | S46: =R46-60 -> 60 | T46: =S46-60+60 -> 60 | U46: =T46+60 -> 120 | V46: =U46 -> 120 | W46: =V46 -> 120 | X46: =W46 -> 120 | Y46: =X46-60 -> 60 | Z46: =Y46-60+60 -> 60 | AA46: =Z46+60 -> 120 | AB46: =AA46 -> 120
A47: Pnimales cebo campo | B47: 0 | C47: =B47 -> 0 | D47: =C47 -> 0 | E47: =D47 -> 0 | F47: =E47 -> 0 | G47: =F47 -> 0 | H47: =G47 -> 0 | I47: =H47 -> 0 | J47: =I47+60 -> 60 | K47: =J47+60 -> 120 | L47: =K47 -> 120 | M47: =L47 -> 120 | N47: =M47 -> 120 | O47: =N47 -> 120 | P47: =O47 -> 120 | Q47: =P47-120 -> 0 | R47: =Q47 -> 0 | S47: =R47 -> 0 | T47: =S47 -> 0 | U47: =T47+60 -> 60 | V47: =U47+60 -> 120 | W47: =V47 -> 120 | X47: =W47 -> 120 | Y47: =X47 -> 120 | Z47: =Y47 -> 120 | AA47: =Z47 -> 120 | AB47: =AA47-120 -> 0
A48: Marrano cebo campo | B48: 0 | C48: =B48 -> 0 | D48: =C48 -> 0 | E48: =D48+60 -> 60 | F48: =E48+60 -> 120 | G48: =F48 -> 120 | H48: =G48 -> 120 | I48: =H48 -> 120 | J48: =I48-60 -> 60 | K48: =J48-60 -> 0 | L48: =K48 -> 0 | M48: =L48 -> 0 | N48: =M48 -> 0 | O48: =N48 -> 0 | P48: =O48+60 -> 60 | Q48: =P48+60 -> 120 | R48: =Q48 -> 120 | S48: =R48 -> 120 | T48: =S48 -> 120 | U48: =T48-60 -> 60 | V48: =U48-60 -> 0 | W48: =V48 -> 0 | X48: =W48 -> 0 | Y48: =X48 -> 0 | Z48: =Y48 -> 0 | AA48: =Z48+60 -> 60 | AB48: =AA48+60 -> 120
A49: Marranos bellota | B49: 120 | C49: =B49 -> 120 | D49: =C49-120 -> 0 | E49: =D49 -> 0 | F49: =E49 -> 0 | G49: =F49 -> 0 | H49: =G49 -> 0 | I49: =H49 -> 0 | J49: =I49 -> 0 | K49: =J49+60 -> 60 | L49: =K49+60 -> 120 | M49: =L49 -> 120 | N49: =M49 -> 120 | O49: =N49 -> 120 | P49: =O49-120 -> 0 | Q49: =P49 -> 0 | R49: =Q49 -> 0 | S49: =R49 -> 0 | T49: =S49 -> 0 | U49: =T49 -> 0 | V49: =U49 -> 0 | W49: =V49+60 -> 60 | X49: =W49+60 -> 120 | Y49: =X49 -> 120 | Z49: =Y49 -> 120 | AA49: =Z49 -> 120 | AB49: =AA49-120 -> 0
A50: Primales bellota | B50: 98 | C50: =B50 -> 98 | D50: =C50+120-98 -> 120 | E50: =D50 -> 120 | F50: =E50 -> 120 | G50: =F50 -> 120 | H50: =G50 -> 120 | I50: =H50 -> 120 | J50: =I50 -> 120 | K50: =J50 -> 120 | L50: =K50 -> 120 | ... O50: =N50 -> 120 | P50: =O50+120-120 -> 120 | Q50: =P50 -> 120 | R50: =Q50 -> 120 | S50: =R50 -> 120 | T50: =S50 -> 120 | U50: =T50 -> 120 | V50: =U50 -> 120 | W50: =V50 -> 120 | X50: =W50 -> 120 | ... AA50: =Z50 -> 120 | AB50: =AA50+120-120 -> 120
A51: Montanera | B51: 0 | C51: =B51 -> 0 | D51: =98 -> 98 | E51: =D51 -> 98 | F51: =E51 -> 98 | G51: =F51 -> 98 | H51: =G51-98 -> 0 | I51: =H51 -> 0 | J51: =I51 -> 0 | K51: =J51 -> 0 | L51: =K51 -> 0 | M51: =L51 -> 0 | N51: =M51 -> 0 | O51: =N51 -> 0 | P51: =O51+120 -> 120 | Q51: =P51 -> 120 | R51: =Q51 -> 120 | S51: =R51 -> 120 | T51: =S51-120 -> 0 | U51: =T51 -> 0 | V51: =U51 -> 0 | W51: =V51 -> 0 | X51: =W51 -> 0 | Y51: =X51 -> 0 | Z51: =Y51 -> 0 | AA51: =Z51 -> 0 | AB51: =AA51+120 -> 120
A52: Montanera reposición | B52: 0 | C52: =B52 -> 0 | D52: 75 | E52: =D52 -> 75 | F52: =E52 -> 75 | G52: =F52 -> 75 | H52: =G52-75 -> 0 | I52: =H52 -> 0 | J52: =I52 -> 0 | K52: =J52 -> 0 | L52: =K52 -> 0 | M52: =L52 -> 0 | N52: =M52 -> 0 | O52: =N52 -> 0 | P52: =O52+125 -> 125 | Q52: =P52 -> 125 | R52: =Q52 -> 125 | S52: =R52 -> 125 | T52: =S52-125 -> 0 | U52: =T52 -> 0 | V52: =U52 -> 0 | W52: =V52 -> 0 | X52: =W52 -> 0 | Y52: =X52 -> 0 | Z52: =Y52 -> 0 | AA52: =Z52 -> 0 | AB52: =AA52+125 -> 125
A53: Madres y Verracos (22+2) | B53: 24 | C53: =B53 -> 24 | D53: =C53 -> 24 | E53: =D53 -> 24 | F53: =E53 -> 24 | G53: =F53 -> 24 | H53: =G53+15 -> 39 | I53: =H53 -> 39 | J53: =I53 -> 39 | K53: =J53 -> 39 | L53: =K53 -> 39 | M53: =L53 -> 39 | N53: =M53 -> 39 | O53: =N53 -> 39 | P53: =O53 -> 39 | ... AB53: =AA53 -> 39
A54: Ventas de cochinos | J54: =14*40*G51+4*40*G52 -> 66880 | R54: =14*27.5*P47 -> 46200 | V54: =14*40*S51+4*40*S52 -> 87200 | AB54: =14*27.5*AA45 -> 46200
A56: Receta actual | B56: Cebada | C56: DDG | D56: Paja | E56: Mezcla | F56: Receta sep23 | H56: Siembra/pasto | I56: Siembra | J56: Pasto | L56: Harina engorde | M56: Harina engorde
A57: Consumos/costes unitarios | B57: Kg/dia | C57: Kg/dia | D57: Kg/dia | E57: Kg/dia | F57: €/dia/animal | H57: Kg/dia | I57: €/dia/animal | J57: €/dia/animal | L57: Kg/dia | M57: €/dia/animal
A58: Lechones cebo campo | B58: =80/130 -> 0.61538462 | C58: 0 | D58: 0 | E58: =D58+C58+B58 -> 0.61538462 | F58: =($B$58*$B$69+$C$58*$C$69+$D$58*$D$32) -> 0.17230769 | S58: a los 40 dias | U58: Primal | V58: Montanera
A59: Primales cebo campo | B59: 1.17 | F59: =($B$59*$B$69+$C$59*$C$69+$D$59*$D$32) -> 0.3276 | P59: lechones montanera 24 | R59: 130 | S59: 0,5 kg | T59: 0.62 | U59: 2 | V59: 0,00-0,7
A60: Lechones cebo campo II | B60: =B58 -> 0.61538462 | C60: 0 | D60: 0 | E60: =D60+C60+B60 -> 0.61538462 | F60: =($B$60*$B$69+$C$60*$C$69+$D$60*$D$32) -> 0.17230769 | P60: Primales montanera 23 | R60: 98
A61: Primales cebo campo II | B61: =B59 -> 1.17 | F61: =($B$61*$B$69+$C$61*$C$69+$D$61*$D$32) -> 0.3276 | P61: Madres y Verraco | R61: =20+2 -> 22
A62: Lechones bellota | B62: =B58 -> 0.61538462 | C62: 0 | D62: 0 | E62: =D62+C62+B62 -> 0.61538462 | F62: =($B$62*$B$69+$C$62*$C$69+$D$62*$D$32) -> 0.17230769
A63: Primales bellota | B63: =B59 -> 1.17 | F63: =($B$63*$B$69+$C$63*$C$69+$D$63*$D$32) -> 0.3276
A64: Montanera reposición | B64: 0 | C64: 0 | D64: 0 | E64: =D64+C64+B64 -> 0 | F64: =($B$64*$B$69+$C$64*$C$69+$D$64*$D$32) -> 0 | L64: 0.5 | M64: =L64*L69 -> 0.22382143
A65: Madres y Verracos (22+2) | B65: 1 | C65: 0 | D65: 0 | E65: =D65+C65+B65 -> 1 | F65: =($B$65*$B$69+$C$65*$C$69+$D$65*$D$32) -> 0.28
A67: Precios alimento
A68: Eur/Kg | B68: 0.26 | C68: 0.39 | D68: =0.059 -> 0.059 | E68: =D68+C68+B68 -> 0.709 | L68: =5667/14000 -> 0.40478571 | R68: =1260*2+120*3 -> 2880 | S68: =R68/0.845 -> 3408.284
A69: Eur/Kg con transporte | B69: =B68+0.02 -> 0.28 | C69: =C68+(900/25000) -> 0.426 | D69: =D68+0.041 -> 0.1 | E69: =D69+C69+B69 -> 0.806 | L69: =L68+600/14000 -> 0.44764286
A71: Consumo mensual Eur
A72: Animales cebo campo | C72: =C45*$F$58*30 -> 0 | D72: =D45*$F$59*30 -> 0 | E72: =E45*$F$59*30 -> 0 | F72: =F45*$F$59*30 -> 0 | G72: =G45*$F$59*30 -> 0 | H72: =H45*$F$59*30 -> 0 | I72: =I45*$F$59*30 -> 0 | J72: =J45*$F$59*30 -> 0 | K72: =K45*$F$59*30 -> 0 | ... AB72: =AB45*$F$59*30 -> 1179.36
A73: Animales cebo campo II | C73: =#REF!*$F$60*30 -> #REF! | D73: =#REF!*$F$60*30 -> #REF! | E73: =#REF!*$F$60*30 -> #REF! | F73: =#REF!*$F$60*30 -> #REF! | G73: =#REF!*$F$60*30 -> #REF! | H73: =#REF!*$F$60*30 -> #REF! | I73: =#REF!*$F$60*30 -> #REF! | J73: =#REF!*$F$60*30 -> #REF! | ... M73: =#REF!*$F$60*30 -> #REF! | N73: =#REF!*$F$61*30 -> #REF! | O73: =#REF!*$F$61*30 -> #REF! | P73: =#REF!*$F$61*30 -> #REF! | Q73: =#REF!*$F$61*30 -> #REF! | R73: =#REF!*$F$61*30 -> #REF! | S73: =#REF!*$F$61*30 -> #REF! | T73: =#REF!*$F$61*30 -> #REF! | U73: =#REF!*$F$61*30 -> #REF! | ... AB73: =#REF!*$F$61*30 -> #REF!
A74: Lechones bellota | C74: =C49*$F$62*30 -> 620.30769 | D74: =D49*$F$62*30 -> 0 | E74: =E49*$F$62*30 -> 0 | F74: =F49*$F$62*30 -> 0 | G74: =G49*$F$62*30 -> 0 | H74: =H49*$F$62*30 -> 0 | I74: =I49*$F$62*30 -> 0 | J74: =J49*$F$62*30 -> 0 | ... AB74: =AB49*$F$62*30 -> 0
A75: Primales bellota | C75: =C50*$F$63*30 -> 963.144 | D75: =D50*$F$63*30 -> 1179.36 | E75: =E50*$F$63*30 -> 1179.36 | F75: =F50*$F$63*30 -> 1179.36 | G75: =G50*$F$63*30 -> 1179.36 | H75: =H50*$F$63*30 -> 1179.36 | I75: =I50*$F$63*30 -> 1179.36 | J75: =J50*$F$63*30 -> 1179.36 | ... AB75: =AB50*$F$63*30 -> 1179.36
A76: Montanera reposición | C76: =C52*$M$64*30 -> 0 | D76: =D52*$M$64*30 -> 503.59821 | E76: =E52*$M$64*30 -> 503.59821 | F76: =F52*$M$64*30 -> 503.59821 | G76: =G52*$M$64*30 -> 503.59821 | H76: =H52*$M$64*30 -> 0 | I76: =I52*$M$64*30 -> 0 | J76: =J52*$M$64*30 -> 0 | ... AB76: =AB52*$M$64*30 -> 839.33036
A77: Madres y Verracos (22+2) | C77: =C53*$F$65*30 -> 201.6 | D77: =D53*$F$65*30 -> 201.6 | E77: =E53*$F$65*30 -> 201.6 | F77: =F53*$F$65*30 -> 201.6 | G77: =G53*$F$65*30 -> 201.6 | H77: =H53*$F$65*30 -> 327.6 | I77: =I53*$F$65*30 -> 327.6 | J77: =J53*$F$65*30 -> 327.6 | ... AB77: =AB53*$F$65*30 -> 327.6
C78: =SUM(C72:C77) -> #REF! | D78: =SUM(D72:D77) -> #REF! | E78: =SUM(E72:E77) -> #REF! | F78: =SUM(F72:F77) -> #REF! | G78: =SUM(G72:G77) -> #REF! | H78: =SUM(H72:H77) -> #REF! | I78: =SUM(I72:I77) -> #REF! | J78: =SUM(J72:J77) -> #REF! | ... AB78: =SUM(AB72:AB77) -> #REF!
A81: Almacen Cebada vacas
A82: Existencias iniciales Kg | B82: 20000
