Workbook

Sheet P&L
B2: Sales | F2: =F26 -> 136700 | H2: Expenses | J2: =SUM(J4,J17,J21) -> 22119.098 | L2: Profit | M2: =F2-J2 -> 114580.9
D4: Dropet | F4: NixAl | H4: Trips | J4: =SUM(J12,J5) -> 10545 | L4: Goal | M4: 130000
B5: Client | C5: Price | D5: % | E5: Eur | H5: Conferences | J5: =SUM(J6:J10) -> 6065 | L5: % vs. Goal | M5: =M2/M4 -> 0.88139155
B6: Bioagra | C6: 35000 | D6: 0.5 | E6: =C6*D6 -> 17500 | F6: =C6-E6 -> 17500 | H6: February RFA - US | J6: =850+500+500 -> 1850 | L6: Eur vs. Goal | M6: =M2-M4 -> -15419.098
B7: Verbio | C7: 15000 | D7: 0.3 | E7: =C7*D7 -> 4500 | F7: =C7-E7 -> 10500 | H7: May Dropet conference | J7: 500 | L7: Potencial | M7: =F29+F46 -> 164121.95
B8: Alco | C8: 15000 | D8: 0.3 | E8: =C8*D8 -> 4500 | F8: =C8-E8 -> 10500 | H8: May Sugar Week - US | J8: =850+500+500 -> 1850
B9: Vertex | C9: 30000 | D9: 0 | E9: =C9*D9 -> 0 | F9: =C9-E9 -> 30000 | H9: Oct Argus Bios - LDN | J9: =250+50+215 -> 515
B10: Mabanaft | C10: 5000 | D10: 0.3 | E10: =C10*D10 -> 1500 | F10: =C10-E10 -> 3500 | H10: Nov FO Licht - Brussel | J10: =550+550+250 -> 1350
B11: Vertex Ad Hoc | C11: 15000 | D11: 0 | E11: =C11*D11 -> 0 | F11: =C11-E11 -> 15000
B12: Shell | C12: 5000 | D12: 0.3 | E12: =C12*D12 -> 1500 | F12: =C12-E12 -> 3500 | H12: Others | J12: =SUM(J13:J14) -> 4480
B13: Neste | C13: 7500 | D13: 0.3 | E13: =C13*D13 -> 2250 | F13: =C13-E13 -> 5250 | H13: Madrid x 6 | J13: =(130+100+100)*6 -> 1980
B14: Enviral | C14: 18500 | D14: 0.3 | E14: =C14*D14 -> 5550 | F14: =C14-E14 -> 12950 | H14: Europe summer | J14: 2500
B15: Cramer | C15: 15000 | D15: 0.3 | E15: =C15*D15 -> 4500 | F15: =C15-E15 -> 10500
B16: Repsol | C16: 15000 | D16: 0.3 | E16: =C16*D16 -> 4500 | F16: =C16-E16 -> 10500
B17: Raizen | C17: 0 | H17: Personnel | J17: =SUM(J18:J19) -> 3300
B18: P66 | H18: Jesus López López | J18: =15000*0+(200*12) -> 2400
B19: Sucden | C19: 15000 | H19: Felipe Fontes | J19: =75*12 -> 900
B20: Ruhr | C20: 10000 | D20: 0.3 | E20: =C20*D20 -> 3000 | F20: =C20-E20 -> 7000
B21: AdBio | C21: 0 | D21: 0.3 | E21: =C21*D21 -> 0 | F21: =C21-E21 -> 0 | H21: Services | J21: =SUM(J22:J25) -> 8274.0984
B22: Sao Martinho | H22: Fiscal, HR, Accounting (Creativa) | J22: =85*12 -> 1020
B23: Kurana | H23: Legal | J23: 1000
B24: Totsa | C24: 15000 | H24: ICE | J24: =280*12/1.22 -> 2754.0984
B25: Roquette | C25: 15000 | D25: 0.3 | H25: Opis | J25: 3500
B26: Total | C26: =SUM(C6:C25) -> 231000 | E26: =SUM(E6:E25) -> 49300 | F26: =SUM(F6:F25) -> 136700
B29: Proposals | C29: =SUM(C30:C42) -> 80121.951 | E29: =SUM(E30:E42) -> 22500 | F29: =SUM(F30:F42) -> 57621.951
B30: Cepsa | C30: 0 | D30: 0 | E30: =C30*D30 -> 0 | F30: =C30-E30 -> 0
B31: Cramer | C31: 15000 | D31: 0.3 | E31: =C31*D31 -> 4500 | F31: =C31-E31 -> 10500
B32: Sucden | C32: 15000 | D32: 0.3 | E32: =C32*D32 -> 4500 | F32: =C32-E32 -> 10500
B33: Ruhr | D33: 0.3 | E33: =C33*D33 -> 0 | F33: =C33-E33 -> 0
B34: Snetor | C34: 0 | D34: 0.3 | E34: =C34*D34 -> 0 | F34: =C34-E34 -> 0
B35: Envien | C35: 15000 | D35: 0.3 | E35: =C35*D35 -> 4500 | F35: =C35-E35 -> 10500
B36: Varo | C36: 0 | D36: 0.3 | E36: =C36*D36 -> 0 | F36: =C36-E36 -> 0
B37: Totsa | C37: 15000 | D37: 0.3 | E37: =C37*D37 -> 4500 | F37: =C37-E37 -> 10500
D38: 0.3 | E38: =C38*D38 -> 0 | F38: =C38-E38 -> 0
B39: Repsol | C39: 15000 | D39: 0.3 | E39: =C39*D39 -> 4500 | F39: =C39-E39 -> 10500
B40: Kurana | C40: 0 | D40: 0.3 | E40: =C40*D40 -> 0 | F40: =C40-E40 -> 0
B41: Matt Sneyder | C41: =6300/1.23 -> 5121.9512 | D41: 0 | E41: =C41*D41 -> 0 | F41: =C41-E41 -> 5121.9512
B42: Crop | C42: 0 | D42: 0 | E42: =C42*D42 -> 0 | F42: =C42-E42 -> 0
B44: Sales & Proposals | C44: =SUM(C26,C29) -> 311121.95 | E44: =SUM(E26,E29) -> 71800 | F44: =SUM(F26,F29) -> 194321.95
B46: Prospects | C46: =SUM(C47:C56) -> 120000 | E46: =SUM(E47:E56) -> 13500 | F46: =SUM(F47:F56) -> 106500
B47: Marquis | C47: 15000 | D47: 0 | E47: =C47*D47 -> 0 | F47: =C47-E47 -> 15000
B48: GreenPlains | C48: 15000 | D48: 0 | E48: =C48*D48 -> 0 | F48: =C48-E48 -> 15000
B49: Biosev | C49: 15000 | D49: 0 | E49: =C49*D49 -> 0 | F49: =C49-E49 -> 15000
B50: Sao Martinho | C50: 15000 | D50: 0 | E50: =C50*D50 -> 0 | F50: =C50-E50 -> 15000
B51: Neste | C51: 15000 | D51: 0.3 | E51: =C51*D51 -> 4500 | F51: =C51-E51 -> 10500
B52: Agroetanol | C52: 15000 | D52: 0.3 | E52: =C52*D52 -> 4500 | F52: =C52-E52 -> 10500
B53: Mercuria | C53: 15000 | D53: 0.3 | E53: =C53*D53 -> 4500 | F53: =C53-E53 -> 10500
B54: Adecoagro | C54: 15000 | D54: 0 | E54: =C54*D54 -> 0 | F54: =C54-E54 -> 15000
B55: SCA
B57: Sales & Proposals & Prospects | C57: =C44+C46 -> 431121.95 | E57: =E44+E46 -> 85300 | F57: =F44+F46 -> 300821.95
B59: Potential clients
B60: Brasil
B61: Cerradinho | C61: Van a construir una planta de corn en Brasil
B62: FS Bioenergia | C62: Tienen planta de corn de 60 MG y estan ampliando hasta 140 MG - Paulo Truco
B63: Bioagencia
B64: Coper
B65: Ipiranga
B66: Alesate - Fernando Hayoshi
B67: Alta Mogiana (Luis Antonio)
B68: Colombo?
B69: Unica
B70: Bunge
B71: Raizen
B72: Guaraní/Tereos
B73: Nobel do Brazil (Mauricio Sacramento)
B75: US
B76: CCI
B77: Mitsubishi | C77: Pdte call con Zach
B78: CHS
B79: POET
B80: Kappa
B81: The Andersons
B82: Valero
B83: Vopack
B84: Lukoil
B86: EU
B87: Gunvor | C87: Almudena con paciencia
B88: Vitol | C88: Almudena con paciencia
B89: Vivergo | C89: Les ponemos en trial en Abril para cerrar en mayo
B90: Cristalco | C90: Almudena va a verles
B91: Tereos | C91: Almudena va a verles
B92: Agroetanol | C92: Almudena está enviando reports
B93: Motoroil grupo HELAS - Griegos | C93: Me tiene que pasar contacto Almudena
B94: Mitsui
B95: P66 | C95: IP week Almudena
B96: ePure
B97: Ecofuel | C97: michaela.cappannelli@ecofuel.eni.com | F97: Milan, trader, +390252056164)
B98: Exxon | C98: katja.beitzen@exxonmobil.com | F98: Begium, Refining and supply, +3127222066
B99: GALP
B100: Prio
B101: MOH | C101: Los griegos - Almudena

Sheet Tesoreria
C2: 2018 | P2: 2019 | AC2: 2020 | AL2: 2020/2021 | AY2: 2021/2022 | BL2: 2022/2023 | BY2: 2023/2024 | CM2: 2024/2025 | CZ2: 2025/2026
B3: Previsiones Caja | C3: Ene | D3: Feb | E3: Mar | F3: Abr | G3: May | H3: Jun | I3: Jul | J3: Ago | K3: Sep | L3: Oct | M3: Nov | N3: Dic | O3: Totales | P3: Ene | Q3: Feb | R3: Mar | S3: Abr | T3: May | U3: Jun | V3: Jul | W3: Ago | X3: Sep | Y3: Oct | Z3: Nov | AA3: Dic | AB3: Totales | AC3: Ene | AD3: Feb | AE3: Mar | AF3: Abr | AG3: May | AH3: Jun | AI3: Jul | AJ3: Ago | AK3: Totales | AL3: Sep | AM3: Oct | AN3: Nov | AO3: Dic | AP3: Ene | AQ3: Feb | AR3: Mar | AS3: Abr | AT3: May | AU3: Jun | AV3: Jul | AW3: Ago | AX3: Totales | AY3: Sep | AZ3: Oct | BA3: Nov | BB3: Dic | BC3: Ene | BD3: Feb | BE3: Mar | BF3: Abr | BG3: May | BH3: Jun | BI3: Jul | BJ3: Ago | BK3: Totales | BL3: Sep | BM3: Oct | BN3: Nov | BO3: Dic | BP3: Ene | BQ3: Feb | BR3: Mar | BS3: Abr | BT3: May | BU3: Jun | BV3: Jul | BW3: Ago | BX3: Totales | BY3: Sep | BZ3: Oct | CA3: Nov | CB3: Dic | CC3: Ene | CD3: Feb | CE3: Mar | CF3: Abr | CG3: May | CH3: Jun | CI3: Jul | CJ3: Ago | CK3: Totales | CL3: Saco Ptes. | CM3: Sep | CN3: Oct | CO3: Nov | CP3: Dic | CQ3: Ene | CR3: Feb | CS3: Mar | CT3: Abr | CU3: May | CV3: Jun | CW3: Jul | CX3: Ago | CY3: Totales | CZ3: Sep | DA3: Oct | DB3: Nov | DC3: Dic | DD3: Ene | DE3: Feb | DF3: Mar | DG3: Abr | DH3: May | DI3: Jun | DJ3: Jul | DK3: Ago | DL3: Totales
B4: Cobros
B5: MKT INTELIGENCE | AK5: =SUM(AC5:AJ5) -> 0
B6: Alcodis | C6: 15000 | O6: =SUM(C6:N6) -> 15000 | Q6: 15000 | AB6: =SUM(P6:AA6) -> 15000 | AC6: 15000 | AK6: =SUM(AC6:AJ6) -> 15000 | AP6: 15000 | AX6: =SUM(AL6:AW6) -> 15000 | BC6: 15000 | BK6: =SUM(AY6:BJ6) -> 15000 | BR6: 15000 | BX6: =SUM(BL6:BW6) -> 15000 | CC6: 15000 | CK6: =SUM(BY6:CJ6) -> 15000 | CQ6: 15000 | CY6: =SUM(CM6:CX6) -> 15000 | DD6: 15000 | DL6: =SUM(CZ6:DK6) -> 15000
B7: Bioagra | D7: 35000 | O7: =SUM(C7:N7) -> 35000 | P7: 40000 | AB7: =SUM(P7:AA7) -> 40000 | AD7: 40000 | AK7: =SUM(AC7:AJ7) -> 40000 | AP7: 40000 | AX7: =SUM(AL7:AW7) -> 40000 | BE7: =40000+10000 -> 50000 | BK7: =SUM(AY7:BJ7) -> 50000 | BP7: =40000 -> 40000 | BX7: =SUM(BL7:BW7) -> 40000 | CC7: =41500 -> 41500 | CD7: =4200 -> 4200 | CK7: =SUM(BY7:CJ7) -> 45700 | CQ7: 41500 | CY7: =SUM(CM7:CX7) -> 41500 | DD7: 41500 | DL7: =SUM(CZ7:DK7) -> 41500
B8: Verbio | E8: 15000 | O8: =SUM(C8:N8) -> 15000 | V8: 9000 | AB8: =SUM(P8:AA8) -> 9000 | AE8: =9000+30000 -> 39000 | AK8: =SUM(AC8:AJ8) -> 39000 | AU8: =9000 -> 9000 | AV8: 30000 | AX8: =SUM(AL8:AW8) -> 39000 | BF8: =9000+30000 -> 39000 | BK8: =SUM(AY8:BJ8) -> 39000 | BQ8: 15000 | BX8: =SUM(BL8:BW8) -> 15000 | CF8: =15000+4300 -> 19300 | CK8: =SUM(BY8:CJ8) -> 19300 | CR8: 15000 | CY8: =SUM(CM8:CX8) -> 15000 | DE8: 15000 | DL8: =SUM(CZ8:DK8) -> 15000
B9: Vertex | E9: 0 | F9: 0 | G9: 0 | H9: 0 | O9: =SUM(C9:N9) -> 0 | Z9: =15000*1.21 -> 18150 | AB9: =SUM(P9:AA9) -> 18150 | AC9: 15000 | AK9: =SUM(AC9:AJ9) -> 15000 | AR9: =25000 -> 25000 | AX9: =SUM(AL9:AW9) -> 25000 | BA9: 25000 | BF9: =25000 -> 25000 | BK9: =SUM(AY9:BJ9) -> 50000 | BN9: =50000*0 -> 0 | BP9: =25000 -> 25000 | BS9: 25000 | BX9: =SUM(BL9:BW9) -> 50000 | CB9: 25000 | CF9: =4200+25000 -> 29200 | CK9: =SUM(BY9:CJ9) -> 54200 | CP9: 25000 | CT9: 25000 | CY9: =SUM(CM9:CX9) -> 50000 | DC9: 25000 | DG9: 25000 | DL9: =SUM(CZ9:DK9) -> 50000
B10: Shell | I10: 5000 | O10: =SUM(C10:N10) -> 5000 | V10: 4500 | AB10: =SUM(P10:AA10) -> 4500 | AG10: =4500 -> 4500 | AK10: =SUM(AC10:AJ10) -> 4500 | AP10: =4500 -> 4500 | AQ10: =4500 -> 4500 | AX10: =SUM(AL10:AW10) -> 9000 | AZ10: 4500 | BC10: 4500 | BK10: =SUM(AY10:BJ10) -> 9000 | BO10: 6000 | BS10: 6000 | BX10: =SUM(BL10:BW10) -> 12000 | BY10: 6000 | CB10: 6000 | CI10: 6000 | CK10: =SUM(BY10:CJ10) -> 18000 | CP10: 6000 | CW10: 6000 | CY10: =SUM(CM10:CX10) -> 12000 | DC10: 6000 | DJ10: 6000 | DL10: =SUM(CZ10:DK10) -> 12000
B11: Ruhr | J11: 10000 | O11: =SUM(C11:N11) -> 10000 | X11: 10000 | AB11: =SUM(P11:AA11) -> 10000 | AK11: =SUM(AC11:AJ11) -> 0 | AL11: 10000 | AX11: =SUM(AL11:AW11) -> 10000 | AZ11: 10000 | BK11: =SUM(AY11:BJ11) -> 10000 | BL11: 10000 | BW11: 10500 | BX11: =SUM(BL11:BW11) -> 20500 | CJ11: 10500 | CK11: =SUM(BY11:CJ11) -> 10500 | CX11: 10500 | CY11: =SUM(CM11:CX11) -> 10500 | DK11: 10500 | DL11: =SUM(CZ11:DK11) -> 10500
B12: Cremer | M12: 7500 | O12: =SUM(C12:N12) -> 7500 | U12: 7500 | Y12: 7500 | AB12: =SUM(P12:AA12) -> 15000 | AG12: 7500 | AK12: =SUM(AC12:AJ12) -> 7500 | AN12: 7500 | AR12: 7500 | AX12: =SUM(AL12:AW12) -> 15000 | BA12: 7500 | BF12: 7500 | BK12: =SUM(AY12:BJ12) -> 15000 | BO12: 7500 | BR12: 7500 | BX12: =SUM(BL12:BW12) -> 15000 | CK12: =SUM(BY12:CJ12) -> 0 | CY12: =SUM(CM12:CX12) -> 0 | DL12: =SUM(CZ12:DK12) -> 0
B13: Lantmannen | O13: =SUM(C13:N13) -> 0 | P13: 10000 | AB13: =SUM(P13:AA13) -> 10000 | AI13: 12500 | AK13: =SUM(AC13:AJ13) -> 12500 | AR13: 10000 | AX13: =SUM(AL13:AW13) -> 10000 | BE13: 10000 | BK13: =SUM(AY13:BJ13) -> 10000 | BR13: 12500 | BX13: =SUM(BL13:BW13) -> 12500 | CD13: 12000 | CK13: =SUM(BY13:CJ13) -> 12000 | CR13: 12000 | CY13: =SUM(CM13:CX13) -> 12000 | DE13: 12000 | DL13: =SUM(CZ13:DK13) -> 12000
B14: Neste | O14: =SUM(C14:N14) -> 0 | Q14: 6000 | V14: 6000 | AB14: =SUM(P14:AA14) -> 12000 | AD14: 6000 | AJ14: 6000 | AK14: =SUM(AC14:AJ14) -> 12000 | AQ14: 6000 | AX14: =SUM(AL14:AW14) -> 6000 | AY14: 6000 | BF14: 6000 | BJ14: 6000 | BK14: =SUM(AY14:BJ14) -> 18000 | BQ14: 6000 | BV14: 6000 | BX14: =SUM(BL14:BW14) -> 12000 | CK14: =SUM(BY14:CJ14) -> 0 | CY14: =SUM(CM14:CX14) -> 0 | DL14: =SUM(CZ14:DK14) -> 0
B15: Mabanaft | G15: 0 | H15: 5000 | O15: =SUM(C15:N15) -> 5000 | X15: =5000+5000 -> 10000 | AB15: =SUM(P15:AA15) -> 10000 | AD15: -5000 | AK15: =SUM(AC15:AJ15) -> -5000 | AX15: =SUM(AL15:AW15) -> 0 | BK15: =SUM(AY15:BJ15) -> 0 | BX15: =SUM(BL15:BW15) -> 0 | CK15: =SUM(BY15:CJ15) -> 0 | CY15: =SUM(CM15:CX15) -> 0 | DL15: =SUM(CZ15:DK15) -> 0
B16: Sucden | O16: =SUM(C16:N16) -> 0 | S16: 4500 | AB16: =SUM(P16:AA16) -> 4500 | AI16: 4500 | AK16: =SUM(AC16:AJ16) -> 4500 | AX16: =SUM(AL16:AW16) -> 0 | BB16: 10000 | BK16: =SUM(AY16:BJ16) -> 10000 | BX16: =SUM(BL16:BW16) -> 0 | BY16: =5285+5715 -> 11000 | CF16: 4200 | CK16: =SUM(BY16:CJ16) -> 15200 | CX16: 6000 | CY16: =SUM(CM16:CX16) -> 6000 | DK16: 6000 | DL16: =SUM(CZ16:DK16) -> 6000
B17: Roquette | O17: =SUM(C17:N17) -> 0 | Q17: 12500 | AB17: =SUM(P17:AA17) -> 12500 | AC17: =12500 -> 12500 | AK17: =SUM(AC17:AJ17) -> 12500 | AN17: =12500*0 -> 0 | AX17: =SUM(AL17:AW17) -> 0 | BK17: =SUM(AY17:BJ17) -> 0 | BX17: =SUM(BL17:BW17) -> 0 | CK17: =SUM(BY17:CJ17) -> 0 | CY17: =SUM(CM17:CX17) -> 0 | DL17: =SUM(CZ17:DK17) -> 0
B18: Greenergy | O18: =SUM(C18:N18) -> 0 | AB18: =SUM(P18:AA18) -> 0 | AF18: 12000 | AK18: =SUM(AC18:AJ18) -> 12000 | AU18: 12000 | AX18: =SUM(AL18:AW18) -> 12000 | BE18: 12000 | BK18: =SUM(AY18:BJ18) -> 12000 | BR18: 12000 | BX18: =SUM(BL18:BW18) -> 12000 | CD18: 13200 | CK18: =SUM(BY18:CJ18) -> 13200 | CR18: 13200 | CY18: =SUM(CM18:CX18) -> 13200 | DE18: 13200 | DL18: =SUM(CZ18:DK18) -> 13200
B19: Agrana | O19: =SUM(C19:N19) -> 0 | V19: 12500 | AB19: =SUM(P19:AA19) -> 12500 | AK19: =SUM(AC19:AJ19) -> 0 | AM19: 11500 | AW19: 12500 | AX19: =SUM(AL19:AW19) -> 24000 | BK19: =SUM(AY19:BJ19) -> 0 | BL19: 11500 | BV19: 12000 | BX19: =SUM(BL19:BV19) -> 23500 | CJ19: 12000 | CK19: =SUM(BY19:CJ19) -> 12000 | CX19: 12000 | CY19: =SUM(CM19:CX19) -> 12000 | DK19: 12000 | DL19: =SUM(CZ19:DK19) -> 12000
B20: SCA | O20: =SUM(C20:N20) -> 0 | T20: 7069.18 | AB20: =SUM(P20:AA20) -> 7069.18 | AI20: =4000/1.1608 -> 3445.8994 | AK20: =SUM(AC20:AJ20) -> 3445.8994 | AT20: =5000/1.2059 -> 4146.2808 | AX20: =SUM(AL20:AW20) -> 4146.2808 | BH20: =6000/1.0726 -> 5593.884 | BK20: =SUM(AY20:BJ20) -> 5593.884 | BS20: =6000/1.094 -> 5484.4607 | BX20: =SUM(BL20:BW20) -> 5484.4607 | CF20: =6000/1 -> 6000 | CK20: =SUM(BY20:CJ20) -> 6000 | CT20: 6000 | CY20: =SUM(CM20:CX20) -> 6000 | DG20: 6000 | DL20: =SUM(CZ20:DK20) -> 6000
B21: Raizen | O21: =SUM(C21:N21) -> 0 | AB21: =SUM(P21:AA21) -> 0 | AK21: =SUM(AC21:AJ21) -> 0 | AL21: 22000 | AV21: =22000/1.1767 -> 18696.354 | AX21: =SUM(AL21:AW21) -> 40696.354 | BF21: =22000/1.083 -> 20313.943 | BK21: =SUM(AY21:BJ21) -> 20313.943 | BR21: =22000/1.0875 -> 20229.885 | BX21: =SUM(BL21:BW21) -> 20229.885 | CF21: =22000/1 -> 22000 | CK21: =SUM(BY21:CJ21) -> 22000 | CS21: =22000/1 -> 22000 | CY21: =SUM(CM21:CX21) -> 22000 | DF21: =22000/1 -> 22000 | DL21: =SUM(CZ21:DK21) -> 22000
B22: Repsol | O22: =SUM(C22:N22) -> 0 | S22: =15000*1.21 -> 18150 | AB22: =SUM(P22:AA22) -> 18150 | AK22: =SUM(AC22:AJ22) -> 0 | AM22: =15000*1.21 -> 18150 | AT22: =15000*1.21 -> 18150 | AX22: =SUM(AL22:AW22) -> 36300 | BD22: =3750*1.21 -> 4537.5 | BH22: =15000*1.21 -> 18150 | BK22: =SUM(AY22:BJ22) -> 22687.5 | BS22: =16500*1.21 -> 19965 | BX22: =SUM(BL22:BW22) -> 19965 | CG22: =16900*1.21 -> 20449 | CK22: =SUM(BY22:CJ22) -> 20449 | CT22: 16500 | CY22: =SUM(CM22:CX22) -> 16500 | DG22: =16500 -> 16500 | DL22: =SUM(CZ22:DK22) -> 16500
B23: Amerra | O23: =SUM(C23:N23) -> 0 | W23: 10771.99 | AB23: =SUM(P23:AA23) -> 10771.99 | AG23: =9000/1.0792 -> 8339.5107 | AK23: =SUM(AC23:AJ23) -> 8339.5107 | AX23: =SUM(AL23:AW23) -> 0 | BK23: =SUM(AY23:BJ23) -> 0 | BX23: =SUM(BL23:BW23) -> 0 | CK23: =SUM(BY23:CJ23) -> 0 | CY23: =SUM(CM23:CX23) -> 0 | DL23: =SUM(CZ23:DK23) -> 0
B24: Amerra -RAA | AB24: =SUM(P24:AA24) -> 0 | AK24: =SUM(AC24:AJ24) -> 0 | AX24: =SUM(AL24:AW24) -> 0 | BI24: =15000/1.0005 -> 14992.504 | BK24: =SUM(AY24:BJ24) -> 14992.504 | BM24: =15000/1.0037 -> 14944.705 | BS24: =15000/1.0978 -> 13663.691 | BX24: =SUM(BL24:BW24) -> 28608.396 | CA24: =15000/1.0741 -> 13965.18 | CG24: =15000/1 -> 15000 | CK24: =SUM(BY24:CJ24) -> 28965.18 | CO24: =15000/1 -> 15000 | CT24: =15000/1 -> 15000 | CY24: =SUM(CM24:CX24) -> 30000 | DB24: =15000/1 -> 15000 | DG24: =15000/1 -> 15000 | DL24: =SUM(CZ24:DK24) -> 30000
B25: Amerra -SBA | AB25: =SUM(P25:AA25) -> 0 | AK25: =SUM(AC25:AJ25) -> 0 | AX25: =SUM(AL25:AW25) -> 0 | BI25: =5000/1.0425 -> 4796.1631 | BK25: =SUM(AY25:BJ25) -> 4796.1631 | BM25: =5000/0.986 -> 5070.9939 | BU25: =5000/1.0951 -> 4565.7931 | BX25: =SUM(BL25:BW25) -> 9636.787 | BZ25: =(5000-15)/1.053+15/1.0538 -> 4748.3273 | CG25: 5000 | CK25: =SUM(BY25:CJ25) -> 9748.3273 | CO25: 5000 | CT25: 5000 | CY25: =SUM(CM25:CX25) -> 10000 | DB25: 5000 | DG25: 5000 | DL25: =SUM(CZ25:DK25) -> 10000
B26: Varo | O26: =SUM(C26:N26) -> 0 | T26: 12500 | AB26: =SUM(P26:AA26) -> 12500 | AG26: 12500 | AK26: =SUM(AC26:AJ26) -> 12500 | AW26: 0 | AX26: =SUM(AL26:AW26) -> 0 | BK26: =SUM(AY26:BJ26) -> 0 | BX26: =SUM(BL26:BW26) -> 0 | CK26: =SUM(BY26:CJ26) -> 0 | CY26: =SUM(CM26:CX26) -> 0 | DL26: =SUM(CZ26:DK26) -> 0
B27: Enviral | M27: 18500 | O27: =SUM(C27:N27) -> 18500 | AB27: =SUM(P27:AA27) -> 0 | AG27: 18500 | AK27: =SUM(AC27:AJ27) -> 18500 | AN27: 18500 | AX27: =SUM(AL27:AW27) -> 18500 | BA27: 18500 | BK27: =SUM(AY27:BJ27) -> 18500 | BN27: 15000 | BX27: =SUM(BL27:BW27) -> 15000 | CA27: 15000 | CK27: =SUM(BY27:CJ27) -> 15000 | CN27: 15000 | CY27: =SUM(CM27:CX27) -> 15000 | DA27: 15000 | DL27: =SUM(CZ27:DK27) -> 15000
B28: Vivergo | O28: =SUM(C28:N28) -> 0 | V28: 12500 | AB28: =SUM(P28:AA28) -> 12500 | AJ28: 12500 | AK28: =SUM(AC28:AJ28) -> 12500 | AV28: 12500 | AX28: =SUM(AL28:AW28) -> 12500 | BK28: =SUM(AY28:BJ28) -> 0 | BL28: 12500 | BW28: 14000 | BX28: =SUM(BL28:BW28) -> 26500 | CI28: 14000 | CK28: =SUM(BY28:CJ28) -> 14000 | CW28: 14000 | CY28: =SUM(CM28:CX28) -> 14000 | DJ28: 14000 | DL28: =SUM(CZ28:DK28) -> 14000
B29: Neot | O29: =SUM(C29:N29) -> 0 | Y29: =500*12 -> 6000 | AB29: =SUM(P29:AA29) -> 6000 | AH29: 6000 | AK29: =SUM(AC29:AJ29) -> 6000 | AX29: =SUM(AL29:AW29) -> 0 | BA29: 8000 | BH29: 8000 | BK29: =SUM(AY29:BJ29) -> 16000 | BW29: 12000 | BX29: =SUM(BL29:BW29) -> 12000 | CI29: 12000 | CK29: =SUM(BY29:CJ29) -> 12000 | CW29: 12000 | CY29: =SUM(CM29:CX29) -> 12000 | DJ29: 12000 | DL29: =SUM(CZ29:DK29) -> 12000
B30: Panonnia | O30: =SUM(C30:N30) -> 0 | Y30: 10000 | AB30: =SUM(P30:AA30) -> 10000 | AK30: =SUM(AC30:AJ30) -> 0 | AN30: 12500 | AX30: =SUM(AL30:AW30) -> 12500 | BA30: 12500 | BK30: =SUM(AY30:BJ30) -> 12500 | BN30: 12500 | BX30: =SUM(BL30:BW30) -> 12500 | CB30: 12500 | CF30: =4200 -> 4200 | CK30: =SUM(BY30:CJ30) -> 16700 | CN30: 12500 | CY30: =SUM(CM30:CX30) -> 12500 | DA30: 12500 | DL30: =SUM(CZ30:DK30) -> 12500
B31: Marquis | O31: =SUM(C31:N31) -> 0 | AB31: =SUM(P31:AA31) -> 0 | AD31: =4570.32 -> 4570.32 | AK31: =SUM(AC31:AJ31) -> 4570.32 | AO31: =4109.32-1 -> 4108.32 | AX31: =SUM(AL31:AW31) -> 4108.32 | AZ31: =5041.8/1.1603+1933.2/1.1603 -> 6011.3764 | BK31: =SUM(AY31:BJ31) -> 6011.3764 | BR31: =9708.56/1.0586 -> 9171.1317 | BS31: =(10000-9708.56)/1.0972 -> 265.62158 | BX31: =SUM(BL31:BW31) -> 9436.7533 | BZ31: =10000/1.0569 -> 9461.6331 | CK31: =SUM(BY31:CJ31) -> 9461.6331 | CO31: 10000 | CY31: =SUM(CM31:CX31) -> 10000 | DB31: 10000 | DL31: =SUM(CZ31:DK31) -> 10000
B32: FC Betterave (Cristalco) | O32: =SUM(C32:N32) -> 0 | Y32: =12500*1.21 -> 15125 | AB32: =SUM(P32:AA32) -> 15125 | AK32: =SUM(AC32:AJ32) -> 0 | AM32: =12500*1.21 -> 15125 | AX32: =SUM(AL32:AW32) -> 15125 | AZ32: =12500*1.21 -> 15125 | BK32: =SUM(AY32:BJ32) -> 15125 | BN32: =12500*1.21 -> 15125 | BX32: =SUM(BL32:BW32) -> 15125 | CA32: =13000*1.21 -> 15730 | CK32: =SUM(BY32:CJ32) -> 15730 | CO32: 13000 | CY32: =SUM(CM32:CX32) -> 13000 | DB32: 13000 | DL32: =SUM(CZ32:DK32) -> 13000
B33: Redwood Group | O33: =SUM(C33:N33) -> 0 | AB33: =SUM(P33:AA33) -> 0 | AF33: 9074.41 | AI33: 4208.4 | AK33: =SUM(AC33:AJ33) -> 13282.81 | AT33: =5000/1.206+3000/1.206+3000/1.206 -> 9121.0614 | AW33: =3000/1.1736 -> 2556.2372 | AX33: =SUM(AL33:AW33) -> 11677.299 | BA33: =3000/1.1368 -> 2638.9866 | BF33: =3000/1.1052 -> 2714.4408 | BG33: =3000/1.0524 -> 2850.6271 | BI33: =3000/1.0124 -> 2963.2556 | BK33: =SUM(AY33:BJ33) -> 11167.31 | BM33: =3000/0.9778 -> 3068.1121 | BQ33: =3000/1.07 -> 2803.7383 | BS33: =3000/1.1002 -> 2726.7769 | BV33: =3000/1.1059 -> 2712.7227 | BX33: =SUM(BL33:BV33) -> 11311.35 | BZ33: =3000/1.0597 -> 2830.9899 | CK33: =SUM(BY33:CJ33) -> 2830.9899 | CY33: =SUM(CM33:CX33) -> 0 | DL33: =SUM(CZ33:DK33) -> 0
B34: Nordzucker AG | O34: =SUM(C34:N34) -> 0 | AB34: =SUM(P34:AA34) -> 0 | AF34: 5000 | AK34: =SUM(AC34:AJ34) -> 5000 | AP34: 5000 | AX34: =SUM(AL34:AW34) -> 5000 | BD34: 5000 | BK34: =SUM(AY34:BJ34) -> 5000 | BR34: 5000 | BX34: =SUM(BL34:BW34) -> 5000 | CD34: 5500 | CK34: =SUM(BY34:CJ34) -> 5500 | CR34: 5500 | CY34: =SUM(CM34:CX34) -> 5500 | DE34: 5500 | DL34: =SUM(CZ34:DK34) -> 5500
B35: Castleton Commodities Int. LLC | O35: =SUM(C35:N35) -> 0 | AB35: =SUM(P35:AA35) -> 0 | AH35: =8000/1.1285 -> 7089.0563 | AK35: =SUM(AC35:AJ35) -> 7089.0563 | AX35: =SUM(AL35:AW35) -> 0 | AZ35: =7987/1.16 -> 6885.3448 | BK35: =SUM(AZ35:BJ35) -> 6885.3448 | BX35: =SUM(BL35:BW35) -> 0 | CK35: =SUM(BY35:CJ35) -> 0 | CY35: =SUM(CM35:CX35) -> 0 | DL35: =SUM(CZ35:DK35) -> 0
B36: OCI FUELS B.V. | O36: =SUM(C36:N36) -> 0 | AB36: 0 | AI36: 22000 | AK36: =SUM(AC36:AJ36) -> 22000 | AX36: =SUM(AL36:AW36) -> 0 | BB36: 22000 | BJ36: 22000 | BK36: =SUM(BB36:BJ36) -> 44000 | BW36: 16500 | BX36: =SUM(BL36:BW36) -> 16500 | CI36: 16500 | CK36: =SUM(BY36:CJ36) -> 16500 | CW36: 16500 | CY36: =SUM(CM36:CX36) -> 16500 | DJ36: 16500 | DL36: =SUM(CZ36:DK36) -> 16500
B37: Poet | AB37: 0 | AK37: =SUM(AC37:AJ37) -> 0 | AP37: =(7000-33)/1.2166-27.87/1.224 -> 5703.8455 | AQ37: =21.87/1.224 -> 17.867647 | AX37: =SUM(AL37:AW37) -> 5721.7132 | BC37: =(7000-335.72)/1.116 -> 5971.5771 | BJ37: 0 | BK37: =SUM(AY37:BJ37) -> 5971.5771 | BP37: =11720.21/1.0903 -> 10749.528 | BQ37: =280/1.0988 -> 254.82344 | BX37: =SUM(BL37:BW37) -> 11004.351 | CF37: =15000/1 -> 15000 | CK37: =SUM(BY37:CJ37) -> 15000 | CQ37: =15000/1 -> 15000 | CY37: =SUM(CM37:CX37) -> 15000 | DD37: =15000/1 -> 15000 | DL37: =SUM(CZ37:DK37) -> 15000
B38: OMV | AB38: 0 | AK38: =SUM(AC38:AJ38) -> 0 | AW38: =7600+13000 -> 20600 | AX38: =SUM(AL38:AW38) -> 20600 | BK38: =SUM(AY38:BJ38) -> 0 | BR38: =15000+15000 -> 30000 | BX38: =SUM(BL38:BW38) -> 30000 | CK38: =SUM(BY38:CJ38) -> 0 | CS38: =15000+15000 -> 30000 | CY38: =SUM(CM38:CX38) -> 30000 | DL38: =SUM(CZ38:DK38) -> 0
B39: Totsa | AB39: 0 | AK39: =SUM(AC39:AJ39) -> 0 | AX39: =SUM(AL39:AW39) -> 0 | AY39: 24000 | BK39: =SUM(AY39:BJ39) -> 24000 | BN39: 24000 | BX39: =SUM(BL39:BW39) -> 24000 | BZ39: 36000 | CK39: =SUM(BZ39:CJ39) -> 36000 | CQ39: 24000 | CY39: =SUM(CM39:CX39) -> 24000 | DD39: 24000 | DL39: =SUM(CZ39:DK39) -> 24000
B40: Trafigura | AB40: 0 | AK40: =SUM(AC40:AJ40) -> 0 | AX40: =SUM(AL40:AW40) -> 0 | BD40: 15000 | BK40: =SUM(AY40:BJ40) -> 15000 | BQ40: 15000 | BX40: =SUM(BL40:BW40) -> 15000 | BZ40: 15900 | CK40: =SUM(BY40:CJ40) -> 15900 | CO40: 15900 | CY40: =SUM(CM40:CX40) -> 15900 | DB40: 15900 | DL40: =SUM(CZ40:DK40) -> 15900
B41: Ethanol Energy | AB41: 0 | AK41: =SUM(AC41:AJ41) -> 0 | AX41: =SUM(AL41:AW41) -> 0 | BD41: 10000 | BK41: =SUM(AY41:BJ41) -> 10000 | BQ41: 10000 | BX41: =SUM(BL41:BW41) -> 10000 | CD41: 10000 | CK41: =SUM(BY41:CJ41) -> 10000 | CR41: 10000 | CY41: =SUM(CM41:CX41) -> 10000 | DE41: 10000 | DL41: =SUM(CZ41:DK41) -> 10000
B42: Pantaleon Commodities Corp. | AB42: 0 | AK42: =SUM(AC42:AJ42) -> 0 | AX42: =SUM(AL42:AW42) -> 0 | BF42: =12000/1.0746 -> 11166.946 | BK42: =SUM(AY42:BJ42) -> 11166.946 | BS42: =14000/1.087 -> 12879.485 | BX42: =SUM(BL42:BW42) -> 12879.485 | CF42: =14000/1 -> 14000 | CK42: =SUM(BY42:CJ42) -> 14000 | CS42: =14000/1 -> 14000 | CY42: =SUM(CM42:CX42) -> 14000 | DF42: =14000/1 -> 14000 | DL42: =SUM(CZ42:DK42) -> 14000
B43: KWST Alambix | AB43: 0 | AK43: =SUM(AC43:AJ43) -> 0 | AX43: =SUM(AL43:AW43) -> 0 | BG43: 4000 | BK43: =SUM(AY43:BJ43) -> 4000 | BS43: =4000-4000 -> 0 | BU43: =4000 -> 4000 | BX43: =SUM(BL43:BW43) -> 4000 | CK43: =SUM(BY43:CJ43) -> 0 | CY43: =SUM(CM43:CX43) -> 0 | DL43: =SUM(CZ43:DK43) -> 0
B44: EDF Trading | AB44: 0 | AK44: =SUM(AC44:AJ44) -> 0 | AX44: =SUM(AL44:AW44) -> 0 | BI44: 9000 | BK44: =SUM(AY44:BJ44) -> 9000 | BO44: 9000 | BU44: 8250 | BX44: =SUM(BL44:BW44) -> 17250 | CA44: 8250 | CH44: 8250 | CK44: =SUM(BY44:CJ44) -> 16500 | CO44: 8250 | CV44: 8250 | CY44: =SUM(CM44:CX44) -> 16500 | DB44: 8250 | DI44: 8250 | DL44: =SUM(CZ44:DK44) -> 16500
B45: Vopak Chemicals Logistics B.V. | AB45: 0 | AK45: =SUM(AC45:AJ45) -> 0 | AX45: =SUM(AL45:AW45) -> 0 | BI45: 8000 | BK45: =SUM(AY45:BJ45) -> 8000 | BW45: 8000 | BX45: =SUM(BL45:BW45) -> 8000 | CK45: =SUM(BY45:CJ45) -> 0 | CY45: =SUM(CM45:CX45) -> 0 | DK45: 8000 | DL45: =SUM(CZ45:DK45) -> 8000
B46: Harvestone Commodities, LLC | AB46: 0 | AK46: =SUM(AC46:AJ46) -> 0 | AX46: =SUM(AL46:AW46) -> 0 | BK46: =SUM(AY46:BJ46) -> 0 | BM46: =12000/0.9778 -> 12272.448 | BX46: =SUM(BL46:BW46) -> 12272.448 | CK46: =SUM(BY46:CJ46) -> 0 | CY46: =SUM(CM46:CX46) -> 0 | DL46: =SUM(CZ46:DK46) -> 0
B47: Almagest EAD | AB47: 0 | AK47: =SUM(AC47:AJ47) -> 0 | AX47: =SUM(AL47:AW47) -> 0 | BK47: =SUM(AY47:BJ47) -> 0 | BV47: 9000 | BX47: =SUM(BL47:BW47) -> 9000 | CH47: 9000 | CK47: =SUM(BY47:CJ47) -> 9000 | CV47: 9000 | CY47: =SUM(CM47:CX47) -> 9000 | DI47: 9000 | DL47: =SUM(CZ47:DK47) -> 9000
B48: U.S. Grains Council | AB48: 0 | AK48: =SUM(AC48:AJ48) -> 0 | AX48: =SUM(AL48:AW48) -> 0 | BK48: =SUM(AY48:BJ48) -> 0 | BX48: =SUM(BL48:BW48) -> 0 | BY48: =(1755.6-20)/1.0704 -> 1621.4499 | BZ48: =(4200+4200+3165.84-25)/1.053 -> 10959.962 | CC48: =(4762.25+3857.18+4200+4200+4200+2830.19+2780.42-35)/1.0887 -> 24611.959 | CD48: =(4960-20)/1.0826 -> 4563.0889 | CE48: =(4960-20)/1.0892 -> 4535.4389 | CF48: =4960/1 -> 4960 | CG48: =4960/1 -> 4960 | CH48: =4960/1 -> 4960 | CI48: =4960/1 -> 4960 | CJ48: =4960/1 -> 4960 | CK48: =SUM(BY48:CJ48) -> 71091.899 | CM48: =4960/1 -> 4960 | CN48: =4960/1 -> 4960 | CO48: =4960/1 -> 4960 | CP48: =4960/1 -> 4960 | CQ48: =4960/1 -> 4960 | CY48: =SUM(CM48:CX48) -> 24800 | DL48: =SUM(CZ48:DK48) -> 0
B49: Lyondell Chemie Nederland B.V. | AB49: 0 | AK49: =SUM(AC49:AJ49) -> 0 | AX49: =SUM(AL49:AW49) -> 0 | BK49: =SUM(AY49:BJ49) -> 0 | BX49: =SUM(BL49:BW49) -> 0 | BY49: =15000/1.0663 -> 14067.336 | CD49: =15000/1.0856 -> 13817.244 | CK49: =SUM(BY49:CJ49) -> 27884.58 | CQ49: =15000/1 -> 15000 | CY49: =SUM(CM49:CX49) -> 15000 | DD49: =15000/1 -> 15000 | DL49: =SUM(CZ49:DK49) -> 15000
B50: AdHoc | O50: =SUM(C50:N50) -> 0 | BX50: =SUM(BL50:BW50) -> 0 | CK50: =SUM(BY50:CJ50) -> 0 | CY50: =SUM(CM50:CX50) -> 0 | DL50: =SUM(CZ50:DK50) -> 0
B51: Dropet Intertrading | O51: =SUM(C51:N51) -> 0 | X51: 2076.36 | AB51: =SUM(P51:AA51) -> 2076.36 | AK51: =SUM(AC51:AJ51) -> 0 | AX51: =SUM(AL51:AW51) -> 0 | BK51: =SUM(AY51:BJ51) -> 0 | BX51: =SUM(BL51:BW51) -> 0 | CK51: =SUM(BY51:CJ51) -> 0 | CY51: =SUM(CM51:CX51) -> 0 | DL51: =SUM(CZ51:DK51) -> 0
B52: Repsol | O52: =SUM(C52:N52) -> 0 | R52: =15000*0.75*1.21 -> 13612.5 | AB52: =SUM(P52:AA52) -> 13612.5 | AK52: =SUM(AC52:AJ52) -> 0 | AX52: =SUM(AL52:AW52) -> 0 | BJ52: =15000*0.25*0 -> 0 | BK52: =SUM(AY52:BJ52) -> 0 | BX52: =SUM(BL52:BW52) -> 0 | CK52: =SUM(BY52:CJ52) -> 0 | CY52: =SUM(CM52:CX52) -> 0 | DL52: =SUM(CZ52:DK52) -> 0
B53: Vertex | G53: =4000*1.21 -> 4840 | O53: =SUM(C53:N53) -> 4840 | Q53: 7260 | AB53: =SUM(P53:AA53) -> 7260 | AC53: =5000 -> 5000 | AD53: 7260 | AK53: =SUM(AC53:AJ53) -> 12260 | AX53: =SUM(AL53:AW53) -> 0 | BK53: =SUM(AY53:BJ53) -> 0 | BX53: =SUM(BL53:BW53) -> 0 | CK53: =SUM(BY53:CJ53) -> 0 | CY53: =SUM(CM53:CX53) -> 0 | DL53: =SUM(CZ53:DK53) -> 0
B54: Cepsa | O54: =SUM(C54:N54) -> 0 | U54: 1512.5 | AB54: =SUM(P54:AA54) -> 1512.5 | AK54: =SUM(AC54:AJ54) -> 0 | AX54: =SUM(AL54:AW54) -> 0 | BK54: =SUM(AY54:BJ54) -> 0 | BX54: =SUM(BL54:BW54) -> 0 | CK54: =SUM(BY54:CJ54) -> 0 | CY54: =SUM(CM54:CX54) -> 0 | DL54: =SUM(CZ54:DK54) -> 0
B55: Guidepoint | O55: =SUM(C55:N55) -> 0 | W55: 238.55 | AB55: =SUM(P55:AA55) -> 238.55 | AC55: =720.83 -> 720.83 | AG55: =215.93 -> 215.93 | AK55: =SUM(AC55:AJ55) -> 936.76 | AX55: =SUM(AL55:AW55) -> 0 | BE55: 650 | BK55: =SUM(AY55:BJ55) -> 650 | BW55: 273.33 | BX55: =SUM(BL55:BW55) -> 273.33 | CK55: =SUM(BY55:CJ55) -> 0 | CY55: =SUM(CM55:CX55) -> 0 | DL55: =SUM(CZ55:DK55) -> 0
B56: DWS Alternatives Global Limited-PEIF | O56: =SUM(C56:N56) -> 0 | AB56: =SUM(P56:AA56) -> 0 | AK56: =SUM(AC56:AJ56) -> 0 | AL56: 19508 | AM56: 2782.5 | AX56: =SUM(AL56:AW56) -> 22290.5 | BK56: =SUM(AY56:BJ56) -> 0 | BX56: =SUM(BL56:BW56) -> 0 | CK56: =SUM(BY56:CJ56) -> 0 | CY56: =SUM(CM56:CX56) -> 0 | DL56: =SUM(CZ56:DK56) -> 0
B57: Tomsa Destil, S.L. | AB57: =SUM(P57:AA57) -> 0 | AK57: =SUM(AC57:AJ57) -> 0 | AO57: =2201.63*1.21 -> 2663.9723 | AX57: =SUM(AL57:AW57) -> 2663.9723 | BK57: =SUM(AY57:BJ57) -> 0 | BX57: =SUM(BL57:BW57) -> 0 | CK57: =SUM(BY57:CJ57) -> 0 | CY57: =SUM(CM57:CX57) -> 0 | DL57: =SUM(CZ57:DK57) -> 0
B58: BROKERAGE | O58: =SUM(C58:N58) -> 0 | BX58: =SUM(BL58:BW58) -> 0 | CK58: =SUM(BY58:CJ58) -> 0 | CY58: =SUM(CM58:CX58) -> 0 | DL58: =SUM(CZ58:DK58) -> 0
B59: Enviral | O59: =SUM(C59:N59) -> 0 | V59: =1174.58 -> 1174.58 | AB59: =SUM(P59:AA59) -> 1174.58 | AK59: =SUM(AC59:AJ59) -> 0 | AX59: =SUM(AL59:AW59) -> 0 | BK59: =SUM(AY59:BJ59) -> 0 | BX59: =SUM(BL59:BW59) -> 0 | CK59: =SUM(BY59:CJ59) -> 0 | CY59: =SUM(CM59:CX59) -> 0 | DL59: =SUM(CZ59:DK59) -> 0
B60: Interalco | O60: =SUM(C60:N60) -> 0 | V60: =1203.1+4975.49 -> 6178.59 | W60: =2294.62+5739.08 -> 8033.7 | AB60: =SUM(P60:AA60) -> 14212.29 | AK60: =SUM(AC60:AJ60) -> 0 | AX60: =SUM(AL60:AW60) -> 0 | BK60: =SUM(AY60:BJ60) -> 0 | BX60: =SUM(BL60:BW60) -> 0 | CK60: =SUM(BY60:CJ60) -> 0 | CY60: =SUM(CM60:CX60) -> 0 | DL60: =SUM(CZ60:DK60) -> 0
B61: Murex | O61: =SUM(C61:N61) -> 0 | T61: 5893.52 | W61: 5442.38 | AB61: =SUM(P61:AA61) -> 11335.9 | AK61: =SUM(AC61:AJ61) -> 0 | AX61: =SUM(AL61:AW61) -> 0 | BK61: =SUM(AY61:BJ61) -> 0 | BX61: =SUM(BL61:BW61) -> 0 | CK61: =SUM(BY61:CJ61) -> 0 | CY61: =SUM(CM61:CX61) -> 0 | DL61: =SUM(CZ61:DK61) -> 0
B62: Seaboard | O62: =SUM(C62:N62) -> 0 | AA62: =12803.93-25.61 -> 12778.32 | AB62: =SUM(P62:AA62) -> 12778.32 | AH62: =7000*2.5/1.1*0 -> 0 | AI62: =7000*2.5/1.1*0 -> 0 | AJ62: =7000*2.5/1.1*0 -> 0 | AK62: =SUM(AC62:AJ62) -> 0 | AS62: =15000/1.2007 -> 12492.713 | AX62: =SUM(AL62:AW62) -> 12492.713 | BK62: =SUM(AY62:BJ62) -> 0 | BL62: =15000*2/1.1*0 -> 0 | BX62: =SUM(BL62:BW62) -> 0 | CK62: =SUM(BY62:CJ62) -> 0 | CY62: =SUM(CM62:CX62) -> 0 | DL62: =SUM(CZ62:DK62) -> 0
B63: Cremer | O63: =SUM(C63:N63) -> 0 | X63: 21889.39 | Z63: =12963.73-25.93 -> 12937.8 | AB63: =SUM(P63:AA63) -> 34827.19 | AK63: =SUM(AC63:AJ63) -> 0 | AM63: =7522*2/1.177 -> 12781.648 | AU63: =45126*0 -> 0 | AX63: =SUM(AL63:AW63) -> 12781.648 | AZ63: =9804.98*2/1.1645 -> 16839.811 | BK63: =SUM(AY63:BJ63) -> 16839.811 | BX63: =SUM(BL63:BW63) -> 0 | CK63: =SUM(BY63:CJ63) -> 0 | CY63: =SUM(CM63:CX63) -> 0 | DL63: =SUM(CZ63:DK63) -> 0
B64: ACA Bio | O64: =SUM(C64:N64) -> 0 | AB64: 0 | AK64: =SUM(AC64:AJ64) -> 0 | AL64: =5659/1.1787 -> 4801.052 | AO64: =8500*0.75*0.9/1.2267-1 -> 4676.1827 | AT64: =(2625*0.9)/1.2201 -> 1936.3167 | AU64: =+AU63*0.15 -> 0 | AX64: =SUM(AL64:AW64) -> 11413.551 | BB64: =(9804.98*0.75-735.37)/1.1291 -> 5861.6287 | BE64: =(637.5+262.5)/1.225073 -> 734.6501 | BK64: =SUM(AY64:BJ64) -> 6596.2788 | BR64: =735.37/1.128664+(20000-2000)/1.0745 -> 17403.518 | BX64: =SUM(BL64:BW64) -> 17403.518 | CF64: =(20000-18000)/0.929454 -> 2151.8009 | CI64: =(20000-2000)/1 -> 18000 | CK64: =SUM(BY64:CJ64) -> 20151.801 | CY64: =SUM(CM64:CX64) -> 0 | DL64: =SUM(CZ64:DK64) -> 0
B65: CCI - Castleton Commodities Int LLC | O65: =SUM(C65:N65) -> 0 | AB65: 0 | AK65: =SUM(AC65:AJ65) -> 0 | AM65: =7521.147*1.5/1.173 -> 9617.835 | AX65: =SUM(AL65:AW65) -> 9617.835 | BK65: =SUM(AY65:BJ65) -> 0 | BX65: =SUM(BL65:BW65) -> 0 | CK65: =SUM(BY65:CJ65) -> 0 | CY65: =SUM(CM65:CX65) -> 0 | DL65: =SUM(CZ65:DK65) -> 0
B66: Ruhr Petrol | O66: =SUM(C66:N66) -> 0 | AB66: 0 | AK66: =SUM(AC66:AJ66) -> 0 | AM66: =6768.95+5460 -> 12228.95 | AX66: =SUM(AL66:AW66) -> 12228.95 | BG66: =4083.177*1.05 -> 4287.3359 | BH66: =6000*6 -> 36000 | BJ66: 0 | BK66: =SUM(AY66:BJ66) -> 40287.336 | BX66: =SUM(BL66:BW66) -> 0 | CK66: =SUM(BY66:CJ66) -> 0 | CY66: =SUM(CM66:CX66) -> 0 | DL66: =SUM(CZ66:DK66) -> 0
B67: Bioagra | AB67: =SUM(P67:AA67) -> 0 | AK67: =SUM(AC67:AJ67) -> 0 | AQ67: =2859*1 -> 2859 | AX67: =SUM(AL67:AW67) -> 2859 | BK67: =SUM(AY67:BJ67) -> 0 | BX67: =SUM(BL67:BW67) -> 0 | CK67: =SUM(BY67:CJ67) -> 0 | CY67: =SUM(CM67:CX67) -> 0 | DL67: =SUM(CZ67:DK67) -> 0
B68: Czanikow | AX68: =SUM(AL68:AW68) -> 0 | BH68: =(6000*2.5+8400*10+4083*13.5)/1.0743 -> 143461.32 | BK68: =SUM(AY68:BJ68) -> 143461.32 | BL68: 0 | BP68: =43400/1.0696 -> 40575.916 | BX68: =SUM(BL68:BW68) -> 40575.916 | CK68: =SUM(BY68:CJ68) -> 0 | CY68: =SUM(CM68:CX68) -> 0 | DL68: =SUM(CZ68:DK68) -> 0
B69: EDF Trading | BK69: =SUM(AY69:BJ69) -> 0 | BS69: =20440/1.1042 -> 18511.139 | BX69: =SUM(BL69:BW69) -> 18511.139 | CK69: =SUM(BY69:CJ69) -> 0 | CY69: =SUM(CM69:CX69) -> 0 | DL69: =SUM(CZ69:DK69) -> 0
B70: FUTUROS | O70: =SUM(C70:N70) -> 0 | BX70: =SUM(BL70:BW70) -> 0 | CK70: =SUM(BY70:CJ70) -> 0 | CY70: =SUM(CM70:CX70) -> 0 | DL70: =SUM(CZ70:DK70) -> 0
B71: Paragon | O71: =SUM(C71:N71) -> 0 | AB71: =SUM(P71:AA71) -> 0 | AG71: =21420/1.1136 -> 19234.914 | AH71: =-2625/1.1174-75/1.121+(1050+19593+14994)/1.121 -> 29374.258 | AK71: =SUM(AC71:AJ71) -> 48609.171 | AT71: =92575/1.2081 -> 76628.59 | AU71: -20000 | AV71: =41591-20500 -> 21091 | AW71: 216 | AX71: =SUM(AL71:AW71) -> 77935.59 | AY71: =52200+33560-17360/1.1629 -> 70831.803 | BB71: =701700-93925 -> 607775 | BG71: =637500-16642.5/1.1328 -> 622808.53 | BJ71: =38752/1.0195 -> 38010.79 | BK71: =SUM(AY71:BJ71) -> 1339426.1 | BM71: =-19792.08/1.0927 -> -18113.004 | BN71: =-5952.24/1.0927+26992/1.0366-159215-270000-270000 -> -678623.3 | BO71: =24375/1.0538 -> 23130.575 | BR71: =5040/1.0586-4480/1.0596 -> 532.99453 | BV71: =-1087.2/1.0821 -> -1004.7131 | BX71: =SUM(BL71:BW71) -> -674077.45 | CA71: =600/1.0683-11550/1.0813 -> -10119.947 | CC71: =-14114.44+19406.74-60952.97+31291.39+11589.4+11589.4 -> -1190.48 | CK71: =SUM(BY71:CJ71) -> -11310.427 | CY71: =SUM(CM71:CX71) -> 0 | DL71: =SUM(CZ71:DK71) -> 0
B72: FC Stone | O72: =SUM(C72:N72) -> 0 | AB72: =SUM(P72:AA72) -> 0 | AK72: =SUM(AC72:AJ72) -> 0 | AX72: =SUM(AL72:AW72) -> 0 | BK72: =SUM(AY72:BJ72) -> 0 | BX72: =SUM(BL72:BW72) -> 0 | CK72: =SUM(BY72:CJ72) -> 0 | CY72: =SUM(CM72:CX72) -> 0 | DL72: =SUM(CZ72:DK72) -> 0
B73: VARIOS | C73: 1000 | AB73: =SUM(P73:AA73) -> 0 | AK73: =SUM(AC73:AJ73) -> 0 | BK73: =SUM(AY73:BJ73) -> 0 | BX73: =SUM(BL73:BW73) -> 0 | CK73: =SUM(BY73:CJ73) -> 0 | CY73: =SUM(CM73:CX73) -> 0 | DL73: =SUM(CZ73:DK73) -> 0
B74: Total Cobros (mes) | C74: =SUM(C5:C73) -> 16000 | D74: =SUM(D5:D73) -> 35000 | E74: =SUM(E5:E73) -> 15000 | F74: =SUM(F5:F73) -> 0 | G74: =SUM(G5:G73) -> 4840 | H74: =SUM(H5:H73) -> 5000 | I74: =SUM(I5:I73) -> 5000 | J74: =SUM(J5:J73) -> 10000 | ... N74: =SUM(N5:N73) -> 0 | O74: =SUM(C74:N74) -> 116840 | P74: =SUM(P5:P73) -> 50000 | Q74: =SUM(Q5:Q73) -> 40760 | R74: =SUM(R5:R73) -> 13612.5 | S74: =SUM(S5:S73) -> 22650 | T74: =SUM(T5:T73) -> 25462.7 | U74: =SUM(U5:U73) -> 9012.5 | V74: =SUM(V5:V73) -> 51853.17 | W74: =SUM(W5:W73) -> 24486.62 | ... AW74: =SUM(AW5:AW73) -> 35872.237 | AX74: =SUM(AX4:AX73) -> 556158.73 | AY74: =SUM(AY5:AY73) -> 100831.8 | AZ74: =SUM(AZ5:AZ73) -> 59361.532 | BA74: =SUM(BA5:BA73) -> 74138.987 | BB74: =SUM(BB5:BB73) -> 645636.63 | BC74: =SUM(BC5:BC73) -> 25471.577 | BD74: =SUM(BD5:BD73) -> 34537.5 | BE74: =SUM(BE5:BE73) -> 73384.65 | BF74: =SUM(BF5:BF73) -> 111695.33 | ... BJ74: =SUM(BJ5:BJ73) -> 66010.79 | BK74: =SUM(BK4:BK73) -> 2075972.4 | BL74: =SUM(BL5:BL73) -> 34000 | BM74: =SUM(BM5:BM73) -> 17243.254 | BN74: =SUM(BN5:BN73) -> -611998.3 | BO74: =SUM(BO5:BO73) -> 45630.575 | BP74: =SUM(BP5:BP73) -> 116325.44 | BQ74: =SUM(BQ5:BQ73) -> 49058.562 | BR74: =SUM(BR5:BR73) -> 129337.53 | BS74: =SUM(BS5:BS73) -> 104496.17 | ... BW74: =SUM(BW5:BW73) -> 61273.33 | BX74: =SUM(BL74:BW74) -> -9109.6324 | BY74: =SUM(BY5:BY73) -> 32688.786 | BZ74: =SUM(BZ5:BZ73) -> 79900.912 | CA74: =SUM(CA5:CA73) -> 42825.233 | CB74: =SUM(CB5:CB73) -> 43500 | CC74: =SUM(CC5:CC73) -> 79921.479 | CD74: =SUM(CD5:CD73) -> 63280.333 | CE74: =SUM(CE5:CE73) -> 4535.4389 | CF74: =SUM(CF5:CF73) -> 121011.8 | ... CJ74: =SUM(CJ5:CJ73) -> 27460 | CK74: =SUM(CK4:CK73) -> 634202.98 | CM74: =SUM(CM5:CM73) -> 4960 | CN74: =SUM(CN5:CN73) -> 32460 | CO74: =SUM(CO5:CO73) -> 72110 | CP74: =SUM(CP5:CP73) -> 35960 | CQ74: =SUM(CQ5:CQ73) -> 115460 | CR74: =SUM(CR5:CR73) -> 55700 | CS74: =SUM(CS5:CS73) -> 66000 | CT74: =SUM(CT5:CT73) -> 67500 | ... CX74: =SUM(CX5:CX73) -> 28500 | CY74: =SUM(CY4:CY73) -> 544400 | DL74: =SUM(DL4:DL73) -> 497600
AX75: =SUM(AL74:AW74)-AX74 -> 0 | BK75: =SUM(AY74:BJ74)-BK74 -> 0 | BX75: =SUM(BL75:BW75) -> 0 | CK75: =SUM(BY74:CJ74)-CK74 -> 0 | CY75: =SUM(CM74:CX74)-CY74 -> 0 | DL75: =SUM(CZ74:DK74)-DL74 -> -497600
B76: Pagos
B77: GENERALES
B78: Conferencia Dropet | D78: =5445+21175 -> 26620 | E78: 5445 | F78: 0 | H78: =1500*1.21 -> 1815 | I78: =1500*1.21 -> 1815 | J78: =J11*0.3 -> 3000 | M78: 2722.5 | O78: =SUM(C78:N78) -> 41417.5 | AB78: =SUM(P78:AA78) -> 0 | AC78: 762.3 | AK78: =SUM(AC78:AJ78) -> 762.3 | AX78: =SUM(AL78:AW78) -> 0 | BG78: =920*1.21 -> 1113.2 | BK78: =SUM(AY78:BJ78) -> 1113.2 | BO78: =950*1.21 -> 1149.5 | BX78: =SUM(BL78:BW78) -> 1149.5 | CC78: =1050*1.21 -> 1270.5 | CK78: =SUM(BY78:CJ78) -> 1270.5 | CQ78: 1500 | CY78: =SUM(CM78:CX78) -> 1500 | DD78: 1500 | DL78: =SUM(CZ78:DK78) -> 1500
B79: Compras inmobilizado | D79: 120 | O79: =SUM(C79:N79) -> 120 | Q79: 859 | T79: =632.33 -> 632.33 | U79: =632.33+171.22+71.27 -> 874.82 | V79: 632.34 | W79: 559.99 | AB79: =SUM(P79:AA79) -> 3558.48 | AH79: =301+71.27+171.22 -> 543.49 | AI79: =903/3 -> 301 | AJ79: =903/3 -> 301 | AK79: =SUM(AC79:AJ79) -> 1145.49 | AP79: 418.95 | AQ79: =-418.95+(418.95+6)*1.21 -> 95.2395 | AR79: =73.83*1.21 -> 89.3343 | AU79: =71.27 -> 71.27 | AV79: =(3*126*1.21+46.5*1.21) -> 513.645 | AX79: =SUM(AL79:AW79) -> 1188.4388 | AZ79: 1559.01 | BA79: 228.69 | BB79: 989.33 | BC79: =1198 -> 1198 | BG79: =(61.2+8.5)*1.21 -> 84.337 | BI79: 513.65 | BJ79: =1205.79+544.5 -> 1750.29 | BK79: =SUM(AY79:BJ79) -> 6323.307 | BR79: 239.83 | BU79: =(67.2+8.5)*1.21 -> 91.597 | BV79: =(140.4*3+46.5)*1.21 -> 565.917 | BX79: =SUM(BL79:BW79) -> 897.344 | BZ79: =(108.47-46.98)*1.21 -> 74.4029 | CC79: 1500 | CI79: 735 | CK79: =SUM(BY79:CJ79) -> 2309.4029 | CW79: 735 | CY79: =SUM(CM79:CX79) -> 735 | DJ79: 735 | DL79: =SUM(CZ79:DK79) -> 735
B80: Suministros informáticos y mantenimiento | AB80: =SUM(P80:AA80) -> 0 | AK80: =SUM(AC80:AJ80) -> 0 | AX80: =SUM(AL80:AW80) -> 0 | BK80: =SUM(AY80:BJ80) -> 0 | BQ80: =23.39 -> 23.39 | BS80: 17.09 | BT80: 34.05 | BU80: =(190+20+20)*(1.21-0.15) -> 243.8 | BW80: 9.24 | BX80: =SUM(BL80:BW80) -> 327.57 | BZ80: 68.97 | CA80: =25.88+10.71 -> 36.59 | CB80: =29.09 -> 29.09 | CC80: =36.06+12.61+74.98 -> 123.65 | CD80: =48.52 -> 48.52 | CE80: 73.3 | CK80: =SUM(BY80:CJ80) -> 380.12 | CY80: =SUM(CM80:CX80) -> 0 | DL80: =SUM(CZ80:DK80) -> 0
B81: Trips/commercial expenses | D81: =146.1+485.77 -> 631.87 | O81: =SUM(C81:N81) -> 631.87 | P81: 719.95 | Q81: 4700 | S81: 3260.56 | T81: =777.7+217.1+1159.95 -> 2154.75 | W81: =453.05+2000+625 -> 3078.05 | X81: =637.1+1190.63+1052.75 -> 2880.48 | Y81: =193.85 -> 193.85 | Z81: =(357.28+78.86)+(24.99+1964.84+14.63)+(271.48+85.04) -> 2797.12 | AA81: =(205.77+10.4+53+171.76)+(741.77+40.51+180.78)+(223.8+536.1) -> 2163.89 | AB81: =SUM(P81:AA81) -> 21948.65 | AC81: =403.12 -> 403.12 | AD81: =1255.01+1099.75+951.98 -> 3306.74 | AE81: =1196.19 -> 1196.19 | AK81: =SUM(AC81:AJ81) -> 4906.05 | AQ81: =47.6+22.82+17.25+113.96+148.02+781.18+112.57+45.4+61.3+891.3 -> 2241.4 | AV81: =239.58 -> 239.58 | AX81: =SUM(AL81:AW81) -> 2480.98 | AZ81: =(76.1+89+131+26+184.5+10.45+225.5+18+126.35+13+18+75+3.35+5.2+3.35)+400 -> 1404.8 | BB81: =1426.47+424.42 -> 1850.89 | BF81: =1487.52+11560 -> 13047.52 | BG81: 144.98 | BH81: 96.99 | BK81: =SUM(AY81:BJ81) -> 16545.18 | BL81: =536.44/0.865295 -> 619.95042 | BN81: =297 -> 297 | BQ81: =1041.1 -> 1041.1 | BR81: 2456.49 | BS81: 3373.49 | BT81: 3978.46 | BU81: 3401.57 | BV81: 1161.44 | BW81: 1061.8 | BX81: =SUM(BL81:BW81) -> 17391.3 | BY81: =1514.37-10.91 -> 1503.46 | BZ81: =535.61/0.8609+(2534.77-925.21) -> 2231.7112 | CA81: 3275.29 | CB81: 4393.77 | CC81: 1311.37 | CD81: 726.56 | CE81: 1117.22 | CF81: =5000/2+250+1000 -> 3750 | CG81: 3000 | CH81: 250 | CI81: 500 | CJ81: 500 | CK81: =SUM(BY81:CJ81) -> 22559.381 | CM81: 500 | CN81: 2000 | CO81: =1500 -> 1500 | CP81: 500 | CQ81: 500 | CR81: 500 | CS81: =5000/2 -> 2500 | CT81: =5000/2+250+1000 -> 3750 | CU81: 3000 | CV81: 250 | CW81: 500 | CX81: 500 | CY81: =SUM(CM81:CX81) -> 16000 | CZ81: 500 | DA81: 2000 | DB81: =1500 -> 1500 | DC81: 500 | DD81: 500 | DE81: 500 | DF81: =5000/2 -> 2500 | DG81: =5000/2+250+1000 -> 3750 | DH81: 3000 | DI81: 250 | DJ81: 500 | DK81: 500 | DL81: =SUM(CZ81:DK81) -> 16000
B82: Personnel - Felipe Fontes | O82: =SUM(C82:N82) -> 0 | Q82: 1425 | U82: 1500 | Z82: 1500 | AB82: =SUM(P82:AA82) -> 4425 | AK82: =SUM(AC82:AJ82) -> 0 | AP82: 3536 | AX82: =SUM(AL82:AW82) -> 3536 | BC82: 4540 | BK82: =SUM(AY82:BJ82) -> 4540 | BR82: =180*6+180*6 -> 2160 | BS82: 3940 | BX82: =SUM(BL82:BW82) -> 6100 | CE82: =180*6+180*6 -> 2160 | CF82: 3940 | CK82: =SUM(BY82:CJ82) -> 6100 | CS82: =180*6+180*6 -> 2160 | CT82: 3940 | CY82: =SUM(CM82:CX82) -> 6100 | DF82: =180*6+180*6 -> 2160 | DG82: 3940 | DL82: =SUM(CZ82:DK82) -> 6100
B83: Personnel - Alfonso Carmona Bosch | O83: =SUM(C83:N83) -> 0 | Y83: 3213.33 | Z83: =1584.94 -> 1584.94 | AA83: 2994 | AB83: =SUM(P83:AA83) -> 7792.27 | AC83: =2000-1409.06/3 -> 1530.3133 | AD83: =2000-1409.06/3 -> 1530.3133 | AE83: =2000-1409.06/3 -> 1530.3133 | AF83: =1782.45-652.64 -> 1129.81 | AG83: 1959.52 | AH83: 1959.52 | AI83: 1959.52 | AJ83: 1959.52 | AK83: =SUM(AC83:AJ83) -> 13558.83 | AL83: 1959.52 | AM83: 3950 | AN83: 3950 | AO83: 3950 | AP83: 3950 | AQ83: 3950 | AR83: 3950 | AS83: 3950 | AT83: 3950 | AU83: 3950 | AV83: 3950 | AW83: 3950 | AX83: =SUM(AL83:AW83) -> 45409.52 | AY83: 3950 | AZ83: 3950 | BA83: 3950 | BB83: 3950 | BC83: 3950.06 | BD83: 3950 | BE83: 3950 | BF83: 3950 | BG83: =1250+5200 -> 6450 | BH83: 5200 | BI83: 5200 | BJ83: 5200 | BK83: =SUM(AY83:BJ83) -> 53650.06 | BL83: 5200 | BM83: =274.95+3000 -> 3274.95 | BN83: 3000 | BO83: 3000 | BP83: 3000 | BQ83: 4300 | BR83: 4300 | BS83: 4300 | BT83: 4300 | BU83: 4300 | BV83: 4300 | BW83: 4300 | BX83: =SUM(BL83:BW83) -> 47574.95 | BY83: 4300 | BZ83: 4300 | CA83: 4300 | CB83: 4300 | CC83: 4300 | CD83: 4300 | CE83: 4300 | CF83: 4300 | CG83: 4300 | CH83: 4300 | CI83: 4300 | CJ83: 4300 | CK83: =SUM(BY83:CJ83) -> 51600 | CM83: 4300 | CN83: 4300 | CO83: 4300 | CP83: 4300 | CQ83: 4300 | CR83: 4300 | CS83: 4300 | CT83: 4300 | CU83: 4300 | CV83: 4300 | CW83: 4300 | CX83: 4300 | CY83: =SUM(CM83:CX83) -> 51600 | CZ83: 4300 | DA83: 4300 | DB83: 4300 | DC83: 4300 | DD83: 4300 | DE83: 4300 | DF83: 4300 | DG83: 4300 | DH83: 4300 | DI83: 4300 | DJ83: 4300 | DK83: 4300 | DL83: =SUM(CZ83:DK83) -> 51600
B84: Personnel - Alberto Carmona | M84: 16000 | N84: =8000+5000 -> 13000 | O84: =SUM(C84:N84) -> 29000 | Q84: =8000+8480 -> 16480 | R84: 10600 | S84: 10600 | T84: 11660 | U84: 13780 | V84: 13780 | W84: 13780 | X84: 11660 | Y84: 11660 | Z84: 11660 | AA84: 11660 | AB84: =SUM(P84:AA84) -> 137320 | AC84: 13780 | AD84: 11660 | AE84: 11660 | AF84: 11660 | AG84: 11660 | AH84: 11660 | AI84: 13780 | AJ84: 11660 | AK84: =SUM(AC84:AJ84) -> 97520 | AL84: 11660 | AM84: 11660 | AN84: 11660 | AO84: 11660 | AP84: 11660 | AQ84: 11660 | AR84: 11660 | AS84: 11660 | AT84: 11660 | AU84: 11660 | AV84: 11660 | AW84: 11660 | AX84: =SUM(AL84:AW84) -> 139920 | AY84: 11660 | AZ84: 11660 | BA84: 11660 | BB84: 11660 | BC84: 11660 | BD84: 11660 | BE84: 11660 | BF84: 11660 | BG84: 11660 | BH84: 11660 | BI84: 11660 | BJ84: 11660 | BK84: =SUM(AY84:BJ84) -> 139920 | BL84: 11660 | BM84: 11660 | BN84: 11660 | BO84: 11660 | BP84: 11660 | BQ84: 11660 | BR84: 11660 | BS84: 11660 | BT84: 11660 | BU84: 11660 | BV84: 11660 | BW84: 11660 | BX84: =SUM(BL84:BW84) -> 139920 | BY84: 11660 | BZ84: 11660 | CA84: 11660 | CB84: 11660 | CC84: 11660 | CD84: 11660 | CE84: 11660 | CF84: 11660 | CG84: 11660 | CH84: 11660 | CI84: 11660 | CJ84: 11660 | CK84: =SUM(BY84:CJ84) -> 139920 | CM84: 11660 | CN84: 11660 | CO84: 11660 | CP84: 11660 | CQ84: 11660 | CR84: 11660 | CS84: 11660 | CT84: 11660 | CU84: 11660 | CV84: 11660 | CW84: 11660 | CX84: 11660 | CY84: =SUM(CM84:CX84) -> 139920 | CZ84: 11660 | DA84: 11660 | DB84: 11660 | DC84: 11660 | DD84: 11660 | DE84: 11660 | DF84: 11660 | DG84: 11660 | DH84: 11660 | DI84: 11660 | DJ84: 11660 | DK84: 11660 | DL84: =SUM(CZ84:DK84) -> 139920
B85: Personnel - Rosa Jiménez | AB85: =SUM(P85:AA85) -> 0 | AK85: =SUM(AC85:AJ85) -> 0 | AM85: 800 | AN85: 800 | AQ85: 800 | AR85: 800 | AS85: 453.33 | AW85: 613.33 | AX85: =SUM(AL85:AW85) -> 4266.66 | AY85: 800 | AZ85: 800 | BA85: 800 | BB85: 800 | BC85: 800 | BD85: 800 | BE85: 800 | BF85: 800 | BG85: 800 | BH85: 800 | BI85: 800 | BJ85: 800 | BK85: =SUM(AY85:BJ85) -> 9600 | BL85: 800 | BM85: 800 | BN85: 800 | BO85: 800 | BP85: 800 | BQ85: 800 | BR85: =800 -> 800 | BS85: 1280 | BT85: 1280 | BU85: 1280 | BV85: 1280 | BW85: 1280 | BX85: =SUM(BL85:BW85) -> 12000 | BY85: 1280 | BZ85: 1280 | CA85: 1280 | CB85: 1280 | CC85: 1280 | CD85: 1280 | CE85: 1280 | CF85: 1280 | CG85: 1280 | CH85: 1280 | CI85: 1280 | CJ85: 1280 | CK85: =SUM(BY85:CJ85) -> 15360 | CM85: 1280 | CN85: 1280 | CO85: 1280 | CP85: 1280 | CQ85: 1280 | CR85: 1280 | CS85: 1280 | CT85: 1280 | CU85: 1280 | CV85: 1280 | CW85: 1280 | CX85: 1280 | CY85: =SUM(CM85:CX85) -> 15360 | CZ85: 1280 | DA85: 1280 | DB85: 1280 | DC85: 1280 | DD85: 1280 | DE85: 1280 | DF85: 1280 | DG85: 1280 | DH85: 1280 | DI85: 1280 | DJ85: 1280 | DK85: 1280 | DL85: =SUM(CZ85:DK85) -> 15360
B86: Personnel - María Lacañina | AB86: =SUM(P86:AA86) -> 0 | AK86: =SUM(AC86:AJ86) -> 0 | AP86: 296.1 | AQ86: 634.52 | AR86: 632.27 | AS86: =479.44+233.93 -> 713.37 | AT86: 701.8 | AX86: =SUM(AL86:AW86) -> 2978.06 | BK86: =SUM(AY86:BJ86) -> 0 | BX86: =SUM(BL86:BW86) -> 0 | BY86: 1313.4 | BZ86: 1313.4 | CA86: 1313.4 | CB86: 1313.4 | CC86: 1323.6 | CD86: 1327.2 | CE86: 1327.2 | CF86: 1313.4 | CG86: 1313.4 | CH86: 1313.4 | CI86: 1313.4 | CJ86: 1313.4 | CK86: =SUM(BY86:CJ86) -> 15798.6 | CM86: 1313.4 | CN86: 1313.4 | CO86: 1313.4 | CP86: 1313.4 | CQ86: 1313.4 | CR86: 1313.4 | CS86: 1313.4 | CT86: 1313.4 | CU86: 1313.4 | CV86: 1313.4 | CW86: 1313.4 | CX86: 1313.4 | CY86: =SUM(CM86:CX86) -> 15760.8 | CZ86: 1313.4 | DA86: 1313.4 | DB86: 1313.4 | DC86: 1313.4 | DD86: 1313.4 | DE86: 1313.4 | DF86: 1313.4 | DG86: 1313.4 | DH86: 1313.4 | DI86: 1313.4 | DJ86: 1313.4 | DK86: 1313.4 | DL86: =SUM(CZ86:DK86) -> 15760.8
B87: Soc. Security | O87: =SUM(C87:N87) -> 0 | U87: 0 | Z87: =128.61 -> 128.61 | AA87: =748.03 -> 748.03 | AB87: =SUM(P87:AA87) -> 876.64 | AC87: =748.03 -> 748.03 | AD87: =736.28 -> 736.28 | AE87: =736.28 -> 736.28 | AF87: =736.28 -> 736.28 | AG87: =736.28 -> 736.28 | AH87: =736.28+11.75 -> 748.03 | AI87: =736.28+11.75 -> 748.03 | AJ87: =736.28+11.75 -> 748.03 | AK87: =SUM(AC87:AJ87) -> 5937.24 | AL87: =736.28+11.75 -> 748.03 | AM87: =736.28+11.75 -> 748.03 | AN87: =1673.52-582.75 -> 1090.77 | AO87: =1673.52-582.75 -> 1090.77 | AR87: =1331.99+741.57+1239.97 -> 3313.53 | AS87: =-720.06 -> -720.06 | AW87: =1254.09+1031.7+660.55+611.93+611.93 -> 4170.2 | AX87: =SUM(AL87:AW87) -> 10441.27 | BB87: =880.42+962.17+951.05 -> 2793.64 | BD87: =951.31+951.05 -> 1902.36 | BG87: =979.54+956.72+956.72+956.72 -> 3849.7 | BJ87: =956.72+956.72+956.72 -> 2870.16 | BK87: =SUM(AY87:BJ87) -> 11415.86 | BN87: =956.72+956.72 -> 1913.44 | BO87: =956.72+956.72 -> 1913.44 | BQ87: =956.73+1018.43 -> 1975.16 | BV87: =1018.43+1018.43+1225.27+1213.49 -> 4475.62 | BW87: =1213.49+1213.49 -> 2426.98 | BX87: =SUM(BL87:BW87) -> 12704.64 | BY87: =1015.02+1131.54 -> 2146.56 | BZ87: =1131.54+1015.02 -> 2146.56 | CA87: =15.13+26.97+(1131.54+673.7) -> 1847.34 | CB87: =1131.54+696.96-23.27 -> 1805.23 | CC87: =1131.54+1022.83-349.13 -> 1805.24 | CD87: =2209.93-377.24 -> 1832.69 | CE87: =3469.41-377.24 -> 3092.17 | CF87: 1805 | CG87: 1805 | CH87: 1805 | CI87: 1805 | CJ87: 1805 | CK87: =SUM(BY87:CJ87) -> 23700.79 | CM87: 1805 | CN87: 1805 | CO87: 1805 | CP87: 1805 | CQ87: 1805 | CR87: 1805 | CS87: 1805 | CT87: 1805 | CU87: 1805 | CV87: 1805 | CW87: 1805 | CX87: 1805 | CY87: =SUM(CM87:CX87) -> 21660 | CZ87: 1805 | DA87: 1805 | DB87: 1805 | DC87: 1805 | DD87: 1805 | DE87: 1805 | DF87: 1805 | DG87: 1805 | DH87: 1805 | DI87: 1805 | DJ87: 1805 | DK87: 1805 | DL87: =SUM(CZ87:DK87) -> 21660
B88: Fiscal, Accounting agency | C88: 104.35 | D88: 102.85 | E88: 102.85 | F88: =E88 -> 102.85 | G88: =F88 -> 102.85 | H88: =G88 -> 102.85 | I88: =H88 -> 102.85 | J88: =I88 -> 102.85 | K88: =J88 -> 102.85 | L88: =K88 -> 102.85 | M88: 102.85 | N88: =102.85+102.85 -> 205.7 | O88: =SUM(C88:N88) -> 1338.55 | Q88: 104.6 | R88: 104.6 | S88: =254.91+104.6+45.79 -> 405.3 | T88: 182.31 | U88: 182.31 | V88: 224.66 | W88: =363+224.66 -> 587.66 | X88: =185.67*1.21+29.04 -> 253.7007 | Y88: =185.67*1.21+200*1.21 -> 466.6607 | Z88: =199.67*1.21+600*1.21+2504.7 -> 3472.3007 | AA88: =199.67*1.21 -> 241.6007 | AB88: =SUM(P88:AA88) -> 6225.7028 | AC88: =199.67*1.21 -> 241.6007 | AD88: =(199.67*1.21+104.16)+600*1.21+480*1.21 -> 1652.5607 | AE88: =(199.67+100)*1.21 -> 362.6007 | AF88: =199.67*1.21+1579*1.21/2 -> 1196.8957 | AG88: =(199.67+6.58)*1.21+600*1.21 -> 975.5625 | AH88: =199.67*1.21 -> 241.6007 | AI88: =199.67*1.21+50*1.21 -> 302.1007 | AJ88: =(199.67+9.56)*1.21+600*1.21 -> 979.1683 | AK88: =SUM(AC88:AJ88) -> 5952.09 | AL88: =199.67*1.21 -> 241.6007 | AM88: =199.67*1.21+48.97 -> 290.5707 | AN88: =213.67*1.21 -> 258.5407 | AO88: =213.67*1.21 -> 258.5407 | AQ88: =(313.67+313.67+300)*1.21+29.04 -> 1151.1214 | AR88: =313.67*1.21+104.16 -> 483.7007 | AS88: =313.67*1.21 -> 379.5407 | AT88: =313.67*1.21 -> 379.5407 | AU88: 379.54 | AV88: 430.54 | AW88: =386.78-1576.4+102.85+102.85+248.05+102.85 -> -633.02 | AX88: =SUM(AL88:AW88) -> 3620.2163 | AY88: 379.54 | AZ88: =379.54+270.23 -> 649.77 | BA88: 649.77 | BD88: =(150+252+15+20)*1.21*3 -> 1586.31 | BE88: =437*1.21-121*2+67.86+8.73 -> 363.36 | BF88: =437*1.21 -> 528.77 | BG88: =437*1.21+57.91 -> 586.68 | BH88: =437*1.21 -> 528.77 | BI88: =(437+300+27.95)*1.21 -> 925.5895 | BJ88: =(437+100)*1.21 -> 649.77 | BK88: =SUM(AY88:BJ88) -> 6848.3295 | BL88: =437*1.21 -> 528.77 | BM88: =437*1.21 -> 528.77 | BN88: =437*1.21 -> 528.77 | BO88: =437*1.21 -> 528.77 | BP88: =437*1.21+29.04 -> 557.81 | BQ88: =(437+30)*1.21+67.86 -> 632.93 | BR88: =461.91*1.21 -> 558.9111 | BS88: =461.91*1.21 -> 558.9111 | BT88: =(461.91+14.99)*1.21+60.09 -> 637.139 | BU88: =(461.91+27.95)*1.21 -> 592.7306 | BV88: =(461.91+200)*1.21 -> 800.9111 | BW88: =461.91*1.21+199.8 -> 758.7111 | BX88: =SUM(BL88:BW88) -> 7213.134 | BY88: =(461.91+27.95)*1.21 -> 592.7306 | BZ88: 558.91 | CA88: 558.91 | CB88: 558.91 | CC88: 558.91 | CD88: 595.21 | CE88: 644.11 | CF88: 558.91 | CG88: 558.91 | CH88: 558.91 | CI88: 558.91 | CJ88: 558.91 | CK88: =SUM(BY88:CJ88) -> 6862.2406 | CM88: 558.91 | CN88: 558.91 | CO88: 558.91 | CP88: 558.91 | CQ88: 558.91 | CR88: 558.91 | CS88: 558.91 | CT88: 558.91 | CU88: 558.91 | CV88: 558.91 | CW88: 558.91 | CX88: 558.91 | CY88: =SUM(CM88:CX88) -> 6706.92 | CZ88: 558.91 | DA88: 558.91 | DB88: 558.91 | DC88: 558.91 | DD88: 558.91 | DE88: 558.91 | DF88: 558.91 | DG88: 558.91 | DH88: 558.91 | DI88: 558.91 | DJ88: 558.91 | DK88: 558.91 | DL88: =SUM(CZ88:DK88) -> 6706.92
B89: Laboral Agency | AB89: =SUM(P89:AA89) -> 0 | AK89: =SUM(AC89:AJ89) -> 0 | AX89: =SUM(AL89:AW89) -> 0 | BK89: =SUM(AY89:BJ89) -> 0 | BX89: =SUM(BL89:BW89) -> 0 | CK89: =SUM(BY89:CJ89) -> 0 | CY89: =SUM(CM89:CX89) -> 0 | DL89: =SUM(CZ89:DK89) -> 0
B90: Legal | D90: =72.6+14520 -> 14592.6 | E90: 302.5 | G90: 500 | O90: =SUM(C90:N90) -> 15395.1 | Q90: =423.5+181.5+423.5 -> 1028.5 | R90: 303 | S90: 75 | T90: =302.5+8470 -> 8772.5 | V90: 181.5 | AA90: 363 | AB90: =SUM(P90:AA90) -> 10723.5 | AF90: =377.12+376.34 -> 753.46 | AG90: =181.5+302.5+363 -> 847 | AH90: 363 | AK90: =SUM(AC90:AJ90) -> 1963.46 | AM90: 15.75 | AN90: 1644 | AO90: =3519.57*1.21+3500*1.21 -> 8493.6797 | AQ90: =895.42*1.21+(594.34+250+647.74-1644)+700+525 -> 2156.5382 | AU90: =810.4 -> 810.4 | AV90: 229.9 | AW90: 484 | AX90: =SUM(AL90:AW90) -> 13834.268 | BB90: =241.88+363 -> 604.88 | BC90: 302.5 | BF90: 242 | BG90: 605 | BK90: =SUM(AY90:BJ90) -> 1754.38 | BL90: =1575*1.21 -> 1905.75 | BO90: =133*1.21 -> 160.93 | BP90: 1427.13 | BQ90: =145.89+268.78+501.89 -> 916.56 | BR90: 307.91 | BX90: =SUM(BL90:BW90) -> 4718.28 | BZ90: =135.59+307.56+310.09+307.56 -> 1060.8 | CA90: 478.86 | CF90: =121 -> 121 | CI90: =514.57 -> 514.57 | CJ90: 700 | CK90: =SUM(BY90:CJ90) -> 2875.23 | CN90: 700 | CQ90: 700 | CT90: 700 | CW90: 700 | CY90: =SUM(CM90:CX90) -> 2800 | DA90: 700 | DD90: 700 | DG90: 700 | DJ90: 700 | DL90: =SUM(CZ90:DK90) -> 2800
B91: ISCC | AB91: =SUM(P91:AA91) -> 0 | AK91: =SUM(AC91:AJ91) -> 0 | AT91: =1800*1.21 -> 2178 | AU91: =2783 -> 2783 | AX91: =SUM(AL91:AW91) -> 4961 | BB91: =500*1.21 -> 605 | BG91: =2300*1.21 -> 2783 | BK91: =SUM(AY91:BJ91) -> 3388 | BX91: =SUM(BL91:BW91) -> 0 | CD91: =(1000+500+400+400)*1.21 -> 2783 | CH91: 2783 | CK91: =SUM(BZ91:CJ91) -> 5566 | CV91: 2783 | CY91: =SUM(CM91:CX91) -> 2783 | DI91: 2783 | DL91: =SUM(CZ91:DK91) -> 2783
B92: ICE | F92: 230 | G92: =F92 -> 230 | H92: =G92 -> 230 | I92: =H92 -> 230 | J92: =I92 -> 230 | K92: =J92 -> 230 | L92: =K92 -> 230 | N92: =M92 -> 0 | O92: =SUM(C92:N92) -> 1610 | X92: 3054.54 | AB92: =SUM(P92:AA92) -> 3054.54 | AK92: =SUM(AC92:AJ92) -> 0 | AM92: =3544/1.1759 -> 3013.8617 | AX92: =SUM(AL92:AW92) -> 3013.8617 | AZ92: =3738/1.1606 -> 3220.7479 | BK92: =SUM(AY92:BJ92) -> 3220.7479 | BM92: =3924/0.996 -> 3939.759 | BX92: =SUM(BL92:BW92) -> 3939.759 | CA92: =4179/1.0815 -> 3864.0777 | CK92: =SUM(BY92:CJ92) -> 3864.0777 | CN92: 4000 | CY92: =SUM(CM92:CX92) -> 4000 | DA92: 4000 | DL92: =SUM(CZ92:DK92) -> 4000
B93: OPIS + SCI + TRS + FO Licht + ISO+ARA Storage | E93: 2725.42 | O93: =SUM(C93:N93) -> 2725.42 | Q93: 993.37 | X93: =3432.03+1090.91 -> 4522.94 | AA93: =1085/1.109338895 -> 978.06 | AB93: =SUM(P93:AA93) -> 6494.37 | AH93: =1200/1.0792 -> 1111.9348 | AK93: =SUM(AC93:AJ93) -> 1111.9348 | AL93: =(3650+1280)/1.1626 -> 4240.4954 | AO93: =1830/1.21180015+(42-13.5-15) -> 1523.65 | AQ93: =(6000+36+18.03)/1.224046+2000/1.1748+15-(18.03+21)/1.224046 -> 6631.4484 | AU93: =1200/1.20499 -> 995.85889 | AV93: =3650/1.15876 -> 3149.9189 | AX93: =SUM(AL93:AW93) -> 16541.372 | AY93: =3410/1.1767 -> 2897.9349 | BD93: =8000/1.138449716 -> 7027.1 | BE93: 1265 | BH93: =1230/1.088 -> 1130.5147 | BI93: =3780/1.0192 -> 3708.7912 | BK93: =SUM(AY93:BJ93) -> 16029.341 | BN93: =3410/0.9907 -> 3442.0107 | BO93: 1265 | BR93: =8720/1.076 -> 8104.0892 | BU93: 0 | BX93: =SUM(BL93:BW93) -> 12811.1 | BY93: =1230/1.2451+375 -> 1362.8725 | CF93: =8720/1+17892/1 -> 26612 | CH93: 1230 | CI93: 1265 | CK93: =SUM(BY93:CJ93) -> 30469.872 | CO93: =1500 -> 1500 | CS93: =8200 -> 8200 | CV93: 1230 | CY93: =SUM(CM93:CX93) -> 10930 | DL93: =SUM(CZ93:DK93) -> 0
B94: AgriCensus (Fastmarkets) + European Gas Hub+Quantum | O94: =SUM(C94:N94) -> 0 | S94: 1600 | AB94: =SUM(P94:AA94) -> 1600 | AF94: 2000 | AK94: =SUM(AC94:AJ94) -> 2000 | AN94: 1500 | AT94: =2000+1500 -> 3500 | AX94: =SUM(AL94:AW94) -> 5000 | BC94: 240 | BG94: =975+975 -> 1950 | BK94: =SUM(AY94:BJ94) -> 2190 | BP94: 240 | BT94: =1062.75+1062.75 -> 2125.5 | BX94: =SUM(BL94:BW94) -> 2365.5 | CD94: 2000 | CG94: 2125.5 | CK94: =SUM(BY94:CJ94) -> 4125.5 | CR94: 2000 | CY94: =SUM(CM94:CX94) -> 2000 | DE94: 2000 | DL94: =SUM(CZ94:DK94) -> 2000
B95: IVA | O95: =SUM(C95:N95) -> 0 | P95: -17.85 | Q95: =-490.35+193.16 -> -297.19 | R95: =-225.34+3413.21 -> 3187.87 | T95: =-1928.22-131.25+1087.8+7.24 -> -964.43 | U95: -1274.7 | V95: =5273.77 -> 5273.77 | W95: -3895.02 | X95: =-2701.72 -> -2701.72 | Y95: =-1503.4 -> -1503.4 | Z95: 234.08 | AA95: =205.85+1293.82-3007.48-1133.47 -> -2641.28 | AB95: =SUM(P95:AA95) -> -4599.87 | AF95: =-1757.82 -> -1757.82 | AG95: =-6799.75-2599.73 -> -9399.48 | AH95: -149.04 | AI95: =5532.53-2503.41 -> 3029.12 | AK95: =SUM(AC95:AJ95) -> -8277.22 | AL95: -2820.73 | AM95: 10560.38 | AN95: -2793.64 | AO95: -6970.42 | AP95: -2563.85 | AQ95: 918.07 | AR95: 8180.2 | AT95: =2315.58+52.72 -> 2368.3 | AU95: =-17193.52+2754.41-282.76 -> -14721.87 | AV95: =9146.69+8383.86 -> 17530.55 | AW95: =-1344.4+6610.91+648.82 -> 5915.33 | AX95: =SUM(AL95:AW95) -> 15602.32 | BB95: =-(6963.8-157.2)+3034.69 -> -3771.91 | BC95: =-(5030.09-2625) -> -2405.09 | BD95: =-(5646.53-1642.54)+2576.05+1242.79 -> -185.15 | BE95: -237.37 | BF95: -4582.61 | BG95: =-4611.52+191.81+2175.68+1942.75 -> -301.28 | BH95: =-103.6 -> -103.6 | BJ95: =-2413.07 -> -2413.07 | BK95: =SUM(AY95:BJ95) -> -14000.08 | BL95: =-9203.26-13942.94-12337.68 -> -35483.88 | BN95: =(4778.21+3667.53+2428.27)+(-7312.8-60.11)-9926.25-10125.68 -> -16550.83 | BO95: =-11339.06+2935.11+6152.25+6954.88+6336.17 -> 11039.35 | BP95: =-9497.58 -> -9497.58 | BQ95: =-14834.8+2854.63+3706.36 -> -8273.81 | BR95: =-15472.99 -> -15472.99 | BT95: =(-19049.98+167.66) -> -18882.32 | BU95: =-5113.31-34410.49 -> -39523.8 | BV95: =-5799.9+607.72+8959.67+9212.5+2988.74 -> 15968.73 | BW95: =-31631.49+16403.48 -> -15228.01 | BX95: =SUM(BL95:BW95) -> -131905.14 | BZ95: =-10540.54 -> -10540.54 | CA95: =-5016.39-(4659.34-61.33) -> -9614.4 | CB95: -3628.38 | CC95: -8805.44 | CE95: -5831.05 | CF95: -4256.5 | CG95: -7846.44 | CH95: -4243.13 | CK95: =SUM(BZ95:CJ95) -> -54765.88 | CY95: =SUM(CM95:CX95) -> 0 | DL95: =SUM(CZ95:DK95) -> 0
B96: IRPF | O96: =SUM(C96:N96) -> 0 | S96: 2657.05 | V96: -2469.94 | Y96: =6053.41 -> 6053.41 | AB96: =SUM(P96:AA96) -> 6240.52 | AC96: 6893.49 | AG96: =7065.63 -> 7065.63 | AI96: 6864.49 | AK96: =SUM(AC96:AJ96) -> 20823.61 | AM96: 7143.48 | AP96: 5826.81 | AR96: =8429.64-5826.81 -> 2602.83 | AS96: =9854.3-703.46 -> 9150.84 | AV96: =10254.14 -> 10254.14 | AW96: =-823.92 -> -823.92 | AX96: =SUM(AL96:AW96) -> 34154.18 | AZ96: 10039.38 | BB96: -237.59 | BC96: 10792.67 | BD96: -1338.53 | BF96: 10200.62 | BG96: -789.8 | BI96: 12531.59 | BJ96: -385.47 | BK96: =SUM(AY96:BJ96) -> 40812.87 | BM96: 18046.59 | BN96: -5680.89 | BP96: 11632.67 | BQ96: =175.21-2015.57-175.21 -> -2015.57 | BS96: =12102.52 -> 12102.52 | BV96: =-1028.48+13140.02-1893.55 -> 10217.99 | BX96: =SUM(BL96:BW96) -> 44303.31 | BZ96: 11833.83 | CC96: =12418.39-(1.56+24) -> 12392.83 | CE96: 206.64 | CF96: =1650*3+2075*3+89.85*3 -> 11444.55 | CI96: =1650*3+2075*3+89.85*3 -> 11444.55 | CK96: =SUM(BY96:CJ96) -> 47322.4 | CN96: =1650*3+2075*3+89.85*3 -> 11444.55 | CQ96: =1650*3+2075*3+89.85*3 -> 11444.55 | CT96: =1650*3+2075*3+89.85*3 -> 11444.55 | CW96: =1650*3+2075*3+89.85*3 -> 11444.55 | CY96: =SUM(CM96:CX96) -> 45778.2 | DA96: =1650*3+2075*3+89.85*3 -> 11444.55 | DD96: =1650*3+2075*3+89.85*3 -> 11444.55 | DG96: =1650*3+2075*3+89.85*3 -> 11444.55 | DJ96: =1650*3+2075*3+89.85*3 -> 11444.55 | DL96: =SUM(CZ96:DK96) -> 45778.2
B97: IS | O97: =SUM(C97:N97) -> 0 | V97: =3095.49 -> 3095.49 | AA97: =557.19*2 -> 1114.38 | AB97: =SUM(P97:AA97) -> 4209.87 | AG97: =557.19 -> 557.19 | AI97: 14219.73 | AK97: =SUM(AC97:AJ97) -> 14776.92 | AM97: 2760.14 | AO97: 2760.14 | AS97: =-624.19 -> -624.19 | AX97: =SUM(AL97:AW97) -> 4896.09 | BE97: =32326.09-2760.14*2+734.65 -> 27540.46 | BF97: 5818.7 | BK97: =SUM(AY97:BJ97) -> 33359.16 | BM97: 5818.7 | BO97: 5818.7 | BR97: =(233541.66-5818.7*1)-29971.42 -> 197751.54 | BS97: 1008 | BU97: =(227071.42-197100)+143.44 -> 30114.86 | BX97: =SUM(BL97:BW97) -> 240511.8 | BZ97: 1008 | CB97: 1008 | CF97: =(-5818.7*2-1008)+4298.08 -> -8347.32 | CG97: =17192.3*0.18 -> 3094.614 | CH97: =(227071.42*0.18-1008-1008)*3*0 -> 0 | CK97: =SUM(BZ97:CJ97) -> -3236.706 | CN97: =17192.3*0.18 -> 3094.614 | CP97: =17192.3*0.18 -> 3094.614 | CS97: =-227071.42*0.18*2*0 -> 0 | CY97: =SUM(CN97:CX97) -> 6189.228 | DF97: =-227071.42*0.18*2*0 -> 0 | DL97: =SUM(DA97:DK97) -> 0
B98: Otros impuestos | C98: 64.65 | E98: -2551.29 | F98: -5597.55 | G98: =4000*0.21-1500*0.21 -> 525 | I98: =2500*0.21 -> 525 | J98: =2500*0.21 -> 525 | K98: =2500*0.21 -> 525 | L98: =2500*0.21 -> 525 | N98: -93.4 | O98: =SUM(C98:N98) -> -5552.59 | X98: =40.8 -> 40.8 | AB98: =SUM(P98:AA98) -> 40.8 | AH98: -76.64 | AK98: =SUM(AC98:AJ98) -> -76.64 | AQ98: =4.6+25 -> 29.6 | AX98: =SUM(AL98:AW98) -> 29.6 | BI98: =645.94+32.3 -> 678.24 | BK98: =SUM(AY98:BJ98) -> 678.24 | BN98: =613.64 -> 613.64 | BO98: 15.75 | BT98: 132.99 | BU98: =613.64 -> 613.64 | BX98: =SUM(BL98:BW98) -> 1376.02 | BZ98: =978+931.43 -> 1909.43 | CA98: =613.64 -> 613.64 | CH98: 613.64 | CK98: =SUM(BY98:CJ98) -> 3136.71 | CO98: =613.64 -> 613.64 | CT98: =645.94 -> 645.94 | CV98: 613.64 | CY98: =SUM(CM98:CX98) -> 1873.22 | DB98: 613.64 | DI98: 613.64 | DL98: =SUM(CZ98:DK98) -> 1227.28
B99: Gastos Bancarios y comisiones | C99: =6.09+3.95+5.91-3.95+0.67 -> 12.67 | D99: =70+0.67 -> 70.67 | E99: 0.79 | N99: -3.95 | O99: =SUM(C99:N99) -> 80.18 | P99: 12 | Q99: =12.1+3.95+3.95-12-12.1+50 -> 45.9 | R99: =-50-3.95-3.95 -> -57.9 | T99: 28.28 | V99: 77.6 | W99: =0.3+15+21.77 -> 37.07 | X99: =87.56-43.78-7.5-10.89 -> 25.39 | AB99: =SUM(P99:AA99) -> 168.34 | AC99: =1+25+7.5 -> 33.5 | AD99: =80+1 -> 81 | AE99: 78 | AF99: =250+20/1.0849+145.8/1.0849 -> 402.82515 | AG99: =77.6+1+72.9/1.0849+20.61/1.0905 -> 164.69472 | AH99: =0.3+52.29/1.0898+145.8/1.0975 -> 181.12866 | AI99: =80+20/1.0981 -> 98.213277 | AJ99: 145.09 | AK99: =SUM(AC99:AJ99) -> 1184.4518 | AL99: =-145.09+7 -> -138.09 | AM99: =4.78+1200+20/1.1094 -> 1222.8078 | AO99: =269.25 -> 269.25 | AP99: =80+25*4+220/1.225+403.18/1.2240464+145.8/1.1094 -> 820.39717 | AQ99: =-214/1.224046-(192.5+18.18)/1.224046-80-12.5*4 -> -476.94775 | AR99: =274.8/1.1338 -> 242.37079 | AS99: =14.4/1.224+7.39/1.2018+1.39+14.85+68.7/1.1338 -> 94.746513 | AT99: =15+15+7.41/1.20388+7.49/1.20499-7.5-7.5+5517.46/1.13377 -> 4893.843 | AU99: =1+2+(18.27/1.20499)+(65.57/1.20499)+(556.38/1.1539)+(30/1.1539)+30+(55/1.205) -> 656.39278 | AV99: =1+178.97+2.43+1200+(171.75/1.153899) -> 1531.2432 | AW99: =10.34+(34.35/1.153899) -> 40.108637 | AX99: =SUM(AL99:AW99) -> 9156.122 | AY99: =3+3+716.07/1.1539+673.17/1.1629+78.3+120 -> 1403.7368 | AZ99: =7.12/1.1637-120+24.88+12.13+31.33/1.1637 -> -49.948838 | BB99: =70-70+3+78.3+504.47 -> 585.77 | BC99: =12.28+30.45/1.1374 -> 39.051584 | BD99: =1+88.78 -> 89.78 | BE99: =1+4.43+88.92 -> 94.35 | BF99: =12.29+59.28+(832.3+173.64) -> 1077.51 | BG99: =238.84+1.63 -> 240.47 | BH99: =-(752.3+143.64)+225.51+15+0.91+28.85/1.0784 -> -627.7674 | BI99: =292.78+11.93+6.13+0.36+12 -> 323.2 | BJ99: =12+782.17 -> 794.17 | BK99: =SUM(AY99:BJ99) -> 3970.3222 | BL99: =-287.24+1.09+12 -> -274.15 | BM99: =16.53+12+11.89+26.77 -> 67.19 | BN99: =660.5+12+0.54 -> 673.04 | BO99: =112.21+27.91+12+0.36 -> 152.48 | BP99: =4.05+13.22+0.18+12 -> 29.45 | BQ99: =1.09+12 -> 13.09 | BR99: =26.61+12+762/1.075+762/1.0596 -> 1466.5865 | BS99: =0.73-0.73-1.09-0.18-0.36-0.54+12+100/1.0821 -> 102.2429 | BT99: =12 -> 12 | BU99: =27.72+12 -> 39.72 | BV99: =18.73+18.73+12 -> 49.46 | BW99: =12+63.26-63.26 -> 12 | BX99: =SUM(BL99:BW99) -> 2343.1094 | BY99: =12 -> 12 | BZ99: =12+48.59+349.54+95.95+52.82+48.43+73.95/1.0815 -> 675.70725 | CA99: =15.08+1051.8/1.0813+12 -> 999.79802 | CB99: 12 | CC99: =12+40+40+572.86/1.0866 -> 619.20412 | CD99: =12+90.34+66.31 -> 168.65 | CE99: =89.68+12 -> 101.68 | CG99: =-269.25 -> -269.25 | CK99: =SUM(CD99:CJ99) -> 1.08 | CY99: =SUM(CM99:CX99) -> 0 | DL99: =SUM(CZ99:DK99) -> 0
B100: Intereses prestamo ICO Caixa | AB100: =SUM(P100:AA100) -> 0 | AG100: =36.52 -> 36.52 | AH100: =123.75 -> 123.75 | AI100: =123.75 -> 123.75 | AJ100: =123.75 -> 123.75 | AK100: =SUM(AC100:AJ100) -> 407.77 | AL100: =123.75 -> 123.75 | AM100: =123.75 -> 123.75 | AN100: =123.75 -> 123.75 | AO100: =123.75 -> 123.75 | AP100: =123.75 -> 123.75 | AQ100: =123.75 -> 123.75 | AR100: =123.75 -> 123.75 | AS100: =123.75 -> 123.75 | ... AU100: =123.75 -> 123.75 | AV100: =AU148*0.015/12 -> 123.75 | AW100: =AV148*0.015/12 -> 123.75 | AX100: =SUM(AL100:AW100) -> 1485 | AY100: =AW148*0.015/12 -> 123.75 | AZ100: =AY148*0.015/12 -> 123.75 | BA100: =AZ148*0.015/12 -> 123.75 | BB100: =BA148*0.015/12 -> 123.75 | BC100: =BB148*0.015/12 -> 123.75 | BD100: =BC148*0.015/12 -> 123.75 | BE100: =BD148*0.015/12 -> 123.75 | BF100: =BE148*0.015/12 -> 123.75 | BG100: =BF148*0.015/12 -> 123.75 | ... BJ100: =BI148*0.015/12 -> 118.81292 | BK100: =SUM(AY100:BJ100) -> 1475.13 | BL100: =BJ148*0.015/12 -> 117.16311 | BM100: =BL148*0.015/12 -> 115.51124 | BN100: =BM148*0.015/12 -> 113.8573 | BO100: =BN148*0.015/12 -> 112.2013 | BP100: =BO148*0.015/12 -> 110.54322 | BQ100: =BP148*0.015/12 -> 108.88307 | BR100: =BQ148*0.015/12 -> 107.22085 | BS100: =BR148*0.015/12 -> 105.55655 | BT100: =BS148*0.015/12 -> 103.89017 | ... BW100: =BV148*0.015/12 -> 98.878525 | BX100: =SUM(BL100:BW100) -> 1296.4782 | BY100: =BW148*0.015/12 -> 97.2038 | BZ100: =BY148*0.015/12 -> 95.526975 | CA100: =BZ148*0.015/12 -> 93.848062 | CB100: =CA148*0.015/12 -> 92.16705 | CC100: =CB148*0.015/12 -> 90.483937 | CD100: =CC148*0.015/12 -> 88.798712 | CE100: =CD148*0.015/12 -> 87.111387 | CF100: =CE148*0.015/12 -> 85.42195 | CG100: =CF148*0.015/12 -> 83.7304 | ... CJ100: =CI148*0.015/12 -> 78.643062 | CK100: =SUM(BY100:CJ100) -> 1055.313 | CM100: =CJ100-2 -> 76.643062 | CN100: =CM100-2 -> 74.643062 | CO100: =CN100-2 -> 72.643062 | CP100: =CO100-2 -> 70.643062 | CQ100: =CP100-2 -> 68.643062 | CR100: =CQ100-2 -> 66.643062 | CS100: =CR100-2 -> 64.643062 | CT100: =CS100-2 -> 62.643062 | CU100: =CT100-2 -> 60.643062 | ... CX100: =CW100-2 -> 54.643062 | CY100: =SUM(CM100:CX100) -> 787.71675 | DL100: =SUM(CZ100:DK100) -> 0
B101: Intereses poliza credito Caixa | AB101: =SUM(P101:AA101) -> 0 | AG101: =33.33 -> 33.33 | AH101: =43.06 -> 43.06 | AI101: =41.67 -> 41.67 | AJ101: =43.06 -> 43.06 | AK101: =SUM(AC101:AJ101) -> 161.12 | AL101: =43.06 -> 43.06 | AM101: =41.67 -> 41.67 | AN101: =45.25 -> 45.25 | AO101: =41.67 -> 41.67 | AP101: =43.06 -> 43.06 | AQ101: =43.06 -> 43.06 | AR101: =38.89 -> 38.89 | AS101: =43.06 -> 43.06 | AX101: =SUM(AL101:AW101) -> 339.72 | BK101: =SUM(AY101:BJ101) -> 0 | BX101: =SUM(BL101:BW101) -> 0 | BZ101: =11.11 -> 11.11 | CC101: 255.56 | CK101: =SUM(BY101:CJ101) -> 266.67 | CY101: =SUM(CM101:CX101) -> 0 | DL101: =SUM(CZ101:DK101) -> 0
...

Sheet Resumen cierre
A3: Previsiones Caja | B3: Totales Agosto 2021 | C3: Totales Agosto 2022 | D3: Totales a cierre Febrero 2023 | E3: Totales a cierre Agosto 2023 | F3: diferencia
A4: Cobros
A5: MKT INTELIGENCE | B5: 0
A6: Alcodis | B6: 15000 | C6: 15000 | D6: 15000 | E6: 15000 | F6: =E6-D6 -> 0
A7: Bioagra | B7: 40000 | C7: 50000 | D7: 40000 | E7: 40000 | F7: =E7-D7 -> 0
A8: Verbio | B8: 39000 | C8: 39000 | D8: 15000 | E8: 15000 | F8: =E8-D8 -> 0
A9: Vertex | B9: 25000 | C9: 50000 | D9: 50000 | E9: 50000 | F9: =E9-D9 -> 0
A10: Shell | B10: 9000 | C10: 9000 | D10: 12000 | E10: 12000 | F10: =E10-D10 -> 0
A11: Ruhr | B11: 10000 | C11: 10000 | D11: 10000 | E11: 20500 | F11: =E11-D11 -> 10500
A12: Cremer | B12: 15000 | C12: 15000 | D12: 15000 | E12: 15000 | F12: =E12-D12 -> 0
A13: Lantmannen | B13: 10000 | C13: 10000 | D13: 12500 | E13: 12500 | F13: =E13-D13 -> 0
A14: Neste | B14: 6000 | C14: 18000 | D14: 12000 | E14: 12000 | F14: =E14-D14 -> 0
A15: Mabanaft | B15: 0 | C15: 0 | D15: 0 | E15: 0 | F15: =E15-D15 -> 0
A16: Sucden | B16: 0 | C16: 10000 | D16: 7500 | E16: 0 | F16: =E16-D16 -> -7500
A17: Roquette | B17: 0 | C17: 0 | D17: 0 | E17: 0 | F17: =E17-D17 -> 0
... A46: Harvestone Commodities, LLC | B46: 0 | C46: 0 | D46: 12272.448 | E46: 12272.448 | F46: =E46-D46 -> 0
A47: Almagest EAD | B47: 0 | C47: 0 | E47: 9000 | F47: =E47-D47 -> 9000
A48: AdHoc | E48: 0 | F48: =E48-D48 -> 0
A49: Dropet Intertrading | B49: 0 | C49: 0 | D49: 0 | E49: 0 | F49: =E49-D49 -> 0
A50: Repsol | B50: 0 | C50: 0 | D50: 0 | E50: 0 | F50: =E50-D50 -> 0
A51: Vertex | B51: 0 | C51: 0 | D51: 0 | E51: 0 | F51: =E51-D51 -> 0
A52: Cepsa | B52: 0 | C52: 0 | D52: 0 | E52: 0 | F52: =E52-D52 -> 0
A53: Guidepoint | B53: 0 | C53: 650 | D53: 0 | E53: 273.33 | F53: =E53-D53 -> 273.33
A54: DWS Alternatives Global Limited-PEIF | B54: 22290.5 | C54: 0 | D54: 0 | E54: 0 | F54: =E54-D54 -> 0
A55: Tomsa Destil, S.L. | B55: 2663.9723 | C55: 0 | D55: 0 | E55: 0 | F55: =E55-D55 -> 0
A56: BROKERAGE | E56: 0 | F56: =E56-D56 -> 0
A57: Enviral | B57: 0 | C57: 0 | D57: 0 | E57: 0 | F57: =E57-D57 -> 0
A58: Interalco | B58: 0 | C58: 0 | D58: 0 | E58: 0 | F58: =E58-D58 -> 0
A59: Murex | B59: 0 | C59: 0 | D59: 0 | E59: 0 | F59: =E59-D59 -> 0
A60: Seaboard | B60: 12492.713 | C60: 0 | D60: 0 | E60: 0 | F60: =E60-D60 -> 0
A61: Cremer | B61: 12781.648 | C61: 16839.811 | D61: 0 | E61: 0 | F61: =E61-D61 -> 0
A62: ACA Bio | B62: 11413.551 | C62: 6596.2788 | D62: 20735.37 | E62: 17403.518 | F62: =E62-D62 -> -3331.8521
A63: CCI - Castleton Commodities Int LLC | B63: 9617.835 | C63: 0 | D63: 0 | E63: 0 | F63: =E63-D63 -> 0
A64: Ruhr Petrol | B64: 12228.95 | C64: 40287.336 | D64: 0 | E64: 0 | F64: =E64-D64 -> 0
A65: Bioagra | B65: 2859 | C65: 0 | D65: 0 | E65: 0 | F65: =E65-D65 -> 0
A66: Czanikow | B66: 0 | C66: 143461.32 | D66: 60575.916 | E66: 40575.916 | F66: =E66-D66 -> -20000
A67: EDF Trading | C67: 0 | D67: 20000 | E67: 18511.139 | F67: =E67-D67 -> -1488.8607
A68: FUTUROS | E68: 0 | F68: =E68-D68 -> 0
A69: Paragon | B69: 77935.59 | C69: 1339426.1 | D69: -598605.73 | E69: -674077.45 | F69: =E69-D69 -> -75471.719
A70: FC Stone | B70: 0 | C70: 0 | D70: 0 | E70: 0 | F70: =E70-D70 -> 0
A71: VARIOS | C71: 0 | D71: 0 | E71: 0 | F71: =E71-D71 -> 0
A72: Total Cobros | B72: 556158.73 | C72: 2075972.4 | D72: 85459.901 | E72: -9109.6324 | F72: =E72-D72 -> -94569.534
B73: 0 | C73: 0 | D73: 0 | E73: 0 | F73: =E73-D73 -> 0
A74: Pagos | E74: 0 | F74: =E74-D74 -> 0
A75: GENERALES | E75: 0 | F75: =E75-D75 -> 0
A76: Conferencia Dropet | B76: 0 | C76: 1113.2 | D76: 1149.5 | E76: 1149.5 | F76: =E76-D76 -> 0
A77: Compras inmobilizado | B77: 1188.4388 | C77: 6323.307 | D77: 837.817 | E77: 897.344 | F77: =E77-D77 -> 59.527
A78: Suministros informáticos y mantenimiento | B78: 0 | C78: 0 | D78: 23.39 | E78: 327.57 | F78: =E78-D78 -> 304.18
A79: Trips/commercial expenses | B79: 2480.98 | C79: 16545.18 | D79: 12414.54 | E79: 17391.3 | F79: =E79-D79 -> 4976.76
A80: Personnel - Felipe Fontes | B80: 3536 | C80: 4540 | D80: 6100 | E80: 6100 | F80: =E80-D80 -> 0
A81: Personnel - Alfonso Carmona Bosch | B81: 45409.52 | C81: 53650.06 | D81: 47574.95 | E81: 47574.95 | F81: =E81-D81 -> 0
A82: Personnel - Alberto Carmona | B82: 139920 | C82: 139920 | D82: 139920 | E82: 139920 | F82: =E82-D82 -> 0
A83: Personnel - Rosa Jiménez | B83: 4266.66 | C83: 9600 | D83: 12480 | E83: 12000 | F83: =E83-D83 -> -480
A84: Personnel - María Lacañina | B84: 2978.06 | C84: 0 | D84: 0 | E84: 0 | F84: =E84-D84 -> 0
A85: Soc. Security | B85: 10441.27 | C85: 11415.86 | D85: 11508.34 | E85: 12704.64 | F85: =E85-D85 -> 1196.3
A86: Fiscal, Accounting | B86: 3063.6163 | C86: 6848.3295 | D86: 6659.2866 | E86: 7213.134 | F86: =E86-D86 -> 553.8474
A87: Human Resources | B87: 556.6 | C87: 0 | D87: 0 | E87: 0 | F87: =E87-D87 -> 0
... A110: Seguro Allianz Vida Alberto- Leasing coche | B110: 0 | C110: 393.95 | D110: 393.95 | E110: 393.95 | F110: =E110-D110 -> 0
A111: Seguro Allianz Vida Alfonso- Póliza crédito | C111: 0 | D111: 0 | E111: 393.95 | F111: =E111-D111 -> 393.95
A112: Seguro Vida Caixa Alfonso- Préstamo Reforestación | B112: 0 | C112: 182.64 | D112: 103.2 | E112: 103.2 | F112: =E112-D112 -> 0
A113: Iberica Feeding Stuff | B113: 0 | C113: 0 | D113: 0 | E113: 0 | F113: =E113-D113 -> 0
A114: Safinco- Comunidad y agua Rep. Argentina | B114: 0 | C114: 6150.41 | D114: 6276.1 | E114: 6476.28 | F114: =E114-D114 -> 200.18
A115: Electricidad- Total Energies | B115: 0 | C115: 1108.57 | D115: 2522.78 | E115: 2192.76 | F115: =E115-D115 -> -330.02
A116: Gastos reforma Rep. Argentina 11 | B116: 0 | C116: 6317.84 | D116: 15468.6 | E116: 22115.62 | F116: =E116-D116 -> 6647.02
A117: Otros | B117: 75107.548 | C117: 31365.172 | D117: 11724.92 | E117: 11725.83 | F117: =E117-D117 -> 0.91
A118: Alberto | B118: 4112.03 | C118: 0 | D118: 0 | E118: 0 | F118: =E118-D118 -> 0
E119: 0 | F119: =E119-D119 -> 0
A120: Total Pagos | B120: 409901.81 | C120: 405459.71 | D120: 565262.09 | E120: 492650.51 | F120: =E120-D120 -> -72611.585
E121: 0 | F121: =E121-D121 -> 0
A122: Saldo inicial | B122: 313984.05 | C122: 460240.97 | D122: 2130753.7 | E122: 2130753.7 | F122: =E122-D122 -> 0
A123: Cobros | B123: 556158.73 | C123: 2075972.4 | D123: 85459.901 | E123: -9109.6324 | F123: =E123-D123 -> -94569.534
A124: Pagos | B124: -409901.81 | C124: -405459.71 | D124: -565285.48 | E124: -492650.51 | F124: =E124-D124 -> 72634.975
A125: Saldo final actividad | B125: 460240.97 | C125: 2130753.7 | D125: 1650928.1 | E125: 1628993.5 | F125: =E125-D125 -> -21934.559
A126: Ratio generación caja | F126: =E126-D126 -> 0
F127: =E127-D127 -> 0
A128: Inversiones | F128: =E128-D128 -> 0
A129: Inmueble República Argentina | F129: =E129-D129 -> 0
A130: Coche Land Rover | F130: =E130-D130 -> 0
A131: Compra de Vivienda | F131: =E131-D131 -> 0
A132: Saldo tesorería de inversiones | B132: 709000 | C132: 790708.86 | D132: 1024840.8 | E132: 1025370.6 | F132: =E132-D132 -> 529.81045
F133: =E133-D133 -> 0
A134: Préstamos | F134: =E134-D134 -> 0
A135: Hipotecario Rep. Argentina 11 | F135: =E135-D135 -> 0
A136: Movimiento mensual | F136: =E136-D136 -> 0
A137: Saldo | B137: 398080.67 | C137: 374807.76 | D137: 351084.07 | E137: 351084.07 | F137: =E137-D137 -> 0
A138: Circulante Caixa | F138: =E138-D138 -> 0
A139: Movimiento mensual | F139: =E139-D139 -> 0
A140: Saldo | B140: 99000 | C140: 93730.49 | D140: 77763.04 | E140: 77763.04 | F140: =E140-D140 -> 0
A141: Circulante BBVA | F141: =E141-D141 -> 0
A142: Movimiento mensual | F142: =E142-D142 -> 0
A143: Saldo | D143: 0 | E143: 73633.43 | F143: =E143-D143 -> 73633.43
A144: Trade Industrial | E144: 0 | F144: =E144-D144 -> 0
A145: Movimiento mensual | E145: 0 | F145: =E145-D145 -> 0
A146: Saldo | B146: -12271.254 | C146: 106983.28 | D146: 106983.28 | E146: 106983.28 | F146: =E146-D146 -> 0
A147: Molino Don Zoilo | F147: =E147-D147 -> 0
A148: Movimiento mensual | F148: =E148-D148 -> 0
A149: Saldo | B149: -199346.53 | C149: -590092.27 | D149: -1110552.3 | E149: -1277795.8 | F149: =E149-D149 -> -167243.54
A150: Nixal Agri | F150: =E150-D150 -> 0
A151: Movimiento mensual | F151: =E151-D151 -> 0
A152: Saldo | B152: -3000 | C152: -3500 | D152: -3500 | E152: -7500 | F152: =E152-D152 -> -4000
...

Sheet Clientes
B2: Client | C2: Eur/year | D2: EUR/USD | E2: Duration (yrs) | F2: Begins | G2: Ends | I2: Comments
B3: Alcodis | C3: 16000 | D3: EUR | E3: 1 | F3: 46023 | G3: =F3+365 -> 46388 | L3: Stocks ARA | M3: 17982 | N3: 19144.44 | O3: 20484.55 | P3: =+O3/1.18 -> 17359.788
B4: Bioagra | C4: 41500 | D4: EUR | E4: 2 | F4: 46023 | G4: =F4+365+364 -> 46752 | I4: +4,2k stocks ARA | L4: Per user | M4: =+M3/4 -> 4495.5 | N4: =+N3/4 -> 4786.11 | O4: =+O3/4 -> 5121.1375 | P4: =+P3/4 -> 4339.947
B5: Verbio | C5: 16000 | D5: EUR | E5: 1 | F5: 46023 | G5: =F5+364 -> 46387 | I5: +4,2k stocks ARA | L5: Bioagra | M5: =+M4 -> 4495.5 | N5: =+N4 -> 4786.11 | O5: =+O4 -> 5121.1375 | P5: =+P4 -> 4339.947
B6: Vertex | C6: 50000 | D6: EUR | E6: 1 | F6: 46388 | G6: =F6+364 -> 46752 | I6: 2 invoices of 25000 +4,5k stocks ARA | L6: Verbio | M6: =+M5 -> 4495.5 | N6: =+N5 -> 4786.11 | O6: =+O5 -> 5121.1375 | P6: =+P5 -> 4339.947
B7: Shell | C7: 13000 | D7: EUR | E7: 1 | F7: 45809 | G7: =F7+364 -> 46173 | I7: 2 invoices of 6000 | J7: Enviado email | L7: Panonnia | M7: =+M6 -> 4495.5 | N7: =+N6 -> 4786.11 | O7: =+O6 -> 5121.1375 | P7: =+P6 -> 4339.947
B8: Ruhr | C8: 9000 | D8: EUR | E8: 1 | F8: 45870 | G8: =F8+364 -> 46234 | L8: Vertex | M8: =+M7 -> 4495.5 | N8: =+N7 -> 4786.11 | O8: =+O7 -> 5121.1375 | P8: =+P7 -> 4339.947
B9: CREMER | C9: 0 | D9: EUR | E9: 0 | I9: Dejaron el desk de etanol | L9: Sucden | M9: =+M8 -> 4495.5 | N9: =+N8 -> 4786.11 | O9: =+O8 -> 5121.1375 | P9: =+P8 -> 4339.947
B10: Lantmannen | C10: 12000 | D10: EUR | E10: 1 | F10: 46023 | G10: =F10+364 -> 46387 | L10: Total | M10: =SUM(M5:M9) -> 22477.5 | N10: =SUM(N5:N9) -> 23930.55 | O10: =SUM(O5:O9) -> 25605.688 | P10: =SUM(P5:P9) -> 21699.735
B11: Neste Oil | C11: 0 | D11: EUR | E11: 0 | I11: Dejaron el desk de etanol
B12: Mabanaft | C12: 0 | D12: EUR | E12: 0 | I12: Dejaron el desk de etanol
B13: Sucden | C13: 5500 | D13: EUR | E13: 2 | F13: 45748 | G13: =F13+365 -> 46113 | I13: +4,2k stock ARA
B14: Roquette | C14: =12500*0 -> 0 | D14: EUR | E14: 2 | I14: Me comunicaron baja el 26/11/20 para probar FO Licht
B15: Agrana | C15: =+(12500+11500)/2 -> 12000 | D15: EUR | E15: 2 | F15: 45717 | G15: =F15+(365*2) -> 46447
B16: Repsol | C16: =16500*0 -> 0 | D16: EUR | I16: Baja 4/2/25
B17: Enviral | C17: 16975 | D17: EUR | E17: 3 | F17: 45566 | G17: =F17+(365*E17) -> 46661
B18: SCA | C18: 8500 | D18: USD | E18: 1 | F18: 45748 | G18: =F18+364 -> 46112
B19: Varo | C19: 15000 | D19: EUR | E19: 2 | F19: 45505 | G19: =+F19+(365*2) -> 46235
B20: Amerra-RAA | C20: 42000 | D20: USD | E20: 2 | F20: 45383 | G20: =F20+(365*2) -> 46113 | I20: 2 invoices/year
B21: Vivergo | C21: 14000 | D21: EUR | E21: 2 | F21: 45809 | G21: =F21+364 -> 46173
B22: NEOT | C22: 12600 | D22: EUR | E22: 2 | F22: 45809 | G22: =F22+364 -> 46173
B23: Panonnia | C23: 14000 | D23: EUR | E23: 1 | F23: 45931 | G23: =F23+364 -> 46295 | I23: +4,2k stocks ARA
B24: Marquis | C24: 11000 | D24: USD | E24: 3 | F24: 45931 | G24: =F24+364*3 -> 47023 | I24: 3 year gentelmen agreement
B25: Cristal Union | C25: 12500 | D25: EUR | E25: 1 | F25: 45931 | G25: =F25+364 -> 46295
B26: Greenergy | C26: 14000 | D26: EUR | E26: 1 | F26: 46023 | G26: =F26+364 -> 46387
B27: Redwood | D27: USD | E27: 0
B28: Nordzucker | C28: 6000 | D28: EUR | E28: 1 | F28: 46023 | G28: =F28+364 -> 46387
A29: ok | B29: Raizen | C29: 16500 | D29: USD | E29: 1 | F29: 45658 | G29: =F29+364 -> 46022 | I29: Facturar en abril
B30: CCI | C30: =8000*0 -> 0 | D30: USD | E30: 0
B31: OCI | C31: 16500 | D31: EUR | E31: 1 | F31: 45839 | G31: =F31+364 -> 46203
B32: Poet | C32: 16000 | D32: USD | E32: 1 | F32: 46023 | G32: =F32+364 -> 46387
B33: OMV | C33: 16500 | D33: EUR | E33: 2 | F33: 46023 | G33: =+F33+364 -> 46387 | K33: =12+7 -> 19
B34: TOTSA | C34: 24480 | D34: EUR | E34: 1 | F34: 46023 | G34: =+F34+364 -> 46387 | K34: 15000 | L34: =+K34/12 -> 1250
B35: Trafigura | C35: 16200 | D35: EUR | E35: 1 | F35: 45931 | G35: =+F35+364 -> 46295 | L35: =+L34*19 -> 23750
B36: Ethanol Energy | C36: =10000*0 -> 0 | D36: EUR | E36: 3
B37: Pantaleon | C37: =12000*0 -> 0 | D37: USD | E37: 1 | I37: Baja feb 26
B38: KWST | C38: =4000*0 -> 0 | D38: EUR | E38: 0 | I38: Baja
B39: EDF | D39: EUR | E39: 1 | I39: Baja, salen de etnaol
B40: Liquin | C40: 8000 | D40: EUR | E40: 3 | F40: 45809 | G40: =+F40+365+365+365 -> 46904 | I40: three year agreement
B41: Harvestone | C41: 15000 | D41: USD | E41: 1 | F41: 45931 | G41: =+F41+364 -> 46295
B42: Greenfield | C42: 12800 | D42: USD | E42: 1 | F42: 46023 | G42: =+F42+364 -> 46387
B43: Cargill | C43: 16500 | D43: EUR | E43: 1 | F43: 45809 | G43: =+F43+364 -> 46173
A44: ok | B44: Lyondell | C44: 15000 | D44: USD | E44: 3 | F44: 44927 | G44: =+F44+365*3 -> 46022
B45: US Grains Council | C45: =5310*12 -> 63720 | D45: USD | E45: 1 | F45: 46023 | G45: =+F45+364 -> 46387
B46: Almagest | C46: 9000 | D46: EUR | E46: 1 | F46: 45809 | G46: =+F46+364 -> 46173
B47: Ipiranga | C47: =15000*0 -> 0 | D47: USD | E47: 1 | H47: Baja ene-26
B48: Atvos | C48: 24000 | D48: USD | E48: 1 | F48: 45962 | G48: =+F48+364 -> 46326
B49: Kolmar | C49: 16500 | D49: USD | E49: 1 | F49: 45992 | G49: =+F49+364 -> 46356
A50: ok | B50: ACA Bio | C50: 20000 | D50: USD | E50: 1 | F50: 45658 | G50: =+F50+364 -> 46022
A51: ok | B51: Tricon | C51: 8000 | D51: USD | E51: 1 | F51: 46143 | G51: =+F51+364 -> 46507
B52: Gapuma | C52: 10300 | D52: USD | E52: 1 | F52: 46082 | G52: =+F52+364 -> 46446
B53: Targray | C53: =24000*0 -> 0 | D53: EUR | E53: 0 | F53: 45748 | G53: =+F53+364 -> 46112 | H53: Baja
B54: ADNOC | C54: 25000 | D54: EUR | E54: 1 | F54: 46174 | G54: =+F54+364 -> 46538
B55: Inpasa | C55: 10000 | D55: USD | E55: 3 | F55: 45931 | G55: 47026 | I55: 8+10+12
B56: Bunge | C56: 16500 | D56: EUR | E56: 1 | F56: 46023 | G56: =+F56+364 -> 46387
B57: Total Mkt. Intel | C57: =SUM(C3:C56) -> 718075
B58: Fee medio | C58: =AVERAGE(C3:C8,C10,C13,C15,C17:C26,C28:C29,C31:C35,C40:C46,C48:C52,C54:C56) -> 17514.024
B61: Prospects
B62: Biourja | C62: Tienen que responder | E62: LDC
B63: Ciasa | C63: Volver a tocar | E63: Tereos
E64: Mercuria (AValerio)
E65: Cepsa
B66: Alesat | C66: Volver a tocar | E66: Danny Wilson
B67: Nestle | C67: Volver a tocar | E67: Adecoagro
E68: Murex
B69: Cofco | C69: Volver a tocar | E69: Biosev
B70: Bioagencia | C70: Volver a tocar | E70: Atvos
B71: Valero | C71: Volver a tocar | E71: Bevap | F71: Gabriel, Leandro
B72: Lyondell | C72: Volver a tocar | E72: Vale do Tijuco | F72: Marcelo Bosquetti
B73: GPRE | C73: Volver a tocar | E73: Petrochina
B74: Rosneft | C74: Volver a tocar | E74: Usina Diana
B75: Coper | C75: Volver a tocar | E75: Coruripe
B76: BP | C76: No | E76: Pantaleon
E77: Grupo Lyra (Laryssa)
B78: MOL Group Hungary | C78: molgroup.info/en | E78: Grupo Moreno
B79: Colegas de Andrea Valerio | E79: Impacto
B80: Gran Bio | E80: Caña Brava
B81: Growth Energy
B82: Mitsui | E82: Maple (Avalerio)
B83: Antimo | C83: Brendan Reich | E83: Hearttree
B84: Exxon Europe
B85: Vitol | E85: Caña Brava
B86: Helpe | C86: Fountoukakis George <GFountoukakis@helpe.gr>
B87: Prio/Disa | E87: Kurana
B88: GALP

Sheet Consolidado
C1: 2023/2024 | P1: 2024/2025 | AC1: 2025/2026 | AP1: 2026/2027
C2: Sep | D2: Oct | E2: Nov | F2: Dic | G2: Ene | H2: Feb | I2: Mar | J2: Abr | K2: May | L2: Jun | M2: Jul | N2: Ago | O2: Totales | P2: Sep | Q2: Oct | R2: Nov | S2: Dic | T2: Ene | U2: Feb | V2: Mar | W2: Abr | X2: May | Y2: Jun | Z2: Jul | AA2: Ago | AB2: Totales | AC2: Sep | AD2: Oct | AE2: Nov | AF2: Dic | AG2: Ene | AH2: Feb | AI2: Mar | AJ2: Abr | AK2: May | AL2: Jun | AM2: Jul | AN2: Ago | AO2: Totales | AQ2: Sep | AR2: Oct | AS2: Nov | AT2: Dic | AU2: Ene | AV2: Feb | AW2: Mar | AX2: Abr | AY2: May | AZ2: Jun | BA2: Jul | BB2: Ago | BC2: Totales
B3: Market Intel
B4: Cobros | C4: ='NC-Ingresos'!BY4 -> 32688.786 | D4: ='NC-Ingresos'!BZ4 -> 79900.912 | E4: ='NC-Ingresos'!CA4 -> 42825.233 | F4: ='NC-Ingresos'!CB4 -> 43500 | G4: ='NC-Ingresos'!CC4 -> 79921.479 | H4: ='NC-Ingresos'!CD4 -> 63280.333 | I4: ='NC-Ingresos'!CE4 -> 4535.4389 | J4: ='NC-Ingresos'!CF4 -> 45892.355 | ... N4: ='NC-Ingresos'!CJ4 -> 137858.48 | O4: =SUM(C4:N4) -> 814797.21 | P4: ='NC-Ingresos'!CL4 -> 65669.891 | Q4: ='NC-Ingresos'!CM4 -> 52521.327 | R4: ='NC-Ingresos'!CN4 -> 72545.538 | S4: ='NC-Ingresos'!CO4 -> 44296.859 | T4: ='NC-Ingresos'!CP4 -> 69295.907 | U4: ='NC-Ingresos'!CQ4 -> 188415.03 | V4: ='NC-Ingresos'!CR4 -> 49942.355 | W4: ='NC-Ingresos'!CS4 -> 40241.074 | ... AA4: ='NC-Ingresos'!CW4 -> 30794.444 | AB4: =SUM(P4:AA4) -> 738450.23 | AC4: ='NC-Ingresos'!CY4 -> -15753.245 | AD4: ='NC-Ingresos'!CZ4 -> 36809.702 | AE4: ='NC-Ingresos'!DA4 -> 0 | AF4: ='NC-Ingresos'!DB4 -> 89440.957 | AG4: ='NC-Ingresos'!DC4 -> 36250 | AH4: ='NC-Ingresos'!DD4 -> 55522.949 | AI4: ='NC-Ingresos'!DE4 -> 154869.3 | AJ4: ='NC-Ingresos'!DF4 -> 94488.449 | ... AN4: ='NC-Ingresos'!DJ4 -> 70413.043 | AO4: =SUM(AC4:AN4) -> 1270184 | BC4: =SUM(AQ4:BB4) -> 0
B5: Pagos | C5: ='NC-Gastos'!BY4 -> -23699.643 | D5: ='NC-Gastos'!BZ4 -> -30997.521 | E5: ='NC-Gastos'!CA4 -> -22310.456 | F5: ='NC-Gastos'!CB4 -> -26586.3 | G5: ='NC-Gastos'!CC4 -> -31002.274 | H5: ='NC-Gastos'!CD4 -> -28669.79 | I5: ='NC-Gastos'!CE4 -> -20654.817 | J5: ='NC-Gastos'!CF4 -> -51836.615 | ... N5: ='NC-Gastos'!CJ4 -> -12182.062 | O5: =SUM(C5:N5) -> -332701.61 | P5: ='NC-Gastos'!CL4 -> -22854.57 | Q5: ='NC-Gastos'!CM4 -> -34992.039 | R5: ='NC-Gastos'!CN4 -> -23939.43 | S5: ='NC-Gastos'!CO4 -> -35201.759 | T5: ='NC-Gastos'!CP4 -> -33433.966 | U5: ='NC-Gastos'!CQ4 -> -29391.933 | V5: ='NC-Gastos'!CR4 -> -137630.53 | W5: ='NC-Gastos'!CS4 -> -52016.841 | ... AA5: ='NC-Gastos'!CW4 -> -16586.721 | AB5: =SUM(P5:AA5) -> -490512.8 | AC5: ='NC-Gastos'!CY4 -> -23713.066 | AD5: ='NC-Gastos'!CZ4 -> -60304.337 | AE5: ='NC-Gastos'!DA4 -> -48794.061 | AF5: ='NC-Gastos'!DB4 -> -42438.267 | AG5: ='NC-Gastos'!DC4 -> -45005.811 | AH5: ='NC-Gastos'!DD4 -> -29697.276 | AI5: ='NC-Gastos'!DE4 -> -152955.11 | AJ5: ='NC-Gastos'!DF4 -> -66634.43 | ... AN5: ='NC-Gastos'!DJ4 -> -23288.56 | AO5: =SUM(AC5:AN5) -> -585688.64 | BC5: =SUM(AQ5:BB5) -> 0
B7: Caja Operaciones (mes) | C7: =SUM(C4:C5) -> 8989.1425 | D7: =SUM(D4:D5) -> 48903.391 | E7: =SUM(E4:E5) -> 20514.777 | F7: =SUM(F4:F5) -> 16913.7 | G7: =SUM(G4:G5) -> 48919.205 | H7: =SUM(H4:H5) -> 34610.543 | I7: =SUM(I4:I5) -> -16119.378 | J7: =SUM(J4:J5) -> -5944.2596 | ... N7: =SUM(N4:N5) -> 125676.42 | P7: =SUM(P4:P5) -> 42815.321 | Q7: =SUM(Q4:Q5) -> 17529.289 | R7: =SUM(R4:R5) -> 48606.108 | S7: =SUM(S4:S5) -> 9095.1007 | T7: =SUM(T4:T5) -> 35861.941 | U7: =SUM(U4:U5) -> 159023.09 | V7: =SUM(V4:V5) -> -87688.17 | W7: =SUM(W4:W5) -> -11775.767 | ... AA7: =SUM(AA4:AA5) -> 14207.723 | AC7: =SUM(AC4:AC5) -> -39466.311 | AD7: =SUM(AD4:AD5) -> -23494.635 | AE7: =SUM(AE4:AE5) -> -48794.061 | AF7: =SUM(AF4:AF5) -> 47002.69 | AG7: =SUM(AG4:AG5) -> -8755.8109 | AH7: =SUM(AH4:AH5) -> 25825.673 | AI7: =SUM(AI4:AI5) -> 1914.185 | AJ7: =SUM(AJ4:AJ5) -> 27854.019 | ... AN7: =SUM(AN4:AN5) -> 47124.483
B8: Caja Operaciones (acum.) | C8: =+C7 -> 8989.1425 | D8: =+D7+C8 -> 57892.533 | E8: =+E7+D8 -> 78407.311 | F8: =+F7+E8 -> 95321.011 | G8: =+G7+F8 -> 144240.22 | H8: =+H7+G8 -> 178850.76 | I8: =+I7+H8 -> 162731.38 | J8: =+J7+I8 -> 156787.12 | K8: =+K7+J8 -> 244312.34 | ... N8: =+N7+M8 -> 482095.61 | O8: =SUM(O4:O5) -> 482095.61 | P8: =+P7 -> 42815.321 | Q8: =+Q7+P8 -> 60344.609 | R8: =+R7+Q8 -> 108950.72 | S8: =+S7+R8 -> 118045.82 | T8: =+T7+S8 -> 153907.76 | U8: =+U7+T8 -> 312930.85 | V8: =+V7+U8 -> 225242.68 | W8: =+W7+V8 -> 213466.92 | X8: =+X7+W8 -> 293958.95 | ... AA8: =+AA7+Z8 -> 247937.43 | AB8: =SUM(AB4:AB5) -> 247937.43 | AC8: =+AC7 -> -39466.311 | AD8: =+AD7+AC8 -> -62960.945 | AE8: =+AE7+AD8 -> -111755.01 | AF8: =+AF7+AE8 -> -64752.316 | AG8: =+AG7+AF8 -> -73508.127 | AH8: =+AH7+AG8 -> -47682.453 | AI8: =+AI7+AH8 -> -45768.268 | AJ8: =+AJ7+AI8 -> -17914.249 | AK8: =+AK7+AJ8 -> 214708.49 | ... AN8: =+AN7+AM8 -> 684495.4 | AO8: =SUM(AO4:AO5) -> 684495.4 | BC8: =SUM(BC4:BC5) -> 0
B9: Trade
B10: Cobros | P10: ='Trade-Ingresos'!CL4 -> 0 | Q10: ='Trade-Ingresos'!CM4 -> 0 | R10: ='Trade-Ingresos'!CN4 -> 0 | S10: ='Trade-Ingresos'!CO4 -> 0 | T10: ='Trade-Ingresos'!CP4 -> 526295.29 | U10: ='Trade-Ingresos'!CQ4 -> 522419.65 | V10: ='Trade-Ingresos'!CR4 -> 778499.08 | W10: ='Trade-Ingresos'!CS4 -> 858221.62 | ... AA10: ='Trade-Ingresos'!CW4 -> 1179404.7 | AB10: =SUM(P10:AA10) -> 4937026.5 | AC10: ='Trade-Ingresos'!CY4 -> -1072186.1 | AD10: ='Trade-Ingresos'!CZ4 -> 0 | AE10: ='Trade-Ingresos'!DA4 -> 1579475 | AF10: ='Trade-Ingresos'!DB4 -> 233842.26 | AG10: ='Trade-Ingresos'!DC4 -> 0 | AH10: ='Trade-Ingresos'!DD4 -> 144590.8 | AI10: ='Trade-Ingresos'!DE4 -> 115667.94 | AJ10: ='Trade-Ingresos'!DF4 -> 145805.28 | ... AN10: ='Trade-Ingresos'!DJ4 -> 117500 | AO10: =SUM(AC10:AN10) -> 1639175.7 | BC10: =SUM(AQ10:BB10) -> 0
B11: Pagos | P11: ='Trade-Gastos'!CL4 -> 0 | Q11: ='Trade-Gastos'!CM4 -> 0 | R11: ='Trade-Gastos'!CN4 -> 0 | S11: ='Trade-Gastos'!CO4 -> 0 | T11: ='Trade-Gastos'!CP4 -> -428417.06 | U11: ='Trade-Gastos'!CQ4 -> -543680.83 | V11: ='Trade-Gastos'!CR4 -> -673063.94 | W11: ='Trade-Gastos'!CS4 -> -858753.21 | ... AA11: ='Trade-Gastos'!CW4 -> 0 | AB11: =SUM(P11:AA11) -> -3562884.4 | AC11: ='Trade-Gastos'!CY4 -> -38943.928 | AD11: ='Trade-Gastos'!CZ4 -> -99846.014 | AE11: ='Trade-Gastos'!DA4 -> -528142.27 | AF11: ='Trade-Gastos'!DB4 -> -909159.54 | AG11: ='Trade-Gastos'!DC4 -> -143699.33 | AH11: ='Trade-Gastos'!DD4 -> -28304.34 | AI11: ='Trade-Gastos'!DE4 -> -168310.1 | AJ11: ='Trade-Gastos'!DF4 -> -112846.32 | ... AN11: ='Trade-Gastos'!DJ4 -> -114000 | AO11: =SUM(AC11:AN11) -> -2620199.5 | BC11: =SUM(AQ11:BB11) -> 0
B13: Caja Operaciones (mes) | P13: =SUM(P10:P11) -> 0 | Q13: =SUM(Q10:Q11) -> 0 | R13: =SUM(R10:R11) -> 0 | S13: =SUM(S10:S11) -> 0 | T13: =SUM(T10:T11) -> 97878.23 | U13: =SUM(U10:U11) -> -21261.176 | V13: =SUM(V10:V11) -> 105435.14 | W13: =SUM(W10:W11) -> -531.5858 | ... AA13: =SUM(AA10:AA11) -> 1179404.7 | AC13: =SUM(AC10:AC11) -> -1111130 | AD13: =SUM(AD10:AD11) -> -99846.014 | AE13: =SUM(AE10:AE11) -> 1051332.8 | AF13: =SUM(AF10:AF11) -> -675317.29 | AG13: =SUM(AG10:AG11) -> -143699.33 | AH13: =SUM(AH10:AH11) -> 116286.46 | AI13: =SUM(AI10:AI11) -> -52642.156 | AJ13: =SUM(AJ10:AJ11) -> 32958.96 | ... AN13: =SUM(AN10:AN11) -> 3500
B14: Caja Operaciones (acum.) | P14: =+P13+O14 -> 0 | Q14: =+Q13+P14 -> 0 | R14: =+R13+Q14 -> 0 | S14: =+S13+R14 -> 0 | T14: =+T13+S14 -> 97878.23 | U14: =+U13+T14 -> 76617.054 | V14: =+V13+U14 -> 182052.2 | W14: =+W13+V14 -> 181520.61 | ... AA14: =+AA13+Z14 -> 1374142.1 | AB14: =SUM(AB10:AB11) -> 1374142.1 | AC14: =+AC13 -> -1111130 | AD14: =+AD13+AC14 -> -1210976 | AE14: =+AE13+AD14 -> -159643.27 | AF14: =+AF13+AE14 -> -834960.56 | AG14: =+AG13+AF14 -> -978659.88 | AH14: =+AH13+AG14 -> -862373.42 | AI14: =+AI13+AH14 -> -915015.58 | AJ14: =+AJ13+AI14 -> -882056.62 | AK14: =+AK13+AJ14 -> -938463.95 | ... AN14: =+AN13+AM14 -> -981023.82 | AO14: =SUM(AO10:AO11) -> -981023.82 | AP14: =AO14+1072186+38944+99846 -> 229952.18 | BC14: =SUM(BC10:BC11) -> 0
B15: Actividad Ganadera
B16: Cobros | C16: =Act.Ganadera!BY11 -> 2277.03 | D16: =Act.Ganadera!BZ11 -> 0 | E16: =Act.Ganadera!CA11 -> 0 | F16: =Act.Ganadera!CB11 -> 0 | G16: =Act.Ganadera!CC11 -> 509.17 | H16: =Act.Ganadera!CD11 -> 134.58 | I16: =Act.Ganadera!CE11 -> 0 | J16: =Act.Ganadera!CF11 -> 0 | ... N16: =Act.Ganadera!CJ11 -> 0 | O16: =SUM(C16:N16) -> 2920.78 | P16: =Act.Ganadera!CM11 -> 0 | Q16: =Act.Ganadera!CN11 -> 0 | R16: =Act.Ganadera!CO11 -> 0 | S16: =Act.Ganadera!CP11 -> 18560 | T16: =Act.Ganadera!CQ11 -> 2972.85 | U16: =Act.Ganadera!CR11 -> 0 | V16: =Act.Ganadera!CS11 -> 0 | W16: =Act.Ganadera!CT11 -> 0 | ... AA16: =Act.Ganadera!CX11 -> 0 | AB16: =SUM(P16:AA16) -> 21532.85 | AC16: =Act.Ganadera!CZ11 -> 0 | AD16: =Act.Ganadera!DA11 -> 0 | AE16: =Act.Ganadera!DB11 -> 0 | AF16: =Act.Ganadera!DC11 -> 0 | AG16: =Act.Ganadera!DD11 -> 0 | AH16: =Act.Ganadera!DE11 -> 0 | AI16: =Act.Ganadera!DF11 -> 0 | AJ16: =Act.Ganadera!DG11 -> 0 | ... AN16: =Act.Ganadera!DK11 -> 0 | AO16: =SUM(AC16:AN16) -> 737.53 | BC16: =SUM(AQ16:BB16) -> 0
B17: Pagos | C17: =Act.Ganadera!BY25+Act.Ganadera!BY51 -> -51770.52 | D17: =Act.Ganadera!BZ25+Act.Ganadera!BZ51 -> -1504.79 | E17: =Act.Ganadera!CA25+Act.Ganadera!CA51 -> -21987.725 | F17: =Act.Ganadera!CB25+Act.Ganadera!CB51 -> -13238.728 | G17: =Act.Ganadera!CC25+Act.Ganadera!CC51 -> -29471.34 | H17: =Act.Ganadera!CD25+Act.Ganadera!CD51 -> -32280.45 | I17: =Act.Ganadera!CE25+Act.Ganadera!CE51 -> -14869.92 | J17: =Act.Ganadera!CF25+Act.Ganadera!CF51 -> -5564.36 | ... N17: =Act.Ganadera!CJ25+Act.Ganadera!CJ51 -> 69092.16 | O17: =SUM(C17:N17) -> -170782.21 | P17: =Act.Ganadera!CM25+Act.Ganadera!CM51 -> -14800.2 | Q17: =Act.Ganadera!CN25+Act.Ganadera!CN51 -> -28867.53 | R17: =Act.Ganadera!CO25+Act.Ganadera!CO51 -> -2522.67 | S17: =Act.Ganadera!CP25+Act.Ganadera!CP51 -> -3242.42 | T17: =Act.Ganadera!CQ25+Act.Ganadera!CQ51 -> -14966.05 | U17: =Act.Ganadera!CR25+Act.Ganadera!CR51 -> -20302.74 | V17: =Act.Ganadera!CS25+Act.Ganadera!CS51 -> -20281.49 | W17: =Act.Ganadera!CT25+Act.Ganadera!CT51 -> 2025.34 | ... AA17: =Act.Ganadera!CX25+Act.Ganadera!CX51 -> -10165.692 | AB17: =SUM(P17:AA17) -> -141481.35 | AC17: =Act.Ganadera!CZ25+Act.Ganadera!CZ51 -> -8045.84 | AD17: =Act.Ganadera!DA25+Act.Ganadera!DA51 -> -16162.13 | AE17: =Act.Ganadera!DB25+Act.Ganadera!DB51 -> -2261.05 | AF17: =Act.Ganadera!DC25+Act.Ganadera!DC51 -> -7505.36 | AG17: =Act.Ganadera!DD25+Act.Ganadera!DD51 -> -11435.05 | AH17: =Act.Ganadera!DE25+Act.Ganadera!DE51 -> -6121.96 | AI17: =Act.Ganadera!DF25+Act.Ganadera!DF51 -> -22802.7 | AJ17: =Act.Ganadera!DG25+Act.Ganadera!DG51 -> -253.57 | ... AN17: =Act.Ganadera!DK25+Act.Ganadera!DK51 -> -8247.17 | AO17: =SUM(AC17:AN17) -> -115555.11 | BC17: =SUM(AQ17:BB17) -> 0
B19: Caja Operaciones (mes) | C19: =SUM(C16:C17) -> -49493.49 | D19: =SUM(D16:D17) -> -1504.79 | E19: =SUM(E16:E17) -> -21987.725 | F19: =SUM(F16:F17) -> -13238.728 | G19: =SUM(G16:G17) -> -28962.17 | H19: =SUM(H16:H17) -> -32145.87 | I19: =SUM(I16:I17) -> -14869.92 | J19: =SUM(J16:J17) -> -5564.36 | ... N19: =SUM(N16:N17) -> 69092.16 | P19: =SUM(P16:P17) -> -14800.2 | Q19: =SUM(Q16:Q17) -> -28867.53 | R19: =SUM(R16:R17) -> -2522.67 | S19: =SUM(S16:S17) -> 15317.58 | T19: =SUM(T16:T17) -> -11993.2 | U19: =SUM(U16:U17) -> -20302.74 | V19: =SUM(V16:V17) -> -20281.49 | W19: =SUM(W16:W17) -> 2025.34 | ... AA19: =SUM(AA16:AA17) -> -10165.692 | AC19: =SUM(AC16:AC17) -> -8045.84 | AD19: =SUM(AD16:AD17) -> -16162.13 | AE19: =SUM(AE16:AE17) -> -2261.05 | AF19: =SUM(AF16:AF17) -> -7505.36 | AG19: =SUM(AG16:AG17) -> -11435.05 | AH19: =SUM(AH16:AH17) -> -6121.96 | AI19: =SUM(AI16:AI17) -> -22802.7 | AJ19: =SUM(AJ16:AJ17) -> -253.57 | ... AN19: =SUM(AN16:AN17) -> -8247.17
B20: Caja Operaciones (acum.) | C20: =+C19 -> -49493.49 | D20: =+D19+C20 -> -50998.28 | E20: =+E19+D20 -> -72986.005 | F20: =+F19+E20 -> -86224.733 | G20: =+G19+F20 -> -115186.9 | H20: =+H19+G20 -> -147332.77 | I20: =+I19+H20 -> -162202.69 | J20: =+J19+I20 -> -167767.05 | K20: =+K19+J20 -> -202640.16 | ... N20: =+N19+M20 -> -167861.43 | O20: =SUM(O16:O17) -> -167861.43 | P20: =+P19 -> -14800.2 | Q20: =+Q19+P20 -> -43667.73 | R20: =+R19+Q20 -> -46190.4 | S20: =+S19+R20 -> -30872.82 | T20: =+T19+S20 -> -42866.02 | U20: =+U19+T20 -> -63168.76 | V20: =+V19+U20 -> -83450.25 | W20: =+W19+V20 -> -81424.91 | X20: =+X19+W20 -> -85425.68 | ... AA20: =+AA19+Z20 -> -119948.5 | AB20: =SUM(AB16:AB17) -> -119948.5 | AC20: =+AC19 -> -8045.84 | AD20: =+AD19+AC20 -> -24207.97 | AE20: =+AE19+AD20 -> -26469.02 | AF20: =+AF19+AE20 -> -33974.38 | AG20: =+AG19+AF20 -> -45409.43 | AH20: =+AH19+AG20 -> -51531.39 | AI20: =+AI19+AH20 -> -74334.09 | AJ20: =+AJ19+AI20 -> -74587.66 | AK20: =+AK19+AJ20 -> -75200.63 | ... AN20: =+AN19+AM20 -> -114817.58 | AO20: =SUM(AO16:AO17) -> -114817.58 | BC20: =SUM(BC16:BC17) -> 0
B21: Inversiones
B22: NixAl Commodities | C22: =Inversiones!BY11 -> -1502.78 | D22: =Inversiones!BZ11 -> -1502.78 | E22: =Inversiones!CA11 -> -3353.72 | F22: =Inversiones!CB11 -> -3953.04 | G22: =Inversiones!CC11 -> -6706.405 | H22: =Inversiones!CD11 -> -37062.293 | I22: =Inversiones!CE11 -> -3618.64 | J22: =Inversiones!CF11 -> -3618.64 | ... N22: =Inversiones!CJ11 -> -3695.14 | O22: =SUM(C22:N22) -> -96675.372 | P22: =Inversiones!CM11 -> -3695.14 | Q22: =Inversiones!CN11 -> -3695.14 | R22: =Inversiones!CO11 -> -22859.076 | S22: =Inversiones!CP11 -> -3695.14 | T22: =Inversiones!CQ11 -> -4055.27 | U22: =Inversiones!CR11 -> -4314.99 | V22: =Inversiones!CS11 -> -5276.97 | W22: =Inversiones!CT11 -> -2487.24 | ... AA22: =Inversiones!CX11 -> -1570.97 | AB22: =SUM(P22:AA22) -> -56909.846 | AC22: =Inversiones!CZ11 -> -1570.97 | AD22: =Inversiones!DA11 -> -10739.7 | AE22: =Inversiones!DB11 -> -1570.97 | AF22: =Inversiones!DC11 -> -7581.57 | AG22: =Inversiones!DD11 -> -3901.14 | AH22: =Inversiones!DE11 -> -1570.97 | AI22: =Inversiones!DF11 -> -186491.9 | AJ22: =Inversiones!DG11 -> -4851.7 | ... AN22: =Inversiones!DK11 -> -1570.97 | AO22: =SUM(AC22:AN22) -> -239458 | BC22: =SUM(AQ22:BB22) -> 0
B23: Act. Ganadera | C23: =Inversiones!BY26 -> -410600 | D23: =Inversiones!BZ26 -> 0 | E23: =Inversiones!CA26 -> -5023.58 | F23: =Inversiones!CB26 -> -120341.27 | G23: =Inversiones!CC26 -> -7532.89 | H23: =Inversiones!CD26 -> -15459.55 | I23: =Inversiones!CE26 -> -377.24 | J23: =Inversiones!CF26 -> -1122.45 | ... N23: =Inversiones!CJ26 -> -17049.72 | O23: =SUM(C23:N23) -> -577506.7 | P23: =Inversiones!CM26 -> 0 | Q23: =Inversiones!CN26 -> 0 | R23: =Inversiones!CO26 -> 0 | S23: =Inversiones!CP26 -> 0 | T23: =Inversiones!CQ26 -> 0 | U23: =Inversiones!CR26 -> -1270.1 | V23: =Inversiones!CS26 -> 0 | W23: =Inversiones!CT26 -> -15129.24 | ... AA23: =Inversiones!CX26 -> 0 | AB23: =SUM(P23:AA23) -> -34165.68 | AC23: =Inversiones!CZ26 -> 0 | AD23: =Inversiones!DA26 -> -10587.5 | AE23: =Inversiones!DB26 -> 0 | AF23: =Inversiones!DC26 -> 0 | AG23: =Inversiones!DD26 -> 0 | AH23: =Inversiones!DE26 -> -2013.92 | AI23: =Inversiones!DF26 -> -47795.3 | AJ23: =Inversiones!DG26 -> -1716.87 | ... AN23: =Inversiones!DK26 -> 0 | AO23: =SUM(AC23:AN23) -> -67022.05 | BC23: =SUM(AQ23:BB23) -> 0
B25: Caja Inversiones (mes) | C25: =SUM(C22:C23) -> -412102.78 | D25: =SUM(D22:D23) -> -1502.78 | E25: =SUM(E22:E23) -> -8377.3 | F25: =SUM(F22:F23) -> -124294.31 | G25: =SUM(G22:G23) -> -14239.295 | H25: =SUM(H22:H23) -> -52521.843 | I25: =SUM(I22:I23) -> -3995.88 | J25: =SUM(J22:J23) -> -4741.09 | ... N25: =SUM(N22:N23) -> -20744.86 | P25: =SUM(P22:P23) -> -3695.14 | Q25: =SUM(Q22:Q23) -> -3695.14 | R25: =SUM(R22:R23) -> -22859.076 | S25: =SUM(S22:S23) -> -3695.14 | T25: =SUM(T22:T23) -> -4055.27 | U25: =SUM(U22:U23) -> -5585.09 | V25: =SUM(V22:V23) -> -5276.97 | W25: =SUM(W22:W23) -> -17616.48 | ... AA25: =SUM(AA22:AA23) -> -1570.97 | AC25: =SUM(AC22:AC23) -> -1570.97 | AD25: =SUM(AD22:AD23) -> -21327.2 | AE25: =SUM(AE22:AE23) -> -1570.97 | AF25: =SUM(AF22:AF23) -> -7581.57 | AG25: =SUM(AG22:AG23) -> -3901.14 | AH25: =SUM(AH22:AH23) -> -3584.89 | AI25: =SUM(AI22:AI23) -> -234287.2 | AJ25: =SUM(AJ22:AJ23) -> -6568.57 | ... AN25: =SUM(AN22:AN23) -> -1570.97
B26: Caja Inversiones (acum.) | C26: =+C25 -> -412102.78 | D26: =+D25+C26 -> -413605.56 | E26: =+E25+D26 -> -421982.86 | F26: =+F25+E26 -> -546277.17 | G26: =+G25+F26 -> -560516.47 | H26: =+H25+G26 -> -613038.31 | I26: =+I25+H26 -> -617034.19 | J26: =+J25+I26 -> -621775.28 | K26: =+K25+J26 -> -625393.92 | ... N26: =+N25+M26 -> -674182.07 | O26: =SUM(O22:O23) -> -674182.07 | P26: =+P25 -> -3695.14 | Q26: =+Q25+P26 -> -7390.28 | R26: =+R25+Q26 -> -30249.356 | S26: =+S25+R26 -> -33944.496 | T26: =+T25+S26 -> -37999.766 | U26: =+U25+T26 -> -43584.856 | V26: =+V25+U26 -> -48861.826 | W26: =+W25+V26 -> -66478.306 | X26: =+X25+W26 -> -70129.586 | ... AA26: =+AA25+Z26 -> -91075.526 | AB26: =SUM(AB22:AB23) -> -91075.526 | AC26: =+AC25 -> -1570.97 | AD26: =+AD25+AC26 -> -22898.17 | AE26: =+AE25+AD26 -> -24469.14 | AF26: =+AF25+AE26 -> -32050.71 | AG26: =+AG25+AF26 -> -35951.85 | AH26: =+AH25+AG26 -> -39536.74 | AI26: =+AI25+AH26 -> -273823.94 | AJ26: =+AJ25+AI26 -> -280392.51 | AK26: =+AK25+AJ26 -> -288216.83 | ... AN26: =+AN25+AM26 -> -306480.05 | AO26: =SUM(AO22:AO23) -> -306480.05 | BC26: =SUM(BC22:BC23) -> 0
B27: Financiación | C27: =Financiación!BY4 -> 460898.56 | D27: =Financiación!BZ4 -> 50929.193 | E27: =Financiación!CA4 -> -17795.135 | F27: =Financiación!CB4 -> 222195.88 | G27: =Financiación!CC4 -> -11040.924 | H27: =Financiación!CD4 -> -18191.501 | I27: =Financiación!CE4 -> -164120.39 | J27: =Financiación!CF4 -> -12077.979 | ... N27: =Financiación!CJ4 -> -11624.207 | O27: =SUM(C27:N27) -> 451077.94 | P27: =Financiación!CL4 -> -71050.393 | Q27: =Financiación!CM4 -> -22041.052 | R27: =Financiación!CN4 -> 97064.492 | S27: =Financiación!CO4 -> -39053.978 | T27: =Financiación!CP4 -> -33754.017 | U27: =Financiación!CQ4 -> -21354.518 | V27: =Financiación!CR4 -> -31093.191 | W27: =Financiación!CS4 -> -65717.708 | ... AA27: =Financiación!CW4 -> -156950.81 | AB27: =SUM(P27:AA27) -> -111522.4 | AC27: =Financiación!CY4 -> -74876.79 | AD27: =Financiación!CZ4 -> 107540.31 | AE27: =Financiación!DA4 -> -37738.007 | AF27: =Financiación!DB4 -> -32034.4 | AG27: =Financiación!DC4 -> -49419.317 | AH27: =Financiación!DD4 -> -15576.788 | AI27: =Financiación!DE4 -> 215285.96 | AJ27: =Financiación!DF4 -> -196876.1 | ... AN27: =Financiación!DJ4 -> -26288.998 | AO27: =SUM(AC27:AN27) -> -248274.65 | BC27: =SUM(AQ27:BB27) -> 0
B29: Caja Financiación (mes) | C29: =+C27 -> 460898.56 | D29: =+D27 -> 50929.193 | E29: =+E27 -> -17795.135 | F29: =+F27 -> 222195.88 | G29: =+G27 -> -11040.924 | H29: =+H27 -> -18191.501 | I29: =+I27 -> -164120.39 | J29: =+J27 -> -12077.979 | ... N29: =+N27 -> -11624.207 | P29: =SUM(P27:P27) -> -71050.393 | Q29: =SUM(Q27:Q27) -> -22041.052 | R29: =SUM(R27:R27) -> 97064.492 | S29: =SUM(S27:S27) -> -39053.978 | T29: =SUM(T27:T27) -> -33754.017 | U29: =SUM(U27:U27) -> -21354.518 | V29: =SUM(V27:V27) -> -31093.191 | W29: =SUM(W27:W27) -> -65717.708 | ... AA29: =SUM(AA27:AA27) -> -156950.81 | AC29: =SUM(AC27:AC27) -> -74876.79 | AD29: =SUM(AD27:AD27) -> 107540.31 | AE29: =SUM(AE27:AE27) -> -37738.007 | AF29: =SUM(AF27:AF27) -> -32034.4 | AG29: =SUM(AG27:AG27) -> -49419.317 | AH29: =SUM(AH27:AH27) -> -15576.788 | AI29: =SUM(AI27:AI27) -> 215285.96 | AJ29: =SUM(AJ27:AJ27) -> -196876.1 | ... AN29: =SUM(AN27:AN27) -> -26288.998
B30: Caja Financiación (acum.) | C30: =+C29 -> 460898.56 | D30: =+D29+C30 -> 511827.75 | E30: =+E29+D30 -> 494032.61 | F30: =+F29+E30 -> 716228.5 | G30: =+G29+F30 -> 705187.57 | H30: =+H29+G30 -> 686996.07 | I30: =+I29+H30 -> 522875.68 | J30: =+J29+I30 -> 510797.7 | K30: =+K29+J30 -> 492494.5 | ... N30: =+N29+M30 -> 451077.94 | O30: =SUM(O27:O28) -> 451077.94 | P30: =+P29 -> -71050.393 | Q30: =+Q29+P30 -> -93091.445 | R30: =+R29+Q30 -> 3973.0464 | S30: =+S29+R30 -> -35080.932 | T30: =+T29+S30 -> -68834.949 | U30: =+U29+T30 -> -90189.468 | V30: =+V29+U30 -> -121282.66 | W30: =+W29+V30 -> -187000.37 | X30: =+X29+W30 -> -41755.154 | ... AA30: =+AA29+Z30 -> -111522.4 | AB30: =SUM(AB27:AB28) -> -111522.4 | AC30: =+AC29 -> -74876.79 | AD30: =+AD29+AC30 -> 32663.522 | AE30: =+AE29+AD30 -> -5074.4851 | AF30: =+AF29+AE30 -> -37108.885 | AG30: =+AG29+AF30 -> -86528.202 | AH30: =+AH29+AG30 -> -102104.99 | AI30: =+AI29+AH30 -> 113180.97 | AJ30: =+AJ29+AI30 -> -83695.132 | AK30: =+AK29+AJ30 -> -151352.26 | ... AN30: =+AN29+AM30 -> -248274.65 | AO30: =SUM(AO27:AO28) -> -248274.65 | BC30: =SUM(BC27:BC28) -> 0
B32: Caja opex, capex y serv. deuda | C32: =+C7+C19+C25+C29 -> 8291.4287 | D32: =+D7+D19+D25+D29 -> 96825.014 | E32: =+E7+E19+E25+E29 -> -27645.383 | F32: =+F7+F19+F25+F29 -> 101576.54 | G32: =+G7+G19+G25+G29 -> -5323.1838 | H32: =+H7+H19+H25+H29 -> -68248.671 | I32: =+I7+I19+I25+I29 -> -199105.57 | J32: =+J7+J19+J25+J29 -> -28327.689 | ... N32: =+N7+N19+N25+N29 -> 162399.51 | O32: =SUM(O8,O20,O26,O30) -> 91130.042 | P32: =+P7+P19+P25+P29+P13 -> -46730.412 | Q32: =+Q7+Q19+Q25+Q29+Q13 -> -37074.433 | R32: =+R7+R19+R25+R29+R13 -> 120288.85 | S32: =+S7+S19+S25+S29+S13 -> -18336.438 | T32: =+T7+T19+T25+T29+T13 -> 83937.684 | U32: =+U7+U19+U25+U29+U13 -> 90519.569 | V32: =+V7+V19+V25+V29+V13 -> -38904.68 | W32: =+W7+W19+W25+W29+W13 -> -93616.201 | ... AA32: =+AA7+AA19+AA25+AA29+AA13 -> 1024925 | AB32: =SUM(AB8,AB20,AB26,AB30,AB14) -> 1299533.1 | AC32: =+AC7+AC19+AC25+AC29+AC13 -> -1235089.9 | AD32: =+AD7+AD19+AD25+AD29+AD13 -> -53289.667 | AE32: =+AE7+AE19+AE25+AE29+AE13 -> 960968.69 | AF32: =+AF7+AF19+AF25+AF29+AF13 -> -675435.93 | AG32: =+AG7+AG19+AG25+AG29+AG13 -> -217210.64 | AH32: =+AH7+AH19+AH25+AH29+AH13 -> 116828.5 | AI32: =+AI7+AI19+AI25+AI29+AI13 -> -92531.911 | AJ32: =+AJ7+AJ19+AJ25+AJ29+AJ13 -> -142885.26 | ... AN32: =+AN7+AN19+AN25+AN29+AN13 -> 14517.345 | AO32: =SUM(AO8,AO20,AO26,AO30,AO14) -> -966100.7 | AP32: =AO32-AO14+AP14 -> 244875.3 | BC32: =SUM(BC8,BC20,BC26,BC30,BC14) -> 0
B33: Check | O33: =SUM(C32:N32)-O32 -> 0 | AB33: =SUM(P32:AA32)-AB32 -> 0 | AO33: =SUM(AC32:AN32)-AO32 -> 0 | BC33: =SUM(AQ32:BB32)-BC32 -> 0
B34: Circulante Caixa - 100k Eur | I34: =63000*0 -> 0
B35: Circulante BBVA - 75k Eur | I35: 0
B36: Circulante Bankinter - 100k Eur | I36: =95000*0 -> 0
B37: Total circulante | C37: =SUM(C34:C36) -> 0 | D37: =SUM(D34:D36) -> 0 | E37: =SUM(E34:E36) -> 0 | F37: =SUM(F34:F36) -> 0 | G37: =SUM(G34:G36) -> 0 | H37: =SUM(H34:H36) -> 0 | I37: =SUM(I34:I36) -> 0 | J37: =SUM(J34:J36) -> 0 | ... N37: =SUM(N34:N36) -> 0 | P37: =SUM(P34:P36) -> 0 | Q37: =SUM(Q34:Q36) -> 0 | R37: =SUM(R34:R36) -> 0 | S37: =SUM(S34:S36) -> 0 | T37: =SUM(T34:T36) -> 0 | U37: =SUM(U34:U36) -> 0 | V37: =SUM(V34:V36) -> 0 | W37: =SUM(W34:W36) -> 0 | ... AA37: =SUM(AA34:AA36) -> 0 | AC37: =SUM(AC34:AC36) -> 0 | AD37: =SUM(AD34:AD36) -> 0 | AE37: =SUM(AE34:AE36) -> 0 | AF37: =SUM(AF34:AF36) -> 0 | AG37: =SUM(AG34:AG36) -> 0 | AH37: =SUM(AH34:AH36) -> 0 | AI37: =SUM(AI34:AI36) -> 0 | AJ37: =SUM(AJ34:AJ36) -> 0 | ... AN37: =SUM(AN34:AN36) -> 0
B39: Caja consolidada (mes) | C39: =+C7+C19+C25+C29+C37 -> 8291.4287 | D39: =+D7+D19+D25+D29+D37 -> 96825.014 | E39: =+E7+E19+E25+E29+E37 -> -27645.383 | F39: =+F7+F19+F25+F29+F37 -> 101576.54 | G39: =+G7+G19+G25+G29+G37 -> -5323.1838 | H39: =+H7+H19+H25+H29+H37 -> -68248.671 | I39: =+I7+I19+I25+I29+I37 -> -199105.57 | J39: =+J7+J19+J25+J29+J37 -> -28327.689 | ... N39: =+N7+N19+N25+N29+N37 -> 162399.51 | P39: =+P7+P19+P25+P29+P37 -> -46730.412 | Q39: =+Q7+Q19+Q25+Q29+Q37 -> -37074.433 | R39: =+R7+R19+R25+R29+R37 -> 120288.85 | S39: =+S7+S19+S25+S29+S37 -> -18336.438 | T39: =+T7+T19+T13+T25+T29+T37 -> 83937.684 | U39: =+U7+U19+U13+U25+U29+U37 -> 90519.569 | V39: =+V7+V19+V13+V25+V29+V37 -> -38904.68 | W39: =+W7+W19+W13+W25+W29+W37 -> -93616.201 | X39: =+X7+X19+X13+X25+X29+X37 -> 157576 | Y39: =+Y7+Y19+Y13+Y25+Y29+Y37 -> -96301.983 | Z39: =+Z7+Z19+Z13+Z25+Z29+Z37 -> 153250.16 | AA39: =+AA7+AA19+AA13+AA25+AA29+AA37 -> 1024925 | AC39: =+AC7+AC19+AC13+AC25+AC29+AC37 -> -1235089.9 | AD39: =+AD7+AD19+AD13+AD25+AD29+AD37 -> -53289.667 | AE39: =+AE7+AE19+AE13+AE25+AE29+AE37 -> 960968.69 | AF39: =+AF7+AF19+AF13+AF25+AF29+AF37 -> -675435.93 | AG39: =+AG7+AG19+AG13+AG25+AG29+AG37 -> -217210.64 | AH39: =+AH7+AH19+AH13+AH25+AH29+AH37 -> 116828.5 | AI39: =+AI7+AI19+AI13+AI25+AI29+AI37 -> -92531.911 | AJ39: =+AJ7+AJ19+AJ13+AJ25+AJ29+AJ37 -> -142885.26 | ... AN39: =+AN7+AN19+AN13+AN25+AN29+AN37 -> 14517.345
B40: Caja consolidada (acumulada) | C40: =+C39 -> 8291.4287 | D40: =+D39+C40 -> 105116.44 | E40: =+E39+D40 -> 77471.06 | F40: =+F39+E40 -> 179047.6 | G40: =+G39+F40 -> 173724.42 | H40: =+H39+G40 -> 105475.75 | I40: =+I39+H40 -> -93629.819 | J40: =+J39+I40 -> -121957.51 | K40: =+K39+J40 -> -91227.237 | ... N40: =+N39+M40 -> 91130.042 | P40: =+P39 -> -46730.412 | Q40: =+Q39+P40 -> -83804.846 | R40: =+R39+Q40 -> 36484.008 | S40: =+S39+R40 -> 18147.571 | T40: =+T39+S40 -> 102085.25 | U40: =+U39+T40 -> 192604.82 | V40: =+V39+U40 -> 153700.14 | W40: =+W39+V40 -> 60083.943 | X40: =+X39+W40 -> 217659.95 | ... AA40: =+AA39+Z40 -> 1299533.1 | AC40: =+AC39 -> -1235089.9 | AD40: =+AD39+AC40 -> -1288379.6 | AE40: =+AE39+AD40 -> -327410.92 | AF40: =+AF39+AE40 -> -1002846.9 | AG40: =+AG39+AF40 -> -1220057.5 | AH40: =+AH39+AG40 -> -1103229 | AI40: =+AI39+AH40 -> -1195760.9 | AJ40: =+AJ39+AI40 -> -1338646.2 | AK40: =+AK39+AJ40 -> -1238525.2 | ... AN40: =+AN39+AM40 -> -966100.7
B42: Saldo Inicial | C42: =Tesoreria!$BW$315 -> 65108.2 | H42: =Tesoreria!$CC$302 -> 240150.56 | I42: =+H44 -> 171901.89 | J42: =+I44 -> -27203.678 | K42: =+J44 -> -55531.367 | L42: =+K44 -> -24801.096 | M42: =+L44 -> 7269.8771 | N42: =+M44 -> -4843.327 | P42: =+N44 -> 157556.18 | Q42: =+P44 -> 110825.77 | R42: =+Q44 -> 73751.338 | S42: =+R44 -> 194040.19 | T42: =+S44 -> 175703.75 | U42: =+T44 -> 259641.44 | V42: =+U44 -> 350161.01 | W42: =+V44 -> 311256.33 | X42: =+W44 -> 217640.13 | ... AA42: =+Z44 -> 432164.31 | AC42: =+AA44 -> 1457089.3 | AD42: =+AC44 -> 221999.33 | AE42: =+AD44 -> 168709.67 | AF42: =+AE44 -> 1129678.4 | AG42: =+AF44 -> 454242.43 | AH42: =+AG44 -> 237031.78 | AI42: =+AH44 -> 353860.28 | AJ42: =+AI44 -> 261328.37 | AK42: =+AJ44 -> 118443.11 | ... AN42: =+AM44 -> 476471.23
B43: Caja consolidada | C43: =+C39 -> 8291.4287 | H43: =+H39 -> -68248.671 | I43: =+I39 -> -199105.57 | J43: =+J39 -> -28327.689 | K43: =+K39 -> 30730.271 | L43: =+L39 -> 32070.973 | M43: =+M39 -> -12113.204 | N43: =+N39 -> 162399.51 | P43: =+P39 -> -46730.412 | Q43: =+Q39 -> -37074.433 | R43: =+R39 -> 120288.85 | S43: =+S39 -> -18336.438 | T43: =+T39 -> 83937.684 | U43: =+U39 -> 90519.569 | V43: =+V39 -> -38904.68 | W43: =+W39 -> -93616.201 | ... AA43: =+AA39 -> 1024925 | AC43: =+AC39 -> -1235089.9 | AD43: =+AD39 -> -53289.667 | AE43: =+AE39 -> 960968.69 | AF43: =+AF39 -> -675435.93 | AG43: =+AG39 -> -217210.64 | AH43: =+AH39 -> 116828.5 | AI43: =+AI39 -> -92531.911 | AJ43: =+AJ39 -> -142885.26 | ... AN43: =+AN39 -> 14517.345
B44: Saldo final | C44: =SUM(C42:C43) -> 73399.629 | H44: =SUM(H42:H43) -> 171901.89 | I44: =SUM(I42:I43) -> -27203.678 | J44: =SUM(J42:J43) -> -55531.367 | K44: =SUM(K42:K43) -> -24801.096 | L44: =SUM(L42:L43) -> 7269.8771 | M44: =SUM(M42:M43) -> -4843.327 | N44: =SUM(N42:N43) -> 157556.18 | P44: =SUM(P42:P43) -> 110825.77 | Q44: =SUM(Q42:Q43) -> 73751.338 | R44: =SUM(R42:R43) -> 194040.19 | S44: =SUM(S42:S43) -> 175703.75 | T44: =SUM(T42:T43) -> 259641.44 | U44: =SUM(U42:U43) -> 350161.01 | V44: =SUM(V42:V43) -> 311256.33 | W44: =SUM(W42:W43) -> 217640.13 | ... AA44: =SUM(AA42:AA43) -> 1457089.3 | AC44: =SUM(AC42:AC43) -> 221999.33 | AD44: =SUM(AD42:AD43) -> 168709.67 | AE44: =SUM(AE42:AE43) -> 1129678.4 | AF44: =SUM(AF42:AF43) -> 454242.43 | AG44: =SUM(AG42:AG43) -> 237031.78 | AH44: =SUM(AH42:AH43) -> 353860.28 | AI44: =SUM(AI42:AI43) -> 261328.37 | AJ44: =SUM(AJ42:AJ43) -> 118443.11 | ... AN44: =SUM(AN42:AN43) -> 490988.58
B45: Saldos bancarios
B46: Saldo BBVA EUR | H46: =10469.53-74136.86 -> -63667.33 | I46: =2523.06-73109.06 -> -70586 | J46: =2514.76-74109.06 -> -71594.3 | K46: =1734.67-74109.06 -> -72374.39 | L46: =577.32-74213.91 -> -73636.59 | M46: =172.75-74213.91 -> -74041.16 | N46: =362.27-74213.91 -> -73851.64 | P46: =351.65-72713.91 -> -72362.26 | Q46: =341.03-74271.06 -> -73930.03 | R46: =330.41-74271.06 -> -73940.65 | S46: =319.79-72771.06 -> -72451.27 | T46: =294.62-74186.7 -> -73892.08 | U46: =2195.46-74386.7 -> -72191.24 | V46: =483.08-73622.53 -> -73139.45 | W46: =537.91-61827.58 -> -61289.67 | X46: =3860.91-61827.58 -> -57966.67 | Y46: =647.57-61827.58 -> -61180.01 | Z46: =725.42-62698.58 -> -61973.16 | AA46: =3731.68-45149.18 -> -41417.5 | AC46: =564.38-72149.18 -> -71584.8 | AD46: =642.23-52826.48 -> -52184.25 | AE46: =3965.23+551998.36 -> 555963.59 | AF46: =797.93+28698.81 -> 29496.74 | AG46: =4040.93+28437 -> 32477.93 | AH46: =3870.48+11290.75 -> 15161.23 | AI46: =1267.32-12656.03 -> -11388.71 | AJ46: =1343.4-62388.9 -> -61045.5 | AK46: =4664.4-63003.14 -> -58338.74
B47: Saldo Caixa EUR | H47: 40260.41 | I47: -28069.15 | J47: -50198.29 | K47: -65493.99 | L47: -83056.87 | M47: -78659.97 | N47: -50350.62 | P47: -77272.07 | Q47: -54046.85 | R47: 38618.95 | S47: -3841.8 | T47: 7909.13 | U47: -14135.47 | V47: -50758.09 | W47: -59040.57 | X47: -15300.11 | Y47: -37916.4 | Z47: 109670.4 | AA47: 1253592.1 | AC47: =55527.26+27000+22000 -> 104527.26 | AD47: 28541.07 | AE47: 273961.03 | AF47: 101854.88 | AG47: -50866.66 | AH47: =-48475.75 -> -48475.75 | AI47: =-22286.57 -> -22286.57 | AJ47: -61776.02 | AK47: -54597.91 | AL47: =AK47+AL32 -> 54244.601 | AM47: =AL47+AM32 -> 203309.23 | AN47: =AM47+AN32 -> 217826.57
B48: Saldo Caixa USD (valor aprox €) | H48: 0 | I48: 0 | J48: 0 | K48: 0 | L48: 0 | M48: 0 | N48: 0 | P48: 0 | Q48: 0 | R48: 0 | S48: 0 | T48: 0 | U48: 0 | V48: 0 | W48: 0 | X48: 0 | Y48: 0 | Z48: 0 | AA48: 0 | AC48: 0 | AD48: 0 | AE48: 0 | AF48: 0 | AG48: 0 | AH48: 0 | AI48: 0 | AJ48: 0 | AK48: 0
B49: Saldo Caixa (Cta:.. 3116) | H49: 1764.17 | I49: =5525.51+12.92 -> 5538.43 | J49: =1833.52+3.39 -> 1836.91 | K49: =1376.62+1.79 -> 1378.41 | L49: =6546.92+1.79 -> 6548.71 | M49: =2519.52+2.64 -> 2522.16 | N49: =1981.17+0.21 -> 1981.38 | P49: =859.32+0.34 -> 859.66 | Q49: =1215.5+0.34 -> 1215.84 | R49: =816.92+0.34 -> 817.26 | S49: =3373.54+0.34 -> 3373.88 | T49: =4186.08+0.34 -> 4186.42 | U49: =1711.44+72.54 -> 1783.98 | V49: =2218.67+30.17 -> 2248.84 | W49: =719.64+20.28 -> 739.92 | X49: =3537.65+20.28 -> 3557.93 | Y49: =2287.11+5.06 -> 2292.17 | Z49: =1575.52+138526.37 -> 140101.89 | AA49: =1173.41+703.16 -> 1876.57 | AC49: =4443.72+526.2 -> 4969.92 | AD49: =820.68+1715.15 -> 2535.83 | AE49: =4598.84+1498.19 -> 6097.03 | AF49: =4478.19+1281.23 -> 5759.42 | AG49: =(4172.9+1460)+1064.27 -> 6697.17 | AH49: =(4030.72+10185+1460)+961.31 -> 16637.03 | AI49: =3689.07+744.35 -> 4433.42 | AJ49: =3451.5+527.39 -> 3978.89 | AK49: =1847.32+1310.43 -> 3157.75
B50: Saldo Santander | H50: 262.96 | I50: 2267.88 | J50: 2274.69 | K50: 2029.18 | L50: 2035.99 | M50: 582.8 | N50: 12234.61 | P50: 2059.1 | Q50: 2065.91 | R50: 12257.72 | S50: 2127.28 | T50: 2134.09 | U50: 12325.9 | V50: 2195.46 | W50: 2202.27 | X50: 12394.08 | Y50: 2263.64 | Z50: 2270.45 | AA50: 12462.26 | AC50: 2331.82 | AD50: 2338.63 | AE50: 12530.44 | AF50: 2721.17 | AG50: 1267.98 | AH50: 1235.2 | AI50: 3057.29 | AJ50: 3064.1 | AK50: 13255.91
B51: Saldo Caja Rural | H51: 2439.76 | I51: 2439.76 | J51: 2409.76 | K51: 2409.76 | L51: 2379.76 | M51: 2369.76 | N51: 2369.76 | P51: 448.48 | Q51: 567.7 | R51: 567.7 | S51: 19087.7 | T51: 3314.8 | U51: 3260.12 | V51: 3220.12 | W51: 3220.12 | X51: 3220.12 | Y51: 3180.12 | Z51: 1568.28 | AA51: 1568.28 | AC51: 4147.5 | AD51: 766.72 | AE51: 766.72 | AF51: 726.72 | AG51: 508.72 | AH51: 508.72 | AI51: 468.72 | AJ51: 468.72 | AK51: 472.36
B52: Saldo VFX USD (valor aprox €) | H52: 21421.2 | I52: 16849.84 | J52: 16873.31 | K52: 13915.95 | L52: 43758.69 | M52: 19903.75 | N52: 24526.67 | P52: 64696.56 | Q52: 19676.59 | R52: 13766.04 | S52: 26400.76 | T52: 40764.45 | U52: 14439.7 | V52: 5867.68 | W52: 32908.76 | X52: 16545.49 | Y52: 2286.61 | Z52: 7172.92 | AA52: 11617.36 | AC52: 20358.12 | AD52: 15302.9 | AE52: 15302.9 | AF52: 28068.85 | AG52: 24017.1 | AH52: 696.57 | AI52: 12900.16 | AJ52: 710.1 | AK52: 0
B53: Saldo VFX EUR | H53: 0 | I53: 0 | J53: 0 | K53: 0 | L53: 0 | M53: 245.39 | N53: 245.39 | P53: 0 | Q53: 0 | R53: 0 | S53: 0 | T53: 13200 | U53: 10900 | V53: 10900 | W53: 2900 | X53: 99.56 | Y53: 3894.92 | Z53: 765.29 | AA53: 90.32 | AC53: 15.96 | AD53: 35.19 | AE53: 2701.21 | AF53: 472.22 | AG53: 1276.7 | AH53: 45.55 | AI53: 8717.76 | AJ53: 232.97 | AK53: 0
B54: Saldo Ebury USD (valor aprox €) | H54: 0 | I54: 0 | J54: 0 | K54: 0 | L54: 0 | M54: 0 | N54: 0 | P54: 0 | Q54: 0 | R54: 0 | S54: 0 | T54: 0 | U54: 0 | V54: 0 | W54: 0 | X54: 0 | Y54: 0 | Z54: 0 | AA54: 0 | AC54: 0 | AD54: 0 | AE54: 0 | AF54: 0 | AG54: 0 | AH54: 0 | AI54: 0 | AJ54: 0 | AK54: 0
B55: Saldo Paragon USD (valor aprox €) | H55: 32863.75 | I55: 32768.91 | J55: 32705.69 | K55: 32610.85 | L55: 32547.63 | M55: 44985.55 | N55: 164146.91 | P55: 164119.69 | Q55: 227172.59 | R55: 17486.75 | S55: 17486.75 | T55: -30970.27 | U55: 123026.09 | V55: 123026.09 | W55: 122925.86 | X55: 156124.6 | Y55: 155993.3 | Z55: 155964.63 | AA55: 155866.16 | AC55: 155833.33 | AD55: 155800.51 | AE55: 155564.17 | AF55: 155564.17 | AG55: 155564.17 | AH55: 205455.69 | AI55: 205436.33 | AJ55: 246355.97 | AK55: 258330.75 | AL55: 258330.75
B56: Saldo Paragon EUR | H56: 106343.25 | I56: 106343.25 | J56: 106343.25 | K56: 157890.75 | L56: 174854.75 | M56: 174854.75 | N56: 174854.75 | P56: 124854.75 | Q56: =124854.75-74854.75 -> 50000 | R56: 281399.46 | S56: 281399.46 | T56: 281399.46 | U56: 281399.46 | V56: 281399.46 | W56: 201399.46 | X56: 307899.46 | Y56: 190899.46 | Z56: 150899.46 | AA56: 136649.46 | AC56: 99555.96 | AD56: 90731.96 | AE56: 90731.96 | AF56: 90731.96 | AG56: 90731.96 | AH56: 95164.16 | AI56: 112624.16 | AJ56: 13959.36 | AK56: 37127.32 | AL56: 37127.32
B57: Saldo Marex | AK57: =132025-80000 -> 52025 | AL57: =132025-80000+112487 -> 164512
B58: Saldo Bankinter | H58: 30213.72 | I58: -94756.6 | J58: -96182.39 | K58: -97167.62 | L58: -98162.24 | M58: -97606.43 | N58: -98601.07 | P58: -96577.67 | Q58: -98970.56 | R58: -96932.59 | S58: -97879.46 | T58: 11595.45 | U58: -10647.1 | V58: 6296.15 | W58: -28326.09 | X58: -51358.72 | Y58: 17199.93 | Z58: -74276.27 | AA58: -75216.19 | AC58: -98155.65 | AD58: -75158.8 | AE58: 16059.35 | AF58: 38846.34 | AG58: -24643.1 | AH58: 67431.66 | AI58: =-63425.45+10791.16 -> -52634.29 | AJ58: =-37284.27+9778.31 -> -27505.96 | AK58: =-42646.99+9778.31 -> -32868.68
B59: Check | H59: =SUM(H46:H58) -> 171901.89 | I59: =SUM(I46:I58) -> -27203.68 | J59: =SUM(J46:J58) -> -55531.37 | K59: =SUM(K46:K58) -> -24801.1 | L59: =SUM(L46:L58) -> 7269.83 | M59: =SUM(M46:M58) -> -4843.4 | N59: =SUM(N46:N58) -> 157556.14 | P59: =SUM(P46:P58) -> 110826.24 | Q59: =SUM(Q46:Q58) -> 73751.19 | R59: =SUM(R46:R58) -> 194040.64 | S59: =SUM(S46:S58) -> 175703.3 | T59: =SUM(T46:T58) -> 259641.45 | U59: =SUM(U46:U58) -> 350161.44 | V59: =SUM(V46:V58) -> 311256.26 | W59: =SUM(W46:W58) -> 217640.06 | ... AA59: =SUM(AA46:AA58) -> 1457088.9 | AC59: =SUM(AC46:AC58) -> 221999.42 | AD59: =SUM(AD46:AD58) -> 168709.76 | AE59: =SUM(AE46:AE58) -> 1129678.4 | AF59: =SUM(AF46:AF58) -> 454242.47 | AG59: =SUM(AG46:AG58) -> 237031.97 | AH59: =SUM(AH46:AH58) -> 353860.06 | AI59: =SUM(AI46:AI58) -> 261328.27 | AJ59: =SUM(AJ46:AJ58) -> 118442.63 | ... AN59: =SUM(AN46:AN58) -> 217826.57
B60: Diferencia | H60: =H44-H59 -> 0.001082061 | I60: =I44-I59 -> 0.002175145 | J60: =J44-J59 -> 0.0031379076 | K60: =K44-K59 -> 0.0040702136 | L60: =L44-L59 -> 0.047117164 | M60: =M44-M59 -> 0.073015905 | N60: =N44-N59 -> 0.043673951 | P60: =P44-P59 -> -0.46874256 | Q60: =Q44-Q59 -> 0.14786348 | R60: =R44-R59 -> -0.44795563 | S60: =S44-S59 -> 0.45436643 | T60: =T44-T59 -> -0.012009353 | U60: =U44-U59 -> -0.43276673 | V60: =V44-V59 -> 0.067031493 | W60: =W44-W59 -> 0.06629921 | ... AA60: =AA44-AA59 -> 0.42746104 | AC60: =AC44-AC59 -> -0.085421404 | AD60: =AD44-AD59 -> -0.092862536 | AE60: =AE44-AE59 -> -0.046173931 | AF60: =AF44-AF59 -> -0.042548623 | AG60: =AG44-AG59 -> -0.18606859 | AH60: =AH44-AH59 -> 0.21904946 | AI60: =AI44-AI59 -> 0.098091938 | AJ60: =AJ44-AJ59 -> 0.47559678 | ... AN60: =AN44-AN59 -> 273162

Sheet NC-Ingresos
C2: 2018 | P2: 2019 | AC2: 2020 | AL2: 2020/2021 | AY2: 2021/2022 | BL2: 2022/2023 | BY2: 2023/2024 | CL2: 2024/2025 | CY2: 2025/2026 | DL2: 2026/2027
B3: Previsiones Caja | C3: Ene | D3: Feb | E3: Mar | F3: Abr | G3: May | H3: Jun | I3: Jul | J3: Ago | K3: Sep | L3: Oct | M3: Nov | N3: Dic | O3: Totales | P3: Ene | Q3: Feb | R3: Mar | S3: Abr | T3: May | U3: Jun | V3: Jul | W3: Ago | X3: Sep | Y3: Oct | Z3: Nov | AA3: Dic | AB3: Totales | AC3: Ene | AD3: Feb | AE3: Mar | AF3: Abr | AG3: May | AH3: Jun | AI3: Jul | AJ3: Ago | AK3: Totales | AL3: Sep | AM3: Oct | AN3: Nov | AO3: Dic | AP3: Ene | AQ3: Feb | AR3: Mar | AS3: Abr | AT3: May | AU3: Jun | AV3: Jul | AW3: Ago | AX3: Totales | AY3: Sep | AZ3: Oct | BA3: Nov | BB3: Dic | BC3: Ene | BD3: Feb | BE3: Mar | BF3: Abr | BG3: May | BH3: Jun | BI3: Jul | BJ3: Ago | BK3: Totales | BL3: Sep | BM3: Oct | BN3: Nov | BO3: Dic | BP3: Ene | BQ3: Feb | BR3: Mar | BS3: Abr | BT3: May | BU3: Jun | BV3: Jul | BW3: Ago | BX3: Totales | BY3: Sep | BZ3: Oct | CA3: Nov | CB3: Dic | CC3: Ene | CD3: Feb | CE3: Mar | CF3: Abr | CG3: May | CH3: Jun | CI3: Jul | CJ3: Ago | CK3: Totales | CL3: Sep | CM3: Oct | CN3: Nov | CO3: Dic | CP3: Ene | CQ3: Feb | CR3: Mar | CS3: Abr | CT3: May | CU3: Jun | CV3: Jul | CW3: Ago | CX3: Totales | CY3: Sep | CZ3: Oct | DA3: Nov | DB3: Dic | DC3: Ene | DD3: Feb | DE3: Mar | DF3: Abr | DG3: May | DH3: Jun | DI3: Jul | DJ3: Ago | DK3: Totales | DL3: Sep | DM3: Oct | DN3: Nov | DO3: Dic | DP3: Ene | DQ3: Feb | DR3: Mar | DS3: Abr | DT3: May | DU3: Jun | DV3: Jul | DW3: Ago | DX3: Totales
B4: Cobros | P4: =SUM(P6:P87) -> 50000 | Q4: =SUM(Q6:Q87) -> 40760 | R4: =SUM(R6:R87) -> 13612.5 | S4: =SUM(S6:S87) -> 22650 | T4: =SUM(T6:T87) -> 25462.7 | U4: =SUM(U6:U87) -> 9012.5 | V4: =SUM(V6:V87) -> 51853.17 | W4: =SUM(W6:W87) -> 24486.62 | ... AA4: =SUM(AA6:AA87) -> 12778.32 | AB4: =SUM(P4:AA4) -> 364294.36 | AC4: =SUM(AC6:AC87) -> 48220.83 | AD4: =SUM(AD6:AD87) -> 52830.32 | AE4: =SUM(AE6:AE87) -> 39000 | AF4: =SUM(AF6:AF87) -> 26074.41 | AG4: =SUM(AG6:AG87) -> 70790.355 | AH4: =SUM(AH6:AH87) -> 42463.314 | AI4: =SUM(AI6:AI87) -> 46654.299 | AJ4: =SUM(AJ6:AJ87) -> 18500 | AK4: =SUM(AC4:AJ4) -> 344533.53 | AL4: =SUM(AL6:AL87) -> 56309.052 | AM4: =SUM(AM6:AM87) -> 82185.933 | AN4: =SUM(AN6:AN87) -> 38500 | AO4: =SUM(AO6:AO87) -> 11448.475 | AP4: =SUM(AP6:AP87) -> 70203.846 | AQ4: =SUM(AQ6:AQ87) -> 13376.868 | AR4: =SUM(AR6:AR87) -> 42500 | AS4: =SUM(AS6:AS87) -> 12492.713 | ... AW4: =SUM(AW6:AW87) -> 35872.237 | AX4: =SUM(AL4:AW4) -> 556158.73 | AY4: =SUM(AY6:AY87) -> 100831.8 | AZ4: =SUM(AZ6:AZ87) -> 59361.532 | BA4: =SUM(BA6:BA87) -> 74138.987 | BB4: =SUM(BB6:BB87) -> 645636.63 | BC4: =SUM(BC6:BC87) -> 25471.577 | BD4: =SUM(BD6:BD87) -> 34537.5 | BE4: =SUM(BE6:BE87) -> 73384.65 | BF4: =SUM(BF6:BF87) -> 111695.33 | ... BJ4: =SUM(BJ6:BJ87) -> 66010.79 | BK4: =SUM(AY4:BJ4) -> 2075972.4 | BL4: =SUM(BL6:BL87) -> 34000 | BM4: =SUM(BM6:BM87) -> 17243.254 | BN4: =SUM(BN6:BN87) -> -611998.3 | BO4: =SUM(BO6:BO87) -> 45630.575 | BP4: =SUM(BP6:BP87) -> 116325.44 | BQ4: =SUM(BQ6:BQ87) -> 49058.562 | BR4: =SUM(BR6:BR87) -> 129337.53 | BS4: =SUM(BS6:BS87) -> 104496.17 | ... BW4: =SUM(BW6:BW87) -> 61273.33 | BX4: =SUM(BL4:BW4) -> -9109.6324 | BY4: =SUM(BY6:BY87) -> 32688.786 | BZ4: =SUM(BZ6:BZ87) -> 79900.912 | CA4: =SUM(CA6:CA87) -> 42825.233 | CB4: =SUM(CB6:CB87) -> 43500 | CC4: =SUM(CC6:CC87) -> 79921.479 | CD4: =SUM(CD6:CD87) -> 63280.333 | CE4: =SUM(CE6:CE87) -> 4535.4389 | CF4: =SUM(CF6:CF87) -> 45892.355 | ... CJ4: =SUM(CJ6:CJ87) -> 137858.48 | CK4: =SUM(BY4:CJ4) -> 814797.21 | CL4: =SUM(CL6:CL87) -> 65669.891 | CM4: =SUM(CM6:CM87) -> 52521.327 | CN4: =SUM(CN6:CN87) -> 72545.538 | CO4: =SUM(CO6:CO87) -> 44296.859 | CP4: =SUM(CP6:CP87) -> 69295.907 | CQ4: =SUM(CQ6:CQ87) -> 188415.03 | CR4: =SUM(CR6:CR87) -> 49942.355 | CS4: =SUM(CS6:CS87) -> 40241.074 | ... CW4: =SUM(CW6:CW87) -> 30794.444 | CX4: =SUM(CL4:CW4) -> 738450.23 | CY4: =SUM(CY6:CY87) -> -15753.245 | CZ4: =SUM(CZ6:CZ87) -> 36809.702 | DA4: =SUM(DA6:DA87) -> 0 | DB4: =SUM(DB6:DB87) -> 89440.957 | DC4: =SUM(DC6:DC87) -> 36250 | DD4: =SUM(DD6:DD87) -> 55522.949 | DE4: =SUM(DE6:DE87) -> 154869.3 | DF4: =SUM(DF6:DF87) -> 94488.449 | ... DJ4: =SUM(DJ6:DJ87) -> 70413.043 | DK4: =SUM(CY4:DJ4) -> 1270184 | DL4: =SUM(DL6:DL87) -> 19617.391 | DM4: =SUM(DM6:DM87) -> 82293.972 | DN4: =SUM(DN6:DN87) -> 42108.3 | DO4: =SUM(DO6:DO87) -> 10617.391 | DP4: =SUM(DP6:DP87) -> 138385.77 | DQ4: =SUM(DQ6:DQ87) -> 72700 | DR4: =SUM(DR6:DR87) -> 15000 | DS4: =SUM(DS6:DS87) -> 112272.73 | ... DW4: =SUM(DW6:DW87) -> 38395.652 | DX4: =SUM(DL4:DW4) -> 674763.93
B5: MKT INTELIGENCE | AK5: =SUM(AC5:AJ5) -> 0
B6: Alcodis | C6: 15000 | O6: =SUM(C6:N6) -> 15000 | Q6: 15000 | AB6: =SUM(P6:AA6) -> 15000 | AC6: 15000 | AK6: =SUM(AC6:AJ6) -> 15000 | AP6: 15000 | AX6: =SUM(AL6:AW6) -> 15000 | BC6: 15000 | BK6: =SUM(AY6:BJ6) -> 15000 | BR6: 15000 | BX6: =SUM(BL6:BW6) -> 15000 | CC6: 15000 | CK6: =SUM(BY6:CJ6) -> 15000 | CP6: 16000 | CX6: =SUM(CL6:CW6) -> 16000 | DE6: 16000 | DK6: =SUM(CY6:DJ6) -> 16000 | DP6: 15000 | DX6: =SUM(DL6:DW6) -> 15000
B7: Bioagra | D7: 35000 | O7: =SUM(C7:N7) -> 35000 | P7: 40000 | AB7: =SUM(P7:AA7) -> 40000 | AD7: 40000 | AK7: =SUM(AC7:AJ7) -> 40000 | AP7: 40000 | AX7: =SUM(AL7:AW7) -> 40000 | BE7: =40000+10000 -> 50000 | BK7: =SUM(AY7:BJ7) -> 50000 | BP7: =40000 -> 40000 | BX7: =SUM(BL7:BW7) -> 40000 | CC7: =41500 -> 41500 | CD7: =4200 -> 4200 | CK7: =SUM(BY7:CJ7) -> 45700 | CP7: 41500 | CS7: 4400 | CX7: =SUM(CL7:CW7) -> 45900 | DE7: 42300 | DF7: 8500 | DI7: 4400 | DK7: =SUM(CY7:DJ7) -> 55200 | DP7: 42300 | DX7: =SUM(DL7:DW7) -> 42300
B8: Verbio | E8: 15000 | O8: =SUM(C8:N8) -> 15000 | V8: 9000 | AB8: =SUM(P8:AA8) -> 9000 | AE8: =9000+30000 -> 39000 | AK8: =SUM(AC8:AJ8) -> 39000 | AU8: =9000 -> 9000 | AV8: 30000 | AX8: =SUM(AL8:AW8) -> 39000 | BF8: =9000+30000 -> 39000 | BK8: =SUM(AY8:BJ8) -> 39000 | BQ8: 15000 | BX8: =SUM(BL8:BW8) -> 15000 | CK8: =SUM(BY8:CJ8) -> 0 | CM8: =15000+4300 -> 19300 | CW8: =15000+4400 -> 19400 | CX8: =SUM(CM8:CW8) -> 38700 | DI8: =16000+4400 -> 20400 | DK8: =SUM(CY8:DJ8) -> 20400 | DQ8: 15000 | DX8: =SUM(DL8:DW8) -> 15000
B9: Vertex | E9: 0 | F9: 0 | G9: 0 | H9: 0 | O9: =SUM(C9:N9) -> 0 | Z9: =15000*1.21 -> 18150 | AB9: =SUM(P9:AA9) -> 18150 | AC9: 15000 | AK9: =SUM(AC9:AJ9) -> 15000 | AR9: =25000 -> 25000 | AX9: =SUM(AL9:AW9) -> 25000 | BA9: 25000 | BF9: =25000 -> 25000 | BK9: =SUM(AY9:BJ9) -> 50000 | BN9: =50000*0 -> 0 | BP9: =25000 -> 25000 | BS9: 25000 | BX9: =SUM(BL9:BW9) -> 50000 | CB9: 25000 | CF9: =4200+25000 -> 29200 | CK9: =SUM(BY9:CJ9) -> 54200 | CO9: 25000 | CT9: =25000+4400 -> 29400 | CX9: =SUM(CL9:CW9) -> 54400 | CZ9: =25000 -> 25000 | DG9: =25000 -> 25000 | DJ9: 4400 | DK9: =SUM(CY9:DJ9) -> 54400 | DM9: 25000 | DS9: 25000 | DX9: =SUM(DL9:DW9) -> 50000
B10: Shell | I10: 5000 | O10: =SUM(C10:N10) -> 5000 | V10: 4500 | AB10: =SUM(P10:AA10) -> 4500 | AG10: =4500 -> 4500 | AK10: =SUM(AC10:AJ10) -> 4500 | AP10: =4500 -> 4500 | AQ10: =4500 -> 4500 | AX10: =SUM(AL10:AW10) -> 9000 | AZ10: 4500 | BC10: 4500 | BK10: =SUM(AY10:BJ10) -> 9000 | BO10: 6000 | BS10: 6000 | BX10: =SUM(BL10:BW10) -> 12000 | BY10: 6000 | CB10: 6000 | CK10: =SUM(BY10:CJ10) -> 12000 | CQ10: =6500+6500 -> 13000 | CX10: =SUM(CQ10:CW10) -> 13000 | DE10: =6500+6500 -> 13000 | DI10: 6500 | DK10: =SUM(DA10:DJ10) -> 19500 | DO10: 6000 | DV10: 6000 | DX10: =SUM(DL10:DW10) -> 12000
B11: Ruhr | J11: 10000 | O11: =SUM(C11:N11) -> 10000 | X11: 10000 | AB11: =SUM(P11:AA11) -> 10000 | AK11: =SUM(AC11:AJ11) -> 0 | AL11: 10000 | AX11: =SUM(AL11:AW11) -> 10000 | AZ11: 10000 | BK11: =SUM(AY11:BJ11) -> 10000 | BL11: 10000 | BW11: 10500 | BX11: =SUM(BL11:BW11) -> 20500 | CK11: =SUM(BY11:CJ11) -> 0 | CL11: 9000 | CX11: =SUM(CL11:CW11) -> 9000 | DB11: 9000 | DJ11: 10500 | DK11: =SUM(DB11:DJ11) -> 19500 | DW11: 10500 | DX11: =SUM(DL11:DW11) -> 10500
B12: Cremer | M12: 7500 | O12: =SUM(C12:N12) -> 7500 | U12: 7500 | Y12: 7500 | AB12: =SUM(P12:AA12) -> 15000 | AG12: 7500 | AK12: =SUM(AC12:AJ12) -> 7500 | AN12: 7500 | AR12: 7500 | AX12: =SUM(AL12:AW12) -> 15000 | BA12: 7500 | BF12: 7500 | BK12: =SUM(AY12:BJ12) -> 15000 | BO12: 7500 | BR12: 7500 | BX12: =SUM(BL12:BW12) -> 15000 | CK12: =SUM(BY12:CJ12) -> 0 | CX12: =SUM(CL12:CW12) -> 0 | DK12: =SUM(CY12:DJ12) -> 0 | DX12: =SUM(DL12:DW12) -> 0
B13: Lantmannen | O13: =SUM(C13:N13) -> 0 | P13: 10000 | AB13: =SUM(P13:AA13) -> 10000 | AI13: 12500 | AK13: =SUM(AC13:AJ13) -> 12500 | AR13: 10000 | AX13: =SUM(AL13:AW13) -> 10000 | BE13: 10000 | BK13: =SUM(AY13:BJ13) -> 10000 | BR13: 12500 | BX13: =SUM(BL13:BW13) -> 12500 | CD13: 12000 | CK13: =SUM(BY13:CJ13) -> 12000 | CQ13: 12000 | CX13: =SUM(CL13:CW13) -> 12000 | DE13: 12000 | DK13: =SUM(CY13:DJ13) -> 12000 | DQ13: 12000 | DX13: =SUM(DL13:DW13) -> 12000
B14: Neste | O14: =SUM(C14:N14) -> 0 | Q14: 6000 | V14: 6000 | AB14: =SUM(P14:AA14) -> 12000 | AD14: 6000 | AJ14: 6000 | AK14: =SUM(AC14:AJ14) -> 12000 | AQ14: 6000 | AX14: =SUM(AL14:AW14) -> 6000 | AY14: 6000 | BF14: 6000 | BJ14: 6000 | BK14: =SUM(AY14:BJ14) -> 18000 | BQ14: 6000 | BV14: 6000 | BX14: =SUM(BL14:BW14) -> 12000 | CK14: =SUM(BY14:CJ14) -> 0 | CX14: =SUM(CL14:CW14) -> 0 | DK14: =SUM(CY14:DJ14) -> 0 | DX14: =SUM(DL14:DW14) -> 0
B15: Mabanaft | G15: 0 | H15: 5000 | O15: =SUM(C15:N15) -> 5000 | X15: =5000+5000 -> 10000 | AB15: =SUM(P15:AA15) -> 10000 | AD15: -5000 | AK15: =SUM(AC15:AJ15) -> -5000 | AX15: =SUM(AL15:AW15) -> 0 | BK15: =SUM(AY15:BJ15) -> 0 | BX15: =SUM(BL15:BW15) -> 0 | CK15: =SUM(BY15:CJ15) -> 0 | CX15: =SUM(CL15:CW15) -> 0 | DK15: =SUM(CY15:DJ15) -> 0 | DX15: =SUM(DL15:DW15) -> 0
B16: Sucden | O16: =SUM(C16:N16) -> 0 | S16: 4500 | AB16: =SUM(P16:AA16) -> 4500 | AI16: 4500 | AK16: =SUM(AC16:AJ16) -> 4500 | AX16: =SUM(AL16:AW16) -> 0 | BB16: 10000 | BK16: =SUM(AY16:BJ16) -> 10000 | BX16: =SUM(BL16:BW16) -> 0 | BY16: =5285+5715 -> 11000 | CG16: 4200 | CK16: =SUM(BY16:CJ16) -> 15200 | CS16: 4400 | CX16: =SUM(CL16:CW16) -> 4400 | DB16: 5500 | DH16: 4400 | DJ16: 6000 | DK16: =SUM(DB16:DJ16) -> 15900 | DW16: 6000 | DX16: =SUM(DL16:DW16) -> 6000
B17: Roquette | O17: =SUM(C17:N17) -> 0 | Q17: 12500 | AB17: =SUM(P17:AA17) -> 12500 | AC17: =12500 -> 12500 | AK17: =SUM(AC17:AJ17) -> 12500 | AN17: =12500*0 -> 0 | AX17: =SUM(AL17:AW17) -> 0 | BK17: =SUM(AY17:BJ17) -> 0 | BX17: =SUM(BL17:BW17) -> 0 | CK17: =SUM(BY17:CJ17) -> 0 | CX17: =SUM(CL17:CW17) -> 0 | DK17: =SUM(CY17:DJ17) -> 0 | DX17: =SUM(DL17:DW17) -> 0
B18: Greenergy | O18: =SUM(C18:N18) -> 0 | AB18: =SUM(P18:AA18) -> 0 | AF18: 12000 | AK18: =SUM(AC18:AJ18) -> 12000 | AU18: 12000 | AX18: =SUM(AL18:AW18) -> 12000 | BE18: 12000 | BK18: =SUM(AY18:BJ18) -> 12000 | BR18: 12000 | BX18: =SUM(BL18:BW18) -> 12000 | CD18: 13200 | CK18: =SUM(BY18:CJ18) -> 13200 | CP18: 13200 | CX18: =SUM(CL18:CW18) -> 13200 | DC18: 14000 | DK18: =SUM(CY18:DJ18) -> 14000 | DQ18: 13200 | DX18: =SUM(DL18:DW18) -> 13200
B19: Agrana | O19: =SUM(C19:N19) -> 0 | V19: 12500 | AB19: =SUM(P19:AA19) -> 12500 | AK19: =SUM(AC19:AJ19) -> 0 | AM19: 11500 | AW19: 12500 | AX19: =SUM(AL19:AW19) -> 24000 | BK19: =SUM(AY19:BJ19) -> 0 | BL19: 11500 | BV19: 12000 | BX19: =SUM(BL19:BV19) -> 23500 | CJ19: 12000 | CK19: =SUM(BY19:CJ19) -> 12000 | CW19: 13200 | CX19: =SUM(CL19:CW19) -> 13200 | DJ19: 13200 | DK19: =SUM(CY19:DJ19) -> 13200 | DW19: 13200 | DX19: =SUM(DL19:DW19) -> 13200
B20: SCA | O20: =SUM(C20:N20) -> 0 | T20: 7069.18 | AB20: =SUM(P20:AA20) -> 7069.18 | AI20: =4000/1.1608 -> 3445.8994 | AK20: =SUM(AC20:AJ20) -> 3445.8994 | AT20: =5000/1.2059 -> 4146.2808 | AX20: =SUM(AL20:AW20) -> 4146.2808 | BH20: =6000/1.0726 -> 5593.884 | BK20: =SUM(AY20:BJ20) -> 5593.884 | BS20: =6000/1.094 -> 5484.4607 | BX20: =SUM(BL20:BW20) -> 5484.4607 | CF20: =8000/1.072 -> 7462.6866 | CK20: =SUM(BY20:CJ20) -> 7462.6866 | CS20: =8500/1.1358 -> 7483.7119 | CX20: =SUM(CL20:CW20) -> 7483.7119 | DH20: =8500/1.15 -> 7391.3043 | DK20: =SUM(CY20:DJ20) -> 7391.3043 | DS20: =8000/1.1 -> 7272.7273 | DX20: =SUM(DL20:DW20) -> 7272.7273
B21: Raizen | O21: =SUM(C21:N21) -> 0 | AB21: =SUM(P21:AA21) -> 0 | AK21: =SUM(AC21:AJ21) -> 0 | AL21: 22000 | AV21: =22000/1.1767 -> 18696.354 | AX21: =SUM(AL21:AW21) -> 40696.354 | BF21: =22000/1.083 -> 20313.943 | BK21: =SUM(AY21:BJ21) -> 20313.943 | BR21: =22000/1.0875 -> 20229.885 | BX21: =SUM(BL21:BW21) -> 20229.885 | CH21: =22000/1.0842 -> 20291.459 | CK21: =SUM(BY21:CJ21) -> 20291.459 | CV21: =16500/1.1728 -> 14068.895 | CX21: =SUM(CL21:CW21) -> 14068.895 | DJ21: =10000/1.15 -> 8695.6522 | DK21: =SUM(CY21:DJ21) -> 8695.6522 | DR21: =16500/1.1 -> 15000 | DX21: =SUM(DL21:DW21) -> 15000
B22: Repsol | O22: =SUM(C22:N22) -> 0 | S22: =15000*1.21 -> 18150 | AB22: =SUM(P22:AA22) -> 18150 | AK22: =SUM(AC22:AJ22) -> 0 | AM22: =15000*1.21 -> 18150 | AT22: =15000*1.21 -> 18150 | AX22: =SUM(AL22:AW22) -> 36300 | BD22: =3750*1.21 -> 4537.5 | BH22: =15000*1.21 -> 18150 | BK22: =SUM(AY22:BJ22) -> 22687.5 | BS22: =16500*1.21 -> 19965 | BX22: =SUM(BL22:BW22) -> 19965 | CG22: =16900*1.21 -> 20449 | CK22: =SUM(BY22:CJ22) -> 20449 | CX22: =SUM(CL22:CW22) -> 0 | DK22: =SUM(CY22:DJ22) -> 0 | DX22: =SUM(DL22:DW22) -> 0
B23: Amerra | O23: =SUM(C23:N23) -> 0 | W23: 10771.99 | AB23: =SUM(P23:AA23) -> 10771.99 | AG23: =9000/1.0792 -> 8339.5107 | AK23: =SUM(AC23:AJ23) -> 8339.5107 | AX23: =SUM(AL23:AW23) -> 0 | BK23: =SUM(AY23:BJ23) -> 0 | BX23: =SUM(BL23:BW23) -> 0 | CK23: =SUM(BY23:CJ23) -> 0 | CX23: =SUM(CL23:CW23) -> 0 | DK23: =SUM(CY23:DJ23) -> 0 | DX23: =SUM(DL23:DW23) -> 0
B24: Amerra -RAA | AB24: =SUM(P24:AA24) -> 0 | AK24: =SUM(AC24:AJ24) -> 0 | AX24: =SUM(AL24:AW24) -> 0 | BI24: =15000/1.0005 -> 14992.504 | BK24: =SUM(AY24:BJ24) -> 14992.504 | BM24: =15000/1.0037 -> 14944.705 | BS24: =15000/1.0978 -> 13663.691 | BX24: =SUM(BL24:BW24) -> 28608.396 | CA24: =15000/1.0741 -> 13965.18 | CH24: =(24500-62)/1.0715 -> 22807.28 | CK24: =SUM(BY24:CJ24) -> 36772.46 | CT24: =(24500+17500-56)/1.1317 -> 37062.826 | CX24: =SUM(CL24:CW24) -> 37062.826 | DH24: =(24500+17500)/1.15 -> 36521.739 | DK24: =SUM(CY24:DJ24) -> 36521.739 | DS24: =(24500+17500)/1.1 -> 38181.818 | DX24: =SUM(DL24:DW24) -> 38181.818
B25: Amerra -SBA | AB25: =SUM(P25:AA25) -> 0 | AK25: =SUM(AC25:AJ25) -> 0 | AX25: =SUM(AL25:AW25) -> 0 | BI25: =5000/1.0425 -> 4796.1631 | BK25: =SUM(AY25:BJ25) -> 4796.1631 | BM25: =5000/0.986 -> 5070.9939 | BU25: =5000/1.0951 -> 4565.7931 | BX25: =SUM(BL25:BW25) -> 9636.787 | BZ25: =(5000-15)/1.053+15/1.0538 -> 4748.3273 | CH25: =17500/1.0705 -> 16347.501 | CK25: =SUM(BY25:CJ25) -> 21095.828 | CX25: =SUM(CL25:CW25) -> 0 | DK25: =SUM(CY25:DJ25) -> 0 | DX25: =SUM(DL25:DW25) -> 0
B26: Varo | O26: =SUM(C26:N26) -> 0 | T26: 12500 | AB26: =SUM(P26:AA26) -> 12500 | AG26: 12500 | AK26: =SUM(AC26:AJ26) -> 12500 | AW26: 0 | AX26: =SUM(AL26:AW26) -> 0 | BK26: =SUM(AY26:BJ26) -> 0 | BX26: =SUM(BL26:BW26) -> 0 | CK26: =SUM(BY26:CJ26) -> 0 | CM26: 15000 | CX26: =SUM(CL26:CW26) -> 15000 | DB26: 15000 | DK26: =SUM(DB26:DJ26) -> 15000 | DL26: 15000 | DX26: =SUM(DL26:DW26) -> 15000
B27: Enviral | M27: 18500 | O27: =SUM(C27:N27) -> 18500 | AB27: =SUM(P27:AA27) -> 0 | AG27: 18500 | AK27: =SUM(AC27:AJ27) -> 18500 | AN27: 18500 | AX27: =SUM(AL27:AW27) -> 18500 | BA27: 18500 | BK27: =SUM(AY27:BJ27) -> 18500 | BN27: 15000 | BX27: =SUM(BL27:BW27) -> 15000 | CA27: 15000 | CK27: =SUM(BY27:CJ27) -> 15000 | CQ27: 16975 | CX27: =SUM(CL27:CW27) -> 16975 | DB27: 16975 | DK27: =SUM(CY27:DJ27) -> 16975 | DM27: 16975 | DX27: =SUM(DL27:DW27) -> 16975
B28: Vivergo- British Sugar | O28: =SUM(C28:N28) -> 0 | V28: 12500 | AB28: =SUM(P28:AA28) -> 12500 | AJ28: 12500 | AK28: =SUM(AC28:AJ28) -> 12500 | AV28: 12500 | AX28: =SUM(AL28:AW28) -> 12500 | BK28: =SUM(AY28:BJ28) -> 0 | BL28: 12500 | BW28: 14000 | BX28: =SUM(BL28:BW28) -> 26500 | CI28: 14000 | CK28: =SUM(BY28:CJ28) -> 14000 | CV28: =14000*0 -> 0 | CX28: =SUM(CL28:CW28) -> 0 | DC28: 14000 | DJ28: 14000 | DK28: =SUM(CY28:DJ28) -> 28000 | DV28: =14000*0 -> 0 | DX28: =SUM(DL28:DW28) -> 0
B29: Neot | O29: =SUM(C29:N29) -> 0 | Y29: =500*12 -> 6000 | AB29: =SUM(P29:AA29) -> 6000 | AH29: 6000 | AK29: =SUM(AC29:AJ29) -> 6000 | AX29: =SUM(AL29:AW29) -> 0 | BA29: 8000 | BH29: 8000 | BK29: =SUM(AY29:BJ29) -> 16000 | BW29: 12000 | BX29: =SUM(BL29:BW29) -> 12000 | CH29: 12000 | CK29: =SUM(BY29:CJ29) -> 12000 | CX29: =SUM(CL29:CW29) -> 0 | CY29: 12600 | DI29: 12600 | DK29: =SUM(CY29:DJ29) -> 25200 | DV29: 12600 | DX29: =SUM(DL29:DW29) -> 12600
B30: Panonnia | O30: =SUM(C30:N30) -> 0 | Y30: 10000 | AB30: =SUM(P30:AA30) -> 10000 | AK30: =SUM(AC30:AJ30) -> 0 | AN30: 12500 | AX30: =SUM(AL30:AW30) -> 12500 | BA30: 12500 | BK30: =SUM(AY30:BJ30) -> 12500 | BN30: 12500 | BX30: =SUM(BL30:BW30) -> 12500 | CB30: 12500 | CG30: =4200 -> 4200 | CK30: =SUM(BY30:CJ30) -> 16700 | CP30: 12500 | CS30: 4400 | CX30: =SUM(CL30:CW30) -> 16900 | DB30: 14000 | DH30: 4400 | DK30: =SUM(CY30:DJ30) -> 18400 | DM30: 12500 | DX30: =SUM(DL30:DW30) -> 12500
B31: Marquis | O31: =SUM(C31:N31) -> 0 | AB31: =SUM(P31:AA31) -> 0 | AD31: =4570.32 -> 4570.32 | AK31: =SUM(AC31:AJ31) -> 4570.32 | AO31: =4109.32-1 -> 4108.32 | AX31: =SUM(AL31:AW31) -> 4108.32 | AZ31: =5041.8/1.1603+1933.2/1.1603 -> 6011.3764 | BK31: =SUM(AY31:BJ31) -> 6011.3764 | BR31: =9708.56/1.0586 -> 9171.1317 | BS31: =(10000-9708.56)/1.0972 -> 265.62158 | BX31: =SUM(BL31:BW31) -> 9436.7533 | BZ31: =10000/1.0569 -> 9461.6331 | CK31: =SUM(BY31:CJ31) -> 9461.6331 | CN31: =10000/1.0578 -> 9453.5829 | CX31: =SUM(CL31:CW31) -> 9453.5829 | DF31: =11000/1.1797 -> 9324.4045 | DK31: =SUM(CY31:DJ31) -> 9324.4045 | DM31: =11000/1.15 -> 9565.2174 | DN31: =10000/1.1 -> 9090.9091 | DX31: =SUM(DL31:DW31) -> 18656.126 | DZ31: =11000/1.15 -> 9565.2174
B32: FC Betterave (Cristalco) | O32: =SUM(C32:N32) -> 0 | Y32: =12500*1.21 -> 15125 | AB32: =SUM(P32:AA32) -> 15125 | AK32: =SUM(AC32:AJ32) -> 0 | AM32: =12500*1.21 -> 15125 | AX32: =SUM(AL32:AW32) -> 15125 | AZ32: =12500*1.21 -> 15125 | BK32: =SUM(AY32:BJ32) -> 15125 | BN32: =12500*1.21 -> 15125 | BX32: =SUM(BL32:BW32) -> 15125 | CA32: =13000*1.21 -> 15730 | CK32: =SUM(BY32:CJ32) -> 15730 | CQ32: 12500 | CX32: =SUM(CL32:CW32) -> 12500 | DE32: 12500 | DK32: =SUM(CY32:DJ32) -> 12500 | DN32: 12500 | DX32: =SUM(DL32:DW32) -> 12500
B33: Redwood Group | O33: =SUM(C33:N33) -> 0 | AB33: =SUM(P33:AA33) -> 0 | AF33: 9074.41 | AI33: 4208.4 | AK33: =SUM(AC33:AJ33) -> 13282.81 | AT33: =5000/1.206+3000/1.206+3000/1.206 -> 9121.0614 | AW33: =3000/1.1736 -> 2556.2372 | AX33: =SUM(AL33:AW33) -> 11677.299 | BA33: =3000/1.1368 -> 2638.9866 | BF33: =3000/1.1052 -> 2714.4408 | BG33: =3000/1.0524 -> 2850.6271 | BI33: =3000/1.0124 -> 2963.2556 | BK33: =SUM(AY33:BJ33) -> 11167.31 | BM33: =3000/0.9778 -> 3068.1121 | BQ33: =3000/1.07 -> 2803.7383 | BS33: =3000/1.1002 -> 2726.7769 | BV33: =3000/1.1059 -> 2712.7227 | BX33: =SUM(BL33:BV33) -> 11311.35 | BZ33: =3000/1.0597 -> 2830.9899 | CK33: =SUM(BY33:CJ33) -> 2830.9899 | CX33: =SUM(CL33:CW33) -> 0 | DK33: =SUM(CY33:DJ33) -> 0 | DX33: =SUM(DL33:DW33) -> 0
B34: Nordzucker AG | O34: =SUM(C34:N34) -> 0 | AB34: =SUM(P34:AA34) -> 0 | AF34: 5000 | AK34: =SUM(AC34:AJ34) -> 5000 | AP34: 5000 | AX34: =SUM(AL34:AW34) -> 5000 | BD34: 5000 | BK34: =SUM(AY34:BJ34) -> 5000 | BR34: 5000 | BX34: =SUM(BL34:BW34) -> 5000 | CD34: 5500 | CK34: =SUM(BY34:CJ34) -> 5500 | CQ34: 6000 | CX34: =SUM(CL34:CW34) -> 6000 | DE34: 6000 | DK34: =SUM(CY34:DJ34) -> 6000 | DQ34: 6000 | DX34: =SUM(DL34:DW34) -> 6000
B35: Castleton Commodities Int. LLC | O35: =SUM(C35:N35) -> 0 | AB35: =SUM(P35:AA35) -> 0 | AH35: =8000/1.1285 -> 7089.0563 | AK35: =SUM(AC35:AJ35) -> 7089.0563 | AX35: =SUM(AL35:AW35) -> 0 | AZ35: =7987/1.16 -> 6885.3448 | BK35: =SUM(AZ35:BJ35) -> 6885.3448 | BX35: =SUM(BL35:BW35) -> 0 | CK35: =SUM(BY35:CJ35) -> 0 | CX35: =SUM(CL35:CW35) -> 0 | DK35: =SUM(CY35:DJ35) -> 0 | DX35: =SUM(DL35:DW35) -> 0
B36: OCI FUELS B.V. | O36: =SUM(C36:N36) -> 0 | AB36: 0 | AI36: 22000 | AK36: =SUM(AC36:AJ36) -> 22000 | AX36: =SUM(AL36:AW36) -> 0 | BB36: 22000 | BJ36: 22000 | BK36: =SUM(BB36:BJ36) -> 44000 | BW36: 16500 | BX36: =SUM(BL36:BW36) -> 16500 | CI36: 16500 | CK36: =SUM(BY36:CJ36) -> 16500 | CU36: 16500 | CX36: =SUM(CL36:CW36) -> 16500 | DI36: 16500 | DK36: =SUM(CY36:DJ36) -> 16500 | DV36: 16500 | DX36: =SUM(DL36:DW36) -> 16500
B37: Poet | AB37: 0 | AK37: =SUM(AC37:AJ37) -> 0 | AP37: =(7000-33)/1.2166-27.87/1.224 -> 5703.8455 | AQ37: =21.87/1.224 -> 17.867647 | AX37: =SUM(AL37:AW37) -> 5721.7132 | BC37: =(7000-335.72)/1.116 -> 5971.5771 | BJ37: 0 | BK37: =SUM(AY37:BJ37) -> 5971.5771 | BP37: =11720.21/1.0903 -> 10749.528 | BQ37: =280/1.0988 -> 254.82344 | BX37: =SUM(BL37:BW37) -> 11004.351 | CG37: =15000/1.0698 -> 14021.312 | CK37: =SUM(BY37:CJ37) -> 14021.312 | CP37: =15000/1.0443 -> 14363.689 | CX37: =SUM(CL37:CW37) -> 14363.689 | DE37: =16000/1.1555 -> 13846.82 | DK37: =SUM(CY37:DJ37) -> 13846.82 | DP37: =15000/1.1 -> 13636.364 | DX37: =SUM(DL37:DW37) -> 13636.364
B38: OMV | AB38: 0 | AK38: =SUM(AC38:AJ38) -> 0 | AW38: =7600+13000 -> 20600 | AX38: =SUM(AL38:AW38) -> 20600 | BK38: =SUM(AY38:BJ38) -> 0 | BR38: =15000+15000 -> 30000 | BX38: =SUM(BL38:BW38) -> 30000 | CK38: =SUM(BY38:CJ38) -> 0 | CR38: 16500 | CX38: =SUM(CL38:CW38) -> 16500 | DH38: 16500 | DK38: =SUM(CY38:DJ38) -> 16500 | DP38: 16500 | DX38: =SUM(DL38:DW38) -> 16500
B39: Totsa | AB39: 0 | AK39: =SUM(AC39:AJ39) -> 0 | AX39: =SUM(AL39:AW39) -> 0 | AY39: 24000 | BK39: =SUM(AY39:BJ39) -> 24000 | BN39: 24000 | BX39: =SUM(BL39:BW39) -> 24000 | BZ39: 36000 | CK39: =SUM(BZ39:CJ39) -> 36000 | CR39: 24000 | CX39: =SUM(CL39:CW39) -> 24000 | DF39: 24480 | DK39: =SUM(CY39:DJ39) -> 24480 | DP39: 24000 | DX39: =SUM(DL39:DW39) -> 24000
B40: Trafigura | AB40: 0 | AK40: =SUM(AC40:AJ40) -> 0 | AX40: =SUM(AL40:AW40) -> 0 | BD40: 15000 | BK40: =SUM(AY40:BJ40) -> 15000 | BQ40: 15000 | BX40: =SUM(BL40:BW40) -> 15000 | BZ40: 15900 | CK40: =SUM(BY40:CJ40) -> 15900 | CN40: 15900 | CX40: =SUM(CL40:CW40) -> 15900 | DB40: 16200 | DK40: =SUM(CY40:DJ40) -> 16200 | DN40: 15900 | DX40: =SUM(DL40:DW40) -> 15900
B41: Ethanol Energy | AB41: 0 | AK41: =SUM(AC41:AJ41) -> 0 | AX41: =SUM(AL41:AW41) -> 0 | BD41: 10000 | BK41: =SUM(AY41:BJ41) -> 10000 | BQ41: 10000 | BX41: =SUM(BL41:BW41) -> 10000 | CD41: 10000 | CK41: =SUM(BY41:CJ41) -> 10000 | CW41: =10000*0 -> 0 | CX41: =SUM(CL41:CW41) -> 0 | DD41: 0 | DK41: =SUM(CY41:DJ41) -> 0 | DQ41: 10000 | DX41: =SUM(DL41:DW41) -> 10000
B42: Pantaleon Commodities Corp. | AB42: 0 | AK42: =SUM(AC42:AJ42) -> 0 | AX42: =SUM(AL42:AW42) -> 0 | BF42: =12000/1.0746 -> 11166.946 | BK42: =SUM(AY42:BJ42) -> 11166.946 | BS42: =14000/1.087 -> 12879.485 | BX42: =SUM(BL42:BW42) -> 12879.485 | CG42: =15000/1.0779 -> 13915.948 | CK42: =SUM(BY42:CJ42) -> 13915.948 | CU42: =12000/1.141 -> 10517.09 | CX42: =SUM(CL42:CW42) -> 10517.09 | DE42: 0 | DK42: =SUM(CY42:DJ42) -> 0 | DR42: 0 | DX42: =SUM(DL42:DW42) -> 0
B43: KWST Alambix | AB43: 0 | AK43: =SUM(AC43:AJ43) -> 0 | AX43: =SUM(AL43:AW43) -> 0 | BG43: 4000 | BK43: =SUM(AY43:BJ43) -> 4000 | BS43: =4000-4000 -> 0 | BU43: =4000 -> 4000 | BX43: =SUM(BL43:BW43) -> 4000 | CK43: =SUM(BY43:CJ43) -> 0 | CX43: =SUM(CL43:CW43) -> 0 | DK43: =SUM(CY43:DJ43) -> 0 | DX43: =SUM(DL43:DW43) -> 0
B44: EDF Trading | AB44: 0 | AK44: =SUM(AC44:AJ44) -> 0 | AX44: =SUM(AL44:AW44) -> 0 | BI44: 9000 | BK44: =SUM(AY44:BJ44) -> 9000 | BO44: 9000 | BU44: 8250 | BX44: =SUM(BL44:BW44) -> 17250 | CA44: 8250 | CK44: =SUM(BY44:CJ44) -> 8250 | CL44: 16500 | CT44: 16500 | CX44: =SUM(CL44:CW44) -> 33000 | DH44: 0 | DK44: =SUM(CY44:DJ44) -> 0 | DX44: =SUM(DL44:DW44) -> 0
B45: Vopak- Liquin B.V. | AB45: 0 | AK45: =SUM(AC45:AJ45) -> 0 | AX45: =SUM(AL45:AW45) -> 0 | BI45: 8000 | BK45: =SUM(AY45:BJ45) -> 8000 | BW45: 8000 | BX45: =SUM(BL45:BW45) -> 8000 | CH45: 8000 | CK45: =SUM(BY45:CJ45) -> 8000 | CW45: 8000 | CX45: =SUM(CL45:CW45) -> 8000 | DI45: 8000 | DK45: =SUM(CY45:DJ45) -> 8000 | DV45: 8000 | DX45: =SUM(DL45:DW45) -> 8000
B46: Harvestone Commodities, LLC | AB46: 0 | AK46: =SUM(AC46:AJ46) -> 0 | AX46: =SUM(AL46:AW46) -> 0 | BK46: =SUM(AY46:BJ46) -> 0 | BM46: =12000/0.9778 -> 12272.448 | BX46: =SUM(BL46:BW46) -> 12272.448 | CK46: =SUM(BY46:CJ46) -> 0 | CM46: =15000/1.0897 -> 13765.256 | CX46: =SUM(CL46:CW46) -> 13765.256 | DB46: =15000/1.175 -> 12765.957 | DK46: =SUM(CY46:DJ46) -> 12765.957 | DM46: =15000/1.1 -> 13636.364 | DX46: =SUM(DL46:DW46) -> 13636.364
B47: Almagest EAD | AB47: 0 | AK47: =SUM(AC47:AJ47) -> 0 | AX47: =SUM(AL47:AW47) -> 0 | BK47: =SUM(AY47:BJ47) -> 0 | BV47: 9000 | BX47: =SUM(BL47:BW47) -> 9000 | CI47: 9000 | CK47: =SUM(BY47:CJ47) -> 9000 | CU47: 9000 | CX47: =SUM(CL47:CW47) -> 9000 | DJ47: 9000 | DK47: =SUM(CY47:DJ47) -> 9000 | DU47: 9000 | DX47: =SUM(DL47:DW47) -> 9000
B48: U.S. Grains Council | AB48: 0 | AK48: =SUM(AC48:AJ48) -> 0 | AX48: =SUM(AL48:AW48) -> 0 | BK48: =SUM(AY48:BJ48) -> 0 | BX48: =SUM(BL48:BW48) -> 0 | BY48: =(1755.6-20)/1.0704 -> 1621.4499 | BZ48: =(4200+4200+3165.84-25)/1.053 -> 10959.962 | CC48: =(4762.25+3857.18+4200+4200+4200+2830.19+2780.42-35)/1.0887 -> 24611.959 | CD48: =(4960-20)/1.0826 -> 4563.0889 | CE48: =(4960-20)/1.0892 -> 4535.4389 | CF48: =(4960+5088.42-25)/1.086 -> 9229.6685 | CH48: =(4960-20)/1.073 -> 4603.9143 | CI48: =(4960+3584.28+2914.91-25)/1.0758+5149.6/1.0907+(4960-20)/1.0848 -> 19903.753 | CJ48: =(4960+219.3-40)/1.1117 -> 4622.9199 | CK48: =SUM(BY48:CJ48) -> 84652.154 | CL48: =(4960-20)/1.1119 -> 4442.8456 | CM48: =(4960-20)/1.1086 -> 4456.0707 | CO48: =(4960+4960-20)/1.0496+5812.9/1.0389 -> 15027.41 | CQ48: =(4960+4389.22)/1.032 -> 9059.3217 | CR48: =(5160+5160-25)/1.0903 -> 9442.3553 | CT48: =(5160-20)/1.136+(5160-20)/1.1185 -> 9120.0882 | CV48: =(5160-20)/1.1602 -> 4430.2706 | CW48: =(5160-20)/1.1565 -> 4444.4444 | CX48: =SUM(CL48:CW48) -> 60422.806 | CY48: =(5160-20)/1.1766+(5160-20)/1.1756 -> 8740.7549 | CZ48: =(5160-20)/1.1724+2794.78/1.1569+6483.89/1.1612 -> 12383.702 | DD48: =((5160+5160+5160)-50)/1.1886+((4051.34+9390.61+2702.16)-50)/1.1826 -> 26590.749 | DE48: =(5310+5310-50)/1.1539 -> 9160.2392 | DG48: =(5310+2483.1+5561.48-50)/1.1762 -> 11311.495 | DH48: =(5310+5310)/1.15 -> 9234.7826 | DI48: =5310/1.15 -> 4617.3913 | DJ48: =5310/1.15 -> 4617.3913 | DK48: =SUM(CY48:DJ48) -> 86656.505 | DL48: =5310/1.15 -> 4617.3913 | DM48: =5310/1.15 -> 4617.3913 | DN48: =5310/1.15 -> 4617.3913 | DO48: =5310/1.15 -> 4617.3913 | DP48: =5310/1.15 -> 4617.3913 | DX48: =SUM(DL48:DW48) -> 23086.957
B49: Lyondell Chemie Nederland B.V. | AB49: 0 | AK49: =SUM(AC49:AJ49) -> 0 | AX49: =SUM(AL49:AW49) -> 0 | BK49: =SUM(AY49:BJ49) -> 0 | BX49: =SUM(BL49:BW49) -> 0 | BY49: =15000/1.0663 -> 14067.336 | CD49: =15000/1.0856 -> 13817.244 | CK49: =SUM(BY49:CJ49) -> 27884.58 | CQ49: =15000/1.0447 -> 14358.189 | CX49: =SUM(CL49:CW49) -> 14358.189 | DI49: =15000/1.15 -> 13043.478 | DK49: =SUM(CY49:DJ49) -> 13043.478 | DP49: =15000/1.1 -> 13636.364 | DX49: =SUM(DL49:DW49) -> 13636.364
B50: Ipiranga Trading Limited | AX50: =SUM(AL50:AW50) -> 0 | BK50: =SUM(AY50:BJ50) -> 0 | BX50: =SUM(BL50:BW50) -> 0 | CK50: =SUM(BY50:CJ50) -> 0 | CN50: =4500/1.0531 -> 4273.0985 | CO50: =4500/1.054 -> 4269.4497 | CV50: =15000/1.1698 -> 12822.705 | CX50: =SUM(CL50:CW50) -> 21365.253 | DH50: =15000/1.1*0 -> 0 | DK50: =SUM(CY50:DJ50) -> 0 | DT50: =15000/1.1*0 -> 0 | DX50: =SUM(DL50:DW50) -> 0
B51: Kolmar Americas, Inc. | AX51: =SUM(AL51:AW51) -> 0 | BK51: =SUM(AY51:BJ51) -> 0 | BX51: =SUM(BL51:BW51) -> 0 | CK51: =SUM(BY51:CJ51) -> 0 | CV51: =16500/1.1698 -> 14104.975 | CX51: =SUM(CL51:CW51) -> 14104.975 | DH51: =16500/1.15 -> 14347.826 | DK51: =SUM(CY51:DJ51) -> 14347.826 | DT51: =16500/1.1 -> 15000 | DX51: =SUM(DL51:DW51) -> 15000
B52: Gapuma Switzerland AG | AX52: =SUM(AL52:AW52) -> 0 | BK52: =SUM(AY52:BJ52) -> 0 | BX52: =SUM(BL52:BW52) -> 0 | CK52: =SUM(BY52:CJ52) -> 0 | CS52: =10000/1.1082 -> 9023.6419 | CX52: =SUM(CL52:CW52) -> 9023.6419 | DE52: 8631.17 | DF52: =-8631.17+10300/1.1797 -> 99.863314 | DK52: =SUM(CY52:DJ52) -> 8731.0333 | DS52: =10000/1.1 -> 9090.9091 | DX52: =SUM(DL52:DW52) -> 9090.9091
B53: Targray | AX53: =SUM(AL53:AW53) -> 0 | BK53: =SUM(AY53:BJ53) -> 0 | BX53: =SUM(BL53:BW53) -> 0 | CK53: =SUM(BY53:CJ53) -> 0 | CU53: 24000 | CX53: =SUM(CL53:CW53) -> 24000 | DE53: -3000 | DK53: =SUM(CY53:DJ53) -> -3000 | DU53: 24000 | DX53: =SUM(DL53:DW53) -> 24000
B54: Tricon | CK54: =SUM(BY54:CJ54) -> 0 | CT54: =8000/1.1185 -> 7152.4363 | CX54: =SUM(CL54:CW54) -> 7152.4363 | DH54: =8000/1.15 -> 6956.5217 | DK54: =SUM(CY54:DJ54) -> 6956.5217 | DT54: =8000/1.1 -> 7272.7273 | DX54: =SUM(DL54:DW54) -> 7272.7273
B55: Greenfield | CK55: =SUM(BY55:CJ55) -> 0 | CS55: =(12000-20)/1.1373 -> 10533.72 | CX55: =SUM(CL55:CW55) -> 10533.72 | DF55: =(12800-135.55)/1.1782 -> 10748.981 | DK55: =SUM(CY55:DJ55) -> 10748.981 | DS55: =12000/1.1 -> 10909.091 | DX55: =SUM(DL55:DW55) -> 10909.091
B56: Atvos | AX56: =SUM(AL56:AW56) -> 0 | BK56: =SUM(AY56:BJ56) -> 0 | CK56: =SUM(BY56:CJ56) -> 0 | CU56: =24000/1.1386 -> 21078.517 | CX56: =SUM(CL56:CW56) -> 21078.517 | DH56: =24000/1.15 -> 20869.565 | DK56: =SUM(CY56:DJ56) -> 20869.565 | DS56: =24000/1.1 -> 21818.182 | DX56: =SUM(DL56:DW56) -> 21818.182
B57: Cargill | CK57: =SUM(BY57:CJ57) -> 0 | CX57: =SUM(CL57:CW57) -> 0 | CZ57: =16500/2 -> 8250 | DC57: =16500/2 -> 8250 | DK57: =SUM(CY57:DJ57) -> 16500 | DX57: =SUM(DL57:DW57) -> 0
B58: ADNOC Global Trading Europe S.A | CK58: =SUM(BY58:CJ58) -> 0 | CX58: =SUM(CL58:CW58) -> 0 | DD58: 24500 | DI58: 25000 | DK58: =SUM(CY58:DJ58) -> 49500 | DU58: 25000 | DX58: =SUM(DL58:DW58) -> 25000
B59: Inpasa | CX59: =SUM(CL59:CW59) -> 0 | DE59: =8000/1.1476 -> 6971.0701 | DK59: =SUM(CY59:DJ59) -> 6971.0701 | DP59: =10000/1.15 -> 8695.6522 | DW59: =10000/1.15 -> 8695.6522 | DX59: =SUM(DL59:DW59) -> 17391.304
B60: Bunge | DG60: 16500 | DK60: =SUM(CY60:DJ60) -> 16500 | DQ60: 16500 | DX60: =SUM(DL60:DW60) -> 16500
B61: AdHoc | O61: =SUM(C61:N61) -> 0 | BX61: =SUM(BL61:BW61) -> 0 | CK61: =SUM(BY61:CJ61) -> 0 | CX61: =SUM(CL61:CW61) -> 0 | DK61: =SUM(CY61:DJ61) -> 0 | DX61: =SUM(DL61:DW61) -> 0
B62: Dropet Intertrading | O62: =SUM(C62:N62) -> 0 | X62: 2076.36 | AB62: =SUM(P62:AA62) -> 2076.36 | AK62: =SUM(AC62:AJ62) -> 0 | AX62: =SUM(AL62:AW62) -> 0 | BK62: =SUM(AY62:BJ62) -> 0 | BX62: =SUM(BL62:BW62) -> 0 | CK62: =SUM(BY62:CJ62) -> 0 | CX62: =SUM(CL62:CW62) -> 0 | DK62: =SUM(CY62:DJ62) -> 0 | DX62: =SUM(DL62:DW62) -> 0
B63: Repsol | O63: =SUM(C63:N63) -> 0 | R63: =15000*0.75*1.21 -> 13612.5 | AB63: =SUM(P63:AA63) -> 13612.5 | AK63: =SUM(AC63:AJ63) -> 0 | AX63: =SUM(AL63:AW63) -> 0 | BJ63: =15000*0.25*0 -> 0 | BK63: =SUM(AY63:BJ63) -> 0 | BX63: =SUM(BL63:BW63) -> 0 | CK63: =SUM(BY63:CJ63) -> 0 | CX63: =SUM(CL63:CW63) -> 0 | DK63: =SUM(CY63:DJ63) -> 0 | DX63: =SUM(DL63:DW63) -> 0
B64: Vertex | G64: =4000*1.21 -> 4840 | O64: =SUM(C64:N64) -> 4840 | Q64: 7260 | AB64: =SUM(P64:AA64) -> 7260 | AC64: =5000 -> 5000 | AD64: 7260 | AK64: =SUM(AC64:AJ64) -> 12260 | AX64: =SUM(AL64:AW64) -> 0 | BK64: =SUM(AY64:BJ64) -> 0 | BX64: =SUM(BL64:BW64) -> 0 | CK64: =SUM(BY64:CJ64) -> 0 | CX64: =SUM(CL64:CW64) -> 0 | DK64: =SUM(CY64:DJ64) -> 0 | DX64: =SUM(DL64:DW64) -> 0
B65: Cepsa | O65: =SUM(C65:N65) -> 0 | U65: 1512.5 | AB65: =SUM(P65:AA65) -> 1512.5 | AK65: =SUM(AC65:AJ65) -> 0 | AX65: =SUM(AL65:AW65) -> 0 | BK65: =SUM(AY65:BJ65) -> 0 | BX65: =SUM(BL65:BW65) -> 0 | CK65: =SUM(BY65:CJ65) -> 0 | CX65: =SUM(CL65:CW65) -> 0 | DK65: =SUM(CY65:DJ65) -> 0 | DX65: =SUM(DL65:DW65) -> 0
B66: Guidepoint | O66: =SUM(C66:N66) -> 0 | W66: 238.55 | AB66: =SUM(P66:AA66) -> 238.55 | AC66: =720.83 -> 720.83 | AG66: =215.93 -> 215.93 | AK66: =SUM(AC66:AJ66) -> 936.76 | AX66: =SUM(AL66:AW66) -> 0 | BE66: 650 | BK66: =SUM(AY66:BJ66) -> 650 | BW66: 273.33 | BX66: =SUM(BL66:BW66) -> 273.33 | CK66: =SUM(BY66:CJ66) -> 0 | CX66: =SUM(CL66:CW66) -> 0 | DK66: =SUM(CY66:DJ66) -> 0 | DX66: =SUM(DL66:DW66) -> 0
B67: DWS Alternatives Global Limited-PEIF | O67: =SUM(C67:N67) -> 0 | AB67: =SUM(P67:AA67) -> 0 | AK67: =SUM(AC67:AJ67) -> 0 | AL67: 19508 | AM67: 2782.5 | AX67: =SUM(AL67:AW67) -> 22290.5 | BK67: =SUM(AY67:BJ67) -> 0 | BX67: =SUM(BL67:BW67) -> 0 | CK67: =SUM(BY67:CJ67) -> 0 | CX67: =SUM(CL67:CW67) -> 0 | DK67: =SUM(CY67:DJ67) -> 0 | DX67: =SUM(DL67:DW67) -> 0
B68: Tomsa Destil, S.L. | AB68: =SUM(P68:AA68) -> 0 | AK68: =SUM(AC68:AJ68) -> 0 | AO68: =2201.63*1.21 -> 2663.9723 | AX68: =SUM(AL68:AW68) -> 2663.9723 | BK68: =SUM(AY68:BJ68) -> 0 | BX68: =SUM(BL68:BW68) -> 0 | CK68: =SUM(BY68:CJ68) -> 0 | CX68: =SUM(CL68:CW68) -> 0 | DK68: =SUM(CY68:DJ68) -> 0 | DX68: =SUM(DL68:DW68) -> 0
B69: GranBio | CK69: =SUM(BY69:CJ69) -> 0 | CU69: =(5980-5) -> 5975 | CV69: =(10000-5) -> 9995 | CX69: =SUM(CL69:CW69) -> 15970 | DI69: =13920-2135 -> 11785 | DK69: =SUM(DI69:DJ69) -> 11785 | DX69: =SUM(DL69:DW69) -> 0
B70: BROKERAGE | O70: =SUM(C70:N70) -> 0 | BX70: =SUM(BL70:BW70) -> 0 | CK70: =SUM(BY70:CJ70) -> 0 | CX70: =SUM(CL70:CW70) -> 0 | DK70: =SUM(CY70:DJ70) -> 0 | DX70: =SUM(DL70:DW70) -> 0
B71: Enviral | O71: =SUM(C71:N71) -> 0 | V71: =1174.58 -> 1174.58 | AB71: =SUM(P71:AA71) -> 1174.58 | AK71: =SUM(AC71:AJ71) -> 0 | AX71: =SUM(AL71:AW71) -> 0 | BK71: =SUM(AY71:BJ71) -> 0 | BX71: =SUM(BL71:BW71) -> 0 | CK71: =SUM(BY71:CJ71) -> 0 | CX71: =SUM(CL71:CW71) -> 0 | DK71: =SUM(CY71:DJ71) -> 0 | DX71: =SUM(DL71:DW71) -> 0
B72: Interalco | O72: =SUM(C72:N72) -> 0 | V72: =1203.1+4975.49 -> 6178.59 | W72: =2294.62+5739.08 -> 8033.7 | AB72: =SUM(P72:AA72) -> 14212.29 | AK72: =SUM(AC72:AJ72) -> 0 | AX72: =SUM(AL72:AW72) -> 0 | BK72: =SUM(AY72:BJ72) -> 0 | BX72: =SUM(BL72:BW72) -> 0 | CK72: =SUM(BY72:CJ72) -> 0 | CX72: =SUM(CL72:CW72) -> 0 | DK72: =SUM(CY72:DJ72) -> 0 | DX72: =SUM(DL72:DW72) -> 0
B73: Murex | O73: =SUM(C73:N73) -> 0 | T73: 5893.52 | W73: 5442.38 | AB73: =SUM(P73:AA73) -> 11335.9 | AK73: =SUM(AC73:AJ73) -> 0 | AX73: =SUM(AL73:AW73) -> 0 | BK73: =SUM(AY73:BJ73) -> 0 | BX73: =SUM(BL73:BW73) -> 0 | CK73: =SUM(BY73:CJ73) -> 0 | CX73: =SUM(CL73:CW73) -> 0 | DK73: =SUM(CY73:DJ73) -> 0 | DX73: =SUM(DL73:DW73) -> 0
B74: Seaboard | O74: =SUM(C74:N74) -> 0 | AA74: =12803.93-25.61 -> 12778.32 | AB74: =SUM(P74:AA74) -> 12778.32 | AH74: =7000*2.5/1.1*0 -> 0 | AI74: =7000*2.5/1.1*0 -> 0 | AJ74: =7000*2.5/1.1*0 -> 0 | AK74: =SUM(AC74:AJ74) -> 0 | AS74: =15000/1.2007 -> 12492.713 | AX74: =SUM(AL74:AW74) -> 12492.713 | BK74: =SUM(AY74:BJ74) -> 0 | BL74: =15000*2/1.1*0 -> 0 | BX74: =SUM(BL74:BW74) -> 0 | CK74: =SUM(BY74:CJ74) -> 0 | CX74: =SUM(CL74:CW74) -> 0 | DK74: =SUM(CY74:DJ74) -> 0 | DX74: =SUM(DL74:DW74) -> 0
B75: Cremer | O75: =SUM(C75:N75) -> 0 | X75: 21889.39 | Z75: =12963.73-25.93 -> 12937.8 | AB75: =SUM(P75:AA75) -> 34827.19 | AK75: =SUM(AC75:AJ75) -> 0 | AM75: =7522*2/1.177 -> 12781.648 | AU75: =45126*0 -> 0 | AX75: =SUM(AL75:AW75) -> 12781.648 | AZ75: =9804.98*2/1.1645 -> 16839.811 | BK75: =SUM(AY75:BJ75) -> 16839.811 | BX75: =SUM(BL75:BW75) -> 0 | CK75: =SUM(BY75:CJ75) -> 0 | CX75: =SUM(CL75:CW75) -> 0 | DK75: =SUM(CY75:DJ75) -> 0 | DX75: =SUM(DL75:DW75) -> 0
B76: ACA Bio | O76: =SUM(C76:N76) -> 0 | AB76: 0 | AK76: =SUM(AC76:AJ76) -> 0 | AL76: =5659/1.1787 -> 4801.052 | AO76: =8500*0.75*0.9/1.2267-1 -> 4676.1827 | AT76: =(2625*0.9)/1.2201 -> 1936.3167 | AU76: =+AU75*0.15 -> 0 | AX76: =SUM(AL76:AW76) -> 11413.551 | BB76: =(9804.98*0.75-735.37)/1.1291 -> 5861.6287 | BE76: =(637.5+262.5)/1.225073 -> 734.6501 | BK76: =SUM(AY76:BJ76) -> 6596.2788 | BR76: =735.37/1.128664+(20000-2000)/1.0745 -> 17403.518 | BX76: =SUM(BL76:BW76) -> 17403.518 | CI76: =(20000-18000)/0.929454 -> 2151.8009 | CK76: =SUM(BY76:CJ76) -> 2151.8009 | CL76: =40000/1.1196 -> 35727.045 | CM76: =20000/1-20000/1+20000/1-20000/1 -> 0 | CX76: =SUM(CL76:CW76) -> 35727.045 | DH76: =20000/1.15 -> 17391.304 | DI76: 20000 | DK76: =SUM(CZ76:DJ76) -> 37391.304 | DV76: 20000 | DX76: =SUM(DL76:DW76) -> 20000
B77: CCI - Castleton Commodities Int LLC | O77: =SUM(C77:N77) -> 0 | AB77: 0 | AK77: =SUM(AC77:AJ77) -> 0 | AM77: =7521.147*1.5/1.173 -> 9617.835 | AX77: =SUM(AL77:AW77) -> 9617.835 | BK77: =SUM(AY77:BJ77) -> 0 | BX77: =SUM(BL77:BW77) -> 0 | CK77: =SUM(BY77:CJ77) -> 0 | CX77: =SUM(CL77:CW77) -> 0 | DK77: =SUM(CY77:DJ77) -> 0 | DX77: =SUM(DL77:DW77) -> 0
B78: Ruhr Petrol | O78: =SUM(C78:N78) -> 0 | AB78: 0 | AK78: =SUM(AC78:AJ78) -> 0 | AM78: =6768.95+5460 -> 12228.95 | AX78: =SUM(AL78:AW78) -> 12228.95 | BG78: =4083.177*1.05 -> 4287.3359 | BH78: =6000*6 -> 36000 | BJ78: 0 | BK78: =SUM(AY78:BJ78) -> 40287.336 | BX78: =SUM(BL78:BW78) -> 0 | CK78: =SUM(BY78:CJ78) -> 0 | CX78: =SUM(CL78:CW78) -> 0 | DK78: =SUM(CY78:DJ78) -> 0 | DX78: =SUM(DL78:DW78) -> 0
B79: Bioagra | AB79: =SUM(P79:AA79) -> 0 | AK79: =SUM(AC79:AJ79) -> 0 | AQ79: =2859*1 -> 2859 | AX79: =SUM(AL79:AW79) -> 2859 | BK79: =SUM(AY79:BJ79) -> 0 | BX79: =SUM(BL79:BW79) -> 0 | CK79: =SUM(BY79:CJ79) -> 0 | CX79: =SUM(CL79:CW79) -> 0 | DK79: =SUM(CY79:DJ79) -> 0 | DX79: =SUM(DL79:DW79) -> 0
B80: Czanikow | AX80: =SUM(AL80:AW80) -> 0 | BH80: =(6000*2.5+8400*10+4083*13.5)/1.0743 -> 143461.32 | BK80: =SUM(AY80:BJ80) -> 143461.32 | BL80: 0 | BP80: =43400/1.0696 -> 40575.916 | BX80: =SUM(BL80:BW80) -> 40575.916 | CK80: =SUM(BY80:CJ80) -> 0 | CX80: =SUM(CL80:CW80) -> 0 | DK80: =SUM(CY80:DJ80) -> 0 | DX80: =SUM(DL80:DW80) -> 0
B81: EDF Trading | BK81: =SUM(AY81:BJ81) -> 0 | BS81: =20440/1.1042 -> 18511.139 | BX81: =SUM(BL81:BW81) -> 18511.139 | CK81: =SUM(BY81:CJ81) -> 0 | CX81: =SUM(CL81:CW81) -> 0 | DK81: =SUM(CY81:DJ81) -> 0 | DX81: =SUM(DL81:DW81) -> 0
B82: Cargill | CK82: =SUM(BY82:CJ82) -> 0 | CP82: =9960.518+9952.501 -> 19913.019 | CX82: =SUM(CL82:CW82) -> 19913.019 | DK82: =SUM(CY82:DJ82) -> 0
B83: FUTUROS | O83: =SUM(C83:N83) -> 0 | BX83: =SUM(BL83:BW83) -> 0 | CK83: =SUM(BY83:CJ83) -> 0 | CX83: =SUM(CL83:CW83) -> 0 | DK83: =SUM(CY83:DJ83) -> 0 | DX83: =SUM(DL83:DW83) -> 0
B84: Paragon | O84: =SUM(C84:N84) -> 0 | AB84: =SUM(P84:AA84) -> 0 | AG84: =21420/1.1136 -> 19234.914 | AH84: =-2625/1.1174-75/1.121+(1050+19593+14994)/1.121 -> 29374.258 | AK84: =SUM(AC84:AJ84) -> 48609.171 | AT84: =92575/1.2081 -> 76628.59 | AU84: -20000 | AV84: =41591-20500 -> 21091 | AW84: 216 | AX84: =SUM(AL84:AW84) -> 77935.59 | AY84: =52200+33560-17360/1.1629 -> 70831.803 | BB84: =701700-93925 -> 607775 | BG84: =637500-16642.5/1.1328 -> 622808.53 | BJ84: =38752/1.0195 -> 38010.79 | BK84: =SUM(AY84:BJ84) -> 1339426.1 | BM84: =-19792.08/1.0927 -> -18113.004 | BN84: =-5952.24/1.0927+26992/1.0366-159215-270000-270000 -> -678623.3 | BO84: =24375/1.0538 -> 23130.575 | BR84: =5040/1.0586-4480/1.0596 -> 532.99453 | BV84: =-1087.2/1.0821 -> -1004.7131 | BX84: =SUM(BL84:BW84) -> -674077.45 | CA84: =600/1.0683-11550/1.0813 -> -10119.947 | CC84: =-14114.44+19406.74-60952.97+31291.39+11589.4+11589.4 -> -1190.48 | CG84: =15047.5+36500 -> 51547.5 | CH84: =16964 -> 16964 | CI84: =2534.87+1745.67-268.01+9478.2 -> 13490.73 | CJ84: =36325.71+31824.48+53085.37 -> 121235.56 | CK84: =SUM(BY84:CJ84) -> 191927.36 | CN84: =(11500+11500+11500)-2100/1.0951+10336.49 -> 42918.857 | CP84: =9699.9/1.0426+10950/1.0304-(24150+24150+24150)/1.0637 -> -48180.801 | CQ84: =107700/1.0304 -> 104522.52 | CU84: -117000 | CW84: -14250 | CX84: =SUM(CL84:CW84) -> -31989.428 | CY84: -37094 | CZ84: -8824 | DD84: 4432.2 | DE84: 17460 | DF84: 41335.2 | DG84: 83415 | DH84: 40000 | DK84: =SUM(CY84:DJ84) -> 140724.4 | DX84: =SUM(DL84:DW84) -> 0
B85: Marex | DG85: 132025 | DH85: 112487 | DI85: 46545.48 | DK85: =SUM(CY85:DJ85) -> 291057.48
B86: FC Stone | O86: =SUM(C86:N86) -> 0 | AB86: =SUM(P86:AA86) -> 0 | AK86: =SUM(AC86:AJ86) -> 0 | AX86: =SUM(AL86:AW86) -> 0 | BK86: =SUM(AY86:BJ86) -> 0 | BX86: =SUM(BL86:BW86) -> 0 | CK86: =SUM(BY86:CJ86) -> 0 | CX86: =SUM(CL86:CW86) -> 0 | DK86: =SUM(CY86:DJ86) -> 0 | DX86: =SUM(DL86:DW86) -> 0
B87: VARIOS | C87: 1000 | AB87: =SUM(P87:AA87) -> 0 | AK87: =SUM(AC87:AJ87) -> 0 | BK87: =SUM(AY87:BJ87) -> 0 | BX87: =SUM(BL87:BW87) -> 0 | CK87: =SUM(BY87:CJ87) -> 0 | CX87: =SUM(CL87:CW87) -> 0 | DK87: =SUM(CY87:DJ87) -> 0 | DX87: =SUM(DL87:DW87) -> 0

Sheet NC-Gastos
C2: 2018 | P2: 2019 | AC2: 2020 | AL2: 2020/2021 | AY2: 2021/2022 | BL2: 2022/2023 | BY2: 2023/2024 | CL2: 2024/2025 | CY2: 2025/2026 | DL2: 2026/2027
B3: Previsiones Caja | C3: Ene | D3: Feb | E3: Mar | F3: Abr | G3: May | H3: Jun | I3: Jul | J3: Ago | K3: Sep | L3: Oct | M3: Nov | N3: Dic | O3: Totales | P3: Ene | Q3: Feb | R3: Mar | S3: Abr | T3: May | U3: Jun | V3: Jul | W3: Ago | X3: Sep | Y3: Oct | Z3: Nov | AA3: Dic | AB3: Totales | AC3: Ene | AD3: Feb | AE3: Mar | AF3: Abr | AG3: May | AH3: Jun | AI3: Jul | AJ3: Ago | AK3: Totales | AL3: Sep | AM3: Oct | AN3: Nov | AO3: Dic | AP3: Ene | AQ3: Feb | AR3: Mar | AS3: Abr | AT3: May | AU3: Jun | AV3: Jul | AW3: Ago | AX3: Totales | AY3: Sep | AZ3: Oct | BA3: Nov | BB3: Dic | BC3: Ene | BD3: Feb | BE3: Mar | BF3: Abr | BG3: May | BH3: Jun | BI3: Jul | BJ3: Ago | BK3: Totales | BL3: Sep | BM3: Oct | BN3: Nov | BO3: Dic | BP3: Ene | BQ3: Feb | BR3: Mar | BS3: Abr | BT3: May | BU3: Jun | BV3: Jul | BW3: Ago | BX3: Totales | BY3: Sep | BZ3: Oct | CA3: Nov | CB3: Dic | CC3: Ene | CD3: Feb | CE3: Mar | CF3: Abr | CG3: May | CH3: Jun | CI3: Jul | CJ3: Ago | CK3: Totales | CL3: Sep | CM3: Oct | CN3: Nov | CO3: Dic | CP3: Ene | CQ3: Feb | CR3: Mar | CS3: Abr | CT3: May | CU3: Jun | CV3: Jul | CW3: Ago | CX3: Totales | CY3: Sep | CZ3: Oct | DA3: Nov | DB3: Dic | DC3: Ene | DD3: Feb | DE3: Mar | DF3: Abr | DG3: May | DH3: Jun | DI3: Jul | DJ3: Ago | DK3: Totales | DL3: Sep | DM3: Oct | DN3: Nov | DO3: Dic | DP3: Ene | DQ3: Feb | DR3: Mar | DS3: Abr | DT3: May | DU3: Jun | DV3: Jul | DW3: Ago | DX3: Totales
B4: Total Pagos (mes) | P4: =-SUM(P6:P56) -> -714.1 | Q4: =-SUM(Q6:Q56) -> -25339.18 | R4: =-SUM(R6:R56) -> -19717.57 | S4: =-SUM(S6:S56) -> -22147.54 | T4: =-SUM(T6:T56) -> -24854.55 | U4: =-SUM(U6:U56) -> -15062.43 | V4: =-SUM(V6:V56) -> -20795.42 | W4: =-SUM(W6:W56) -> -14998.21 | ... AA4: =-SUM(AA6:AA56) -> -19327.231 | AB4: =SUM(P4:AA4) -> -224217.11 | AC4: =-SUM(AC6:AC56) -> -25102.724 | AD4: =-SUM(AD6:AD56) -> -19652.334 | AE4: =-SUM(AE6:AE56) -> -16377.324 | AF4: =-SUM(AF6:AF56) -> -28525.131 | AG4: =-SUM(AG6:AG56) -> -14806.397 | AH4: =-SUM(AH6:AH56) -> -16862.274 | AI4: =-SUM(AI6:AI56) -> -37575.804 | AJ4: =-SUM(AJ6:AJ56) -> -16209.028 | AK4: =SUM(AC4:AJ4) -> -175111.02 | AL4: =-SUM(AL6:AL56) -> -21518.454 | AM4: =-SUM(AM6:AM56) -> -42345.46 | AN4: =-SUM(AN6:AN56) -> -18394.751 | AO4: =-SUM(AO6:AO56) -> -24122.33 | AP4: =-SUM(AP6:AP56) -> -26295.567 | AQ4: =-SUM(AQ6:AQ56) -> -33224.69 | AR4: =-SUM(AR6:AR56) -> -32784.576 | AS4: =-SUM(AS6:AS56) -> -25923.767 | ... AW4: =-SUM(AW6:AW56) -> -27743.969 | AX4: =SUM(AL4:AW4) -> -407247.72 | AY4: =-SUM(AY6:AY56) -> -22285.152 | AZ4: =-SUM(AZ6:AZ56) -> -35329.529 | BA4: =-SUM(BA6:BA56) -> -18442.73 | BB4: =-SUM(BB6:BB56) -> -24368.48 | BC4: =-SUM(BC6:BC56) -> -32460.142 | BD4: =-SUM(BD6:BD56) -> -26812.29 | BE4: =-SUM(BE6:BE56) -> -51007.07 | BF4: =-SUM(BF6:BF56) -> -47151.62 | ... BJ4: =-SUM(BJ6:BJ56) -> -23912.93 | BK4: =SUM(AY4:BJ4) -> -396545.52 | BL4: =-SUM(BL6:BL56) -> 10662.29 | BM4: =-SUM(BM6:BM56) -> -49593.279 | BN4: =-SUM(BN6:BN56) -> -5978.5507 | BO4: =-SUM(BO6:BO56) -> -47250.49 | BP4: =-SUM(BP6:BP56) -> -30477.21 | BQ4: =-SUM(BQ6:BQ56) -> -14893.77 | BR4: =-SUM(BR6:BR56) -> -218708.26 | BS4: =-SUM(BS6:BS56) -> -41384.964 | ... BW4: =-SUM(BW6:BW56) -> -8290.5911 | BX4: =SUM(BL4:BW4) -> -484365.77 | BY4: =-SUM(BY6:BY56) -> -23699.643 | BZ4: =-SUM(BZ6:BZ56) -> -30997.521 | CA4: =-SUM(CA6:CA56) -> -22310.456 | CB4: =-SUM(CB6:CB56) -> -26586.3 | CC4: =-SUM(CC6:CC56) -> -31002.274 | CD4: =-SUM(CD6:CD56) -> -28669.79 | CE4: =-SUM(CE6:CE56) -> -20654.817 | CF4: =-SUM(CF6:CF56) -> -51836.615 | ... CJ4: =-SUM(CJ6:CJ56) -> -12182.062 | CK4: =SUM(BY4:CJ4) -> -332701.61 | CL4: =-SUM(CL6:CL56) -> -22854.57 | CM4: =-SUM(CM6:CM56) -> -34992.039 | CN4: =-SUM(CN6:CN56) -> -23939.43 | CO4: =-SUM(CO6:CO56) -> -35201.759 | CP4: =-SUM(CP6:CP56) -> -33433.966 | CQ4: =-SUM(CQ6:CQ56) -> -29391.933 | CR4: =-SUM(CR6:CR56) -> -137630.53 | CS4: =-SUM(CS6:CS56) -> -52016.841 | ... CW4: =-SUM(CW6:CW56) -> -16586.721 | CX4: =SUM(CL4:CW4) -> -490512.8 | CY4: =-SUM(CY6:CY56) -> -23713.066 | CZ4: =-SUM(CZ6:CZ56) -> -60304.337 | DA4: =-SUM(DA6:DA56) -> -48794.061 | DB4: =-SUM(DB6:DB56) -> -42438.267 | DC4: =-SUM(DC6:DC56) -> -45005.811 | DD4: =-SUM(DD6:DD56) -> -29697.276 | DE4: =-SUM(DE6:DE56) -> -152955.11 | DF4: =-SUM(DF6:DF56) -> -66634.43 | ... DJ4: =-SUM(DJ6:DJ56) -> -23288.56 | DK4: =SUM(CY4:DJ4) -> -585688.64 | DX4: =SUM(DL4:DW4) -> 0
B5: GENERALES
B6: Conferencia Dropet | D6: =5445+21175 -> 26620 | E6: 5445 | F6: 0 | H6: =1500*1.21 -> 1815 | I6: =1500*1.21 -> 1815 | J6: =#REF!*0.3 -> #REF! | M6: 2722.5 | O6: =SUM(C6:N6) -> #REF! | AB6: =SUM(P6:AA6) -> 0 | AC6: 762.3 | AK6: =SUM(AC6:AJ6) -> 762.3 | AX6: =SUM(AL6:AW6) -> 0 | BG6: =920*1.21 -> 1113.2 | BK6: =SUM(AY6:BJ6) -> 1113.2 | BO6: =950*1.21 -> 1149.5 | BX6: =SUM(BL6:BW6) -> 1149.5 | CC6: =1050*1.21 -> 1270.5 | CK6: =SUM(BY6:CJ6) -> 1270.5 | CP6: =1100*1.21 -> 1331 | CX6: =SUM(CL6:CW6) -> 1331 | DC6: =1200*1.23 -> 1476 | DH6: =(3000+2000)-(3000+2000) -> 0 | DK6: =SUM(CY6:DJ6) -> 1476 | DP6: 1500 | DX6: =SUM(DL6:DW6) -> 1500
B7: Compras inmobilizado | D7: 120 | O7: =SUM(C7:N7) -> 120 | Q7: 859 | T7: =632.33 -> 632.33 | U7: =632.33+171.22+71.27 -> 874.82 | V7: 632.34 | W7: 559.99 | AB7: =SUM(P7:AA7) -> 3558.48 | AH7: =301+71.27+171.22 -> 543.49 | AI7: =903/3 -> 301 | AJ7: =903/3 -> 301 | AK7: =SUM(AC7:AJ7) -> 1145.49 | AP7: 418.95 | AQ7: =-418.95+(418.95+6)*1.21 -> 95.2395 | AR7: =73.83*1.21 -> 89.3343 | AU7: =71.27 -> 71.27 | AV7: =(3*126*1.21+46.5*1.21) -> 513.645 | AX7: =SUM(AL7:AW7) -> 1188.4388 | AZ7: 1559.01 | BA7: 228.69 | BB7: 989.33 | BC7: =1198 -> 1198 | BG7: =(61.2+8.5)*1.21 -> 84.337 | BI7: 513.65 | BJ7: =1205.79+544.5 -> 1750.29 | BK7: =SUM(AY7:BJ7) -> 6323.307 | BR7: 239.83 | BU7: =(67.2+8.5)*1.21 -> 91.597 | BV7: =(140.4*3+46.5)*1.21 -> 565.917 | BX7: =SUM(BL7:BW7) -> 897.344 | BZ7: =(108.47-46.98)*1.21 -> 74.4029 | CC7: 1500 | CK7: =SUM(BY7:CJ7) -> 1574.4029 | CM7: =(140.4*4+62)*1.21 -> 754.556 | CU7: =(140.4*4+62)*1.21 -> 754.556 | CX7: =SUM(CL7:CW7) -> 1509.112 | CY7: =337.2*1.21 -> 408.012 | DE7: =630+420+1210-1210+1049.99 -> 2099.99 | DH7: =(156.98*4+65.12)*1.21+1513 -> 2351.5784 | DJ7: =(3000+2000)-(3000+2000) -> 0 | DK7: =SUM(CY7:DJ7) -> 4859.5804 | DV7: 755 | DX7: =SUM(DL7:DW7) -> 755
B8: Suministros informáticos y mantenimiento | AB8: =SUM(P8:AA8) -> 0 | AK8: =SUM(AC8:AJ8) -> 0 | AX8: =SUM(AL8:AW8) -> 0 | BK8: =SUM(AY8:BJ8) -> 0 | BQ8: =23.39 -> 23.39 | BS8: 17.09 | BT8: 34.05 | BU8: =(190+20+20)*(1.21-0.15) -> 243.8 | BW8: 9.24 | BX8: =SUM(BL8:BW8) -> 327.57 | BZ8: 68.97 | CA8: =25.88+10.71 -> 36.59 | CB8: =29.09 -> 29.09 | CC8: =36.06+12.61+74.98 -> 123.65 | CD8: =48.52 -> 48.52 | CE8: =73.3+15.46 -> 88.76 | CF8: =27.58 -> 27.58 | CG8: =16.13+9.45 -> 25.58 | CH8: =23.85+13.75+((200+20+20)*(1.21-0.15)) -> 292 | CI8: 11.13 | CK8: =SUM(BY8:CJ8) -> 751.87 | CL8: =1.15 -> 1.15 | CM8: =51+26.32 -> 77.32 | CN8: 83.08 | CO8: =166.69+15.05+8.8 -> 190.54 | CP8: =166.69+45.15+74.98 -> 286.82 | CQ8: 33.13 | CR8: =63.37+12.12 -> 75.49 | CS8: 17.51 | CT8: 33.73 | CU8: =14.9+15.16+16.67 -> 46.73 | CV8: =(93.74-46.87)*1.21+93.74*1.21+36.28+12.09 -> 218.5081 | CW8: 6.34 | CX8: =SUM(CL8:CW8) -> 1070.3481 | CY8: 9.33 | CZ8: 89.31 | DA8: 74.56 | DB8: =39.6+8.86 -> 48.46 | DC8: =74.98+26.51 -> 101.49 | DD8: 28.93 | DE8: =113.43+113.43+37.91+12.29+30.23 -> 307.29 | DF8: =108.74+29.48 -> 138.22 | DG8: =108.9+18.14+9.15+10.43 -> 146.62 | DH8: =25+(113.43*2) -> 251.86 | DI8: 25 | DJ8: 25 | DK8: =SUM(CY8:DJ8) -> 1246.07 | DL8: 25 | DM8: 25 | DN8: 25 | DO8: 25 | DP8: =25+74.98 -> 99.98 | DQ8: 25 | DR8: 25 | DS8: 25 | DT8: 25 | DU8: =25+(113.43*2) -> 251.86 | DV8: 25 | DW8: 25 | DX8: =SUM(DL8:DW8) -> 601.84
B9: Trips/commercial expenses | D9: =146.1+485.77 -> 631.87 | O9: =SUM(C9:N9) -> 631.87 | P9: 719.95 | Q9: 4700 | S9: 3260.56 | T9: =777.7+217.1+1159.95 -> 2154.75 | W9: =453.05+2000+625 -> 3078.05 | X9: =637.1+1190.63+1052.75 -> 2880.48 | Y9: =193.85 -> 193.85 | Z9: =(357.28+78.86)+(24.99+1964.84+14.63)+(271.48+85.04) -> 2797.12 | AA9: =(205.77+10.4+53+171.76)+(741.77+40.51+180.78)+(223.8+536.1) -> 2163.89 | AB9: =SUM(P9:AA9) -> 21948.65 | AC9: =403.12 -> 403.12 | AD9: =1255.01+1099.75+951.98 -> 3306.74 | AE9: =1196.19 -> 1196.19 | AK9: =SUM(AC9:AJ9) -> 4906.05 | AQ9: =47.6+22.82+17.25+113.96+148.02+781.18+112.57+45.4+61.3+891.3 -> 2241.4 | AV9: =239.58 -> 239.58 | AX9: =SUM(AL9:AW9) -> 2480.98 | AZ9: =(76.1+89+131+26+184.5+10.45+225.5+18+126.35+13+18+75+3.35+5.2+3.35)+400 -> 1404.8 | BB9: =1426.47+424.42 -> 1850.89 | BF9: =1487.52+11560 -> 13047.52 | BG9: 144.98 | BH9: 96.99 | BK9: =SUM(AY9:BJ9) -> 16545.18 | BL9: =536.44/0.865295 -> 619.95042 | BN9: =297 -> 297 | BQ9: =1041.1 -> 1041.1 | BR9: 2456.49 | BS9: 3373.49 | BT9: 3978.46 | BU9: 3401.57 | BV9: 1161.44 | BW9: 1061.8 | BX9: =SUM(BL9:BW9) -> 17391.3 | BY9: =1514.37-10.91 -> 1503.46 | BZ9: =535.61/0.8609+(2534.77-925.21) -> 2231.7112 | CA9: 3275.29 | CB9: 4393.77 | CC9: 1311.37 | CD9: 726.56 | CE9: 1117.22 | CF9: 1007.7 | CG9: 5245.52 | CH9: 4678.96 | CI9: 1730.23 | CJ9: =46.08+(2150.85-237) -> 1959.93 | CK9: =SUM(BY9:CJ9) -> 29181.721 | CL9: 160.88 | CM9: =66+1407.5 -> 1473.5 | CN9: =3802.12-207 -> 3595.12 | CO9: 2850.33 | CP9: =1605.97-338.46 -> 1267.51 | CQ9: 7369.52 | CR9: =9495.14-3706 -> 5789.14 | CS9: =1500+2270.9 -> 3770.9 | CT9: 3396.39 | CU9: =7861.74-693-1781.03-9.56*5 -> 5339.91 | CV9: =(4181.08-56.72-36.28-113.43-12.09) -> 3962.56 | CW9: 1297.79 | CX9: =SUM(CL9:CW9) -> 40273.55 | CY9: 313.68 | CZ9: =66+((1453.49-1224.45+1075.71)) -> 1370.75 | DA9: 1840.81 | DB9: =(9309.72-338.46) -> 8971.26 | DC9: =(1435.93-617) -> 818.93 | DD9: 2010.46 | DE9: =8052+(4570.98-1049.99) -> 11572.99 | DF9: =617.27-187.77 -> 429.5 | DG9: =2037.73+6516.12+7142.29 -> 15696.14 | DH9: 2130.74 | DI9: 500 | DJ9: 500 | DK9: =SUM(CY9:DJ9) -> 46155.26 | DL9: 500 | DM9: 2000 | DN9: =1500 -> 1500 | DO9: 500 | DP9: 500 | DQ9: 500 | DR9: =5000/2 -> 2500 | DS9: =5000/2+250+1000 -> 3750 | DT9: 3000 | DU9: 250 | DV9: 500 | DW9: 500 | DX9: =SUM(DL9:DW9) -> 16000
B10: Personnel - Felipe Fontes | O10: =SUM(C10:N10) -> 0 | Q10: 1425 | U10: 1500 | Z10: 1500 | AB10: =SUM(P10:AA10) -> 4425 | AK10: =SUM(AC10:AJ10) -> 0 | AP10: 3536 | AX10: =SUM(AL10:AW10) -> 3536 | BC10: 4540 | BK10: =SUM(AY10:BJ10) -> 4540 | BR10: =180*6+180*6 -> 2160 | BS10: 3940 | BX10: =SUM(BL10:BW10) -> 6100 | CI10: =2365 -> 2365 | CK10: =SUM(BY10:CJ10) -> 2365 | CU10: =2179.64 -> 2179.64 | CV10: 2165.17 | CW10: 2174.97 | CX10: =SUM(CL10:CW10) -> 6519.78 | CY10: 2174.36 | CZ10: =3100+2219.69 -> 5319.69 | DA10: 2242.98 | DB10: 2228.99 | DC10: 2195.52 | DD10: 2231.15 | DE10: 2258.96 | DF10: 3253.62 | DG10: 2399.51 | DH10: 2436.03 | DI10: 2300 | DJ10: 2300 | DK10: =SUM(CY10:DJ10) -> 31340.81 | DL10: 2300 | DM10: 2300 | DN10: 2300 | DO10: 2300 | DP10: 2300 | DQ10: 2300 | DR10: 2300 | DS10: 2300 | DT10: 2300 | DU10: 2300 | DV10: 2300 | DW10: 2300 | DX10: =SUM(DL10:DW10) -> 27600
B11: Personnel - Alfonso Carmona Bosch | O11: =SUM(C11:N11) -> 0 | Y11: 3213.33 | Z11: =1584.94 -> 1584.94 | AA11: 2994 | AB11: =SUM(P11:AA11) -> 7792.27 | AC11: =2000-1409.06/3 -> 1530.3133 | AD11: =2000-1409.06/3 -> 1530.3133 | AE11: =2000-1409.06/3 -> 1530.3133 | AF11: =1782.45-652.64 -> 1129.81 | AG11: 1959.52 | AH11: 1959.52 | AI11: 1959.52 | AJ11: 1959.52 | AK11: =SUM(AC11:AJ11) -> 13558.83 | AL11: 1959.52 | AM11: 3950 | AN11: 3950 | AO11: 3950 | AP11: 3950 | AQ11: 3950 | AR11: 3950 | AS11: 3950 | AT11: 3950 | AU11: 3950 | AV11: 3950 | AW11: 3950 | AX11: =SUM(AL11:AW11) -> 45409.52 | AY11: 3950 | AZ11: 3950 | BA11: 3950 | BB11: 3950 | BC11: 3950.06 | BD11: 3950 | BE11: 3950 | BF11: 3950 | BG11: =1250+5200 -> 6450 | BH11: 5200 | BI11: 5200 | BJ11: 5200 | BK11: =SUM(AY11:BJ11) -> 53650.06 | BL11: 5200 | BM11: =274.95+3000 -> 3274.95 | BN11: 3000 | BO11: 3000 | BP11: 3000 | BQ11: 4300 | BR11: 4300 | BS11: 4300 | BT11: 4300 | BU11: 4300 | BV11: 4300 | BW11: 4300 | BX11: =SUM(BL11:BW11) -> 47574.95 | BY11: 4300 | BZ11: 4300 | CA11: 4300 | CB11: 4300 | CC11: 4300 | CD11: 4300 | CE11: 4300 | CF11: 4300 | CG11: 4300 | CH11: 4300 | CI11: 4300 | CJ11: 4300 | CK11: =SUM(BY11:CJ11) -> 51600 | CL11: 4300 | CM11: 4300 | CN11: 4300 | CO11: 4300 | CP11: 4300 | CQ11: 4300 | CR11: 4300 | CS11: 4300 | CT11: 4300 | CU11: 4300 | CV11: 4300 | CW11: 4300 | CX11: =SUM(CL11:CW11) -> 51600 | CY11: 4300 | CZ11: 4300 | DA11: 4300 | DB11: 4300 | DC11: 4300 | DD11: 4300 | DE11: 4300 | DF11: 4300 | DG11: 4300 | DH11: 4300 | DI11: 4300 | DJ11: 4300 | DK11: =SUM(CY11:DJ11) -> 51600 | DL11: 4300 | DM11: 4300 | DN11: 4300 | DO11: 4300 | DP11: 4300 | DQ11: 4300 | DR11: 4300 | DS11: 4300 | DT11: 4300 | DU11: 4300 | DV11: 4300 | DW11: 4300 | DX11: =SUM(DL11:DW11) -> 51600
B12: Personnel - Alberto Carmona | M12: 16000 | N12: =8000+5000 -> 13000 | O12: =SUM(C12:N12) -> 29000 | Q12: =8000+8480 -> 16480 | R12: 10600 | S12: 10600 | T12: 11660 | U12: 13780 | V12: 13780 | W12: 13780 | X12: 11660 | Y12: 11660 | Z12: 11660 | AA12: 11660 | AB12: =SUM(P12:AA12) -> 137320 | AC12: 13780 | AD12: 11660 | AE12: 11660 | AF12: 11660 | AG12: 11660 | AH12: 11660 | AI12: 13780 | AJ12: 11660 | AK12: =SUM(AC12:AJ12) -> 97520 | AL12: 11660 | AM12: 11660 | AN12: 11660 | AO12: 11660 | AP12: 11660 | AQ12: 11660 | AR12: 11660 | AS12: 11660 | AT12: 11660 | AU12: 11660 | AV12: 11660 | AW12: 11660 | AX12: =SUM(AL12:AW12) -> 139920 | AY12: 11660 | AZ12: 11660 | BA12: 11660 | BB12: 11660 | BC12: 11660 | BD12: 11660 | BE12: 11660 | BF12: 11660 | BG12: 11660 | BH12: 11660 | BI12: 11660 | BJ12: 11660 | BK12: =SUM(AY12:BJ12) -> 139920 | BL12: 11660 | BM12: 11660 | BN12: 11660 | BO12: 11660 | BP12: 11660 | BQ12: 11660 | BR12: 11660 | BS12: 11660 | BT12: 11660 | BU12: 11660 | BV12: 11660 | BW12: 11660 | BX12: =SUM(BL12:BW12) -> 139920 | BY12: 11660 | BZ12: 11660 | CA12: 11660 | CB12: 11660 | CC12: 11660 | CD12: 11660 | CE12: 11660 | CF12: 11660 | CG12: 11660 | CH12: 11660 | CI12: 11660 | CJ12: 11660 | CK12: =SUM(BY12:CJ12) -> 139920 | CL12: 11660 | CM12: 11660 | CN12: 11660 | CO12: 11660 | CP12: 11660 | CQ12: 11660 | CR12: 11660 | CS12: 11660 | CT12: 11660 | CU12: 11660 | CV12: 11660 | CW12: 11660 | CX12: =SUM(CL12:CW12) -> 139920 | CY12: 11660 | CZ12: 11660 | DA12: 11660 | DB12: 11660 | DC12: 11660 | DD12: 11660 | DE12: 11660 | DF12: 11660 | DG12: 11660 | DH12: 11660 | DI12: 11660 | DJ12: 11660 | DK12: =SUM(CY12:DJ12) -> 139920 | DL12: 11660 | DM12: 11660 | DN12: 11660 | DO12: 11660 | DP12: 11660 | DQ12: 11660 | DR12: 11660 | DS12: 11660 | DT12: 11660 | DU12: 11660 | DV12: 11660 | DW12: 11660 | DX12: =SUM(DL12:DW12) -> 139920
B13: Personnel - Rosa Jiménez | AB13: =SUM(P13:AA13) -> 0 | AK13: =SUM(AC13:AJ13) -> 0 | AM13: 800 | AN13: 800 | AQ13: 800 | AR13: 800 | AS13: 453.33 | AW13: 613.33 | AX13: =SUM(AL13:AW13) -> 4266.66 | AY13: 800 | AZ13: 800 | BA13: 800 | BB13: 800 | BC13: 800 | BD13: 800 | BE13: 800 | BF13: 800 | BG13: 800 | BH13: 800 | BI13: 800 | BJ13: 800 | BK13: =SUM(AY13:BJ13) -> 9600 | BL13: 800 | BM13: 800 | BN13: 800 | BO13: 800 | BP13: 800 | BQ13: 800 | BR13: =800 -> 800 | BS13: 1280 | BT13: 1280 | BU13: 1280 | BV13: 1280 | BW13: 1280 | BX13: =SUM(BL13:BW13) -> 12000 | BY13: 1280 | BZ13: 1280 | CA13: 1280 | CB13: 1280 | CC13: 1280 | CD13: 1280 | CE13: 1280 | CF13: 1280 | CG13: 1280 | CH13: 1280 | CI13: 1280 | CJ13: 1280 | CK13: =SUM(BY13:CJ13) -> 15360 | CL13: 1280 | CM13: 1280 | CN13: 1280 | CO13: 1280 | CP13: =1280+46.75 -> 1326.75 | CQ13: 1326.75 | CR13: 1326.75 | CS13: 1326.75 | CT13: 1326.75 | CU13: 1326.75 | CV13: 1326.75 | CW13: 1326.75 | CX13: =SUM(CL13:CW13) -> 15734 | CY13: 1326.75 | CZ13: 1326.75 | DA13: 1326.75 | DB13: 1326.75 | DC13: 1326.45 | DD13: 1326.45 | DE13: 1326.45 | DF13: =1458.01+437.39 -> 1895.4 | DG13: 1434.84 | DH13: 1458.01 | DI13: 1458.01 | DJ13: 1458.01 | DK13: =SUM(CY13:DJ13) -> 16990.62 | DL13: 1458.01 | DM13: 1458.01 | DN13: 1458.01 | DO13: 1458.01 | DP13: 1458.01 | DQ13: 1458.01 | DR13: 1458.01 | DS13: 1458.01 | DT13: 1458.01 | DU13: 1458.01 | DV13: 1458.01 | DW13: 1458.01 | DX13: =SUM(DL13:DW13) -> 17496.12
B14: Personnel - María Lacañina | AB14: =SUM(P14:AA14) -> 0 | AK14: =SUM(AC14:AJ14) -> 0 | AP14: 296.1 | AQ14: 634.52 | AR14: 632.27 | AS14: =479.44+233.93 -> 713.37 | AT14: 701.8 | AX14: =SUM(AL14:AW14) -> 2978.06 | BK14: =SUM(AY14:BJ14) -> 0 | BX14: =SUM(BL14:BW14) -> 0 | BY14: 1313.4 | BZ14: 1313.4 | CA14: 1313.4 | CB14: 1313.4 | CC14: 1323.6 | CD14: 1327.2 | CE14: 1327.2 | CF14: 1327.2 | CG14: 1327.2 | CH14: 1327.2 | CI14: 1327.2 | CJ14: 1327.2 | CK14: =SUM(BY14:CJ14) -> 15867.6 | CL14: 1327.2 | CM14: 1327.2 | CN14: 1327.2 | CO14: 1327.2 | CP14: =1326.75+50.53 -> 1377.28 | CQ14: 1377.28 | CR14: 1377.28 | CS14: 1377.28 | CT14: 1377.28 | CU14: 1377.28 | CV14: 1377.28 | CW14: 1377.28 | CX14: =SUM(CL14:CW14) -> 16327.04 | CY14: 1377.28 | CZ14: 1377.28 | DA14: 1377.28 | DB14: 1377.28 | DC14: 1377.96 | DD14: 1376.96 | DE14: 1376.96 | DF14: =1640.21+1141.6 -> 2781.81 | DG14: 1617.5 | DH14: 1640.21 | DI14: 1640.21 | DJ14: 1640.21 | DK14: =SUM(CY14:DJ14) -> 18960.94 | DL14: 1640.21 | DM14: 1640.21 | DN14: 1640.21 | DO14: 1640.21 | DP14: 1640.21 | DQ14: 1640.21 | DR14: 1640.21 | DS14: 1640.21 | DT14: 1640.21 | DU14: 1640.21 | DV14: 1640.21 | DW14: 1640.21 | DX14: =SUM(DL14:DW14) -> 19682.52
B15: Soc. Security | O15: =SUM(C15:N15) -> 0 | U15: 0 | Z15: =128.61 -> 128.61 | AA15: =748.03 -> 748.03 | AB15: =SUM(P15:AA15) -> 876.64 | AC15: =748.03 -> 748.03 | AD15: =736.28 -> 736.28 | AE15: =736.28 -> 736.28 | AF15: =736.28 -> 736.28 | AG15: =736.28 -> 736.28 | AH15: =736.28+11.75 -> 748.03 | AI15: =736.28+11.75 -> 748.03 | AJ15: =736.28+11.75 -> 748.03 | AK15: =SUM(AC15:AJ15) -> 5937.24 | AL15: =736.28+11.75 -> 748.03 | AM15: =736.28+11.75 -> 748.03 | AN15: =1673.52-582.75 -> 1090.77 | AO15: =1673.52-582.75 -> 1090.77 | AR15: =1331.99+741.57+1239.97 -> 3313.53 | AS15: =-720.06 -> -720.06 | AW15: =1254.09+1031.7+660.55+611.93+611.93 -> 4170.2 | AX15: =SUM(AL15:AW15) -> 10441.27 | BB15: =880.42+962.17+951.05 -> 2793.64 | BD15: =951.31+951.05 -> 1902.36 | BG15: =979.54+956.72+956.72+956.72 -> 3849.7 | BJ15: =956.72+956.72+956.72 -> 2870.16 | BK15: =SUM(AY15:BJ15) -> 11415.86 | BN15: =956.72+956.72 -> 1913.44 | BO15: =956.72+956.72 -> 1913.44 | BQ15: =956.73+1018.43 -> 1975.16 | BV15: =1018.43+1018.43+1225.27+1213.49 -> 4475.62 | BW15: =1213.49+1213.49 -> 2426.98 | BX15: =SUM(BL15:BW15) -> 12704.64 | BY15: =1015.02+1131.54 -> 2146.56 | BZ15: =1131.54+1015.02 -> 2146.56 | CA15: =15.13+26.97+(1131.54+673.7) -> 1847.34 | CB15: =1131.54+696.96-23.27 -> 1805.23 | CC15: =1131.54+1022.83-349.13 -> 1805.24 | CD15: =2209.93-377.24 -> 1832.69 | CE15: =3469.41-377.24 -> 3092.17 | CF15: =3603.38-352.08 -> 3251.3 | CG15: =3727.21 -> 3727.21 | CH15: 2485.93 | CI15: =1151.22+698.18 -> 1849.4 | CJ15: =1151.22+698.18 -> 1849.4 | CK15: =SUM(BY15:CJ15) -> 27839.03 | CL15: =1151.22+698.18 -> 1849.4 | CM15: 1849.39 | CN15: =1151.22+698.18 -> 1849.4 | CO15: =1615.55+1151.22 -> 2766.77 | CP15: =1725.54+1151.22+8.33 -> 2885.09 | CQ15: =1229.15+945.13 -> 2174.28 | CR15: =1229.15+736.63 -> 1965.78 | CS15: =1965.76 -> 1965.76 | CT15: =736.63+1229.15 -> 1965.78 | CU15: =736.67+1229.15 -> 1965.82 | CV15: =1547.59+736.67 -> 2284.26 | CW15: =1229.15+736.67 -> 1965.82 | CX15: =SUM(CL15:CW15) -> 25487.55 | CY15: =1229.15+736.67 -> 1965.82 | CZ15: =1229.15+736.67 -> 1965.82 | DA15: =1229.15+736.67 -> 1965.82 | DB15: =1229.15+736.67 -> 1965.82 | DC15: =1229.15+736.67+13.4-13.4 -> 1965.82 | DD15: =1993.21+2587.08 -> 4580.29 | DE15: =1232.25+760.96 -> 1993.21 | DF15: =1232.25+760.96 -> 1993.21 | DG15: 3026.7 | DH15: 2251.58 | DI15: 1805 | DJ15: 1805 | DK15: =SUM(CY15:DJ15) -> 27284.09 | DL15: 1805 | DM15: 1805 | DN15: 1805 | DO15: 1805 | DP15: 1805 | DQ15: 1805 | DR15: 1805 | DS15: 1805 | DT15: 1805 | DU15: 1805 | DV15: 1805 | DW15: 1805 | DX15: =SUM(DL15:DW15) -> 21660
B16: Fiscal, Accounting agency | C16: 104.35 | D16: 102.85 | E16: 102.85 | F16: =E16 -> 102.85 | G16: =F16 -> 102.85 | H16: =G16 -> 102.85 | I16: =H16 -> 102.85 | J16: =I16 -> 102.85 | K16: =J16 -> 102.85 | L16: =K16 -> 102.85 | M16: 102.85 | N16: =102.85+102.85 -> 205.7 | O16: =SUM(C16:N16) -> 1338.55 | Q16: 104.6 | R16: 104.6 | S16: =254.91+104.6+45.79 -> 405.3 | T16: 182.31 | U16: 182.31 | V16: 224.66 | W16: =363+224.66 -> 587.66 | X16: =185.67*1.21+29.04 -> 253.7007 | Y16: =185.67*1.21+200*1.21 -> 466.6607 | Z16: =199.67*1.21+600*1.21+2504.7 -> 3472.3007 | AA16: =199.67*1.21 -> 241.6007 | AB16: =SUM(P16:AA16) -> 6225.7028 | AC16: =199.67*1.21 -> 241.6007 | AD16: =(199.67*1.21+104.16)+600*1.21+480*1.21 -> 1652.5607 | AE16: =(199.67+100)*1.21 -> 362.6007 | AF16: =199.67*1.21+1579*1.21/2 -> 1196.8957 | AG16: =(199.67+6.58)*1.21+600*1.21 -> 975.5625 | AH16: =199.67*1.21 -> 241.6007 | AI16: =199.67*1.21+50*1.21 -> 302.1007 | AJ16: =(199.67+9.56)*1.21+600*1.21 -> 979.1683 | AK16: =SUM(AC16:AJ16) -> 5952.09 | AL16: =199.67*1.21 -> 241.6007 | AM16: =199.67*1.21+48.97 -> 290.5707 | AN16: =213.67*1.21 -> 258.5407 | AO16: =213.67*1.21 -> 258.5407 | AQ16: =(313.67+313.67+300)*1.21+29.04 -> 1151.1214 | AR16: =313.67*1.21+104.16 -> 483.7007 | AS16: =313.67*1.21 -> 379.5407 | AT16: =313.67*1.21 -> 379.5407 | AU16: 379.54 | AV16: 430.54 | AW16: =386.78-1576.4+102.85+102.85+248.05+102.85 -> -633.02 | AX16: =SUM(AL16:AW16) -> 3620.2163 | AY16: 379.54 | AZ16: =379.54+270.23 -> 649.77 | BA16: 649.77 | BD16: =(150+252+15+20)*1.21*3 -> 1586.31 | BE16: =437*1.21-121*2+67.86+8.73 -> 363.36 | BF16: =437*1.21 -> 528.77 | BG16: =437*1.21+57.91 -> 586.68 | BH16: =437*1.21 -> 528.77 | BI16: =(437+300+27.95)*1.21 -> 925.5895 | BJ16: =(437+100)*1.21 -> 649.77 | BK16: =SUM(AY16:BJ16) -> 6848.3295 | BL16: =437*1.21 -> 528.77 | BM16: =437*1.21 -> 528.77 | BN16: =437*1.21 -> 528.77 | BO16: =437*1.21 -> 528.77 | BP16: =437*1.21+29.04 -> 557.81 | BQ16: =(437+30)*1.21+67.86 -> 632.93 | BR16: =461.91*1.21 -> 558.9111 | BS16: =461.91*1.21 -> 558.9111 | BT16: =(461.91+14.99)*1.21+60.09 -> 637.139 | BU16: =(461.91+27.95)*1.21 -> 592.7306 | BV16: =(461.91+200)*1.21 -> 800.9111 | BW16: =461.91*1.21+199.8 -> 758.7111 | BX16: =SUM(BL16:BW16) -> 7213.134 | BY16: =(461.91+27.95)*1.21 -> 592.7306 | BZ16: 558.91 | CA16: 558.91 | CB16: 558.91 | CC16: 558.91 | CD16: 595.21 | CE16: 644.11 | CF16: 576.25 | CG16: 576.25 | CH16: 576.25 | CI16: =576.25+1302.25 -> 1878.5 | CK16: =SUM(BY16:CJ16) -> 7674.9406 | CL16: =576.25 -> 576.25 | CM16: =576.25+(2.6*1.21+68.5) -> 647.896 | CN16: =576.25 -> 576.25 | CO16: =476.24*1.21+29.04 -> 605.2904 | CP16: =576.25+(1452/2)+1452/2 -> 2028.25 | CQ16: =576.25 -> 576.25 | CR16: =592.37+(300*1.21+67.86) -> 1023.23 | CS16: =592.37 -> 592.37 | CT16: =592.37+450*1.21+90 -> 1226.87 | CU16: =592.37 -> 592.37 | CV16: =592.37 -> 592.37 | CW16: =592.37+544.5+29.04+70 -> 1235.91 | CX16: =SUM(CL16:CW16) -> 10273.306 | CY16: =592.37 -> 592.37 | CZ16: =592.37+(592.37+2.6*1.21+60.01) -> 1247.896 | DB16: =592.37+592.37 -> 1184.74 | DD16: =652.87 -> 652.87 | DE16: =710.15+787.49 -> 1497.64 | DG16: =726.99 -> 726.99 | DH16: 558.91 | DI16: 558.91 | DJ16: 558.91 | DK16: =SUM(CY16:DJ16) -> 7579.236 | DL16: 558.91 | DM16: 558.91 | DN16: 558.91 | DO16: 558.91 | DP16: 558.91 | DQ16: 558.91 | DR16: 558.91 | DS16: 558.91 | DT16: 558.91 | DU16: 558.91 | DV16: 558.91 | DW16: 558.91 | DX16: =SUM(DL16:DW16) -> 6706.92
B17: Laboral Agency | AB17: =SUM(P17:AA17) -> 0 | AK17: =SUM(AC17:AJ17) -> 0 | AX17: =SUM(AL17:AW17) -> 0 | BK17: =SUM(AY17:BJ17) -> 0 | BX17: =SUM(BL17:BW17) -> 0 | CK17: =SUM(BY17:CJ17) -> 0 | CX17: =SUM(CL17:CW17) -> 0 | DK17: =SUM(CY17:DJ17) -> 0 | DX17: =SUM(DL17:DW17) -> 0
B18: Legal | D18: =72.6+14520 -> 14592.6 | E18: 302.5 | G18: 500 | O18: =SUM(C18:N18) -> 15395.1 | Q18: =423.5+181.5+423.5 -> 1028.5 | R18: 303 | S18: 75 | T18: =302.5+8470 -> 8772.5 | V18: 181.5 | AA18: 363 | AB18: =SUM(P18:AA18) -> 10723.5 | AF18: =377.12+376.34 -> 753.46 | AG18: =181.5+302.5+363 -> 847 | AH18: 363 | AK18: =SUM(AC18:AJ18) -> 1963.46 | AM18: 15.75 | AN18: 1644 | AO18: =3519.57*1.21+3500*1.21 -> 8493.6797 | AQ18: =895.42*1.21+(594.34+250+647.74-1644)+700+525 -> 2156.5382 | AU18: =810.4 -> 810.4 | AV18: 229.9 | AW18: 484 | AX18: =SUM(AL18:AW18) -> 13834.268 | BB18: =241.88+363 -> 604.88 | BC18: 302.5 | BF18: 242 | BG18: 605 | BK18: =SUM(AY18:BJ18) -> 1754.38 | BL18: =1575*1.21 -> 1905.75 | BO18: =133*1.21 -> 160.93 | BP18: 1427.13 | BQ18: =145.89+268.78+501.89 -> 916.56 | BR18: 307.91 | BX18: =SUM(BL18:BW18) -> 4718.28 | BZ18: =135.59+307.56+310.09+307.56 -> 1060.8 | CA18: 478.86 | CH18: 43.93 | CI18: =514.57 -> 514.57 | CJ18: =121 -> 121 | CK18: =SUM(BY18:CJ18) -> 2219.16 | CO18: 526.91 | CP18: 443.47 | CR18: =193.6+423.5 -> 617.1 | CS18: 278.49 | CU18: =437.34+1210+(298.89+56.49) -> 2002.72 | CW18: =423.78+509.12+96.8 -> 1029.7 | CX18: =SUM(CL18:CW18) -> 4898.39 | CZ18: 181.5 | DC18: 89.69 | DD18: =455.57+358.42+242 -> 1055.99 | DE18: =181.5+7526.98 -> 7708.48 | DH18: 127.51 | DI18: 700 | DK18: =SUM(CZ18:DJ18) -> 9863.17 | DM18: 700 | DP18: 700 | DS18: 700 | DV18: 700 | DX18: =SUM(DL18:DW18) -> 2800
B19: ISCC | AB19: =SUM(P19:AA19) -> 0 | AK19: =SUM(AC19:AJ19) -> 0 | AT19: =1800*1.21 -> 2178 | AU19: =2783 -> 2783 | AX19: =SUM(AL19:AW19) -> 4961 | BB19: =500*1.21 -> 605 | BG19: =2300*1.21 -> 2783 | BK19: =SUM(AY19:BJ19) -> 3388 | BX19: =SUM(BL19:BW19) -> 0 | CD19: =(1000+500+400+400)*1.21 -> 2783 | CK19: =SUM(BY19:CJ19) -> 2783 | CM19: =(1000+500+400+400)*1.21 -> 2783 | CO19: 250 | CU19: =(1000+500+400+400)*1.21+250 -> 3033 | CX19: =SUM(CM19:CW19) -> 6066 | DF19: =(1000+500+500+500)*1.21 -> 3025 | DH19: =(1000+500+400+750)*1.21 -> 3206.5 | DK19: =SUM(CY19:DJ19) -> 6231.5 | DU19: 2783 | DX19: =SUM(DL19:DW19) -> 2783
B20: ICE | F20: 230 | G20: =F20 -> 230 | H20: =G20 -> 230 | I20: =H20 -> 230 | J20: =I20 -> 230 | K20: =J20 -> 230 | L20: =K20 -> 230 | N20: =M20 -> 0 | O20: =SUM(C20:N20) -> 1610 | X20: 3054.54 | AB20: =SUM(P20:AA20) -> 3054.54 | AK20: =SUM(AC20:AJ20) -> 0 | AM20: =3544/1.1759 -> 3013.8617 | AX20: =SUM(AL20:AW20) -> 3013.8617 | AZ20: =3738/1.1606 -> 3220.7479 | BK20: =SUM(AY20:BJ20) -> 3220.7479 | BM20: =3924/0.996 -> 3939.759 | BX20: =SUM(BL20:BW20) -> 3939.759 | CA20: =4179/1.0815 -> 3864.0777 | CK20: =SUM(BY20:CJ20) -> 3864.0777 | CO20: =4020/1.0537 -> 3815.1276 | CX20: =SUM(CL20:CW20) -> 3815.1276 | DC20: =4261/1.0516 -> 4051.9209 | DK20: =SUM(CY20:DJ20) -> 4051.9209 | DM20: 4000 | DX20: =SUM(DL20:DW20) -> 4000
B21: OPIS + SCI + TRS + FO Licht + ISO+ARA Storage | E21: 2725.42 | O21: =SUM(C21:N21) -> 2725.42 | Q21: 993.37 | X21: =3432.03+1090.91 -> 4522.94 | AA21: =1085/1.109338895 -> 978.06 | AB21: =SUM(P21:AA21) -> 6494.37 | AH21: =1200/1.0792 -> 1111.9348 | AK21: =SUM(AC21:AJ21) -> 1111.9348 | AL21: =(3650+1280)/1.1626 -> 4240.4954 | AO21: =1830/1.21180015+(42-13.5-15) -> 1523.65 | AQ21: =(6000+36+18.03)/1.224046+2000/1.1748+15-(18.03+21)/1.224046 -> 6631.4484 | AU21: =1200/1.20499 -> 995.85889 | AV21: =3650/1.15876 -> 3149.9189 | AX21: =SUM(AL21:AW21) -> 16541.372 | AY21: =3410/1.1767 -> 2897.9349 | BD21: =8000/1.138449716 -> 7027.1 | BE21: 1265 | BH21: =1230/1.088 -> 1130.5147 | BI21: =3780/1.0192 -> 3708.7912 | BK21: =SUM(AY21:BJ21) -> 16029.341 | BN21: =3410/0.9907 -> 3442.0107 | BO21: 1265 | BR21: =8720/1.076 -> 8104.0892 | BU21: 0 | BX21: =SUM(BL21:BW21) -> 12811.1 | BY21: =1230/1.2451+375 -> 1362.8725 | CF21: =17892/1.0734 -> 16668.53 | CK21: =SUM(BY21:CJ21) -> 18031.402 | CO21: =3000/1.0537 -> 2847.1102 | CR21: =19144.44/1.0627 -> 18014.905 | CX21: =SUM(CR21:CW21) -> 18014.905 | DE21: =20484.55/1.1525 -> 17774.013 | DH21: =3000/1.15 -> 2608.6957 | DI21: 1230 | DK21: =SUM(DF21:DJ21) -> 3838.6957 | DO21: =3000/1.05 -> 2857.1429 | DX21: =SUM(DL21:DW21) -> 2857.1429
B22: AgriCensus (Fastmarkets) + European Gas Hub+Quantum | O22: =SUM(C22:N22) -> 0 | S22: 1600 | AB22: =SUM(P22:AA22) -> 1600 | AF22: 2000 | AK22: =SUM(AC22:AJ22) -> 2000 | AN22: 1500 | AT22: =2000+1500 -> 3500 | AX22: =SUM(AL22:AW22) -> 5000 | BC22: 240 | BG22: =975+975 -> 1950 | BK22: =SUM(AY22:BJ22) -> 2190 | BP22: 240 | BT22: =1062.75+1062.75 -> 2125.5 | BX22: =SUM(BL22:BW22) -> 2365.5 | CD22: 2000 | CG22: 2273.75 | CK22: =SUM(BY22:CJ22) -> 4273.75 | CQ22: 2300 | CT22: 2600 | CX22: =SUM(CL22:CW22) -> 4900 | DF22: 3100 | DK22: =SUM(CY22:DJ22) -> 3100 | DQ22: 2000 | DT22: 3100 | DX22: =SUM(DL22:DW22) -> 5100
B23: IVA | O23: =SUM(C23:N23) -> 0 | P23: -17.85 | Q23: =-490.35+193.16 -> -297.19 | R23: =-225.34+3413.21 -> 3187.87 | T23: =-1928.22-131.25+1087.8+7.24 -> -964.43 | U23: -1274.7 | V23: =5273.77 -> 5273.77 | W23: -3895.02 | X23: =-2701.72 -> -2701.72 | Y23: =-1503.4 -> -1503.4 | Z23: 234.08 | AA23: =205.85+1293.82-3007.48-1133.47 -> -2641.28 | AB23: =SUM(P23:AA23) -> -4599.87 | AF23: =-1757.82 -> -1757.82 | AG23: =-6799.75-2599.73 -> -9399.48 | AH23: -149.04 | AI23: =5532.53-2503.41 -> 3029.12 | AK23: =SUM(AC23:AJ23) -> -8277.22 | AL23: -2820.73 | AM23: 10560.38 | AN23: -2793.64 | AO23: -6970.42 | AP23: -2563.85 | AQ23: 918.07 | AR23: 8180.2 | AT23: =2315.58+52.72 -> 2368.3 | AU23: =-17193.52+2754.41-282.76 -> -14721.87 | AV23: =9146.69+8383.86 -> 17530.55 | AW23: =-1344.4+6610.91+648.82 -> 5915.33 | AX23: =SUM(AL23:AW23) -> 15602.32 | BB23: =-(6963.8-157.2)+3034.69 -> -3771.91 | BC23: =-(5030.09-2625) -> -2405.09 | BD23: =-(5646.53-1642.54)+2576.05+1242.79 -> -185.15 | BE23: -237.37 | BF23: -4582.61 | BG23: =-4611.52+191.81+2175.68+1942.75 -> -301.28 | BH23: =-103.6 -> -103.6 | BJ23: =-2413.07 -> -2413.07 | BK23: =SUM(AY23:BJ23) -> -14000.08 | BL23: =-9203.26-13942.94-12337.68 -> -35483.88 | BN23: =(4778.21+3667.53+2428.27)+(-7312.8-60.11)-9926.25-10125.68 -> -16550.83 | BO23: =-11339.06+2935.11+6152.25+6954.88+6336.17 -> 11039.35 | BP23: =-9497.58 -> -9497.58 | BQ23: =-14834.8+2854.63+3706.36 -> -8273.81 | BR23: =-15472.99 -> -15472.99 | BT23: =(-19049.98+167.66) -> -18882.32 | BU23: =-5113.31-34410.49 -> -39523.8 | BV23: =-5799.9+607.72+8959.67+9212.5+2988.74 -> 15968.73 | BW23: =-31631.49+16403.48 -> -15228.01 | BX23: =SUM(BL23:BW23) -> -131905.14 | BZ23: =-10540.54 -> -10540.54 | CA23: =-5016.39-(4659.34-61.33) -> -9614.4 | CB23: -3628.38 | CC23: -8805.44 | CE23: -5831.05 | CF23: -4256.5 | CG23: =-7846.44-4243.13 -> -12089.57 | CI23: =-2466.72 -> -2466.72 | CJ23: =-7922.52-7004.21 -> -14926.73 | CK23: =SUM(BY23:CI23) -> -57232.6 | CM23: -7036.27 | CN23: -4539.57 | CP23: =-2766.76-4000.76 -> -6767.52 | CQ23: -4442.34 | CR23: -3270.38 | CS23: -4671.31 | CT23: =-15000.32-18376.33 -> -33376.65 | CW23: =-17549.4+4735.67 -> -12813.73 | CX23: =SUM(CM23:CV23) -> -64104.04 | CY23: =-5460.77+2599.97 -> -2860.8 | DA23: 20244.14 | DB23: =-3243.37-5811.94 -> -9055.31 | DD23: =-2853.75 -> -2853.75 | DE23: =-7997.65 -> -7997.65 | DG23: =-5168.87-4216.89 -> -9385.76 | DH23: =-5180.25+8274.86 -> 3094.61 | DI23: -25975.4 | DJ23: -4058.44 | DK23: =SUM(CY23:DJ23) -> -38848.36 | DX23: =SUM(DL23:DW23) -> 0
B24: IRPF | O24: =SUM(C24:N24) -> 0 | S24: 2657.05 | V24: -2469.94 | Y24: =6053.41 -> 6053.41 | AB24: =SUM(P24:AA24) -> 6240.52 | AC24: 6893.49 | AG24: =7065.63 -> 7065.63 | AI24: 6864.49 | AK24: =SUM(AC24:AJ24) -> 20823.61 | AM24: 7143.48 | AP24: 5826.81 | AR24: =8429.64-5826.81 -> 2602.83 | AS24: =9854.3-703.46 -> 9150.84 | AV24: =10254.14 -> 10254.14 | AW24: =-823.92 -> -823.92 | AX24: =SUM(AL24:AW24) -> 34154.18 | AZ24: 10039.38 | BB24: -237.59 | BC24: 10792.67 | BD24: -1338.53 | BF24: 10200.62 | BG24: -789.8 | BI24: 12531.59 | BJ24: -385.47 | BK24: =SUM(AY24:BJ24) -> 40812.87 | BM24: 18046.59 | BN24: -5680.89 | BP24: 11632.67 | BQ24: =175.21-2015.57-175.21 -> -2015.57 | BS24: =12102.52 -> 12102.52 | BV24: =-1028.48+13140.02-1893.55 -> 10217.99 | BX24: =SUM(BL24:BW24) -> 44303.31 | BZ24: 11833.83 | CC24: =12418.39-(1.56+24) -> 12392.83 | CE24: 206.64 | CF24: =(13276.21-(26.46+26.46+24.7))+45 -> 13243.59 | CI24: =13194.02 -> 13194.02 | CK24: =SUM(BY24:CJ24) -> 50870.91 | CM24: 11657.96 | CP24: 11991.57 | CS24: 11873.37 | CV24: 14262.77 | CX24: =SUM(CL24:CW24) -> 49785.67 | CZ24: 11926.61 | DC24: 11803.14 | DF24: 11936.81 | DI24: =1650*3+2075*3+89.85*3 -> 11444.55 | DK24: =SUM(CY24:DJ24) -> 47111.11 | DM24: =1650*3+2075*3+89.85*3 -> 11444.55 | DP24: =1650*3+2075*3+89.85*3 -> 11444.55 | DS24: =1650*3+2075*3+89.85*3 -> 11444.55 | DV24: =1650*3+2075*3+89.85*3 -> 11444.55 | DX24: =SUM(DL24:DW24) -> 45778.2
B25: IS | O25: =SUM(C25:N25) -> 0 | V25: =3095.49 -> 3095.49 | AA25: =557.19*2 -> 1114.38 | AB25: =SUM(P25:AA25) -> 4209.87 | AG25: =557.19 -> 557.19 | AI25: 14219.73 | AK25: =SUM(AC25:AJ25) -> 14776.92 | AM25: 2760.14 | AO25: 2760.14 | AS25: =-624.19 -> -624.19 | AX25: =SUM(AL25:AW25) -> 4896.09 | BE25: =32326.09-2760.14*2+734.65 -> 27540.46 | BF25: 5818.7 | BK25: =SUM(AY25:BJ25) -> 33359.16 | BM25: 5818.7 | BO25: 5818.7 | BR25: =(233541.66-5818.7*1)-29971.42 -> 197751.54 | BS25: 1008 | BU25: =(227071.42-197100)+143.44 -> 30114.86 | BX25: =SUM(BL25:BW25) -> 240511.8 | BZ25: 1008 | CB25: 1008 | CH25: =2146.28*0.18 -> 386.3304 | CI25: =(-5818.7*2-1008)+4298.08 -> -8347.32 | CK25: =SUM(BY25:CJ25) -> -5944.9896 | CM25: =2146.28*0.18 -> 386.3304 | CO25: =2146.28*0.18 -> 386.3304 | CQ25: =(227071.42*0.18-1008-1008-1008)*3*0 -> 0 | CR25: =90028.04-1008-1008-386.33 -> 87625.71 | CS25: =90028.04*0.18 -> 16205.047 | CX25: =SUM(CI25:CW25) -> 90311.108 | CZ25: =90028.04*0.18 -> 16205.047 | DB25: =90028.04*0.18 -> 16205.047 | DE25: =416286.06*0.25-386-386-16205.05 -> 87094.465 | DF25: =104071.52*0.18 -> 18732.874 | DK25: =SUM(CY25:DJ25) -> 138237.43 | DM25: =104071.52*0.18 -> 18732.874 | DO25: =104071.52*0.18 -> 18732.874 | DX25: =SUM(DL25:DW25) -> 37465.747
B26: Otros impuestos | C26: 64.65 | E26: -2551.29 | F26: -5597.55 | G26: =4000*0.21-1500*0.21 -> 525 | I26: =2500*0.21 -> 525 | J26: =2500*0.21 -> 525 | K26: =2500*0.21 -> 525 | L26: =2500*0.21 -> 525 | N26: -93.4 | O26: =SUM(C26:N26) -> -5552.59 | X26: =40.8 -> 40.8 | AB26: =SUM(P26:AA26) -> 40.8 | AH26: -76.64 | AK26: =SUM(AC26:AJ26) -> -76.64 | AQ26: =4.6+25 -> 29.6 | AX26: =SUM(AL26:AW26) -> 29.6 | BI26: =645.94+32.3 -> 678.24 | BK26: =SUM(AY26:BJ26) -> 678.24 | BN26: =613.64 -> 613.64 | BO26: 15.75 | BT26: 132.99 | BU26: =613.64 -> 613.64 | BX26: =SUM(BL26:BW26) -> 1376.02 | BZ26: =978+931.43 -> 1909.43 | CA26: =613.64 -> 613.64 | CG26: 127.66 | CH26: =623.45+44.1 -> 667.55 | CK26: =SUM(BY26:CJ26) -> 3318.28 | CM26: =411.24+80.12+922.87 -> 1414.23 | CN26: 623.45 | CR26: 3144 | CS26: 130.93 | CT26: =9211.28+7103.57+527.62+5526.76 -> 22369.23 | CU26: =623.45+9.56+9.56+9.56+9.56+9.56 -> 671.25 | CX26: =SUM(CL26:CW26) -> 28353.09 | CZ26: 100 | DA26: =623.45 -> 623.45 | DE26: 4957.84 | DG26: 127.66 | DH26: =616.93 -> 616.93 | DI26: =922.87 -> 922.87 | DK26: =SUM(CY26:DJ26) -> 7348.75 | DX26: =SUM(DL26:DW26) -> 0
B27: Gastos Bancarios y comisiones | C27: =6.09+3.95+5.91-3.95+0.67 -> 12.67 | D27: =70+0.67 -> 70.67 | E27: 0.79 | N27: -3.95 | O27: =SUM(C27:N27) -> 80.18 | P27: 12 | Q27: =12.1+3.95+3.95-12-12.1+50 -> 45.9 | R27: =-50-3.95-3.95 -> -57.9 | T27: 28.28 | V27: 77.6 | W27: =0.3+15+21.77 -> 37.07 | X27: =87.56-43.78-7.5-10.89 -> 25.39 | AB27: =SUM(P27:AA27) -> 168.34 | AC27: =1+25+7.5 -> 33.5 | AD27: =80+1 -> 81 | AE27: 78 | AF27: =250+20/1.0849+145.8/1.0849 -> 402.82515 | AG27: =77.6+1+72.9/1.0849+20.61/1.0905 -> 164.69472 | AH27: =0.3+52.29/1.0898+145.8/1.0975 -> 181.12866 | AI27: =80+20/1.0981 -> 98.213277 | AJ27: 145.09 | AK27: =SUM(AC27:AJ27) -> 1184.4518 | AL27: =-145.09+7 -> -138.09 | AM27: =4.78+1200+20/1.1094 -> 1222.8078 | AO27: =269.25 -> 269.25 | AP27: =80+25*4+220/1.225+403.18/1.2240464+145.8/1.1094 -> 820.39717 | AQ27: =-214/1.224046-(192.5+18.18)/1.224046-80-12.5*4 -> -476.94775 | AR27: =274.8/1.1338 -> 242.37079 | AS27: =14.4/1.224+7.39/1.2018+1.39+14.85+68.7/1.1338 -> 94.746513 | AT27: =15+15+7.41/1.20388+7.49/1.20499-7.5-7.5+5517.46/1.13377 -> 4893.843 | AU27: =1+2+(18.27/1.20499)+(65.57/1.20499)+(556.38/1.1539)+(30/1.1539)+30+(55/1.205) -> 656.39278 | AV27: =1+178.97+2.43+1200+(171.75/1.153899) -> 1531.2432 | AW27: =10.34+(34.35/1.153899) -> 40.108637 | AX27: =SUM(AL27:AW27) -> 9156.122 | AY27: =3+3+716.07/1.1539+673.17/1.1629+78.3+120 -> 1403.7368 | AZ27: =7.12/1.1637-120+24.88+12.13+31.33/1.1637 -> -49.948838 | BB27: =70-70+3+78.3+504.47 -> 585.77 | BC27: =12.28+30.45/1.1374 -> 39.051584 | BD27: =1+88.78 -> 89.78 | BE27: =1+4.43+88.92 -> 94.35 | BF27: =12.29+59.28+(832.3+173.64) -> 1077.51 | BG27: =238.84+1.63 -> 240.47 | BH27: =-(752.3+143.64)+225.51+15+0.91+28.85/1.0784 -> -627.7674 | BI27: =292.78+11.93+6.13+0.36+12 -> 323.2 | BJ27: =12+782.17 -> 794.17 | BK27: =SUM(AY27:BJ27) -> 3970.3222 | BL27: =-287.24+1.09+12 -> -274.15 | BM27: =16.53+12+11.89+26.77 -> 67.19 | BN27: =660.5+12+0.54 -> 673.04 | BO27: =112.21+27.91+12+0.36 -> 152.48 | BP27: =4.05+13.22+0.18+12 -> 29.45 | BQ27: =1.09+12 -> 13.09 | BR27: =26.61+12+762/1.075+762/1.0596 -> 1466.5865 | BS27: =0.73-0.73-1.09-0.18-0.36-0.54+12+100/1.0821 -> 102.2429 | BT27: =12 -> 12 | BU27: =27.72+12 -> 39.72 | BV27: =18.73+18.73+12 -> 49.46 | BW27: =12+63.26-63.26 -> 12 | BX27: =SUM(BL27:BW27) -> 2343.1094 | BY27: =12 -> 12 | BZ27: =12+48.59+349.54+95.95+52.82+48.43+73.95/1.0815 -> 675.70725 | CA27: =15.08+1051.8/1.0813+12 -> 999.79802 | CB27: 12 | CC27: =12+40+40+572.86/1.0866 -> 619.20412 | CD27: =12+90.34+66.31 -> 168.65 | CE27: =89.68+12+103.05/1.0866+153.85+8.82 -> 359.18711 | CF27: =39.45+119.6+2.09+68.7/1.0866+12.64 -> 237.00474 | CG27: =103.05/1.0866+12 -> 106.83711 | CH27: =46.65+33.1+150.62+111.49+8.03+68.7/1.0866+100+12 -> 525.11474 | CI27: =12.71-100+7.42+174.08+118.26+3.03+1143/1.0857+24.04+12 -> 1304.317 | CJ27: =2.7+12+2286/1.1021 -> 2088.9219 | CK27: =SUM(BY27:CJ27) -> 7108.742 | CL27: =6.34+3.95+16.28+2.77+50.95+27.22+12 -> 119.51 | CM27: =20.12+12+206.1/1.1034+23.77+21.16 -> 263.8363 | CN27: =892.14/1.0951+299.55+12+30/1.0951 -> 1153.6101 | CO27: =228.8+12 -> 240.8 | CP27: =3+3+(12+12+12)+(293.14+293.14+146.57+123.28)+293.29/1.0637+12+40+40+35.47 -> 1301.3262 | CQ27: =12+12+275.4/1.0281+32.25 -> 324.12278 | CR27: =-12-12-12-12-12+32.9+137.37+12 -> 122.27 | CS27: =189.89+1125+12+103.05/1.0281 -> 1427.1234 | CT27: =207.4+12+128.93+160.39 -> 508.72 | CU27: =38.78+144.83+132.27+137.4/1.0465+12 -> 459.17479 | CV27: =30/1.0465+12+22.77 -> 63.436985 | CW27: =12+103.05/1.0465 -> 110.47109 | CX27: =SUM(CL27:CW27) -> 6094.4017 | CY27: =12+34.35/1.0465 -> 44.823698 | CZ27: =202.56+12+34.35/1.0465 -> 247.3837 | DA27: =26+187+247.32/1.0465+12 -> 461.33063 | DB27: =-27.82+3+12 -> -12.82 | DC27: =722.93+360.43+2.41+56+56+40+40+12 -> 1289.77 | DD27: =-56-56+20.61/1.0648+3+3+12 -> -74.644252 | DE27: =-56.97+950+151.9+3+12+20.61/1.0648 -> 1079.2857 | DF27: =12+80.61/1.0825 -> 86.466513 | DG27: =747.69+247.04+30/1.0825+20.61/1.0868+12+2 -> 1055.4076 | DH27: =15+0.91 -> 15.91 | DK27: =SUM(CY27:DJ27) -> 4192.9136 | DX27: =SUM(DL27:DW27) -> 0
B28: Mto. y gasolina Coche | O28: =SUM(C28:N28) -> 0 | S28: 1217.11 | T28: 64.2 | AB28: =SUM(P28:AA28) -> 1281.31 | AK28: =SUM(AC28:AJ28) -> 0 | AX28: =SUM(AL28:AW28) -> 0 | BK28: =SUM(AY28:BJ28) -> 0 | BX28: =SUM(BL28:BW28) -> 0 | CG28: 411.3 | CJ28: =287-50 -> 237 | CK28: =SUM(BY28:CJ28) -> 648.3 | CU28: 829.83 | CX28: =SUM(CL28:CW28) -> 829.83 | CZ28: 484.39 | DH28: =1042.71+218.97 -> 1261.68 | DK28: =SUM(CY28:DJ28) -> 1746.07 | DX28: =SUM(DL28:DW28) -> 0
B29: Publicidad y propaganda | O29: =SUM(C29:N29) -> 0 | AB29: =SUM(P29:AA29) -> 0 | AC29: 200 | AK29: =SUM(AC29:AJ29) -> 200 | AO29: =389.47+389.8 -> 779.27 | AP29: =354.84+336.36+343.07 -> 1034.27 | AQ29: =347.82+194.57+309.1 -> 851.49 | AT29: =312.33 -> 312.33 | AX29: =SUM(AL29:AW29) -> 2977.36 | BB29: =2406.07+715 -> 3121.07 | BG29: 339.63 | BJ29: 162.45 | BK29: =SUM(AY29:BJ29) -> 3623.15 | BP29: 4526.01 | BR29: 466.75 | BS29: -466.75 | BX29: =SUM(BL29:BW29) -> 4526.01 | CA29: =933.15-855.94 -> 77.21 | CB29: =477.95 -> 477.95 | CE29: =933.15-77.21 -> 855.94 | CG29: 121.01 | CK29: =SUM(BY29:CJ29) -> 1532.11 | CM29: 477.88 | CN29: 444.07 | CO29: 400.91 | CX29: =SUM(CM29:CW29) -> 1322.86 | DK29: =SUM(CY29:DJ29) -> 0 | DX29: =SUM(DL29:DW29) -> 0
B30: Bus | O30: =SUM(C30:N30) -> 0 | AB30: =SUM(P30:AA30) -> 0 | AF30: 4200 | AI30: -4200 | AK30: =SUM(AC30:AJ30) -> 0 | AX30: =SUM(AL30:AW30) -> 0 | BK30: =SUM(AY30:BJ30) -> 0 | BX30: =SUM(BL30:BW30) -> 0 | CK30: =SUM(BY30:CJ30) -> 0 | CX30: =SUM(CL30:CW30) -> 0 | DK30: =SUM(CY30:DJ30) -> 0 | DX30: =SUM(DL30:DW30) -> 0
B31: Adaptext traducciones | O31: =SUM(C31:N31) -> 0 | AB31: =SUM(P31:AA31) -> 0 | AE31: =600+126-90 -> 636 | AK31: =SUM(AC31:AJ31) -> 636 | AX31: =SUM(AL31:AW31) -> 0 | BK31: =SUM(AY31:BJ31) -> 0 | BX31: =SUM(BL31:BW31) -> 0 | CK31: =SUM(BY31:CJ31) -> 0 | CX31: =SUM(CL31:CW31) -> 0 | DK31: =SUM(CY31:DJ31) -> 0 | DX31: =SUM(DL31:DW31) -> 0
B32: Mensajería | O32: =SUM(C32:N32) -> 0 | AB32: =SUM(P32:AA32) -> 0 | AC32: =9.78 -> 9.78 | AE32: =8*1.21 -> 9.68 | AF32: =5.12 -> 5.12 | AK32: =SUM(AC32:AJ32) -> 24.58 | AP32: 10.67 | AQ32: 18.61 | AR32: 26.56 | AS32: 4.68 | AU32: 5.63 | AW32: 20.93 | AX32: =SUM(AL32:AW32) -> 87.08 | BC32: 9.37 | BF32: 165.5 | BG32: 8.26 | BK32: =SUM(AY32:BJ32) -> 183.13 | BM32: 13.18 | BN32: 7.15 | BP32: 5.37 | BS32: 7.39 | BU32: 5.67 | BV32: 6.23 | BX32: =SUM(BL32:BW32) -> 44.99 | CC32: 11.16 | CI32: =5.97+35 -> 40.97 | CJ32: =10.22+202.74 -> 212.96 | CK32: =SUM(BY32:CJ32) -> 265.09 | CO32: 98.31 | CP32: 28.04 | CR32: 40.85 | CS32: 26.97 | CT32: 62.24 | CU32: 54.37 | CV32: 74.31 | CX32: =SUM(CL32:CW32) -> 385.09 | DA32: 382.06 | DB32: -382.06 | DE32: 14.34 | DK32: =SUM(CY32:DJ32) -> 14.34 | DX32: =SUM(DL32:DW32) -> 0
